Workbook

Sheet Istruzioni
B1: Budget familiare 2026
B2: Istruzioni d'uso · NettoChiaro · versione 2026.1
B5: Legenda
C6: Celle gialle: da compilare. Tutte le altre contengono formule e si aggiornano da sole.
C7: Celle arancioni: segnalano un dato da controllare (data mancante, categoria non trovata, nome doppio).
C8: Intestazioni verdi: titoli delle colonne. I fogli sono protetti senza password per evitare di cancellare le formule.
B10: Come iniziare
B11: 1. | C11: Impostazioni: anno, saldo di cassa al 1° gennaio (conto corrente più contanti), nomi dei membri della famiglia (facoltativi) e conti o metodi di pagamento.
B12: 2. | C12: Categorie: controlla l'elenco. Puoi rinominare le voci, aggiungerne nelle righe vuote e scegliere il tipo: Entrata, Spesa fissa, Spesa variabile, Risparmio e investimenti.
B13: 3. | C13: Budget: scrivi l'importo tipico mensile di ogni categoria; i 12 mesi si compilano da soli. Per le spese che non sono mensili (TARI, bollo auto, assicurazioni) scrivi l'importo nel mese in cui le paghi.
B14: 4. | C14: Movimenti: registra ogni entrata e uscita con data, descrizione, categoria scelta dal menu e importo. Conto e persona sono facoltativi.
B15: 5. | C15: Mensile e Dashboard: si aggiornano da soli. Mostrano il consuntivo per categoria e per mese, la differenza dal budget, il risparmio e i grafici.
B16: 6. | C16: Obiettivi e Debiti: elenca cosa vuoi mettere da parte e i debiti in corso. Il foglio calcola la quota mensile necessaria e l'ordine di estinzione consigliato.
B18: Regole utili
B19: • | C19: Gli importi si scrivono sempre positivi: è la categoria a dire se sono un'entrata o un'uscita. Un rimborso su una spesa si registra con importo negativo nella stessa categoria.
B20: • | C20: I versamenti su conti di risparmio, investimenti o fondo pensione vanno nelle categorie di tipo «Risparmio e investimenti». Non sono spese, ma escono dal saldo di cassa.
B21: • | C21: Risparmio = entrate − spese. Tasso di risparmio = risparmio / entrate. Avanzo = entrate − spese − versamenti a risparmio.
B22: • | C22: Saldo di cassa = saldo al 1° gennaio + entrate − spese − versamenti a risparmio. Se registri tutti i movimenti, si avvicina al totale di conto corrente e contanti (le spese con carta di credito escono dal conto più tardi).
B23: • | C23: Contano solo i movimenti con una data dell'anno impostato. La colonna «Controllo» dei Movimenti segnala date mancanti, categorie non trovate e movimenti di altri anni.
B24: • | C24: Il registro ha 2.000 righe. In Categorie non eliminare le righe: svuota le celle. Se rinomini una categoria già usata, correggi anche i movimenti con il vecchio nome.
B25: • | C25: Mese di riferimento (Impostazioni): «Automatico» usa il mese della data di riferimento (se la data è vuota, quello di oggi). Serve per i confronti «da inizio anno» di Mensile e Dashboard.
B26: • | C26: Per un mese di budget diverso dal solito scrivi il valore nella cella del mese. Per tornare all'importo tipico copia la cella di un mese non modificato.
B28: Protezione, stampa e nuovo anno
B29: • | C29: Per togliere la protezione (non c'è password): Excel, Revisione > Rimuovi protezione foglio; LibreOffice, Strumenti > Proteggi foglio; Google Sheets, Dati > Proteggi fogli e intervalli.
B30: • | C30: Per ordinare i movimenti togli prima la protezione del foglio Movimenti. Per stampare solo una parte del registro seleziona le righe e scegli «Stampa selezione».
B31: • | C31: Nuovo anno: salva una copia del file, cambia l'anno in Impostazioni, scrivi come saldo iniziale il saldo di cassa di fine anno, svuota i movimenti e aggiorna budget, obiettivi e debiti.
B33: Compatibilità
B34: • | C34: Excel 2016 o successivo (Windows e Mac), Google Sheets (carica il file su Google Drive e aprilo con Google Sheets), LibreOffice Calc. Nessuna macro, nessun collegamento esterno.
B35: • | C35: Excel apre i file scaricati da internet in «Visualizzazione protetta», dove i calcoli non si aggiornano: fai clic su «Abilita modifica».
B36: • | C36: In Google Sheets la protezione dei fogli può non restare attiva: scrivi solo nelle celle gialle. I grafici possono avere uno stile leggermente diverso.
B38: Avvertenze
B39: • | C39: Strumento di organizzazione personale: non è consulenza finanziaria né fiscale. Le stime su obiettivi e debiti ipotizzano tassi e rate costanti; controlla sempre i dati del tuo contratto.
B40: • | C40: Calcolo dello stipendio netto: nettochiaro.com/calcolo-stipendio-netto
B41: • | C41: Calcolo della rata del mutuo: nettochiaro.com/calcolo-rata-mutuo

Sheet Impostazioni
B1: Impostazioni
B2: Compila le celle gialle. Le altre si aggiornano da sole.
B4: Anno del budget | C4: 2026 | D4: Contano solo i movimenti con una data di quest'anno.
B5: Saldo di cassa al 1° gennaio | C5: 3200 | D5: Conto corrente più contanti a inizio anno. Esclude i conti di risparmio e gli investimenti.
B6: Nome della famiglia (facoltativo) | C6: Famiglia Rossi | D6: Compare nel titolo della Dashboard.
B7: Mese di riferimento | C7: Automatico | D7: «Automatico» (o vuoto) usa il mese della data di riferimento. Serve per i confronti «da inizio anno».
B8: Data di riferimento (facoltativa) | C8: 46387 | D8: Lascia vuoto per usare la data di oggi. Serve per obiettivi, debiti e mese automatico.
B10: Valori usati dal foglio (calcolati, non modificare)
B11: Data di riferimento usata | C11: =IF(C8="",TODAY(),C8)
B12: Mese di riferimento usato (numero) | C12: =IF(OR(C7="",C7="Automatico"),IF(YEAR(C11)=C4,MONTH(C11),IF(YEAR(C11)>C4,12,1)),IFERROR(MATCH(C7,Elenchi!$A$2:$A$13,0),12))
B13: Mese di riferimento usato (nome) | C13: =INDEX(Elenchi!$A$2:$A$13,C12)
B15: Membri della famiglia (facoltativo) | D15: Per la colonna «Chi» dei Movimenti e il riepilogo per persona in Dashboard.
B16: Membro 1 | C16: Marco
B17: Membro 2 | C17: Giulia
B18: Membro 3 | C18: Sofia
B19: Membro 4
B20: Membro 5
B21: Membro 6
B23: Conti e metodi di pagamento | D23: Per la colonna «Conto o metodo» dei Movimenti. Puoi rinominarli.
B24: Conto 1 | C24: Conto corrente
B25: Conto 2 | C25: Carta di debito
B26: Conto 3 | C26: Carta di credito
B27: Conto 4 | C27: Contanti
B28: Conto 5 | C28: Carta prepagata
B29: Conto 6
B30: Conto 7
B31: Conto 8

Sheet Categorie
A1: Categorie
A2: Rinomina, aggiungi o svuota le categorie. Non eliminare le righe: per togliere una categoria cancella nome e tipo.
A3: Se rinomini una categoria già usata, correggi anche i movimenti: il registro segnala «Categoria non trovata».
A4: Nei nomi non usare i simboli * ? ~ e non iniziare con < > =.
A5: Categoria | B5: Tipo | C5: Note | D5: Controllo
A6: Stipendio Marco | B6: Entrata | C6: Stipendio netto. | D6: =IF(AND(A6="",B6=""),"",IF(A6="","Manca il nome",IF(OR(ISNUMBER(FIND("*",A6)),ISNUMBER(FIND("?",A6)),ISNUMBER(FIND("~",A6)),ISNUMBER(FIND(LEFT(A6,1),"<>="))),"Simbolo non ammesso",IF(COUNTIF($A$6:$A$65,A6)>1,"Nome doppio",IF(B6="","Manca il tipo","")))))
A7: Stipendio Giulia | B7: Entrata | C7: Stipendio netto. | D7: =IF(AND(A7="",B7=""),"",IF(A7="","Manca il nome",IF(OR(ISNUMBER(FIND("*",A7)),ISNUMBER(FIND("?",A7)),ISNUMBER(FIND("~",A7)),ISNUMBER(FIND(LEFT(A7,1),"<>="))),"Simbolo non ammesso",IF(COUNTIF($A$6:$A$65,A7)>1,"Nome doppio",IF(B7="","Manca il tipo","")))))
A8: Tredicesima e quattordicesima | B8: Entrata | C8: Mensilità aggiuntive. | D8: =IF(AND(A8="",B8=""),"",IF(A8="","Manca il nome",IF(OR(ISNUMBER(FIND("*",A8)),ISNUMBER(FIND("?",A8)),ISNUMBER(FIND("~",A8)),ISNUMBER(FIND(LEFT(A8,1),"<>="))),"Simbolo non ammesso",IF(COUNTIF($A$6:$A$65,A8)>1,"Nome doppio",IF(B8="","Manca il tipo","")))))
A9: Assegno unico figli | B9: Entrata | C9: Assegno unico e universale INPS. | D9: =IF(AND(A9="",B9=""),"",IF(A9="","Manca il nome",IF(OR(ISNUMBER(FIND("*",A9)),ISNUMBER(FIND("?",A9)),ISNUMBER(FIND("~",A9)),ISNUMBER(FIND(LEFT(A9,1),"<>="))),"Simbolo non ammesso",IF(COUNTIF($A$6:$A$65,A9)>1,"Nome doppio",IF(B9="","Manca il tipo","")))))
A10: Entrate extra | B10: Entrata | C10: Lavori occasionali, vendita di oggetti usati. | D10: =IF(AND(A10="",B10=""),"",IF(A10="","Manca il nome",IF(OR(ISNUMBER(FIND("*",A10)),ISNUMBER(FIND("?",A10)),ISNUMBER(FIND("~",A10)),ISNUMBER(FIND(LEFT(A10,1),"<>="))),"Simbolo non ammesso",IF(COUNTIF($A$6:$A$65,A10)>1,"Nome doppio",IF(B10="","Manca il tipo","")))))
A11: Rimborsi e altre entrate | B11: Entrata | C11: Rimborso del 730, rimborsi spese, regali in denaro. | D11: =IF(AND(A11="",B11=""),"",IF(A11="","Manca il nome",IF(OR(ISNUMBER(FIND("*",A11)),ISNUMBER(FIND("?",A11)),ISNUMBER(FIND("~",A11)),ISNUMBER(FIND(LEFT(A11,1),"<>="))),"Simbolo non ammesso",IF(COUNTIF($A$6:$A$65,A11)>1,"Nome doppio",IF(B11="","Manca il tipo","")))))
A12: Affitto o rata mutuo | B12: Spesa fissa | C12: Per stimare la rata del mutuo: nettochiaro.com/calcolo-rata-mutuo | D12: =IF(AND(A12="",B12=""),"",IF(A12="","Manca il nome",IF(OR(ISNUMBER(FIND("*",A12)),ISNUMBER(FIND("?",A12)),ISNUMBER(FIND("~",A12)),ISNUMBER(FIND(LEFT(A12,1),"<>="))),"Simbolo non ammesso",IF(COUNTIF($A$6:$A$65,A12)>1,"Nome doppio",IF(B12="","Manca il tipo","")))))
A13: Condominio | B13: Spesa fissa | D13: =IF(AND(A13="",B13=""),"",IF(A13="","Manca il nome",IF(OR(ISNUMBER(FIND("*",A13)),ISNUMBER(FIND("?",A13)),ISNUMBER(FIND("~",A13)),ISNUMBER(FIND(LEFT(A13,1),"<>="))),"Simbolo non ammesso",IF(COUNTIF($A$6:$A$65,A13)>1,"Nome doppio",IF(B13="","Manca il tipo","")))))
A14: Luce | B14: Spesa fissa | D14: =IF(AND(A14="",B14=""),"",IF(A14="","Manca il nome",IF(OR(ISNUMBER(FIND("*",A14)),ISNUMBER(FIND("?",A14)),ISNUMBER(FIND("~",A14)),ISNUMBER(FIND(LEFT(A14,1),"<>="))),"Simbolo non ammesso",IF(COUNTIF($A$6:$A$65,A14)>1,"Nome doppio",IF(B14="","Manca il tipo","")))))
A15: Gas | B15: Spesa fissa | D15: =IF(AND(A15="",B15=""),"",IF(A15="","Manca il nome",IF(OR(ISNUMBER(FIND("*",A15)),ISNUMBER(FIND("?",A15)),ISNUMBER(FIND("~",A15)),ISNUMBER(FIND(LEFT(A15,1),"<>="))),"Simbolo non ammesso",IF(COUNTIF($A$6:$A$65,A15)>1,"Nome doppio",IF(B15="","Manca il tipo","")))))
A16: Acqua | B16: Spesa fissa | D16: =IF(AND(A16="",B16=""),"",IF(A16="","Manca il nome",IF(OR(ISNUMBER(FIND("*",A16)),ISNUMBER(FIND("?",A16)),ISNUMBER(FIND("~",A16)),ISNUMBER(FIND(LEFT(A16,1),"<>="))),"Simbolo non ammesso",IF(COUNTIF($A$6:$A$65,A16)>1,"Nome doppio",IF(B16="","Manca il tipo","")))))
A17: TARI | B17: Spesa fissa | C17: Tassa sui rifiuti del Comune. | D17: =IF(AND(A17="",B17=""),"",IF(A17="","Manca il nome",IF(OR(ISNUMBER(FIND("*",A17)),ISNUMBER(FIND("?",A17)),ISNUMBER(FIND("~",A17)),ISNUMBER(FIND(LEFT(A17,1),"<>="))),"Simbolo non ammesso",IF(COUNTIF($A$6:$A$65,A17)>1,"Nome doppio",IF(B17="","Manca il tipo","")))))
A18: Internet e telefono | B18: Spesa fissa | D18: =IF(AND(A18="",B18=""),"",IF(A18="","Manca il nome",IF(OR(ISNUMBER(FIND("*",A18)),ISNUMBER(FIND("?",A18)),ISNUMBER(FIND("~",A18)),ISNUMBER(FIND(LEFT(A18,1),"<>="))),"Simbolo non ammesso",IF(COUNTIF($A$6:$A$65,A18)>1,"Nome doppio",IF(B18="","Manca il tipo","")))))
A19: Assicurazioni | B19: Spesa fissa | C19: Auto, casa, salute, vita. | D19: =IF(AND(A19="",B19=""),"",IF(A19="","Manca il nome",IF(OR(ISNUMBER(FIND("*",A19)),ISNUMBER(FIND("?",A19)),ISNUMBER(FIND("~",A19)),ISNUMBER(FIND(LEFT(A19,1),"<>="))),"Simbolo non ammesso",IF(COUNTIF($A$6:$A$65,A19)>1,"Nome doppio",IF(B19="","Manca il tipo","")))))
A20: Bollo auto | B20: Spesa fissa | C20: Tassa automobilistica regionale. | D20: =IF(AND(A20="",B20=""),"",IF(A20="","Manca il nome",IF(OR(ISNUMBER(FIND("*",A20)),ISNUMBER(FIND("?",A20)),ISNUMBER(FIND("~",A20)),ISNUMBER(FIND(LEFT(A20,1),"<>="))),"Simbolo non ammesso",IF(COUNTIF($A$6:$A$65,A20)>1,"Nome doppio",IF(B20="","Manca il tipo","")))))
A21: Abbonamenti | B21: Spesa fissa | C21: Streaming, palestra, quotidiani, app. | D21: =IF(AND(A21="",B21=""),"",IF(A21="","Manca il nome",IF(OR(ISNUMBER(FIND("*",A21)),ISNUMBER(FIND("?",A21)),ISNUMBER(FIND("~",A21)),ISNUMBER(FIND(LEFT(A21,1),"<>="))),"Simbolo non ammesso",IF(COUNTIF($A$6:$A$65,A21)>1,"Nome doppio",IF(B21="","Manca il tipo","")))))
A22: Rate di prestiti | B22: Spesa fissa | C22: Prestiti personali, auto, acquisti a rate. Dettaglio nel foglio Debiti. | D22: =IF(AND(A22="",B22=""),"",IF(A22="","Manca il nome",IF(OR(ISNUMBER(FIND("*",A22)),ISNUMBER(FIND("?",A22)),ISNUMBER(FIND("~",A22)),ISNUMBER(FIND(LEFT(A22,1),"<>="))),"Simbolo non ammesso",IF(COUNTIF($A$6:$A$65,A22)>1,"Nome doppio",IF(B22="","Manca il tipo","")))))
A23: Spesa alimentare | B23: Spesa variabile | C23: Supermercato, mercato, prodotti per la casa. | D23: =IF(AND(A23="",B23=""),"",IF(A23="","Manca il nome",IF(OR(ISNUMBER(FIND("*",A23)),ISNUMBER(FIND("?",A23)),ISNUMBER(FIND("~",A23)),ISNUMBER(FIND(LEFT(A23,1),"<>="))),"Simbolo non ammesso",IF(COUNTIF($A$6:$A$65,A23)>1,"Nome doppio",IF(B23="","Manca il tipo","")))))
A24: Carburante | B24: Spesa variabile | D24: =IF(AND(A24="",B24=""),"",IF(A24="","Manca il nome",IF(OR(ISNUMBER(FIND("*",A24)),ISNUMBER(FIND("?",A24)),ISNUMBER(FIND("~",A24)),ISNUMBER(FIND(LEFT(A24,1),"<>="))),"Simbolo non ammesso",IF(COUNTIF($A$6:$A$65,A24)>1,"Nome doppio",IF(B24="","Manca il tipo","")))))
A25: Trasporti | B25: Spesa variabile | C25: Mezzi pubblici, treni, parcheggi, pedaggi. | D25: =IF(AND(A25="",B25=""),"",IF(A25="","Manca il nome",IF(OR(ISNUMBER(FIND("*",A25)),ISNUMBER(FIND("?",A25)),ISNUMBER(FIND("~",A25)),ISNUMBER(FIND(LEFT(A25,1),"<>="))),"Simbolo non ammesso",IF(COUNTIF($A$6:$A$65,A25)>1,"Nome doppio",IF(B25="","Manca il tipo","")))))
A26: Farmacia e salute | B26: Spesa variabile | C26: Farmaci, visite, ticket, dentista. | D26: =IF(AND(A26="",B26=""),"",IF(A26="","Manca il nome",IF(OR(ISNUMBER(FIND("*",A26)),ISNUMBER(FIND("?",A26)),ISNUMBER(FIND("~",A26)),ISNUMBER(FIND(LEFT(A26,1),"<>="))),"Simbolo non ammesso",IF(COUNTIF($A$6:$A$65,A26)>1,"Nome doppio",IF(B26="","Manca il tipo","")))))
A27: Scuola e figli | B27: Spesa variabile | C27: Mensa, libri, gite, sport, centri estivi. | D27: =IF(AND(A27="",B27=""),"",IF(A27="","Manca il nome",IF(OR(ISNUMBER(FIND("*",A27)),ISNUMBER(FIND("?",A27)),ISNUMBER(FIND("~",A27)),ISNUMBER(FIND(LEFT(A27,1),"<>="))),"Simbolo non ammesso",IF(COUNTIF($A$6:$A$65,A27)>1,"Nome doppio",IF(B27="","Manca il tipo","")))))
A28: Casa e manutenzione | B28: Spesa variabile | C28: Piccoli lavori, arredi, elettrodomestici. | D28: =IF(AND(A28="",B28=""),"",IF(A28="","Manca il nome",IF(OR(ISNUMBER(FIND("*",A28)),ISNUMBER(FIND("?",A28)),ISNUMBER(FIND("~",A28)),ISNUMBER(FIND(LEFT(A28,1),"<>="))),"Simbolo non ammesso",IF(COUNTIF($A$6:$A$65,A28)>1,"Nome doppio",IF(B28="","Manca il tipo","")))))
A29: Abbigliamento | B29: Spesa variabile | D29: =IF(AND(A29="",B29=""),"",IF(A29="","Manca il nome",IF(OR(ISNUMBER(FIND("*",A29)),ISNUMBER(FIND("?",A29)),ISNUMBER(FIND("~",A29)),ISNUMBER(FIND(LEFT(A29,1),"<>="))),"Simbolo non ammesso",IF(COUNTIF($A$6:$A$65,A29)>1,"Nome doppio",IF(B29="","Manca il tipo","")))))
A30: Svago | B30: Spesa variabile | C30: Ristoranti, bar, cinema, hobby. | D30: =IF(AND(A30="",B30=""),"",IF(A30="","Manca il nome",IF(OR(ISNUMBER(FIND("*",A30)),ISNUMBER(FIND("?",A30)),ISNUMBER(FIND("~",A30)),ISNUMBER(FIND(LEFT(A30,1),"<>="))),"Simbolo non ammesso",IF(COUNTIF($A$6:$A$65,A30)>1,"Nome doppio",IF(B30="","Manca il tipo","")))))
A31: Regali | B31: Spesa variabile | D31: =IF(AND(A31="",B31=""),"",IF(A31="","Manca il nome",IF(OR(ISNUMBER(FIND("*",A31)),ISNUMBER(FIND("?",A31)),ISNUMBER(FIND("~",A31)),ISNUMBER(FIND(LEFT(A31,1),"<>="))),"Simbolo non ammesso",IF(COUNTIF($A$6:$A$65,A31)>1,"Nome doppio",IF(B31="","Manca il tipo","")))))
A32: Vacanze | B32: Spesa variabile | D32: =IF(AND(A32="",B32=""),"",IF(A32="","Manca il nome",IF(OR(ISNUMBER(FIND("*",A32)),ISNUMBER(FIND("?",A32)),ISNUMBER(FIND("~",A32)),ISNUMBER(FIND(LEFT(A32,1),"<>="))),"Simbolo non ammesso",IF(COUNTIF($A$6:$A$65,A32)>1,"Nome doppio",IF(B32="","Manca il tipo","")))))
A33: Imprevisti | B33: Spesa variabile | C33: Riparazioni e spese non previste. | D33: =IF(AND(A33="",B33=""),"",IF(A33="","Manca il nome",IF(OR(ISNUMBER(FIND("*",A33)),ISNUMBER(FIND("?",A33)),ISNUMBER(FIND("~",A33)),ISNUMBER(FIND(LEFT(A33,1),"<>="))),"Simbolo non ammesso",IF(COUNTIF($A$6:$A$65,A33)>1,"Nome doppio",IF(B33="","Manca il tipo","")))))
A34: Fondo emergenze | B34: Risparmio e investimenti | C34: Versamenti sul conto di riserva. | D34: =IF(AND(A34="",B34=""),"",IF(A34="","Manca il nome",IF(OR(ISNUMBER(FIND("*",A34)),ISNUMBER(FIND("?",A34)),ISNUMBER(FIND("~",A34)),ISNUMBER(FIND(LEFT(A34,1),"<>="))),"Simbolo non ammesso",IF(COUNTIF($A$6:$A$65,A34)>1,"Nome doppio",IF(B34="","Manca il tipo","")))))
A35: Obiettivi di risparmio | B35: Risparmio e investimenti | C35: Versamenti per gli obiettivi del foglio Obiettivi. | D35: =IF(AND(A35="",B35=""),"",IF(A35="","Manca il nome",IF(OR(ISNUMBER(FIND("*",A35)),ISNUMBER(FIND("?",A35)),ISNUMBER(FIND("~",A35)),ISNUMBER(FIND(LEFT(A35,1),"<>="))),"Simbolo non ammesso",IF(COUNTIF($A$6:$A$65,A35)>1,"Nome doppio",IF(B35="","Manca il tipo","")))))
A36: Investimenti | B36: Risparmio e investimenti | C36: Piani di accumulo, titoli, buoni. | D36: =IF(AND(A36="",B36=""),"",IF(A36="","Manca il nome",IF(OR(ISNUMBER(FIND("*",A36)),ISNUMBER(FIND("?",A36)),ISNUMBER(FIND("~",A36)),ISNUMBER(FIND(LEFT(A36,1),"<>="))),"Simbolo non ammesso",IF(COUNTIF($A$6:$A$65,A36)>1,"Nome doppio",IF(B36="","Manca il tipo","")))))
A37: Previdenza complementare | B37: Risparmio e investimenti | C37: Versamenti volontari al fondo pensione. | D37: =IF(AND(A37="",B37=""),"",IF(A37="","Manca il nome",IF(OR(ISNUMBER(FIND("*",A37)),ISNUMBER(FIND("?",A37)),ISNUMBER(FIND("~",A37)),ISNUMBER(FIND(LEFT(A37,1),"<>="))),"Simbolo non ammesso",IF(COUNTIF($A$6:$A$65,A37)>1,"Nome doppio",IF(B37="","Manca il tipo","")))))
D38: =IF(AND(A38="",B38=""),"",IF(A38="","Manca il nome",IF(OR(ISNUMBER(FIND("*",A38)),ISNUMBER(FIND("?",A38)),ISNUMBER(FIND("~",A38)),ISNUMBER(FIND(LEFT(A38,1),"<>="))),"Simbolo non ammesso",IF(COUNTIF($A$6:$A$65,A38)>1,"Nome doppio",IF(B38="","Manca il tipo","")))))
D39: =IF(AND(A39="",B39=""),"",IF(A39="","Manca il nome",IF(OR(ISNUMBER(FIND("*",A39)),ISNUMBER(FIND("?",A39)),ISNUMBER(FIND("~",A39)),ISNUMBER(FIND(LEFT(A39,1),"<>="))),"Simbolo non ammesso",IF(COUNTIF($A$6:$A$65,A39)>1,"Nome doppio",IF(B39="","Manca il tipo","")))))
D40: =IF(AND(A40="",B40=""),"",IF(A40="","Manca il nome",IF(OR(ISNUMBER(FIND("*",A40)),ISNUMBER(FIND("?",A40)),ISNUMBER(FIND("~",A40)),ISNUMBER(FIND(LEFT(A40,1),"<>="))),"Simbolo non ammesso",IF(COUNTIF($A$6:$A$65,A40)>1,"Nome doppio",IF(B40="","Manca il tipo","")))))
D41: =IF(AND(A41="",B41=""),"",IF(A41="","Manca il nome",IF(OR(ISNUMBER(FIND("*",A41)),ISNUMBER(FIND("?",A41)),ISNUMBER(FIND("~",A41)),ISNUMBER(FIND(LEFT(A41,1),"<>="))),"Simbolo non ammesso",IF(COUNTIF($A$6:$A$65,A41)>1,"Nome doppio",IF(B41="","Manca il tipo","")))))
D42: =IF(AND(A42="",B42=""),"",IF(A42="","Manca il nome",IF(OR(ISNUMBER(FIND("*",A42)),ISNUMBER(FIND("?",A42)),ISNUMBER(FIND("~",A42)),ISNUMBER(FIND(LEFT(A42,1),"<>="))),"Simbolo non ammesso",IF(COUNTIF($A$6:$A$65,A42)>1,"Nome doppio",IF(B42="","Manca il tipo","")))))
D43: =IF(AND(A43="",B43=""),"",IF(A43="","Manca il nome",IF(OR(ISNUMBER(FIND("*",A43)),ISNUMBER(FIND("?",A43)),ISNUMBER(FIND("~",A43)),ISNUMBER(FIND(LEFT(A43,1),"<>="))),"Simbolo non ammesso",IF(COUNTIF($A$6:$A$65,A43)>1,"Nome doppio",IF(B43="","Manca il tipo","")))))
D44: =IF(AND(A44="",B44=""),"",IF(A44="","Manca il nome",IF(OR(ISNUMBER(FIND("*",A44)),ISNUMBER(FIND("?",A44)),ISNUMBER(FIND("~",A44)),ISNUMBER(FIND(LEFT(A44,1),"<>="))),"Simbolo non ammesso",IF(COUNTIF($A$6:$A$65,A44)>1,"Nome doppio",IF(B44="","Manca il tipo","")))))
D45: =IF(AND(A45="",B45=""),"",IF(A45="","Manca il nome",IF(OR(ISNUMBER(FIND("*",A45)),ISNUMBER(FIND("?",A45)),ISNUMBER(FIND("~",A45)),ISNUMBER(FIND(LEFT(A45,1),"<>="))),"Simbolo non ammesso",IF(COUNTIF($A$6:$A$65,A45)>1,"Nome doppio",IF(B45="","Manca il tipo","")))))
D46: =IF(AND(A46="",B46=""),"",IF(A46="","Manca il nome",IF(OR(ISNUMBER(FIND("*",A46)),ISNUMBER(FIND("?",A46)),ISNUMBER(FIND("~",A46)),ISNUMBER(FIND(LEFT(A46,1),"<>="))),"Simbolo non ammesso",IF(COUNTIF($A$6:$A$65,A46)>1,"Nome doppio",IF(B46="","Manca il tipo","")))))
D47: =IF(AND(A47="",B47=""),"",IF(A47="","Manca il nome",IF(OR(ISNUMBER(FIND("*",A47)),ISNUMBER(FIND("?",A47)),ISNUMBER(FIND("~",A47)),ISNUMBER(FIND(LEFT(A47,1),"<>="))),"Simbolo non ammesso",IF(COUNTIF($A$6:$A$65,A47)>1,"Nome doppio",IF(B47="","Manca il tipo","")))))
D48: =IF(AND(A48="",B48=""),"",IF(A48="","Manca il nome",IF(OR(ISNUMBER(FIND("*",A48)),ISNUMBER(FIND("?",A48)),ISNUMBER(FIND("~",A48)),ISNUMBER(FIND(LEFT(A48,1),"<>="))),"Simbolo non ammesso",IF(COUNTIF($A$6:$A$65,A48)>1,"Nome doppio",IF(B48="","Manca il tipo","")))))
D49: =IF(AND(A49="",B49=""),"",IF(A49="","Manca il nome",IF(OR(ISNUMBER(FIND("*",A49)),ISNUMBER(FIND("?",A49)),ISNUMBER(FIND("~",A49)),ISNUMBER(FIND(LEFT(A49,1),"<>="))),"Simbolo non ammesso",IF(COUNTIF($A$6:$A$65,A49)>1,"Nome doppio",IF(B49="","Manca il tipo","")))))
... D65: =IF(AND(A65="",B65=""),"",IF(A65="","Manca il nome",IF(OR(ISNUMBER(FIND("*",A65)),ISNUMBER(FIND("?",A65)),ISNUMBER(FIND("~",A65)),ISNUMBER(FIND(LEFT(A65,1),"<>="))),"Simbolo non ammesso",IF(COUNTIF($A$6:$A$65,A65)>1,"Nome doppio",IF(B65="","Manca il tipo","")))))

Sheet Movimenti
A1: Movimenti
A2: Un movimento per riga. Importi sempre positivi: il tipo lo decide la categoria. Un rimborso su una spesa si scrive in negativo.
C3: Movimenti registrati | D3: =COUNT(D6:D2005) | G3: Righe da controllare | H3: =COUNTIF(H6:H2005,"?*")
A5: Data | B5: Descrizione | C5: Categoria | D5: Importo | E5: Conto o metodo | F5: Chi (facoltativo) | G5: Tipo | H5: Controllo
A6: 46023 | B6: Rata mutuo | C6: Affitto o rata mutuo | D6: 680 | E6: Conto corrente | G6: =IF(C6="","",IFERROR(INDEX(Categorie!$B$6:$B$65,MATCH(C6,Categorie!$A$6:$A$65,0))&"","")) | H6: =IF(AND(A6="",C6="",D6=""),"",IF(D6="","Manca l'importo",IF(NOT(ISNUMBER(D6)),"Importo non valido",IF(NOT(ISNUMBER(A6)),"Data mancante o non valida",IF(YEAR(A6)<>Impostazioni!$C$4,"Fuori dall'anno",IF(C6="","Manca la categoria",IF(ISNA(MATCH(C6,Categorie!$A$6:$A$65,0)),"Categoria non trovata",IF(G6="","Categoria senza tipo",""))))))))
A7: 46025 | B7: Spesa settimanale | C7: Spesa alimentare | D7: 97.53 | E7: Carta di debito | G7: =IF(C7="","",IFERROR(INDEX(Categorie!$B$6:$B$65,MATCH(C7,Categorie!$A$6:$A$65,0))&"","")) | H7: =IF(AND(A7="",C7="",D7=""),"",IF(D7="","Manca l'importo",IF(NOT(ISNUMBER(D7)),"Importo non valido",IF(NOT(ISNUMBER(A7)),"Data mancante o non valida",IF(YEAR(A7)<>Impostazioni!$C$4,"Fuori dall'anno",IF(C7="","Manca la categoria",IF(ISNA(MATCH(C7,Categorie!$A$6:$A$65,0)),"Categoria non trovata",IF(G7="","Categoria senza tipo",""))))))))
A8: 46025 | B8: Abbonamento bus Sofia | C8: Trasporti | D8: 25 | E8: Carta di debito | F8: Sofia | G8: =IF(C8="","",IFERROR(INDEX(Categorie!$B$6:$B$65,MATCH(C8,Categorie!$A$6:$A$65,0))&"","")) | H8: =IF(AND(A8="",C8="",D8=""),"",IF(D8="","Manca l'importo",IF(NOT(ISNUMBER(D8)),"Importo non valido",IF(NOT(ISNUMBER(A8)),"Data mancante o non valida",IF(YEAR(A8)<>Impostazioni!$C$4,"Fuori dall'anno",IF(C8="","Manca la categoria",IF(ISNA(MATCH(C8,Categorie!$A$6:$A$65,0)),"Categoria non trovata",IF(G8="","Categoria senza tipo",""))))))))
A9: 46026 | B9: Mensa scolastica | C9: Scuola e figli | D9: 78 | E9: Conto corrente | F9: Sofia | G9: =IF(C9="","",IFERROR(INDEX(Categorie!$B$6:$B$65,MATCH(C9,Categorie!$A$6:$A$65,0))&"","")) | H9: =IF(AND(A9="",C9="",D9=""),"",IF(D9="","Manca l'importo",IF(NOT(ISNUMBER(D9)),"Importo non valido",IF(NOT(ISNUMBER(A9)),"Data mancante o non valida",IF(YEAR(A9)<>Impostazioni!$C$4,"Fuori dall'anno",IF(C9="","Manca la categoria",IF(ISNA(MATCH(C9,Categorie!$A$6:$A$65,0)),"Categoria non trovata",IF(G9="","Categoria senza tipo",""))))))))
A10: 46026 | B10: Cena con amici | C10: Svago | D10: 48.88 | E10: Carta di debito | G10: =IF(C10="","",IFERROR(INDEX(Categorie!$B$6:$B$65,MATCH(C10,Categorie!$A$6:$A$65,0))&"","")) | H10: =IF(AND(A10="",C10="",D10=""),"",IF(D10="","Manca l'importo",IF(NOT(ISNUMBER(D10)),"Importo non valido",IF(NOT(ISNUMBER(A10)),"Data mancante o non valida",IF(YEAR(A10)<>Impostazioni!$C$4,"Fuori dall'anno",IF(C10="","Manca la categoria",IF(ISNA(MATCH(C10,Categorie!$A$6:$A$65,0)),"Categoria non trovata",IF(G10="","Categoria senza tipo",""))))))))
A11: 46027 | B11: Rifornimento | C11: Carburante | D11: 58.64 | E11: Carta di credito | F11: Marco | G11: =IF(C11="","",IFERROR(INDEX(Categorie!$B$6:$B$65,MATCH(C11,Categorie!$A$6:$A$65,0))&"","")) | H11: =IF(AND(A11="",C11="",D11=""),"",IF(D11="","Manca l'importo",IF(NOT(ISNUMBER(D11)),"Importo non valido",IF(NOT(ISNUMBER(A11)),"Data mancante o non valida",IF(YEAR(A11)<>Impostazioni!$C$4,"Fuori dall'anno",IF(C11="","Manca la categoria",IF(ISNA(MATCH(C11,Categorie!$A$6:$A$65,0)),"Categoria non trovata",IF(G11="","Categoria senza tipo",""))))))))
A12: 46027 | B12: Fibra casa | C12: Internet e telefono | D12: 27.9 | E12: Carta di credito | G12: =IF(C12="","",IFERROR(INDEX(Categorie!$B$6:$B$65,MATCH(C12,Categorie!$A$6:$A$65,0))&"","")) | H12: =IF(AND(A12="",C12="",D12=""),"",IF(D12="","Manca l'importo",IF(NOT(ISNUMBER(D12)),"Importo non valido",IF(NOT(ISNUMBER(A12)),"Data mancante o non valida",IF(YEAR(A12)<>Impostazioni!$C$4,"Fuori dall'anno",IF(C12="","Manca la categoria",IF(ISNA(MATCH(C12,Categorie!$A$6:$A$65,0)),"Categoria non trovata",IF(G12="","Categoria senza tipo",""))))))))
A13: 46027 | B13: Telefono Giulia | C13: Internet e telefono | D13: 7.99 | E13: Carta di credito | F13: Giulia | G13: =IF(C13="","",IFERROR(INDEX(Categorie!$B$6:$B$65,MATCH(C13,Categorie!$A$6:$A$65,0))&"","")) | H13: =IF(AND(A13="",C13="",D13=""),"",IF(D13="","Manca l'importo",IF(NOT(ISNUMBER(D13)),"Importo non valido",IF(NOT(ISNUMBER(A13)),"Data mancante o non valida",IF(YEAR(A13)<>Impostazioni!$C$4,"Fuori dall'anno",IF(C13="","Manca la categoria",IF(ISNA(MATCH(C13,Categorie!$A$6:$A$65,0)),"Categoria non trovata",IF(G13="","Categoria senza tipo",""))))))))
A14: 46027 | B14: Telefono Marco | C14: Internet e telefono | D14: 9.99 | E14: Carta di credito | F14: Marco | G14: =IF(C14="","",IFERROR(INDEX(Categorie!$B$6:$B$65,MATCH(C14,Categorie!$A$6:$A$65,0))&"","")) | H14: =IF(AND(A14="",C14="",D14=""),"",IF(D14="","Manca l'importo",IF(NOT(ISNUMBER(D14)),"Importo non valido",IF(NOT(ISNUMBER(A14)),"Data mancante o non valida",IF(YEAR(A14)<>Impostazioni!$C$4,"Fuori dall'anno",IF(C14="","Manca la categoria",IF(ISNA(MATCH(C14,Categorie!$A$6:$A$65,0)),"Categoria non trovata",IF(G14="","Categoria senza tipo",""))))))))
A15: 46029 | B15: Spesa al mercato | C15: Spesa alimentare | D15: 29.66 | E15: Contanti | G15: =IF(C15="","",IFERROR(INDEX(Categorie!$B$6:$B$65,MATCH(C15,Categorie!$A$6:$A$65,0))&"","")) | H15: =IF(AND(A15="",C15="",D15=""),"",IF(D15="","Manca l'importo",IF(NOT(ISNUMBER(D15)),"Importo non valido",IF(NOT(ISNUMBER(A15)),"Data mancante o non valida",IF(YEAR(A15)<>Impostazioni!$C$4,"Fuori dall'anno",IF(C15="","Manca la categoria",IF(ISNA(MATCH(C15,Categorie!$A$6:$A$65,0)),"Categoria non trovata",IF(G15="","Categoria senza tipo",""))))))))
A16: 46030 | B16: Musica in streaming | C16: Abbonamenti | D16: 10.99 | E16: Carta di credito | F16: Giulia | G16: =IF(C16="","",IFERROR(INDEX(Categorie!$B$6:$B$65,MATCH(C16,Categorie!$A$6:$A$65,0))&"","")) | H16: =IF(AND(A16="",C16="",D16=""),"",IF(D16="","Manca l'importo",IF(NOT(ISNUMBER(D16)),"Importo non valido",IF(NOT(ISNUMBER(A16)),"Data mancante o non valida",IF(YEAR(A16)<>Impostazioni!$C$4,"Fuori dall'anno",IF(C16="","Manca la categoria",IF(ISNA(MATCH(C16,Categorie!$A$6:$A$65,0)),"Categoria non trovata",IF(G16="","Categoria senza tipo",""))))))))
A17: 46030 | B17: Streaming video | C17: Abbonamenti | D17: 13.99 | E17: Carta di credito | G17: =IF(C17="","",IFERROR(INDEX(Categorie!$B$6:$B$65,MATCH(C17,Categorie!$A$6:$A$65,0))&"","")) | H17: =IF(AND(A17="",C17="",D17=""),"",IF(D17="","Manca l'importo",IF(NOT(ISNUMBER(D17)),"Importo non valido",IF(NOT(ISNUMBER(A17)),"Data mancante o non valida",IF(YEAR(A17)<>Impostazioni!$C$4,"Fuori dall'anno",IF(C17="","Manca la categoria",IF(ISNA(MATCH(C17,Categorie!$A$6:$A$65,0)),"Categoria non trovata",IF(G17="","Categoria senza tipo",""))))))))
A18: 46031 | B18: Parcheggio | C18: Trasporti | D18: 8.26 | E18: Contanti | G18: =IF(C18="","",IFERROR(INDEX(Categorie!$B$6:$B$65,MATCH(C18,Categorie!$A$6:$A$65,0))&"","")) | H18: =IF(AND(A18="",C18="",D18=""),"",IF(D18="","Manca l'importo",IF(NOT(ISNUMBER(D18)),"Importo non valido",IF(NOT(ISNUMBER(A18)),"Data mancante o non valida",IF(YEAR(A18)<>Impostazioni!$C$4,"Fuori dall'anno",IF(C18="","Manca la categoria",IF(ISNA(MATCH(C18,Categorie!$A$6:$A$65,0)),"Categoria non trovata",IF(G18="","Categoria senza tipo",""))))))))
A19: 46032 | B19: Saldi invernali | C19: Abbigliamento | D19: 142.8 | E19: Carta di credito | F19: Giulia | G19: =IF(C19="","",IFERROR(INDEX(Categorie!$B$6:$B$65,MATCH(C19,Categorie!$A$6:$A$65,0))&"","")) | H19: =IF(AND(A19="",C19="",D19=""),"",IF(D19="","Manca l'importo",IF(NOT(ISNUMBER(D19)),"Importo non valido",IF(NOT(ISNUMBER(A19)),"Data mancante o non valida",IF(YEAR(A19)<>Impostazioni!$C$4,"Fuori dall'anno",IF(C19="","Manca la categoria",IF(ISNA(MATCH(C19,Categorie!$A$6:$A$65,0)),"Categoria non trovata",IF(G19="","Categoria senza tipo",""))))))))
A20: 46032 | B20: Rata condominio trimestrale | C20: Condominio | D20: 270 | E20: Conto corrente | G20: =IF(C20="","",IFERROR(INDEX(Categorie!$B$6:$B$65,MATCH(C20,Categorie!$A$6:$A$65,0))&"","")) | H20: =IF(AND(A20="",C20="",D20=""),"",IF(D20="","Manca l'importo",IF(NOT(ISNUMBER(D20)),"Importo non valido",IF(NOT(ISNUMBER(A20)),"Data mancante o non valida",IF(YEAR(A20)<>Impostazioni!$C$4,"Fuori dall'anno",IF(C20="","Manca la categoria",IF(ISNA(MATCH(C20,Categorie!$A$6:$A$65,0)),"Categoria non trovata",IF(G20="","Categoria senza tipo",""))))))))
A21: 46032 | B21: Spesa settimanale | C21: Spesa alimentare | D21: 100.34 | E21: Carta di debito | G21: =IF(C21="","",IFERROR(INDEX(Categorie!$B$6:$B$65,MATCH(C21,Categorie!$A$6:$A$65,0))&"","")) | H21: =IF(AND(A21="",C21="",D21=""),"",IF(D21="","Manca l'importo",IF(NOT(ISNUMBER(D21)),"Importo non valido",IF(NOT(ISNUMBER(A21)),"Data mancante o non valida",IF(YEAR(A21)<>Impostazioni!$C$4,"Fuori dall'anno",IF(C21="","Manca la categoria",IF(ISNA(MATCH(C21,Categorie!$A$6:$A$65,0)),"Categoria non trovata",IF(G21="","Categoria senza tipo",""))))))))
A22: 46034 | B22: Corso di nuoto Sofia | C22: Scuola e figli | D22: 165 | E22: Carta di debito | F22: Sofia | G22: =IF(C22="","",IFERROR(INDEX(Categorie!$B$6:$B$65,MATCH(C22,Categorie!$A$6:$A$65,0))&"","")) | H22: =IF(AND(A22="",C22="",D22=""),"",IF(D22="","Manca l'importo",IF(NOT(ISNUMBER(D22)),"Importo non valido",IF(NOT(ISNUMBER(A22)),"Data mancante o non valida",IF(YEAR(A22)<>Impostazioni!$C$4,"Fuori dall'anno",IF(C22="","Manca la categoria",IF(ISNA(MATCH(C22,Categorie!$A$6:$A$65,0)),"Categoria non trovata",IF(G22="","Categoria senza tipo",""))))))))
A23: 46037 | B23: Rata carta revolving | C23: Rate di prestiti | D23: 60 | E23: Conto corrente | G23: =IF(C23="","",IFERROR(INDEX(Categorie!$B$6:$B$65,MATCH(C23,Categorie!$A$6:$A$65,0))&"","")) | H23: =IF(AND(A23="",C23="",D23=""),"",IF(D23="","Manca l'importo",IF(NOT(ISNUMBER(D23)),"Importo non valido",IF(NOT(ISNUMBER(A23)),"Data mancante o non valida",IF(YEAR(A23)<>Impostazioni!$C$4,"Fuori dall'anno",IF(C23="","Manca la categoria",IF(ISNA(MATCH(C23,Categorie!$A$6:$A$65,0)),"Categoria non trovata",IF(G23="","Categoria senza tipo",""))))))))
A24: 46037 | B24: Rata lavatrice a tasso zero | C24: Rate di prestiti | D24: 40 | E24: Conto corrente | G24: =IF(C24="","",IFERROR(INDEX(Categorie!$B$6:$B$65,MATCH(C24,Categorie!$A$6:$A$65,0))&"","")) | H24: =IF(AND(A24="",C24="",D24=""),"",IF(D24="","Manca l'importo",IF(NOT(ISNUMBER(D24)),"Importo non valido",IF(NOT(ISNUMBER(A24)),"Data mancante o non valida",IF(YEAR(A24)<>Impostazioni!$C$4,"Fuori dall'anno",IF(C24="","Manca la categoria",IF(ISNA(MATCH(C24,Categorie!$A$6:$A$65,0)),"Categoria non trovata",IF(G24="","Categoria senza tipo",""))))))))
A25: 46037 | B25: Rata prestito auto | C25: Rate di prestiti | D25: 210 | E25: Conto corrente | G25: =IF(C25="","",IFERROR(INDEX(Categorie!$B$6:$B$65,MATCH(C25,Categorie!$A$6:$A$65,0))&"","")) | H25: =IF(AND(A25="",C25="",D25=""),"",IF(D25="","Manca l'importo",IF(NOT(ISNUMBER(D25)),"Importo non valido",IF(NOT(ISNUMBER(A25)),"Data mancante o non valida",IF(YEAR(A25)<>Impostazioni!$C$4,"Fuori dall'anno",IF(C25="","Manca la categoria",IF(ISNA(MATCH(C25,Categorie!$A$6:$A$65,0)),"Categoria non trovata",IF(G25="","Categoria senza tipo",""))))))))
A26: 46038 | B26: Cena con amici | C26: Svago | D26: 53.4 | E26: Carta di debito | G26: =IF(C26="","",IFERROR(INDEX(Categorie!$B$6:$B$65,MATCH(C26,Categorie!$A$6:$A$65,0))&"","")) | H26: =IF(AND(A26="",C26="",D26=""),"",IF(D26="","Manca l'importo",IF(NOT(ISNUMBER(D26)),"Importo non valido",IF(NOT(ISNUMBER(A26)),"Data mancante o non valida",IF(YEAR(A26)<>Impostazioni!$C$4,"Fuori dall'anno",IF(C26="","Manca la categoria",IF(ISNA(MATCH(C26,Categorie!$A$6:$A$65,0)),"Categoria non trovata",IF(G26="","Categoria senza tipo",""))))))))
A27: 46038 | B27: Pizzeria | C27: Svago | D27: 38.28 | E27: Carta di debito | G27: =IF(C27="","",IFERROR(INDEX(Categorie!$B$6:$B$65,MATCH(C27,Categorie!$A$6:$A$65,0))&"","")) | H27: =IF(AND(A27="",C27="",D27=""),"",IF(D27="","Manca l'importo",IF(NOT(ISNUMBER(D27)),"Importo non valido",IF(NOT(ISNUMBER(A27)),"Data mancante o non valida",IF(YEAR(A27)<>Impostazioni!$C$4,"Fuori dall'anno",IF(C27="","Manca la categoria",IF(ISNA(MATCH(C27,Categorie!$A$6:$A$65,0)),"Categoria non trovata",IF(G27="","Categoria senza tipo",""))))))))
A28: 46039 | B28: Rifornimento | C28: Carburante | D28: 55.83 | E28: Carta di credito | F28: Giulia | G28: =IF(C28="","",IFERROR(INDEX(Categorie!$B$6:$B$65,MATCH(C28,Categorie!$A$6:$A$65,0))&"","")) | H28: =IF(AND(A28="",C28="",D28=""),"",IF(D28="","Manca l'importo",IF(NOT(ISNUMBER(D28)),"Importo non valido",IF(NOT(ISNUMBER(A28)),"Data mancante o non valida",IF(YEAR(A28)<>Impostazioni!$C$4,"Fuori dall'anno",IF(C28="","Manca la categoria",IF(ISNA(MATCH(C28,Categorie!$A$6:$A$65,0)),"Categoria non trovata",IF(G28="","Categoria senza tipo",""))))))))
A29: 46039 | B29: Spesa settimanale | C29: Spesa alimentare | D29: 121.05 | E29: Carta di debito | G29: =IF(C29="","",IFERROR(INDEX(Categorie!$B$6:$B$65,MATCH(C29,Categorie!$A$6:$A$65,0))&"","")) | H29: =IF(AND(A29="",C29="",D29=""),"",IF(D29="","Manca l'importo",IF(NOT(ISNUMBER(D29)),"Importo non valido",IF(NOT(ISNUMBER(A29)),"Data mancante o non valida",IF(YEAR(A29)<>Impostazioni!$C$4,"Fuori dall'anno",IF(C29="","Manca la categoria",IF(ISNA(MATCH(C29,Categorie!$A$6:$A$65,0)),"Categoria non trovata",IF(G29="","Categoria senza tipo",""))))))))
A30: 46039 | B30: Libri | C30: Svago | D30: 22.87 | E30: Carta di debito | G30: =IF(C30="","",IFERROR(INDEX(Categorie!$B$6:$B$65,MATCH(C30,Categorie!$A$6:$A$65,0))&"","")) | H30: =IF(AND(A30="",C30="",D30=""),"",IF(D30="","Manca l'importo",IF(NOT(ISNUMBER(D30)),"Importo non valido",IF(NOT(ISNUMBER(A30)),"Data mancante o non valida",IF(YEAR(A30)<>Impostazioni!$C$4,"Fuori dall'anno",IF(C30="","Manca la categoria",IF(ISNA(MATCH(C30,Categorie!$A$6:$A$65,0)),"Categoria non trovata",IF(G30="","Categoria senza tipo",""))))))))
A31: 46040 | B31: Bolletta gas | C31: Gas | D31: 168.03 | E31: Conto corrente | G31: =IF(C31="","",IFERROR(INDEX(Categorie!$B$6:$B$65,MATCH(C31,Categorie!$A$6:$A$65,0))&"","")) | H31: =IF(AND(A31="",C31="",D31=""),"",IF(D31="","Manca l'importo",IF(NOT(ISNUMBER(D31)),"Importo non valido",IF(NOT(ISNUMBER(A31)),"Data mancante o non valida",IF(YEAR(A31)<>Impostazioni!$C$4,"Fuori dall'anno",IF(C31="","Manca la categoria",IF(ISNA(MATCH(C31,Categorie!$A$6:$A$65,0)),"Categoria non trovata",IF(G31="","Categoria senza tipo",""))))))))
A32: 46040 | B32: Bolletta luce | C32: Luce | D32: 78.95 | E32: Conto corrente | G32: =IF(C32="","",IFERROR(INDEX(Categorie!$B$6:$B$65,MATCH(C32,Categorie!$A$6:$A$65,0))&"","")) | H32: =IF(AND(A32="",C32="",D32=""),"",IF(D32="","Manca l'importo",IF(NOT(ISNUMBER(D32)),"Importo non valido",IF(NOT(ISNUMBER(A32)),"Data mancante o non valida",IF(YEAR(A32)<>Impostazioni!$C$4,"Fuori dall'anno",IF(C32="","Manca la categoria",IF(ISNA(MATCH(C32,Categorie!$A$6:$A$65,0)),"Categoria non trovata",IF(G32="","Categoria senza tipo",""))))))))
A33: 46041 | B33: Farmacia | C33: Farmacia e salute | D33: 19.46 | E33: Carta di debito | G33: =IF(C33="","",IFERROR(INDEX(Categorie!$B$6:$B$65,MATCH(C33,Categorie!$A$6:$A$65,0))&"","")) | H33: =IF(AND(A33="",C33="",D33=""),"",IF(D33="","Manca l'importo",IF(NOT(ISNUMBER(D33)),"Importo non valido",IF(NOT(ISNUMBER(A33)),"Data mancante o non valida",IF(YEAR(A33)<>Impostazioni!$C$4,"Fuori dall'anno",IF(C33="","Manca la categoria",IF(ISNA(MATCH(C33,Categorie!$A$6:$A$65,0)),"Categoria non trovata",IF(G33="","Categoria senza tipo",""))))))))
A34: 46042 | B34: Assegno unico INPS | C34: Assegno unico figli | D34: 145.3 | E34: Conto corrente | G34: =IF(C34="","",IFERROR(INDEX(Categorie!$B$6:$B$65,MATCH(C34,Categorie!$A$6:$A$65,0))&"","")) | H34: =IF(AND(A34="",C34="",D34=""),"",IF(D34="","Manca l'importo",IF(NOT(ISNUMBER(D34)),"Importo non valido",IF(NOT(ISNUMBER(A34)),"Data mancante o non valida",IF(YEAR(A34)<>Impostazioni!$C$4,"Fuori dall'anno",IF(C34="","Manca la categoria",IF(ISNA(MATCH(C34,Categorie!$A$6:$A$65,0)),"Categoria non trovata",IF(G34="","Categoria senza tipo",""))))))))
A35: 46042 | B35: Farmacia | C35: Farmacia e salute | D35: 23.53 | E35: Carta di debito | G35: =IF(C35="","",IFERROR(INDEX(Categorie!$B$6:$B$65,MATCH(C35,Categorie!$A$6:$A$65,0))&"","")) | H35: =IF(AND(A35="",C35="",D35=""),"",IF(D35="","Manca l'importo",IF(NOT(ISNUMBER(D35)),"Importo non valido",IF(NOT(ISNUMBER(A35)),"Data mancante o non valida",IF(YEAR(A35)<>Impostazioni!$C$4,"Fuori dall'anno",IF(C35="","Manca la categoria",IF(ISNA(MATCH(C35,Categorie!$A$6:$A$65,0)),"Categoria non trovata",IF(G35="","Categoria senza tipo",""))))))))
A36: 46043 | B36: Spesa al mercato | C36: Spesa alimentare | D36: 32.08 | E36: Contanti | G36: =IF(C36="","",IFERROR(INDEX(Categorie!$B$6:$B$65,MATCH(C36,Categorie!$A$6:$A$65,0))&"","")) | H36: =IF(AND(A36="",C36="",D36=""),"",IF(D36="","Manca l'importo",IF(NOT(ISNUMBER(D36)),"Importo non valido",IF(NOT(ISNUMBER(A36)),"Data mancante o non valida",IF(YEAR(A36)<>Impostazioni!$C$4,"Fuori dall'anno",IF(C36="","Manca la categoria",IF(ISNA(MATCH(C36,Categorie!$A$6:$A$65,0)),"Categoria non trovata",IF(G36="","Categoria senza tipo",""))))))))
A37: 46046 | B37: Spesa settimanale | C37: Spesa alimentare | D37: 113.07 | E37: Carta di debito | G37: =IF(C37="","",IFERROR(INDEX(Categorie!$B$6:$B$65,MATCH(C37,Categorie!$A$6:$A$65,0))&"","")) | H37: =IF(AND(A37="",C37="",D37=""),"",IF(D37="","Manca l'importo",IF(NOT(ISNUMBER(D37)),"Importo non valido",IF(NOT(ISNUMBER(A37)),"Data mancante o non valida",IF(YEAR(A37)<>Impostazioni!$C$4,"Fuori dall'anno",IF(C37="","Manca la categoria",IF(ISNA(MATCH(C37,Categorie!$A$6:$A$65,0)),"Categoria non trovata",IF(G37="","Categoria senza tipo",""))))))))
A38: 46047 | B38: Farmacia | C38: Farmacia e salute | D38: 30.85 | E38: Carta di debito | G38: =IF(C38="","",IFERROR(INDEX(Categorie!$B$6:$B$65,MATCH(C38,Categorie!$A$6:$A$65,0))&"","")) | H38: =IF(AND(A38="",C38="",D38=""),"",IF(D38="","Manca l'importo",IF(NOT(ISNUMBER(D38)),"Importo non valido",IF(NOT(ISNUMBER(A38)),"Data mancante o non valida",IF(YEAR(A38)<>Impostazioni!$C$4,"Fuori dall'anno",IF(C38="","Manca la categoria",IF(ISNA(MATCH(C38,Categorie!$A$6:$A$65,0)),"Categoria non trovata",IF(G38="","Categoria senza tipo",""))))))))
A39: 46049 | B39: Stipendio | C39: Stipendio Giulia | D39: 1480 | E39: Conto corrente | F39: Giulia | G39: =IF(C39="","",IFERROR(INDEX(Categorie!$B$6:$B$65,MATCH(C39,Categorie!$A$6:$A$65,0))&"","")) | H39: =IF(AND(A39="",C39="",D39=""),"",IF(D39="","Manca l'importo",IF(NOT(ISNUMBER(D39)),"Importo non valido",IF(NOT(ISNUMBER(A39)),"Data mancante o non valida",IF(YEAR(A39)<>Impostazioni!$C$4,"Fuori dall'anno",IF(C39="","Manca la categoria",IF(ISNA(MATCH(C39,Categorie!$A$6:$A$65,0)),"Categoria non trovata",IF(G39="","Categoria senza tipo",""))))))))
A40: 46049 | B40: Stipendio | C40: Stipendio Marco | D40: 1850 | E40: Conto corrente | F40: Marco | G40: =IF(C40="","",IFERROR(INDEX(Categorie!$B$6:$B$65,MATCH(C40,Categorie!$A$6:$A$65,0))&"","")) | H40: =IF(AND(A40="",C40="",D40=""),"",IF(D40="","Manca l'importo",IF(NOT(ISNUMBER(D40)),"Importo non valido",IF(NOT(ISNUMBER(A40)),"Data mancante o non valida",IF(YEAR(A40)<>Impostazioni!$C$4,"Fuori dall'anno",IF(C40="","Manca la categoria",IF(ISNA(MATCH(C40,Categorie!$A$6:$A$65,0)),"Categoria non trovata",IF(G40="","Categoria senza tipo",""))))))))
A41: 46050 | B41: Versamento fondo emergenze | C41: Fondo emergenze | D41: 150 | E41: Conto corrente | G41: =IF(C41="","",IFERROR(INDEX(Categorie!$B$6:$B$65,MATCH(C41,Categorie!$A$6:$A$65,0))&"","")) | H41: =IF(AND(A41="",C41="",D41=""),"",IF(D41="","Manca l'importo",IF(NOT(ISNUMBER(D41)),"Importo non valido",IF(NOT(ISNUMBER(A41)),"Data mancante o non valida",IF(YEAR(A41)<>Impostazioni!$C$4,"Fuori dall'anno",IF(C41="","Manca la categoria",IF(ISNA(MATCH(C41,Categorie!$A$6:$A$65,0)),"Categoria non trovata",IF(G41="","Categoria senza tipo",""))))))))
A42: 46050 | B42: Piano di accumulo mensile | C42: Investimenti | D42: 100 | E42: Conto corrente | G42: =IF(C42="","",IFERROR(INDEX(Categorie!$B$6:$B$65,MATCH(C42,Categorie!$A$6:$A$65,0))&"","")) | H42: =IF(AND(A42="",C42="",D42=""),"",IF(D42="","Manca l'importo",IF(NOT(ISNUMBER(D42)),"Importo non valido",IF(NOT(ISNUMBER(A42)),"Data mancante o non valida",IF(YEAR(A42)<>Impostazioni!$C$4,"Fuori dall'anno",IF(C42="","Manca la categoria",IF(ISNA(MATCH(C42,Categorie!$A$6:$A$65,0)),"Categoria non trovata",IF(G42="","Categoria senza tipo",""))))))))
A43: 46050 | B43: Accantonamento obiettivi | C43: Obiettivi di risparmio | D43: 200 | E43: Conto corrente | G43: =IF(C43="","",IFERROR(INDEX(Categorie!$B$6:$B$65,MATCH(C43,Categorie!$A$6:$A$65,0))&"","")) | H43: =IF(AND(A43="",C43="",D43=""),"",IF(D43="","Manca l'importo",IF(NOT(ISNUMBER(D43)),"Importo non valido",IF(NOT(ISNUMBER(A43)),"Data mancante o non valida",IF(YEAR(A43)<>Impostazioni!$C$4,"Fuori dall'anno",IF(C43="","Manca la categoria",IF(ISNA(MATCH(C43,Categorie!$A$6:$A$65,0)),"Categoria non trovata",IF(G43="","Categoria senza tipo",""))))))))
A44: 46051 | B44: Rifornimento | C44: Carburante | D44: 62.6 | E44: Carta di credito | F44: Marco | G44: =IF(C44="","",IFERROR(INDEX(Categorie!$B$6:$B$65,MATCH(C44,Categorie!$A$6:$A$65,0))&"","")) | H44: =IF(AND(A44="",C44="",D44=""),"",IF(D44="","Manca l'importo",IF(NOT(ISNUMBER(D44)),"Importo non valido",IF(NOT(ISNUMBER(A44)),"Data mancante o non valida",IF(YEAR(A44)<>Impostazioni!$C$4,"Fuori dall'anno",IF(C44="","Manca la categoria",IF(ISNA(MATCH(C44,Categorie!$A$6:$A$65,0)),"Categoria non trovata",IF(G44="","Categoria senza tipo",""))))))))
A45: 46053 | B45: Spesa settimanale | C45: Spesa alimentare | D45: 112.76 | E45: Carta di debito | G45: =IF(C45="","",IFERROR(INDEX(Categorie!$B$6:$B$65,MATCH(C45,Categorie!$A$6:$A$65,0))&"","")) | H45: =IF(AND(A45="",C45="",D45=""),"",IF(D45="","Manca l'importo",IF(NOT(ISNUMBER(D45)),"Importo non valido",IF(NOT(ISNUMBER(A45)),"Data mancante o non valida",IF(YEAR(A45)<>Impostazioni!$C$4,"Fuori dall'anno",IF(C45="","Manca la categoria",IF(ISNA(MATCH(C45,Categorie!$A$6:$A$65,0)),"Categoria non trovata",IF(G45="","Categoria senza tipo",""))))))))
A46: 46054 | B46: Rata mutuo | C46: Affitto o rata mutuo | D46: 680 | E46: Conto corrente | G46: =IF(C46="","",IFERROR(INDEX(Categorie!$B$6:$B$65,MATCH(C46,Categorie!$A$6:$A$65,0))&"","")) | H46: =IF(AND(A46="",C46="",D46=""),"",IF(D46="","Manca l'importo",IF(NOT(ISNUMBER(D46)),"Importo non valido",IF(NOT(ISNUMBER(A46)),"Data mancante o non valida",IF(YEAR(A46)<>Impostazioni!$C$4,"Fuori dall'anno",IF(C46="","Manca la categoria",IF(ISNA(MATCH(C46,Categorie!$A$6:$A$65,0)),"Categoria non trovata",IF(G46="","Categoria senza tipo",""))))))))
A47: 46055 | B47: Gelateria | C47: Svago | D47: 14.93 | E47: Carta di debito | G47: =IF(C47="","",IFERROR(INDEX(Categorie!$B$6:$B$65,MATCH(C47,Categorie!$A$6:$A$65,0))&"","")) | H47: =IF(AND(A47="",C47="",D47=""),"",IF(D47="","Manca l'importo",IF(NOT(ISNUMBER(D47)),"Importo non valido",IF(NOT(ISNUMBER(A47)),"Data mancante o non valida",IF(YEAR(A47)<>Impostazioni!$C$4,"Fuori dall'anno",IF(C47="","Manca la categoria",IF(ISNA(MATCH(C47,Categorie!$A$6:$A$65,0)),"Categoria non trovata",IF(G47="","Categoria senza tipo",""))))))))
A48: 46056 | B48: Abbonamento bus Sofia | C48: Trasporti | D48: 25 | E48: Carta di debito | F48: Sofia | G48: =IF(C48="","",IFERROR(INDEX(Categorie!$B$6:$B$65,MATCH(C48,Categorie!$A$6:$A$65,0))&"","")) | H48: =IF(AND(A48="",C48="",D48=""),"",IF(D48="","Manca l'importo",IF(NOT(ISNUMBER(D48)),"Importo non valido",IF(NOT(ISNUMBER(A48)),"Data mancante o non valida",IF(YEAR(A48)<>Impostazioni!$C$4,"Fuori dall'anno",IF(C48="","Manca la categoria",IF(ISNA(MATCH(C48,Categorie!$A$6:$A$65,0)),"Categoria non trovata",IF(G48="","Categoria senza tipo",""))))))))
A49: 46057 | B49: Mensa scolastica | C49: Scuola e figli | D49: 78 | E49: Conto corrente | F49: Sofia | G49: =IF(C49="","",IFERROR(INDEX(Categorie!$B$6:$B$65,MATCH(C49,Categorie!$A$6:$A$65,0))&"","")) | H49: =IF(AND(A49="",C49="",D49=""),"",IF(D49="","Manca l'importo",IF(NOT(ISNUMBER(D49)),"Importo non valido",IF(NOT(ISNUMBER(A49)),"Data mancante o non valida",IF(YEAR(A49)<>Impostazioni!$C$4,"Fuori dall'anno",IF(C49="","Manca la categoria",IF(ISNA(MATCH(C49,Categorie!$A$6:$A$65,0)),"Categoria non trovata",IF(G49="","Categoria senza tipo",""))))))))
A50: 46057 | B50: Spesa al mercato | C50: Spesa alimentare | D50: 30.75 | E50: Contanti | G50: =IF(C50="","",IFERROR(INDEX(Categorie!$B$6:$B$65,MATCH(C50,Categorie!$A$6:$A$65,0))&"","")) | H50: =IF(AND(A50="",C50="",D50=""),"",IF(D50="","Manca l'importo",IF(NOT(ISNUMBER(D50)),"Importo non valido",IF(NOT(ISNUMBER(A50)),"Data mancante o non valida",IF(YEAR(A50)<>Impostazioni!$C$4,"Fuori dall'anno",IF(C50="","Manca la categoria",IF(ISNA(MATCH(C50,Categorie!$A$6:$A$65,0)),"Categoria non trovata",IF(G50="","Categoria senza tipo",""))))))))
A51: 46058 | B51: Fibra casa | C51: Internet e telefono | D51: 27.9 | E51: Carta di credito | G51: =IF(C51="","",IFERROR(INDEX(Categorie!$B$6:$B$65,MATCH(C51,Categorie!$A$6:$A$65,0))&"","")) | H51: =IF(AND(A51="",C51="",D51=""),"",IF(D51="","Manca l'importo",IF(NOT(ISNUMBER(D51)),"Importo non valido",IF(NOT(ISNUMBER(A51)),"Data mancante o non valida",IF(YEAR(A51)<>Impostazioni!$C$4,"Fuori dall'anno",IF(C51="","Manca la categoria",IF(ISNA(MATCH(C51,Categorie!$A$6:$A$65,0)),"Categoria non trovata",IF(G51="","Categoria senza tipo",""))))))))
A52: 46058 | B52: Telefono Giulia | C52: Internet e telefono | D52: 7.99 | E52: Carta di credito | F52: Giulia | G52: =IF(C52="","",IFERROR(INDEX(Categorie!$B$6:$B$65,MATCH(C52,Categorie!$A$6:$A$65,0))&"","")) | H52: =IF(AND(A52="",C52="",D52=""),"",IF(D52="","Manca l'importo",IF(NOT(ISNUMBER(D52)),"Importo non valido",IF(NOT(ISNUMBER(A52)),"Data mancante o non valida",IF(YEAR(A52)<>Impostazioni!$C$4,"Fuori dall'anno",IF(C52="","Manca la categoria",IF(ISNA(MATCH(C52,Categorie!$A$6:$A$65,0)),"Categoria non trovata",IF(G52="","Categoria senza tipo",""))))))))
A53: 46058 | B53: Telefono Marco | C53: Internet e telefono | D53: 9.99 | E53: Carta di credito | F53: Marco | G53: =IF(C53="","",IFERROR(INDEX(Categorie!$B$6:$B$65,MATCH(C53,Categorie!$A$6:$A$65,0))&"","")) | H53: =IF(AND(A53="",C53="",D53=""),"",IF(D53="","Manca l'importo",IF(NOT(ISNUMBER(D53)),"Importo non valido",IF(NOT(ISNUMBER(A53)),"Data mancante o non valida",IF(YEAR(A53)<>Impostazioni!$C$4,"Fuori dall'anno",IF(C53="","Manca la categoria",IF(ISNA(MATCH(C53,Categorie!$A$6:$A$65,0)),"Categoria non trovata",IF(G53="","Categoria senza tipo",""))))))))
A54: 46060 | B54: Ferramenta | C54: Casa e manutenzione | D54: 23.5 | E54: Contanti | G54: =IF(C54="","",IFERROR(INDEX(Categorie!$B$6:$B$65,MATCH(C54,Categorie!$A$6:$A$65,0))&"","")) | H54: =IF(AND(A54="",C54="",D54=""),"",IF(D54="","Manca l'importo",IF(NOT(ISNUMBER(D54)),"Importo non valido",IF(NOT(ISNUMBER(A54)),"Data mancante o non valida",IF(YEAR(A54)<>Impostazioni!$C$4,"Fuori dall'anno",IF(C54="","Manca la categoria",IF(ISNA(MATCH(C54,Categorie!$A$6:$A$65,0)),"Categoria non trovata",IF(G54="","Categoria senza tipo",""))))))))
A55: 46060 | B55: Spesa settimanale | C55: Spesa alimentare | D55: 93.84 | E55: Carta di debito | G55: =IF(C55="","",IFERROR(INDEX(Categorie!$B$6:$B$65,MATCH(C55,Categorie!$A$6:$A$65,0))&"","")) | H55: =IF(AND(A55="",C55="",D55=""),"",IF(D55="","Manca l'importo",IF(NOT(ISNUMBER(D55)),"Importo non valido",IF(NOT(ISNUMBER(A55)),"Data mancante o non valida",IF(YEAR(A55)<>Impostazioni!$C$4,"Fuori dall'anno",IF(C55="","Manca la categoria",IF(ISNA(MATCH(C55,Categorie!$A$6:$A$65,0)),"Categoria non trovata",IF(G55="","Categoria senza tipo",""))))))))
A56: 46061 | B56: Musica in streaming | C56: Abbonamenti | D56: 10.99 | E56: Carta di credito | F56: Giulia | G56: =IF(C56="","",IFERROR(INDEX(Categorie!$B$6:$B$65,MATCH(C56,Categorie!$A$6:$A$65,0))&"","")) | H56: =IF(AND(A56="",C56="",D56=""),"",IF(D56="","Manca l'importo",IF(NOT(ISNUMBER(D56)),"Importo non valido",IF(NOT(ISNUMBER(A56)),"Data mancante o non valida",IF(YEAR(A56)<>Impostazioni!$C$4,"Fuori dall'anno",IF(C56="","Manca la categoria",IF(ISNA(MATCH(C56,Categorie!$A$6:$A$65,0)),"Categoria non trovata",IF(G56="","Categoria senza tipo",""))))))))
A57: 46061 | B57: Streaming video | C57: Abbonamenti | D57: 13.99 | E57: Carta di credito | G57: =IF(C57="","",IFERROR(INDEX(Categorie!$B$6:$B$65,MATCH(C57,Categorie!$A$6:$A$65,0))&"","")) | H57: =IF(AND(A57="",C57="",D57=""),"",IF(D57="","Manca l'importo",IF(NOT(ISNUMBER(D57)),"Importo non valido",IF(NOT(ISNUMBER(A57)),"Data mancante o non valida",IF(YEAR(A57)<>Impostazioni!$C$4,"Fuori dall'anno",IF(C57="","Manca la categoria",IF(ISNA(MATCH(C57,Categorie!$A$6:$A$65,0)),"Categoria non trovata",IF(G57="","Categoria senza tipo",""))))))))
A58: 46061 | B58: Rifornimento | C58: Carburante | D58: 54.94 | E58: Carta di credito | F58: Giulia | G58: =IF(C58="","",IFERROR(INDEX(Categorie!$B$6:$B$65,MATCH(C58,Categorie!$A$6:$A$65,0))&"","")) | H58: =IF(AND(A58="",C58="",D58=""),"",IF(D58="","Manca l'importo",IF(NOT(ISNUMBER(D58)),"Importo non valido",IF(NOT(ISNUMBER(A58)),"Data mancante o non valida",IF(YEAR(A58)<>Impostazioni!$C$4,"Fuori dall'anno",IF(C58="","Manca la categoria",IF(ISNA(MATCH(C58,Categorie!$A$6:$A$65,0)),"Categoria non trovata",IF(G58="","Categoria senza tipo",""))))))))
A59: 46066 | B59: Gelateria | C59: Svago | D59: 12.23 | E59: Carta di debito | G59: =IF(C59="","",IFERROR(INDEX(Categorie!$B$6:$B$65,MATCH(C59,Categorie!$A$6:$A$65,0))&"","")) | H59: =IF(AND(A59="",C59="",D59=""),"",IF(D59="","Manca l'importo",IF(NOT(ISNUMBER(D59)),"Importo non valido",IF(NOT(ISNUMBER(A59)),"Data mancante o non valida",IF(YEAR(A59)<>Impostazioni!$C$4,"Fuori dall'anno",IF(C59="","Manca la categoria",IF(ISNA(MATCH(C59,Categorie!$A$6:$A$65,0)),"Categoria non trovata",IF(G59="","Categoria senza tipo",""))))))))
A60: 46067 | B60: Spesa settimanale | C60: Spesa alimentare | D60: 122.39 | E60: Carta di debito | G60: =IF(C60="","",IFERROR(INDEX(Categorie!$B$6:$B$65,MATCH(C60,Categorie!$A$6:$A$65,0))&"","")) | H60: =IF(AND(A60="",C60="",D60=""),"",IF(D60="","Manca l'importo",IF(NOT(ISNUMBER(D60)),"Importo non valido",IF(NOT(ISNUMBER(A60)),"Data mancante o non valida",IF(YEAR(A60)<>Impostazioni!$C$4,"Fuori dall'anno",IF(C60="","Manca la categoria",IF(ISNA(MATCH(C60,Categorie!$A$6:$A$65,0)),"Categoria non trovata",IF(G60="","Categoria senza tipo",""))))))))
A61: 46068 | B61: Rata carta revolving | C61: Rate di prestiti | D61: 60 | E61: Conto corrente | G61: =IF(C61="","",IFERROR(INDEX(Categorie!$B$6:$B$65,MATCH(C61,Categorie!$A$6:$A$65,0))&"","")) | H61: =IF(AND(A61="",C61="",D61=""),"",IF(D61="","Manca l'importo",IF(NOT(ISNUMBER(D61)),"Importo non valido",IF(NOT(ISNUMBER(A61)),"Data mancante o non valida",IF(YEAR(A61)<>Impostazioni!$C$4,"Fuori dall'anno",IF(C61="","Manca la categoria",IF(ISNA(MATCH(C61,Categorie!$A$6:$A$65,0)),"Categoria non trovata",IF(G61="","Categoria senza tipo",""))))))))
A62: 46068 | B62: Rata lavatrice a tasso zero | C62: Rate di prestiti | D62: 40 | E62: Conto corrente | G62: =IF(C62="","",IFERROR(INDEX(Categorie!$B$6:$B$65,MATCH(C62,Categorie!$A$6:$A$65,0))&"","")) | H62: =IF(AND(A62="",C62="",D62=""),"",IF(D62="","Manca l'importo",IF(NOT(ISNUMBER(D62)),"Importo non valido",IF(NOT(ISNUMBER(A62)),"Data mancante o non valida",IF(YEAR(A62)<>Impostazioni!$C$4,"Fuori dall'anno",IF(C62="","Manca la categoria",IF(ISNA(MATCH(C62,Categorie!$A$6:$A$65,0)),"Categoria non trovata",IF(G62="","Categoria senza tipo",""))))))))
A63: 46068 | B63: Rata prestito auto | C63: Rate di prestiti | D63: 210 | E63: Conto corrente | G63: =IF(C63="","",IFERROR(INDEX(Categorie!$B$6:$B$65,MATCH(C63,Categorie!$A$6:$A$65,0))&"","")) | H63: =IF(AND(A63="",C63="",D63=""),"",IF(D63="","Manca l'importo",IF(NOT(ISNUMBER(D63)),"Importo non valido",IF(NOT(ISNUMBER(A63)),"Data mancante o non valida",IF(YEAR(A63)<>Impostazioni!$C$4,"Fuori dall'anno",IF(C63="","Manca la categoria",IF(ISNA(MATCH(C63,Categorie!$A$6:$A$65,0)),"Categoria non trovata",IF(G63="","Categoria senza tipo",""))))))))
A64: 46068 | B64: Compleanno nonna | C64: Regali | D64: 40 | E64: Contanti | G64: =IF(C64="","",IFERROR(INDEX(Categorie!$B$6:$B$65,MATCH(C64,Categorie!$A$6:$A$65,0))&"","")) | H64: =IF(AND(A64="",C64="",D64=""),"",IF(D64="","Manca l'importo",IF(NOT(ISNUMBER(D64)),"Importo non valido",IF(NOT(ISNUMBER(A64)),"Data mancante o non valida",IF(YEAR(A64)<>Impostazioni!$C$4,"Fuori dall'anno",IF(C64="","Manca la categoria",IF(ISNA(MATCH(C64,Categorie!$A$6:$A$65,0)),"Categoria non trovata",IF(G64="","Categoria senza tipo",""))))))))
A65: 46069 | B65: Gelateria | C65: Svago | D65: 9.99 | E65: Carta di debito | G65: =IF(C65="","",IFERROR(INDEX(Categorie!$B$6:$B$65,MATCH(C65,Categorie!$A$6:$A$65,0))&"","")) | H65: =IF(AND(A65="",C65="",D65=""),"",IF(D65="","Manca l'importo",IF(NOT(ISNUMBER(D65)),"Importo non valido",IF(NOT(ISNUMBER(A65)),"Data mancante o non valida",IF(YEAR(A65)<>Impostazioni!$C$4,"Fuori dall'anno",IF(C65="","Manca la categoria",IF(ISNA(MATCH(C65,Categorie!$A$6:$A$65,0)),"Categoria non trovata",IF(G65="","Categoria senza tipo",""))))))))
A66: 46070 | B66: Rifornimento | C66: Carburante | D66: 62.59 | E66: Carta di credito | F66: Marco | G66: =IF(C66="","",IFERROR(INDEX(Categorie!$B$6:$B$65,MATCH(C66,Categorie!$A$6:$A$65,0))&"","")) | H66: =IF(AND(A66="",C66="",D66=""),"",IF(D66="","Manca l'importo",IF(NOT(ISNUMBER(D66)),"Importo non valido",IF(NOT(ISNUMBER(A66)),"Data mancante o non valida",IF(YEAR(A66)<>Impostazioni!$C$4,"Fuori dall'anno",IF(C66="","Manca la categoria",IF(ISNA(MATCH(C66,Categorie!$A$6:$A$65,0)),"Categoria non trovata",IF(G66="","Categoria senza tipo",""))))))))
A67: 46071 | B67: Bolletta gas | C67: Gas | D67: 149.52 | E67: Conto corrente | G67: =IF(C67="","",IFERROR(INDEX(Categorie!$B$6:$B$65,MATCH(C67,Categorie!$A$6:$A$65,0))&"","")) | H67: =IF(AND(A67="",C67="",D67=""),"",IF(D67="","Manca l'importo",IF(NOT(ISNUMBER(D67)),"Importo non valido",IF(NOT(ISNUMBER(A67)),"Data mancante o non valida",IF(YEAR(A67)<>Impostazioni!$C$4,"Fuori dall'anno",IF(C67="","Manca la categoria",IF(ISNA(MATCH(C67,Categorie!$A$6:$A$65,0)),"Categoria non trovata",IF(G67="","Categoria senza tipo",""))))))))
A68: 46071 | B68: Bolletta luce | C68: Luce | D68: 73.68 | E68: Conto corrente | G68: =IF(C68="","",IFERROR(INDEX(Categorie!$B$6:$B$65,MATCH(C68,Categorie!$A$6:$A$65,0))&"","")) | H68: =IF(AND(A68="",C68="",D68=""),"",IF(D68="","Manca l'importo",IF(NOT(ISNUMBER(D68)),"Importo non valido",IF(NOT(ISNUMBER(A68)),"Data mancante o non valida",IF(YEAR(A68)<>Impostazioni!$C$4,"Fuori dall'anno",IF(C68="","Manca la categoria",IF(ISNA(MATCH(C68,Categorie!$A$6:$A$65,0)),"Categoria non trovata",IF(G68="","Categoria senza tipo",""))))))))
A69: 46071 | B69: Spesa al mercato | C69: Spesa alimentare | D69: 18.12 | E69: Contanti | G69: =IF(C69="","",IFERROR(INDEX(Categorie!$B$6:$B$65,MATCH(C69,Categorie!$A$6:$A$65,0))&"","")) | H69: =IF(AND(A69="",C69="",D69=""),"",IF(D69="","Manca l'importo",IF(NOT(ISNUMBER(D69)),"Importo non valido",IF(NOT(ISNUMBER(A69)),"Data mancante o non valida",IF(YEAR(A69)<>Impostazioni!$C$4,"Fuori dall'anno",IF(C69="","Manca la categoria",IF(ISNA(MATCH(C69,Categorie!$A$6:$A$65,0)),"Categoria non trovata",IF(G69="","Categoria senza tipo",""))))))))
A70: 46072 | B70: Riparazione auto | C70: Imprevisti | D70: 384.2 | E70: Carta di debito | F70: Marco | G70: =IF(C70="","",IFERROR(INDEX(Categorie!$B$6:$B$65,MATCH(C70,Categorie!$A$6:$A$65,0))&"","")) | H70: =IF(AND(A70="",C70="",D70=""),"",IF(D70="","Manca l'importo",IF(NOT(ISNUMBER(D70)),"Importo non valido",IF(NOT(ISNUMBER(A70)),"Data mancante o non valida",IF(YEAR(A70)<>Impostazioni!$C$4,"Fuori dall'anno",IF(C70="","Manca la categoria",IF(ISNA(MATCH(C70,Categorie!$A$6:$A$65,0)),"Categoria non trovata",IF(G70="","Categoria senza tipo",""))))))))
A71: 46073 | B71: Assegno unico INPS | C71: Assegno unico figli | D71: 145.3 | E71: Conto corrente | G71: =IF(C71="","",IFERROR(INDEX(Categorie!$B$6:$B$65,MATCH(C71,Categorie!$A$6:$A$65,0))&"","")) | H71: =IF(AND(A71="",C71="",D71=""),"",IF(D71="","Manca l'importo",IF(NOT(ISNUMBER(D71)),"Importo non valido",IF(NOT(ISNUMBER(A71)),"Data mancante o non valida",IF(YEAR(A71)<>Impostazioni!$C$4,"Fuori dall'anno",IF(C71="","Manca la categoria",IF(ISNA(MATCH(C71,Categorie!$A$6:$A$65,0)),"Categoria non trovata",IF(G71="","Categoria senza tipo",""))))))))
A72: 46074 | B72: Spesa settimanale | C72: Spesa alimentare | D72: 107.19 | E72: Carta di debito | G72: =IF(C72="","",IFERROR(INDEX(Categorie!$B$6:$B$65,MATCH(C72,Categorie!$A$6:$A$65,0))&"","")) | H72: =IF(AND(A72="",C72="",D72=""),"",IF(D72="","Manca l'importo",IF(NOT(ISNUMBER(D72)),"Importo non valido",IF(NOT(ISNUMBER(A72)),"Data mancante o non valida",IF(YEAR(A72)<>Impostazioni!$C$4,"Fuori dall'anno",IF(C72="","Manca la categoria",IF(ISNA(MATCH(C72,Categorie!$A$6:$A$65,0)),"Categoria non trovata",IF(G72="","Categoria senza tipo",""))))))))
A73: 46075 | B73: Bolletta acqua | C73: Acqua | D73: 91.4 | E73: Conto corrente | G73: =IF(C73="","",IFERROR(INDEX(Categorie!$B$6:$B$65,MATCH(C73,Categorie!$A$6:$A$65,0))&"","")) | H73: =IF(AND(A73="",C73="",D73=""),"",IF(D73="","Manca l'importo",IF(NOT(ISNUMBER(D73)),"Importo non valido",IF(NOT(ISNUMBER(A73)),"Data mancante o non valida",IF(YEAR(A73)<>Impostazioni!$C$4,"Fuori dall'anno",IF(C73="","Manca la categoria",IF(ISNA(MATCH(C73,Categorie!$A$6:$A$65,0)),"Categoria non trovata",IF(G73="","Categoria senza tipo",""))))))))
A74: 46077 | B74: Libri | C74: Svago | D74: 23.46 | E74: Carta di debito | G74: =IF(C74="","",IFERROR(INDEX(Categorie!$B$6:$B$65,MATCH(C74,Categorie!$A$6:$A$65,0))&"","")) | H74: =IF(AND(A74="",C74="",D74=""),"",IF(D74="","Manca l'importo",IF(NOT(ISNUMBER(D74)),"Importo non valido",IF(NOT(ISNUMBER(A74)),"Data mancante o non valida",IF(YEAR(A74)<>Impostazioni!$C$4,"Fuori dall'anno",IF(C74="","Manca la categoria",IF(ISNA(MATCH(C74,Categorie!$A$6:$A$65,0)),"Categoria non trovata",IF(G74="","Categoria senza tipo",""))))))))
A75: 46078 | B75: Farmacia | C75: Farmacia e salute | D75: 16.89 | E75: Carta di debito | G75: =IF(C75="","",IFERROR(INDEX(Categorie!$B$6:$B$65,MATCH(C75,Categorie!$A$6:$A$65,0))&"","")) | H75: =IF(AND(A75="",C75="",D75=""),"",IF(D75="","Manca l'importo",IF(NOT(ISNUMBER(D75)),"Importo non valido",IF(NOT(ISNUMBER(A75)),"Data mancante o non valida",IF(YEAR(A75)<>Impostazioni!$C$4,"Fuori dall'anno",IF(C75="","Manca la categoria",IF(ISNA(MATCH(C75,Categorie!$A$6:$A$65,0)),"Categoria non trovata",IF(G75="","Categoria senza tipo",""))))))))
A76: 46078 | B76: Parcheggio | C76: Trasporti | D76: 5.6 | E76: Contanti | G76: =IF(C76="","",IFERROR(INDEX(Categorie!$B$6:$B$65,MATCH(C76,Categorie!$A$6:$A$65,0))&"","")) | H76: =IF(AND(A76="",C76="",D76=""),"",IF(D76="","Manca l'importo",IF(NOT(ISNUMBER(D76)),"Importo non valido",IF(NOT(ISNUMBER(A76)),"Data mancante o non valida",IF(YEAR(A76)<>Impostazioni!$C$4,"Fuori dall'anno",IF(C76="","Manca la categoria",IF(ISNA(MATCH(C76,Categorie!$A$6:$A$65,0)),"Categoria non trovata",IF(G76="","Categoria senza tipo",""))))))))
A77: 46080 | B77: Stipendio | C77: Stipendio Giulia | D77: 1480 | E77: Conto corrente | F77: Giulia | G77: =IF(C77="","",IFERROR(INDEX(Categorie!$B$6:$B$65,MATCH(C77,Categorie!$A$6:$A$65,0))&"","")) | H77: =IF(AND(A77="",C77="",D77=""),"",IF(D77="","Manca l'importo",IF(NOT(ISNUMBER(D77)),"Importo non valido",IF(NOT(ISNUMBER(A77)),"Data mancante o non valida",IF(YEAR(A77)<>Impostazioni!$C$4,"Fuori dall'anno",IF(C77="","Manca la categoria",IF(ISNA(MATCH(C77,Categorie!$A$6:$A$65,0)),"Categoria non trovata",IF(G77="","Categoria senza tipo",""))))))))
A78: 46080 | B78: Stipendio | C78: Stipendio Marco | D78: 1850 | E78: Conto corrente | F78: Marco | G78: =IF(C78="","",IFERROR(INDEX(Categorie!$B$6:$B$65,MATCH(C78,Categorie!$A$6:$A$65,0))&"","")) | H78: =IF(AND(A78="",C78="",D78=""),"",IF(D78="","Manca l'importo",IF(NOT(ISNUMBER(D78)),"Importo non valido",IF(NOT(ISNUMBER(A78)),"Data mancante o non valida",IF(YEAR(A78)<>Impostazioni!$C$4,"Fuori dall'anno",IF(C78="","Manca la categoria",IF(ISNA(MATCH(C78,Categorie!$A$6:$A$65,0)),"Categoria non trovata",IF(G78="","Categoria senza tipo",""))))))))
A79: 46080 | B79: Parcheggio | C79: Trasporti | D79: 4.63 | E79: Contanti | G79: =IF(C79="","",IFERROR(INDEX(Categorie!$B$6:$B$65,MATCH(C79,Categorie!$A$6:$A$65,0))&"","")) | H79: =IF(AND(A79="",C79="",D79=""),"",IF(D79="","Manca l'importo",IF(NOT(ISNUMBER(D79)),"Importo non valido",IF(NOT(ISNUMBER(A79)),"Data mancante o non valida",IF(YEAR(A79)<>Impostazioni!$C$4,"Fuori dall'anno",IF(C79="","Manca la categoria",IF(ISNA(MATCH(C79,Categorie!$A$6:$A$65,0)),"Categoria non trovata",IF(G79="","Categoria senza tipo",""))))))))
A80: 46081 | B80: Versamento fondo emergenze | C80: Fondo emergenze | D80: 150 | E80: Conto corrente | G80: =IF(C80="","",IFERROR(INDEX(Categorie!$B$6:$B$65,MATCH(C80,Categorie!$A$6:$A$65,0))&"","")) | H80: =IF(AND(A80="",C80="",D80=""),"",IF(D80="","Manca l'importo",IF(NOT(ISNUMBER(D80)),"Importo non valido",IF(NOT(ISNUMBER(A80)),"Data mancante o non valida",IF(YEAR(A80)<>Impostazioni!$C$4,"Fuori dall'anno",IF(C80="","Manca la categoria",IF(ISNA(MATCH(C80,Categorie!$A$6:$A$65,0)),"Categoria non trovata",IF(G80="","Categoria senza tipo",""))))))))
A81: 46081 | B81: Piano di accumulo mensile | C81: Investimenti | D81: 100 | E81: Conto corrente | G81: =IF(C81="","",IFERROR(INDEX(Categorie!$B$6:$B$65,MATCH(C81,Categorie!$A$6:$A$65,0))&"","")) | H81: =IF(AND(A81="",C81="",D81=""),"",IF(D81="","Manca l'importo",IF(NOT(ISNUMBER(D81)),"Importo non valido",IF(NOT(ISNUMBER(A81)),"Data mancante o non valida",IF(YEAR(A81)<>Impostazioni!$C$4,"Fuori dall'anno",IF(C81="","Manca la categoria",IF(ISNA(MATCH(C81,Categorie!$A$6:$A$65,0)),"Categoria non trovata",IF(G81="","Categoria senza tipo",""))))))))
A82: 46081 | B82: Accantonamento obiettivi | C82: Obiettivi di risparmio | D82: 200 | E82: Conto corrente | G82: =IF(C82="","",IFERROR(INDEX(Categorie!$B$6:$B$65,MATCH(C82,Categorie!$A$6:$A$65,0))&"","")) | H82: =IF(AND(A82="",C82="",D82=""),"",IF(D82="","Manca l'importo",IF(NOT(ISNUMBER(D82)),"Importo non valido",IF(NOT(ISNUMBER(A82)),"Data mancante o non valida",IF(YEAR(A82)<>Impostazioni!$C$4,"Fuori dall'anno",IF(C82="","Manca la categoria",IF(ISNA(MATCH(C82,Categorie!$A$6:$A$65,0)),"Categoria non trovata",IF(G82="","Categoria senza tipo",""))))))))
A83: 46081 | B83: Spesa settimanale | C83: Spesa alimentare | D83: 92.67 | E83: Carta di debito | G83: =IF(C83="","",IFERROR(INDEX(Categorie!$B$6:$B$65,MATCH(C83,Categorie!$A$6:$A$65,0))&"","")) | H83: =IF(AND(A83="",C83="",D83=""),"",IF(D83="","Manca l'importo",IF(NOT(ISNUMBER(D83)),"Importo non valido",IF(NOT(ISNUMBER(A83)),"Data mancante o non valida",IF(YEAR(A83)<>Impostazioni!$C$4,"Fuori dall'anno",IF(C83="","Manca la categoria",IF(ISNA(MATCH(C83,Categorie!$A$6:$A$65,0)),"Categoria non trovata",IF(G83="","Categoria senza tipo",""))))))))
A84: 46082 | B84: Rata mutuo | C84: Affitto o rata mutuo | D84: 680 | E84: Conto corrente | G84: =IF(C84="","",IFERROR(INDEX(Categorie!$B$6:$B$65,MATCH(C84,Categorie!$A$6:$A$65,0))&"","")) | H84: =IF(AND(A84="",C84="",D84=""),"",IF(D84="","Manca l'importo",IF(NOT(ISNUMBER(D84)),"Importo non valido",IF(NOT(ISNUMBER(A84)),"Data mancante o non valida",IF(YEAR(A84)<>Impostazioni!$C$4,"Fuori dall'anno",IF(C84="","Manca la categoria",IF(ISNA(MATCH(C84,Categorie!$A$6:$A$65,0)),"Categoria non trovata",IF(G84="","Categoria senza tipo",""))))))))
A85: 46082 | B85: Rifornimento | C85: Carburante | D85: 66.23 | E85: Carta di credito | F85: Giulia | G85: =IF(C85="","",IFERROR(INDEX(Categorie!$B$6:$B$65,MATCH(C85,Categorie!$A$6:$A$65,0))&"","")) | H85: =IF(AND(A85="",C85="",D85=""),"",IF(D85="","Manca l'importo",IF(NOT(ISNUMBER(D85)),"Importo non valido",IF(NOT(ISNUMBER(A85)),"Data mancante o non valida",IF(YEAR(A85)<>Impostazioni!$C$4,"Fuori dall'anno",IF(C85="","Manca la categoria",IF(ISNA(MATCH(C85,Categorie!$A$6:$A$65,0)),"Categoria non trovata",IF(G85="","Categoria senza tipo",""))))))))
A86: 46083 | B86: RC auto | C86: Assicurazioni | D86: 486 | E86: Conto corrente | G86: =IF(C86="","",IFERROR(INDEX(Categorie!$B$6:$B$65,MATCH(C86,Categorie!$A$6:$A$65,0))&"","")) | H86: =IF(AND(A86="",C86="",D86=""),"",IF(D86="","Manca l'importo",IF(NOT(ISNUMBER(D86)),"Importo non valido",IF(NOT(ISNUMBER(A86)),"Data mancante o non valida",IF(YEAR(A86)<>Impostazioni!$C$4,"Fuori dall'anno",IF(C86="","Manca la categoria",IF(ISNA(MATCH(C86,Categorie!$A$6:$A$65,0)),"Categoria non trovata",IF(G86="","Categoria senza tipo",""))))))))
A87: 46084 | B87: Abbonamento bus Sofia | C87: Trasporti | D87: 25 | E87: Carta di debito | F87: Sofia | G87: =IF(C87="","",IFERROR(INDEX(Categorie!$B$6:$B$65,MATCH(C87,Categorie!$A$6:$A$65,0))&"","")) | H87: =IF(AND(A87="",C87="",D87=""),"",IF(D87="","Manca l'importo",IF(NOT(ISNUMBER(D87)),"Importo non valido",IF(NOT(ISNUMBER(A87)),"Data mancante o non valida",IF(YEAR(A87)<>Impostazioni!$C$4,"Fuori dall'anno",IF(C87="","Manca la categoria",IF(ISNA(MATCH(C87,Categorie!$A$6:$A$65,0)),"Categoria non trovata",IF(G87="","Categoria senza tipo",""))))))))
A88: 46085 | B88: Mensa scolastica | C88: Scuola e figli | D88: 78 | E88: Conto corrente | F88: Sofia | G88: =IF(C88="","",IFERROR(INDEX(Categorie!$B$6:$B$65,MATCH(C88,Categorie!$A$6:$A$65,0))&"","")) | H88: =IF(AND(A88="",C88="",D88=""),"",IF(D88="","Manca l'importo",IF(NOT(ISNUMBER(D88)),"Importo non valido",IF(NOT(ISNUMBER(A88)),"Data mancante o non valida",IF(YEAR(A88)<>Impostazioni!$C$4,"Fuori dall'anno",IF(C88="","Manca la categoria",IF(ISNA(MATCH(C88,Categorie!$A$6:$A$65,0)),"Categoria non trovata",IF(G88="","Categoria senza tipo",""))))))))
A89: 46085 | B89: Spesa al mercato | C89: Spesa alimentare | D89: 17.33 | E89: Contanti | G89: =IF(C89="","",IFERROR(INDEX(Categorie!$B$6:$B$65,MATCH(C89,Categorie!$A$6:$A$65,0))&"","")) | H89: =IF(AND(A89="",C89="",D89=""),"",IF(D89="","Manca l'importo",IF(NOT(ISNUMBER(D89)),"Importo non valido",IF(NOT(ISNUMBER(A89)),"Data mancante o non valida",IF(YEAR(A89)<>Impostazioni!$C$4,"Fuori dall'anno",IF(C89="","Manca la categoria",IF(ISNA(MATCH(C89,Categorie!$A$6:$A$65,0)),"Categoria non trovata",IF(G89="","Categoria senza tipo",""))))))))
A90: 46086 | B90: Fibra casa | C90: Internet e telefono | D90: 27.9 | E90: Carta di credito | G90: =IF(C90="","",IFERROR(INDEX(Categorie!$B$6:$B$65,MATCH(C90,Categorie!$A$6:$A$65,0))&"","")) | H90: =IF(AND(A90="",C90="",D90=""),"",IF(D90="","Manca l'importo",IF(NOT(ISNUMBER(D90)),"Importo non valido",IF(NOT(ISNUMBER(A90)),"Data mancante o non valida",IF(YEAR(A90)<>Impostazioni!$C$4,"Fuori dall'anno",IF(C90="","Manca la categoria",IF(ISNA(MATCH(C90,Categorie!$A$6:$A$65,0)),"Categoria non trovata",IF(G90="","Categoria senza tipo",""))))))))
A91: 46086 | B91: Telefono Giulia | C91: Internet e telefono | D91: 7.99 | E91: Carta di credito | F91: Giulia | G91: =IF(C91="","",IFERROR(INDEX(Categorie!$B$6:$B$65,MATCH(C91,Categorie!$A$6:$A$65,0))&"","")) | H91: =IF(AND(A91="",C91="",D91=""),"",IF(D91="","Manca l'importo",IF(NOT(ISNUMBER(D91)),"Importo non valido",IF(NOT(ISNUMBER(A91)),"Data mancante o non valida",IF(YEAR(A91)<>Impostazioni!$C$4,"Fuori dall'anno",IF(C91="","Manca la categoria",IF(ISNA(MATCH(C91,Categorie!$A$6:$A$65,0)),"Categoria non trovata",IF(G91="","Categoria senza tipo",""))))))))
A92: 46086 | B92: Telefono Marco | C92: Internet e telefono | D92: 9.99 | E92: Carta di credito | F92: Marco | G92: =IF(C92="","",IFERROR(INDEX(Categorie!$B$6:$B$65,MATCH(C92,Categorie!$A$6:$A$65,0))&"","")) | H92: =IF(AND(A92="",C92="",D92=""),"",IF(D92="","Manca l'importo",IF(NOT(ISNUMBER(D92)),"Importo non valido",IF(NOT(ISNUMBER(A92)),"Data mancante o non valida",IF(YEAR(A92)<>Impostazioni!$C$4,"Fuori dall'anno",IF(C92="","Manca la categoria",IF(ISNA(MATCH(C92,Categorie!$A$6:$A$65,0)),"Categoria non trovata",IF(G92="","Categoria senza tipo",""))))))))
A93: 46086 | B93: Libri | C93: Svago | D93: 23.48 | E93: Carta di debito | G93: =IF(C93="","",IFERROR(INDEX(Categorie!$B$6:$B$65,MATCH(C93,Categorie!$A$6:$A$65,0))&"","")) | H93: =IF(AND(A93="",C93="",D93=""),"",IF(D93="","Manca l'importo",IF(NOT(ISNUMBER(D93)),"Importo non valido",IF(NOT(ISNUMBER(A93)),"Data mancante o non valida",IF(YEAR(A93)<>Impostazioni!$C$4,"Fuori dall'anno",IF(C93="","Manca la categoria",IF(ISNA(MATCH(C93,Categorie!$A$6:$A$65,0)),"Categoria non trovata",IF(G93="","Categoria senza tipo",""))))))))
A94: 46086 | B94: Parcheggio | C94: Trasporti | D94: 4.98 | E94: Contanti | G94: =IF(C94="","",IFERROR(INDEX(Categorie!$B$6:$B$65,MATCH(C94,Categorie!$A$6:$A$65,0))&"","")) | H94: =IF(AND(A94="",C94="",D94=""),"",IF(D94="","Manca l'importo",IF(NOT(ISNUMBER(D94)),"Importo non valido",IF(NOT(ISNUMBER(A94)),"Data mancante o non valida",IF(YEAR(A94)<>Impostazioni!$C$4,"Fuori dall'anno",IF(C94="","Manca la categoria",IF(ISNA(MATCH(C94,Categorie!$A$6:$A$65,0)),"Categoria non trovata",IF(G94="","Categoria senza tipo",""))))))))
A95: 46088 | B95: Spesa settimanale | C95: Spesa alimentare | D95: 103.68 | E95: Carta di debito | G95: =IF(C95="","",IFERROR(INDEX(Categorie!$B$6:$B$65,MATCH(C95,Categorie!$A$6:$A$65,0))&"","")) | H95: =IF(AND(A95="",C95="",D95=""),"",IF(D95="","Manca l'importo",IF(NOT(ISNUMBER(D95)),"Importo non valido",IF(NOT(ISNUMBER(A95)),"Data mancante o non valida",IF(YEAR(A95)<>Impostazioni!$C$4,"Fuori dall'anno",IF(C95="","Manca la categoria",IF(ISNA(MATCH(C95,Categorie!$A$6:$A$65,0)),"Categoria non trovata",IF(G95="","Categoria senza tipo",""))))))))
A96: 46089 | B96: Musica in streaming | C96: Abbonamenti | D96: 10.99 | E96: Carta di credito | F96: Giulia | G96: =IF(C96="","",IFERROR(INDEX(Categorie!$B$6:$B$65,MATCH(C96,Categorie!$A$6:$A$65,0))&"","")) | H96: =IF(AND(A96="",C96="",D96=""),"",IF(D96="","Manca l'importo",IF(NOT(ISNUMBER(D96)),"Importo non valido",IF(NOT(ISNUMBER(A96)),"Data mancante o non valida",IF(YEAR(A96)<>Impostazioni!$C$4,"Fuori dall'anno",IF(C96="","Manca la categoria",IF(ISNA(MATCH(C96,Categorie!$A$6:$A$65,0)),"Categoria non trovata",IF(G96="","Categoria senza tipo",""))))))))
A97: 46089 | B97: Streaming video | C97: Abbonamenti | D97: 13.99 | E97: Carta di credito | G97: =IF(C97="","",IFERROR(INDEX(Categorie!$B$6:$B$65,MATCH(C97,Categorie!$A$6:$A$65,0))&"","")) | H97: =IF(AND(A97="",C97="",D97=""),"",IF(D97="","Manca l'importo",IF(NOT(ISNUMBER(D97)),"Importo non valido",IF(NOT(ISNUMBER(A97)),"Data mancante o non valida",IF(YEAR(A97)<>Impostazioni!$C$4,"Fuori dall'anno",IF(C97="","Manca la categoria",IF(ISNA(MATCH(C97,Categorie!$A$6:$A$65,0)),"Categoria non trovata",IF(G97="","Categoria senza tipo",""))))))))
A98: 46090 | B98: Cena con amici | C98: Svago | D98: 71.8 | E98: Carta di debito | G98: =IF(C98="","",IFERROR(INDEX(Categorie!$B$6:$B$65,MATCH(C98,Categorie!$A$6:$A$65,0))&"","")) | H98: =IF(AND(A98="",C98="",D98=""),"",IF(D98="","Manca l'importo",IF(NOT(ISNUMBER(D98)),"Importo non valido",IF(NOT(ISNUMBER(A98)),"Data mancante o non valida",IF(YEAR(A98)<>Impostazioni!$C$4,"Fuori dall'anno",IF(C98="","Manca la categoria",IF(ISNA(MATCH(C98,Categorie!$A$6:$A$65,0)),"Categoria non trovata",IF(G98="","Categoria senza tipo",""))))))))
A99: 46092 | B99: Rifornimento | C99: Carburante | D99: 55.65 | E99: Carta di credito | F99: Marco | G99: =IF(C99="","",IFERROR(INDEX(Categorie!$B$6:$B$65,MATCH(C99,Categorie!$A$6:$A$65,0))&"","")) | H99: =IF(AND(A99="",C99="",D99=""),"",IF(D99="","Manca l'importo",IF(NOT(ISNUMBER(D99)),"Importo non valido",IF(NOT(ISNUMBER(A99)),"Data mancante o non valida",IF(YEAR(A99)<>Impostazioni!$C$4,"Fuori dall'anno",IF(C99="","Manca la categoria",IF(ISNA(MATCH(C99,Categorie!$A$6:$A$65,0)),"Categoria non trovata",IF(G99="","Categoria senza tipo",""))))))))
A100: 46095 | B100: Vendita bici usata | C100: Entrate extra | D100: 120 | E100: Contanti | F100: Marco | G100: =IF(C100="","",IFERROR(INDEX(Categorie!$B$6:$B$65,MATCH(C100,Categorie!$A$6:$A$65,0))&"","")) | H100: =IF(AND(A100="",C100="",D100=""),"",IF(D100="","Manca l'importo",IF(NOT(ISNUMBER(D100)),"Importo non valido",IF(NOT(ISNUMBER(A100)),"Data mancante o non valida",IF(YEAR(A100)<>Impostazioni!$C$4,"Fuori dall'anno",IF(C100="","Manca la categoria",IF(ISNA(MATCH(C100,Categorie!$A$6:$A$65,0)),"Categoria non trovata",IF(G100="","Categoria senza tipo",""))))))))
A101: 46095 | B101: Spesa settimanale | C101: Spesa alimentare | D101: 123.3 | E101: Carta di debito | G101: =IF(C101="","",IFERROR(INDEX(Categorie!$B$6:$B$65,MATCH(C101,Categorie!$A$6:$A$65,0))&"","")) | H101: =IF(AND(A101="",C101="",D101=""),"",IF(D101="","Manca l'importo",IF(NOT(ISNUMBER(D101)),"Importo non valido",IF(NOT(ISNUMBER(A101)),"Data mancante o non valida",IF(YEAR(A101)<>Impostazioni!$C$4,"Fuori dall'anno",IF(C101="","Manca la categoria",IF(ISNA(MATCH(C101,Categorie!$A$6:$A$65,0)),"Categoria non trovata",IF(G101="","Categoria senza tipo",""))))))))
...

Sheet Budget
A1: Budget
A2: Scrivi in colonna C l'importo tipico mensile: i mesi si compilano da soli. Per un mese diverso (TARI, bollo, assicurazioni) scrivi l'importo nella cella del mese.
A3: Per tornare all'importo tipico copia la cella di un mese non modificato. Le righe di riepilogo in alto si calcolano da sole.
D4: 1 | E4: 2 | F4: 3 | G4: 4 | H4: 5 | I4: 6 | J4: 7 | K4: 8 | L4: 9 | M4: 10 | N4: 11 | O4: 12
A5: Voce | B5: Tipo | C5: Importo tipico mensile | D5: Gen | E5: Feb | F5: Mar | G5: Apr | H5: Mag | I5: Giu | J5: Lug | K5: Ago | L5: Set | M5: Ott | N5: Nov | O5: Dic | P5: Totale anno
A6: Entrate | B6: Entrata | C6: =SUMIFS(C$14:C$73,$B$14:$B$73,"Entrata") | D6: =SUMIFS(D$14:D$73,$B$14:$B$73,"Entrata") | E6: =SUMIFS(E$14:E$73,$B$14:$B$73,"Entrata") | F6: =SUMIFS(F$14:F$73,$B$14:$B$73,"Entrata") | G6: =SUMIFS(G$14:G$73,$B$14:$B$73,"Entrata") | H6: =SUMIFS(H$14:H$73,$B$14:$B$73,"Entrata") | I6: =SUMIFS(I$14:I$73,$B$14:$B$73,"Entrata") | J6: =SUMIFS(J$14:J$73,$B$14:$B$73,"Entrata") | ... P6: =SUMIFS(P$14:P$73,$B$14:$B$73,"Entrata")
A7: Spese fisse | B7: Spesa fissa | C7: =SUMIFS(C$14:C$73,$B$14:$B$73,"Spesa fissa") | D7: =SUMIFS(D$14:D$73,$B$14:$B$73,"Spesa fissa") | E7: =SUMIFS(E$14:E$73,$B$14:$B$73,"Spesa fissa") | F7: =SUMIFS(F$14:F$73,$B$14:$B$73,"Spesa fissa") | G7: =SUMIFS(G$14:G$73,$B$14:$B$73,"Spesa fissa") | H7: =SUMIFS(H$14:H$73,$B$14:$B$73,"Spesa fissa") | I7: =SUMIFS(I$14:I$73,$B$14:$B$73,"Spesa fissa") | J7: =SUMIFS(J$14:J$73,$B$14:$B$73,"Spesa fissa") | ... P7: =SUMIFS(P$14:P$73,$B$14:$B$73,"Spesa fissa")
A8: Spese variabili | B8: Spesa variabile | C8: =SUMIFS(C$14:C$73,$B$14:$B$73,"Spesa variabile") | D8: =SUMIFS(D$14:D$73,$B$14:$B$73,"Spesa variabile") | E8: =SUMIFS(E$14:E$73,$B$14:$B$73,"Spesa variabile") | F8: =SUMIFS(F$14:F$73,$B$14:$B$73,"Spesa variabile") | G8: =SUMIFS(G$14:G$73,$B$14:$B$73,"Spesa variabile") | H8: =SUMIFS(H$14:H$73,$B$14:$B$73,"Spesa variabile") | I8: =SUMIFS(I$14:I$73,$B$14:$B$73,"Spesa variabile") | J8: =SUMIFS(J$14:J$73,$B$14:$B$73,"Spesa variabile") | ... P8: =SUMIFS(P$14:P$73,$B$14:$B$73,"Spesa variabile")
A9: Totale spese | B9: Spesa totale | C9: =C7+C8 | D9: =D7+D8 | E9: =E7+E8 | F9: =F7+F8 | G9: =G7+G8 | H9: =H7+H8 | I9: =I7+I8 | J9: =J7+J8 | ... P9: =P7+P8
A10: Risparmio e investimenti | B10: Risparmio e investimenti | C10: =SUMIFS(C$14:C$73,$B$14:$B$73,"Risparmio e investimenti") | D10: =SUMIFS(D$14:D$73,$B$14:$B$73,"Risparmio e investimenti") | E10: =SUMIFS(E$14:E$73,$B$14:$B$73,"Risparmio e investimenti") | F10: =SUMIFS(F$14:F$73,$B$14:$B$73,"Risparmio e investimenti") | G10: =SUMIFS(G$14:G$73,$B$14:$B$73,"Risparmio e investimenti") | H10: =SUMIFS(H$14:H$73,$B$14:$B$73,"Risparmio e investimenti") | I10: =SUMIFS(I$14:I$73,$B$14:$B$73,"Risparmio e investimenti") | J10: =SUMIFS(J$14:J$73,$B$14:$B$73,"Risparmio e investimenti") | ... P10: =SUMIFS(P$14:P$73,$B$14:$B$73,"Risparmio e investimenti")
A11: Avanzo (entrate − spese − risparmio) | B11: Risultato | C11: =C6-C9-C10 | D11: =D6-D9-D10 | E11: =E6-E9-E10 | F11: =F6-F9-F10 | G11: =G6-G9-G10 | H11: =H6-H9-H10 | I11: =I6-I9-I10 | J11: =J6-J9-J10 | ... P11: =P6-P9-P10
A12: Saldo di cassa previsto a fine mese | B12: Saldo | D12: =Impostazioni!$C$5+D11 | E12: =D12+E11 | F12: =E12+F11 | G12: =F12+G11 | H12: =G12+H11 | I12: =H12+I11 | J12: =I12+J11 | K12: =J12+K11 | L12: =K12+L11 | ... O12: =N12+O11 | P12: =O12
A13: Dettaglio per categoria
A14: =IF(Categorie!$A6="","",Categorie!$A6) | B14: =IF(A14="","",Categorie!$B6&"") | C14: 1850 | D14: =$C14 | E14: =$C14 | F14: =$C14 | G14: =$C14 | H14: =$C14 | I14: =$C14 | J14: =$C14 | K14: =$C14 | ... O14: =$C14 | P14: =SUM(D14:O14)
A15: =IF(Categorie!$A7="","",Categorie!$A7) | B15: =IF(A15="","",Categorie!$B7&"") | C15: 1480 | D15: =$C15 | E15: =$C15 | F15: =$C15 | G15: =$C15 | H15: =$C15 | I15: =$C15 | J15: =$C15 | K15: =$C15 | ... O15: =$C15 | P15: =SUM(D15:O15)
A16: =IF(Categorie!$A8="","",Categorie!$A8) | B16: =IF(A16="","",Categorie!$B8&"") | D16: =$C16 | E16: =$C16 | F16: =$C16 | G16: =$C16 | H16: =$C16 | I16: =$C16 | J16: =$C16 | K16: =$C16 | ... N16: =$C16 | O16: 3200 | P16: =SUM(D16:O16)
A17: =IF(Categorie!$A9="","",Categorie!$A9) | B17: =IF(A17="","",Categorie!$B9&"") | C17: 145 | D17: =$C17 | E17: =$C17 | F17: =$C17 | G17: =$C17 | H17: =$C17 | I17: =$C17 | J17: =$C17 | K17: =$C17 | ... O17: =$C17 | P17: =SUM(D17:O17)
A18: =IF(Categorie!$A10="","",Categorie!$A10) | B18: =IF(A18="","",Categorie!$B10&"") | D18: =$C18 | E18: =$C18 | F18: =$C18 | G18: =$C18 | H18: =$C18 | I18: =$C18 | J18: =$C18 | K18: =$C18 | ... O18: =$C18 | P18: =SUM(D18:O18)
A19: =IF(Categorie!$A11="","",Categorie!$A11) | B19: =IF(A19="","",Categorie!$B11&"") | D19: =$C19 | E19: =$C19 | F19: =$C19 | G19: =$C19 | H19: =$C19 | I19: =$C19 | J19: 350 | K19: =$C19 | L19: =$C19 | M19: =$C19 | N19: =$C19 | O19: =$C19 | P19: =SUM(D19:O19)
A20: =IF(Categorie!$A12="","",Categorie!$A12) | B20: =IF(A20="","",Categorie!$B12&"") | C20: 680 | D20: =$C20 | E20: =$C20 | F20: =$C20 | G20: =$C20 | H20: =$C20 | I20: =$C20 | J20: =$C20 | K20: =$C20 | ... O20: =$C20 | P20: =SUM(D20:O20)
A21: =IF(Categorie!$A13="","",Categorie!$A13) | B21: =IF(A21="","",Categorie!$B13&"") | D21: 270 | E21: =$C21 | F21: =$C21 | G21: 270 | H21: =$C21 | I21: =$C21 | J21: 270 | K21: =$C21 | L21: =$C21 | M21: 270 | N21: =$C21 | O21: =$C21 | P21: =SUM(D21:O21)
A22: =IF(Categorie!$A14="","",Categorie!$A14) | B22: =IF(A22="","",Categorie!$B14&"") | C22: 75 | D22: =$C22 | E22: =$C22 | F22: =$C22 | G22: =$C22 | H22: =$C22 | I22: =$C22 | J22: =$C22 | K22: =$C22 | ... O22: =$C22 | P22: =SUM(D22:O22)
A23: =IF(Categorie!$A15="","",Categorie!$A15) | B23: =IF(A23="","",Categorie!$B15&"") | D23: 160 | E23: 150 | F23: 120 | G23: 80 | H23: 45 | I23: 30 | J23: 25 | K23: 25 | L23: 30 | M23: 60 | N23: 110 | O23: 160 | P23: =SUM(D23:O23)
A24: =IF(Categorie!$A16="","",Categorie!$A16) | B24: =IF(A24="","",Categorie!$B16&"") | D24: =$C24 | E24: 95 | F24: =$C24 | G24: =$C24 | H24: 95 | I24: =$C24 | J24: =$C24 | K24: 95 | L24: =$C24 | M24: =$C24 | N24: 95 | O24: =$C24 | P24: =SUM(D24:O24)
A25: =IF(Categorie!$A17="","",Categorie!$A17) | B25: =IF(A25="","",Categorie!$B17&"") | D25: =$C25 | E25: =$C25 | F25: =$C25 | G25: 110 | H25: =$C25 | I25: =$C25 | J25: 110 | K25: =$C25 | L25: =$C25 | M25: =$C25 | N25: 110 | O25: =$C25 | P25: =SUM(D25:O25)
A26: =IF(Categorie!$A18="","",Categorie!$A18) | B26: =IF(A26="","",Categorie!$B18&"") | C26: 46 | D26: =$C26 | E26: =$C26 | F26: =$C26 | G26: =$C26 | H26: =$C26 | I26: =$C26 | J26: =$C26 | K26: =$C26 | ... O26: =$C26 | P26: =SUM(D26:O26)
A27: =IF(Categorie!$A19="","",Categorie!$A19) | B27: =IF(A27="","",Categorie!$B19&"") | D27: =$C27 | E27: =$C27 | F27: 480 | G27: =$C27 | H27: =$C27 | I27: 170 | J27: =$C27 | K27: =$C27 | L27: =$C27 | M27: =$C27 | N27: =$C27 | O27: =$C27 | P27: =SUM(D27:O27)
A28: =IF(Categorie!$A20="","",Categorie!$A20) | B28: =IF(A28="","",Categorie!$B20&"") | D28: =$C28 | E28: =$C28 | F28: =$C28 | G28: 235 | H28: =$C28 | I28: =$C28 | J28: =$C28 | K28: =$C28 | L28: =$C28 | M28: =$C28 | N28: =$C28 | O28: =$C28 | P28: =SUM(D28:O28)
A29: =IF(Categorie!$A21="","",Categorie!$A21) | B29: =IF(A29="","",Categorie!$B21&"") | C29: 25 | D29: =$C29 | E29: =$C29 | F29: =$C29 | G29: =$C29 | H29: =$C29 | I29: =$C29 | J29: =$C29 | K29: =$C29 | L29: 315 | M29: =$C29 | N29: =$C29 | O29: =$C29 | P29: =SUM(D29:O29)
A30: =IF(Categorie!$A22="","",Categorie!$A22) | B30: =IF(A30="","",Categorie!$B22&"") | C30: 310 | D30: =$C30 | E30: =$C30 | F30: =$C30 | G30: =$C30 | H30: =$C30 | I30: =$C30 | J30: =$C30 | K30: =$C30 | ... O30: =$C30 | P30: =SUM(D30:O30)
A31: =IF(Categorie!$A23="","",Categorie!$A23) | B31: =IF(A31="","",Categorie!$B23&"") | C31: 520 | D31: =$C31 | E31: =$C31 | F31: =$C31 | G31: =$C31 | H31: =$C31 | I31: =$C31 | J31: =$C31 | K31: =$C31 | ... N31: =$C31 | O31: 620 | P31: =SUM(D31:O31)
A32: =IF(Categorie!$A24="","",Categorie!$A24) | B32: =IF(A32="","",Categorie!$B24&"") | C32: 170 | D32: =$C32 | E32: =$C32 | F32: =$C32 | G32: =$C32 | H32: =$C32 | I32: =$C32 | J32: =$C32 | K32: 220 | L32: =$C32 | M32: =$C32 | N32: =$C32 | O32: =$C32 | P32: =SUM(D32:O32)
A33: =IF(Categorie!$A25="","",Categorie!$A25) | B33: =IF(A33="","",Categorie!$B25&"") | C33: 35 | D33: =$C33 | E33: =$C33 | F33: =$C33 | G33: =$C33 | H33: =$C33 | I33: =$C33 | J33: =$C33 | K33: =$C33 | ... O33: =$C33 | P33: =SUM(D33:O33)
A34: =IF(Categorie!$A26="","",Categorie!$A26) | B34: =IF(A34="","",Categorie!$B26&"") | C34: 50 | D34: =$C34 | E34: =$C34 | F34: =$C34 | G34: =$C34 | H34: =$C34 | I34: =$C34 | J34: =$C34 | K34: =$C34 | ... O34: =$C34 | P34: =SUM(D34:O34)
A35: =IF(Categorie!$A27="","",Categorie!$A27) | B35: =IF(A35="","",Categorie!$B27&"") | C35: 80 | D35: =$C35 | E35: =$C35 | F35: =$C35 | G35: =$C35 | H35: =$C35 | I35: =$C35 | J35: 320 | K35: 0 | L35: 420 | M35: =$C35 | N35: =$C35 | O35: =$C35 | P35: =SUM(D35:O35)
A36: =IF(Categorie!$A28="","",Categorie!$A28) | B36: =IF(A36="","",Categorie!$B28&"") | C36: 30 | D36: =$C36 | E36: =$C36 | F36: =$C36 | G36: =$C36 | H36: =$C36 | I36: =$C36 | J36: =$C36 | K36: =$C36 | ... O36: =$C36 | P36: =SUM(D36:O36)
A37: =IF(Categorie!$A29="","",Categorie!$A29) | B37: =IF(A37="","",Categorie!$B29&"") | C37: 60 | D37: =$C37 | E37: =$C37 | F37: =$C37 | G37: =$C37 | H37: =$C37 | I37: =$C37 | J37: =$C37 | K37: =$C37 | ... O37: =$C37 | P37: =SUM(D37:O37)
A38: =IF(Categorie!$A30="","",Categorie!$A30) | B38: =IF(A38="","",Categorie!$B30&"") | C38: 150 | D38: =$C38 | E38: =$C38 | F38: =$C38 | G38: =$C38 | H38: =$C38 | I38: =$C38 | J38: =$C38 | K38: =$C38 | ... N38: =$C38 | O38: 220 | P38: =SUM(D38:O38)
A39: =IF(Categorie!$A31="","",Categorie!$A31) | B39: =IF(A39="","",Categorie!$B31&"") | C39: 30 | D39: =$C39 | E39: =$C39 | F39: =$C39 | G39: =$C39 | H39: =$C39 | I39: =$C39 | J39: =$C39 | K39: =$C39 | ... N39: =$C39 | O39: 300 | P39: =SUM(D39:O39)
A40: =IF(Categorie!$A32="","",Categorie!$A32) | B40: =IF(A40="","",Categorie!$B32&"") | D40: =$C40 | E40: =$C40 | F40: =$C40 | G40: 300 | H40: =$C40 | I40: =$C40 | J40: 400 | K40: 1100 | L40: =$C40 | M40: =$C40 | N40: =$C40 | O40: =$C40 | P40: =SUM(D40:O40)
A41: =IF(Categorie!$A33="","",Categorie!$A33) | B41: =IF(A41="","",Categorie!$B33&"") | C41: 60 | D41: =$C41 | E41: =$C41 | F41: =$C41 | G41: =$C41 | H41: =$C41 | I41: =$C41 | J41: =$C41 | K41: =$C41 | ... O41: =$C41 | P41: =SUM(D41:O41)
A42: =IF(Categorie!$A34="","",Categorie!$A34) | B42: =IF(A42="","",Categorie!$B34&"") | C42: 150 | D42: =$C42 | E42: =$C42 | F42: =$C42 | G42: =$C42 | H42: =$C42 | I42: =$C42 | J42: =$C42 | K42: =$C42 | ... O42: =$C42 | P42: =SUM(D42:O42)
A43: =IF(Categorie!$A35="","",Categorie!$A35) | B43: =IF(A43="","",Categorie!$B35&"") | C43: 200 | D43: =$C43 | E43: =$C43 | F43: =$C43 | G43: =$C43 | H43: =$C43 | I43: =$C43 | J43: =$C43 | K43: =$C43 | ... O43: =$C43 | P43: =SUM(D43:O43)
A44: =IF(Categorie!$A36="","",Categorie!$A36) | B44: =IF(A44="","",Categorie!$B36&"") | C44: 100 | D44: =$C44 | E44: =$C44 | F44: =$C44 | G44: =$C44 | H44: =$C44 | I44: =$C44 | J44: =$C44 | K44: =$C44 | ... O44: =$C44 | P44: =SUM(D44:O44)
A45: =IF(Categorie!$A37="","",Categorie!$A37) | B45: =IF(A45="","",Categorie!$B37&"") | D45: =$C45 | E45: =$C45 | F45: =$C45 | G45: =$C45 | H45: =$C45 | I45: =$C45 | J45: =$C45 | K45: =$C45 | ... O45: =$C45 | P45: =SUM(D45:O45)
A46: =IF(Categorie!$A38="","",Categorie!$A38) | B46: =IF(A46="","",Categorie!$B38&"") | D46: =$C46 | E46: =$C46 | F46: =$C46 | G46: =$C46 | H46: =$C46 | I46: =$C46 | J46: =$C46 | K46: =$C46 | ... O46: =$C46 | P46: =SUM(D46:O46)
A47: =IF(Categorie!$A39="","",Categorie!$A39) | B47: =IF(A47="","",Categorie!$B39&"") | D47: =$C47 | E47: =$C47 | F47: =$C47 | G47: =$C47 | H47: =$C47 | I47: =$C47 | J47: =$C47 | K47: =$C47 | ... O47: =$C47 | P47: =SUM(D47:O47)
A48: =IF(Categorie!$A40="","",Categorie!$A40) | B48: =IF(A48="","",Categorie!$B40&"") | D48: =$C48 | E48: =$C48 | F48: =$C48 | G48: =$C48 | H48: =$C48 | I48: =$C48 | J48: =$C48 | K48: =$C48 | ... O48: =$C48 | P48: =SUM(D48:O48)
A49: =IF(Categorie!$A41="","",Categorie!$A41) | B49: =IF(A49="","",Categorie!$B41&"") | D49: =$C49 | E49: =$C49 | F49: =$C49 | G49: =$C49 | H49: =$C49 | I49: =$C49 | J49: =$C49 | K49: =$C49 | ... O49: =$C49 | P49: =SUM(D49:O49)
A50: =IF(Categorie!$A42="","",Categorie!$A42) | B50: =IF(A50="","",Categorie!$B42&"") | D50: =$C50 | E50: =$C50 | F50: =$C50 | G50: =$C50 | H50: =$C50 | I50: =$C50 | J50: =$C50 | K50: =$C50 | ... O50: =$C50 | P50: =SUM(D50:O50)
A51: =IF(Categorie!$A43="","",Categorie!$A43) | B51: =IF(A51="","",Categorie!$B43&"") | D51: =$C51 | E51: =$C51 | F51: =$C51 | G51: =$C51 | H51: =$C51 | I51: =$C51 | J51: =$C51 | K51: =$C51 | ... O51: =$C51 | P51: =SUM(D51:O51)
A52: =IF(Categorie!$A44="","",Categorie!$A44) | B52: =IF(A52="","",Categorie!$B44&"") | D52: =$C52 | E52: =$C52 | F52: =$C52 | G52: =$C52 | H52: =$C52 | I52: =$C52 | J52: =$C52 | K52: =$C52 | ... O52: =$C52 | P52: =SUM(D52:O52)
A53: =IF(Categorie!$A45="","",Categorie!$A45) | B53: =IF(A53="","",Categorie!$B45&"") | D53: =$C53 | E53: =$C53 | F53: =$C53 | G53: =$C53 | H53: =$C53 | I53: =$C53 | J53: =$C53 | K53: =$C53 | ... O53: =$C53 | P53: =SUM(D53:O53)
A54: =IF(Categorie!$A46="","",Categorie!$A46) | B54: =IF(A54="","",Categorie!$B46&"") | D54: =$C54 | E54: =$C54 | F54: =$C54 | G54: =$C54 | H54: =$C54 | I54: =$C54 | J54: =$C54 | K54: =$C54 | ... O54: =$C54 | P54: =SUM(D54:O54)
A55: =IF(Categorie!$A47="","",Categorie!$A47) | B55: =IF(A55="","",Categorie!$B47&"") | D55: =$C55 | E55: =$C55 | F55: =$C55 | G55: =$C55 | H55: =$C55 | I55: =$C55 | J55: =$C55 | K55: =$C55 | ... O55: =$C55 | P55: =SUM(D55:O55)
A56: =IF(Categorie!$A48="","",Categorie!$A48) | B56: =IF(A56="","",Categorie!$B48&"") | D56: =$C56 | E56: =$C56 | F56: =$C56 | G56: =$C56 | H56: =$C56 | I56: =$C56 | J56: =$C56 | K56: =$C56 | ... O56: =$C56 | P56: =SUM(D56:O56)
... A73: =IF(Categorie!$A65="","",Categorie!$A65) | B73: =IF(A73="","",Categorie!$B65&"") | D73: =$C73 | E73: =$C73 | F73: =$C73 | G73: =$C73 | H73: =$C73 | I73: =$C73 | J73: =$C73 | K73: =$C73 | ... O73: =$C73 | P73: =SUM(D73:O73)

Sheet Mensile
A1: Mensile: consuntivo e differenze dal budget
A2: Somme dei movimenti per categoria e mese. Differenza = consuntivo − budget: verde se va bene, rosso se va male.
A3: ="Mese di riferimento: "&Impostazioni!$C$13&" (si cambia in Impostazioni)"
C4: 1 | D4: 2 | E4: 3 | F4: 4 | G4: 5 | H4: 6 | I4: 7 | J4: 8 | K4: 9 | L4: 10 | M4: 11 | N4: 12
A5: Voce | B5: Tipo | C5: Gen | D5: Feb | E5: Mar | F5: Apr | G5: Mag | H5: Giu | I5: Lug | J5: Ago | K5: Set | L5: Ott | M5: Nov | N5: Dic | O5: Totale anno | P5: Budget anno | Q5: Differenza anno | R5: % del budget | T5: ="Budget "&LOWER(Impostazioni!$C$13) | U5: ="Consuntivo "&LOWER(Impostazioni!$C$13) | V5: ="Differenza "&LOWER(Impostazioni!$C$13) | W5: Budget da inizio anno | X5: Consuntivo da inizio anno | Y5: Differenza da inizio anno | Z5: Ordine (tecnico)
A6: Entrate | B6: Entrata | C6: =SUMIFS(C$14:C$73,$B$14:$B$73,"Entrata") | D6: =SUMIFS(D$14:D$73,$B$14:$B$73,"Entrata") | E6: =SUMIFS(E$14:E$73,$B$14:$B$73,"Entrata") | F6: =SUMIFS(F$14:F$73,$B$14:$B$73,"Entrata") | G6: =SUMIFS(G$14:G$73,$B$14:$B$73,"Entrata") | H6: =SUMIFS(H$14:H$73,$B$14:$B$73,"Entrata") | I6: =SUMIFS(I$14:I$73,$B$14:$B$73,"Entrata") | J6: =SUMIFS(J$14:J$73,$B$14:$B$73,"Entrata") | ... P6: =SUMIFS(P$14:P$73,$B$14:$B$73,"Entrata") | Q6: =O6-P6 | R6: =IF(P6=0,"",O6/P6) | T6: =SUMIFS(T$14:T$73,$B$14:$B$73,"Entrata") | U6: =SUMIFS(U$14:U$73,$B$14:$B$73,"Entrata") | V6: =U6-T6 | W6: =SUMIFS(W$14:W$73,$B$14:$B$73,"Entrata") | X6: =SUMIFS(X$14:X$73,$B$14:$B$73,"Entrata") | Y6: =X6-W6
A7: Spese fisse | B7: Spesa fissa | C7: =SUMIFS(C$14:C$73,$B$14:$B$73,"Spesa fissa") | D7: =SUMIFS(D$14:D$73,$B$14:$B$73,"Spesa fissa") | E7: =SUMIFS(E$14:E$73,$B$14:$B$73,"Spesa fissa") | F7: =SUMIFS(F$14:F$73,$B$14:$B$73,"Spesa fissa") | G7: =SUMIFS(G$14:G$73,$B$14:$B$73,"Spesa fissa") | H7: =SUMIFS(H$14:H$73,$B$14:$B$73,"Spesa fissa") | I7: =SUMIFS(I$14:I$73,$B$14:$B$73,"Spesa fissa") | J7: =SUMIFS(J$14:J$73,$B$14:$B$73,"Spesa fissa") | ... P7: =SUMIFS(P$14:P$73,$B$14:$B$73,"Spesa fissa") | Q7: =O7-P7 | R7: =IF(P7=0,"",O7/P7) | T7: =SUMIFS(T$14:T$73,$B$14:$B$73,"Spesa fissa") | U7: =SUMIFS(U$14:U$73,$B$14:$B$73,"Spesa fissa") | V7: =U7-T7 | W7: =SUMIFS(W$14:W$73,$B$14:$B$73,"Spesa fissa") | X7: =SUMIFS(X$14:X$73,$B$14:$B$73,"Spesa fissa") | Y7: =X7-W7
A8: Spese variabili | B8: Spesa variabile | C8: =SUMIFS(C$14:C$73,$B$14:$B$73,"Spesa variabile") | D8: =SUMIFS(D$14:D$73,$B$14:$B$73,"Spesa variabile") | E8: =SUMIFS(E$14:E$73,$B$14:$B$73,"Spesa variabile") | F8: =SUMIFS(F$14:F$73,$B$14:$B$73,"Spesa variabile") | G8: =SUMIFS(G$14:G$73,$B$14:$B$73,"Spesa variabile") | H8: =SUMIFS(H$14:H$73,$B$14:$B$73,"Spesa variabile") | I8: =SUMIFS(I$14:I$73,$B$14:$B$73,"Spesa variabile") | J8: =SUMIFS(J$14:J$73,$B$14:$B$73,"Spesa variabile") | ... P8: =SUMIFS(P$14:P$73,$B$14:$B$73,"Spesa variabile") | Q8: =O8-P8 | R8: =IF(P8=0,"",O8/P8) | T8: =SUMIFS(T$14:T$73,$B$14:$B$73,"Spesa variabile") | U8: =SUMIFS(U$14:U$73,$B$14:$B$73,"Spesa variabile") | V8: =U8-T8 | W8: =SUMIFS(W$14:W$73,$B$14:$B$73,"Spesa variabile") | X8: =SUMIFS(X$14:X$73,$B$14:$B$73,"Spesa variabile") | Y8: =X8-W8
A9: Totale spese | B9: Spesa totale | C9: =C7+C8 | D9: =D7+D8 | E9: =E7+E8 | F9: =F7+F8 | G9: =G7+G8 | H9: =H7+H8 | I9: =I7+I8 | J9: =J7+J8 | ... P9: =P7+P8 | Q9: =O9-P9 | R9: =IF(P9=0,"",O9/P9) | T9: =T7+T8 | U9: =U7+U8 | V9: =U9-T9 | W9: =W7+W8 | X9: =X7+X8 | Y9: =X9-W9
A10: Risparmio e investimenti | B10: Risparmio e investimenti | C10: =SUMIFS(C$14:C$73,$B$14:$B$73,"Risparmio e investimenti") | D10: =SUMIFS(D$14:D$73,$B$14:$B$73,"Risparmio e investimenti") | E10: =SUMIFS(E$14:E$73,$B$14:$B$73,"Risparmio e investimenti") | F10: =SUMIFS(F$14:F$73,$B$14:$B$73,"Risparmio e investimenti") | G10: =SUMIFS(G$14:G$73,$B$14:$B$73,"Risparmio e investimenti") | H10: =SUMIFS(H$14:H$73,$B$14:$B$73,"Risparmio e investimenti") | I10: =SUMIFS(I$14:I$73,$B$14:$B$73,"Risparmio e investimenti") | J10: =SUMIFS(J$14:J$73,$B$14:$B$73,"Risparmio e investimenti") | ... P10: =SUMIFS(P$14:P$73,$B$14:$B$73,"Risparmio e investimenti") | Q10: =O10-P10 | R10: =IF(P10=0,"",O10/P10) | T10: =SUMIFS(T$14:T$73,$B$14:$B$73,"Risparmio e investimenti") | U10: =SUMIFS(U$14:U$73,$B$14:$B$73,"Risparmio e investimenti") | V10: =U10-T10 | W10: =SUMIFS(W$14:W$73,$B$14:$B$73,"Risparmio e investimenti") | X10: =SUMIFS(X$14:X$73,$B$14:$B$73,"Risparmio e investimenti") | Y10: =X10-W10
A11: Avanzo (entrate − spese − risparmio) | B11: Risultato | C11: =C6-C9-C10 | D11: =D6-D9-D10 | E11: =E6-E9-E10 | F11: =F6-F9-F10 | G11: =G6-G9-G10 | H11: =H6-H9-H10 | I11: =I6-I9-I10 | J11: =J6-J9-J10 | ... P11: =P6-P9-P10 | Q11: =O11-P11 | R11: =IF(P11=0,"",O11/P11) | T11: =T6-T9-T10 | U11: =U6-U9-U10 | V11: =U11-T11 | W11: =W6-W9-W10 | X11: =X6-X9-X10 | Y11: =X11-W11
A12: Saldo di cassa a fine mese | B12: Saldo | C12: =Impostazioni!$C$5+C11 | D12: =C12+D11 | E12: =D12+E11 | F12: =E12+F11 | G12: =F12+G11 | H12: =G12+H11 | I12: =H12+I11 | J12: =I12+J11 | K12: =J12+K11 | ... N12: =M12+N11 | O12: =N12 | P12: =Budget!P12 | Q12: =O12-P12 | T12: =INDEX(Budget!$D$12:$O$12,Impostazioni!$C$12) | U12: =INDEX($C$12:$N$12,Impostazioni!$C$12) | V12: =U12-T12
A13: Dettaglio per categoria | T13: ="Mese di riferimento: "&LOWER(Impostazioni!$C$13) | W13: Da gennaio al mese di riferimento
A14: =IF(Categorie!$A6="","",Categorie!$A6) | B14: =IF(A14="","",Categorie!$B6&"") | C14: =IF($A14="",0,SUMIFS(Movimenti!$D$6:$D$2005,Movimenti!$C$6:$C$2005,$A14,Movimenti!$A$6:$A$2005,">="&DATE(Impostazioni!$C$4,C$4,1),Movimenti!$A$6:$A$2005,"<"&DATE(Impostazioni!$C$4,C$4+1,1))) | D14: =IF($A14="",0,SUMIFS(Movimenti!$D$6:$D$2005,Movimenti!$C$6:$C$2005,$A14,Movimenti!$A$6:$A$2005,">="&DATE(Impostazioni!$C$4,D$4,1),Movimenti!$A$6:$A$2005,"<"&DATE(Impostazioni!$C$4,D$4+1,1))) | E14: =IF($A14="",0,SUMIFS(Movimenti!$D$6:$D$2005,Movimenti!$C$6:$C$2005,$A14,Movimenti!$A$6:$A$2005,">="&DATE(Impostazioni!$C$4,E$4,1),Movimenti!$A$6:$A$2005,"<"&DATE(Impostazioni!$C$4,E$4+1,1))) | F14: =IF($A14="",0,SUMIFS(Movimenti!$D$6:$D$2005,Movimenti!$C$6:$C$2005,$A14,Movimenti!$A$6:$A$2005,">="&DATE(Impostazioni!$C$4,F$4,1),Movimenti!$A$6:$A$2005,"<"&DATE(Impostazioni!$C$4,F$4+1,1))) | G14: =IF($A14="",0,SUMIFS(Movimenti!$D$6:$D$2005,Movimenti!$C$6:$C$2005,$A14,Movimenti!$A$6:$A$2005,">="&DATE(Impostazioni!$C$4,G$4,1),Movimenti!$A$6:$A$2005,"<"&DATE(Impostazioni!$C$4,G$4+1,1))) | H14: =IF($A14="",0,SUMIFS(Movimenti!$D$6:$D$2005,Movimenti!$C$6:$C$2005,$A14,Movimenti!$A$6:$A$2005,">="&DATE(Impostazioni!$C$4,H$4,1),Movimenti!$A$6:$A$2005,"<"&DATE(Impostazioni!$C$4,H$4+1,1))) | I14: =IF($A14="",0,SUMIFS(Movimenti!$D$6:$D$2005,Movimenti!$C$6:$C$2005,$A14,Movimenti!$A$6:$A$2005,">="&DATE(Impostazioni!$C$4,I$4,1),Movimenti!$A$6:$A$2005,"<"&DATE(Impostazioni!$C$4,I$4+1,1))) | J14: =IF($A14="",0,SUMIFS(Movimenti!$D$6:$D$2005,Movimenti!$C$6:$C$2005,$A14,Movimenti!$A$6:$A$2005,">="&DATE(Impostazioni!$C$4,J$4,1),Movimenti!$A$6:$A$2005,"<"&DATE(Impostazioni!$C$4,J$4+1,1))) | ... N14: =IF($A14="",0,SUMIFS(Movimenti!$D$6:$D$2005,Movimenti!$C$6:$C$2005,$A14,Movimenti!$A$6:$A$2005,">="&DATE(Impostazioni!$C$4,N$4,1),Movimenti!$A$6:$A$2005,"<"&DATE(Impostazioni!$C$4,N$4+1,1))) | O14: =SUM(C14:N14) | P14: =Budget!P14 | Q14: =O14-P14 | R14: =IF(P14=0,"",O14/P14) | T14: =INDEX(Budget!$D14:$O14,Impostazioni!$C$12) | U14: =INDEX($C14:$N14,Impostazioni!$C$12) | V14: =U14-T14 | W14: =SUMIFS(Budget!$D14:$O14,Budget!$D$4:$O$4,"<="&Impostazioni!$C$12) | X14: =SUMIFS($C14:$N14,$C$4:$N$4,"<="&Impostazioni!$C$12) | Y14: =X14-W14 | Z14: =IF(AND(O14>0,LEFT(B14,5)="Spesa"),O14-ROW()/10000000,0)
A15: =IF(Categorie!$A7="","",Categorie!$A7) | B15: =IF(A15="","",Categorie!$B7&"") | C15: =IF($A15="",0,SUMIFS(Movimenti!$D$6:$D$2005,Movimenti!$C$6:$C$2005,$A15,Movimenti!$A$6:$A$2005,">="&DATE(Impostazioni!$C$4,C$4,1),Movimenti!$A$6:$A$2005,"<"&DATE(Impostazioni!$C$4,C$4+1,1))) | D15: =IF($A15="",0,SUMIFS(Movimenti!$D$6:$D$2005,Movimenti!$C$6:$C$2005,$A15,Movimenti!$A$6:$A$2005,">="&DATE(Impostazioni!$C$4,D$4,1),Movimenti!$A$6:$A$2005,"<"&DATE(Impostazioni!$C$4,D$4+1,1))) | E15: =IF($A15="",0,SUMIFS(Movimenti!$D$6:$D$2005,Movimenti!$C$6:$C$2005,$A15,Movimenti!$A$6:$A$2005,">="&DATE(Impostazioni!$C$4,E$4,1),Movimenti!$A$6:$A$2005,"<"&DATE(Impostazioni!$C$4,E$4+1,1))) | F15: =IF($A15="",0,SUMIFS(Movimenti!$D$6:$D$2005,Movimenti!$C$6:$C$2005,$A15,Movimenti!$A$6:$A$2005,">="&DATE(Impostazioni!$C$4,F$4,1),Movimenti!$A$6:$A$2005,"<"&DATE(Impostazioni!$C$4,F$4+1,1))) | G15: =IF($A15="",0,SUMIFS(Movimenti!$D$6:$D$2005,Movimenti!$C$6:$C$2005,$A15,Movimenti!$A$6:$A$2005,">="&DATE(Impostazioni!$C$4,G$4,1),Movimenti!$A$6:$A$2005,"<"&DATE(Impostazioni!$C$4,G$4+1,1))) | H15: =IF($A15="",0,SUMIFS(Movimenti!$D$6:$D$2005,Movimenti!$C$6:$C$2005,$A15,Movimenti!$A$6:$A$2005,">="&DATE(Impostazioni!$C$4,H$4,1),Movimenti!$A$6:$A$2005,"<"&DATE(Impostazioni!$C$4,H$4+1,1))) | I15: =IF($A15="",0,SUMIFS(Movimenti!$D$6:$D$2005,Movimenti!$C$6:$C$2005,$A15,Movimenti!$A$6:$A$2005,">="&DATE(Impostazioni!$C$4,I$4,1),Movimenti!$A$6:$A$2005,"<"&DATE(Impostazioni!$C$4,I$4+1,1))) | J15: =IF($A15="",0,SUMIFS(Movimenti!$D$6:$D$2005,Movimenti!$C$6:$C$2005,$A15,Movimenti!$A$6:$A$2005,">="&DATE(Impostazioni!$C$4,J$4,1),Movimenti!$A$6:$A$2005,"<"&DATE(Impostazioni!$C$4,J$4+1,1))) | ... N15: =IF($A15="",0,SUMIFS(Movimenti!$D$6:$D$2005,Movimenti!$C$6:$C$2005,$A15,Movimenti!$A$6:$A$2005,">="&DATE(Impostazioni!$C$4,N$4,1),Movimenti!$A$6:$A$2005,"<"&DATE(Impostazioni!$C$4,N$4+1,1))) | O15: =SUM(C15:N15) | P15: =Budget!P15 | Q15: =O15-P15 | R15: =IF(P15=0,"",O15/P15) | T15: =INDEX(Budget!$D15:$O15,Impostazioni!$C$12) | U15: =INDEX($C15:$N15,Impostazioni!$C$12) | V15: =U15-T15 | W15: =SUMIFS(Budget!$D15:$O15,Budget!$D$4:$O$4,"<="&Impostazioni!$C$12) | X15: =SUMIFS($C15:$N15,$C$4:$N$4,"<="&Impostazioni!$C$12) | Y15: =X15-W15 | Z15: =IF(AND(O15>0,LEFT(B15,5)="Spesa"),O15-ROW()/10000000,0)
A16: =IF(Categorie!$A8="","",Categorie!$A8) | B16: =IF(A16="","",Categorie!$B8&"") | C16: =IF($A16="",0,SUMIFS(Movimenti!$D$6:$D$2005,Movimenti!$C$6:$C$2005,$A16,Movimenti!$A$6:$A$2005,">="&DATE(Impostazioni!$C$4,C$4,1),Movimenti!$A$6:$A$2005,"<"&DATE(Impostazioni!$C$4,C$4+1,1))) | D16: =IF($A16="",0,SUMIFS(Movimenti!$D$6:$D$2005,Movimenti!$C$6:$C$2005,$A16,Movimenti!$A$6:$A$2005,">="&DATE(Impostazioni!$C$4,D$4,1),Movimenti!$A$6:$A$2005,"<"&DATE(Impostazioni!$C$4,D$4+1,1))) | E16: =IF($A16="",0,SUMIFS(Movimenti!$D$6:$D$2005,Movimenti!$C$6:$C$2005,$A16,Movimenti!$A$6:$A$2005,">="&DATE(Impostazioni!$C$4,E$4,1),Movimenti!$A$6:$A$2005,"<"&DATE(Impostazioni!$C$4,E$4+1,1))) | F16: =IF($A16="",0,SUMIFS(Movimenti!$D$6:$D$2005,Movimenti!$C$6:$C$2005,$A16,Movimenti!$A$6:$A$2005,">="&DATE(Impostazioni!$C$4,F$4,1),Movimenti!$A$6:$A$2005,"<"&DATE(Impostazioni!$C$4,F$4+1,1))) | G16: =IF($A16="",0,SUMIFS(Movimenti!$D$6:$D$2005,Movimenti!$C$6:$C$2005,$A16,Movimenti!$A$6:$A$2005,">="&DATE(Impostazioni!$C$4,G$4,1),Movimenti!$A$6:$A$2005,"<"&DATE(Impostazioni!$C$4,G$4+1,1))) | H16: =IF($A16="",0,SUMIFS(Movimenti!$D$6:$D$2005,Movimenti!$C$6:$C$2005,$A16,Movimenti!$A$6:$A$2005,">="&DATE(Impostazioni!$C$4,H$4,1),Movimenti!$A$6:$A$2005,"<"&DATE(Impostazioni!$C$4,H$4+1,1))) | I16: =IF($A16="",0,SUMIFS(Movimenti!$D$6:$D$2005,Movimenti!$C$6:$C$2005,$A16,Movimenti!$A$6:$A$2005,">="&DATE(Impostazioni!$C$4,I$4,1),Movimenti!$A$6:$A$2005,"<"&DATE(Impostazioni!$C$4,I$4+1,1))) | J16: =IF($A16="",0,SUMIFS(Movimenti!$D$6:$D$2005,Movimenti!$C$6:$C$2005,$A16,Movimenti!$A$6:$A$2005,">="&DATE(Impostazioni!$C$4,J$4,1),Movimenti!$A$6:$A$2005,"<"&DATE(Impostazioni!$C$4,J$4+1,1))) | ... N16: =IF($A16="",0,SUMIFS(Movimenti!$D$6:$D$2005,Movimenti!$C$6:$C$2005,$A16,Movimenti!$A$6:$A$2005,">="&DATE(Impostazioni!$C$4,N$4,1),Movimenti!$A$6:$A$2005,"<"&DATE(Impostazioni!$C$4,N$4+1,1))) | O16: =SUM(C16:N16) | P16: =Budget!P16 | Q16: =O16-P16 | R16: =IF(P16=0,"",O16/P16) | T16: =INDEX(Budget!$D16:$O16,Impostazioni!$C$12) | U16: =INDEX($C16:$N16,Impostazioni!$C$12) | V16: =U16-T16 | W16: =SUMIFS(Budget!$D16:$O16,Budget!$D$4:$O$4,"<="&Impostazioni!$C$12) | X16: =SUMIFS($C16:$N16,$C$4:$N$4,"<="&Impostazioni!$C$12) | Y16: =X16-W16 | Z16: =IF(AND(O16>0,LEFT(B16,5)="Spesa"),O16-ROW()/10000000,0)
A17: =IF(Categorie!$A9="","",Categorie!$A9) | B17: =IF(A17="","",Categorie!$B9&"") | C17: =IF($A17="",0,SUMIFS(Movimenti!$D$6:$D$2005,Movimenti!$C$6:$C$2005,$A17,Movimenti!$A$6:$A$2005,">="&DATE(Impostazioni!$C$4,C$4,1),Movimenti!$A$6:$A$2005,"<"&DATE(Impostazioni!$C$4,C$4+1,1))) | D17: =IF($A17="",0,SUMIFS(Movimenti!$D$6:$D$2005,Movimenti!$C$6:$C$2005,$A17,Movimenti!$A$6:$A$2005,">="&DATE(Impostazioni!$C$4,D$4,1),Movimenti!$A$6:$A$2005,"<"&DATE(Impostazioni!$C$4,D$4+1,1))) | E17: =IF($A17="",0,SUMIFS(Movimenti!$D$6:$D$2005,Movimenti!$C$6:$C$2005,$A17,Movimenti!$A$6:$A$2005,">="&DATE(Impostazioni!$C$4,E$4,1),Movimenti!$A$6:$A$2005,"<"&DATE(Impostazioni!$C$4,E$4+1,1))) | F17: =IF($A17="",0,SUMIFS(Movimenti!$D$6:$D$2005,Movimenti!$C$6:$C$2005,$A17,Movimenti!$A$6:$A$2005,">="&DATE(Impostazioni!$C$4,F$4,1),Movimenti!$A$6:$A$2005,"<"&DATE(Impostazioni!$C$4,F$4+1,1))) | G17: =IF($A17="",0,SUMIFS(Movimenti!$D$6:$D$2005,Movimenti!$C$6:$C$2005,$A17,Movimenti!$A$6:$A$2005,">="&DATE(Impostazioni!$C$4,G$4,1),Movimenti!$A$6:$A$2005,"<"&DATE(Impostazioni!$C$4,G$4+1,1))) | H17: =IF($A17="",0,SUMIFS(Movimenti!$D$6:$D$2005,Movimenti!$C$6:$C$2005,$A17,Movimenti!$A$6:$A$2005,">="&DATE(Impostazioni!$C$4,H$4,1),Movimenti!$A$6:$A$2005,"<"&DATE(Impostazioni!$C$4,H$4+1,1))) | I17: =IF($A17="",0,SUMIFS(Movimenti!$D$6:$D$2005,Movimenti!$C$6:$C$2005,$A17,Movimenti!$A$6:$A$2005,">="&DATE(Impostazioni!$C$4,I$4,1),Movimenti!$A$6:$A$2005,"<"&DATE(Impostazioni!$C$4,I$4+1,1))) | J17: =IF($A17="",0,SUMIFS(Movimenti!$D$6:$D$2005,Movimenti!$C$6:$C$2005,$A17,Movimenti!$A$6:$A$2005,">="&DATE(Impostazioni!$C$4,J$4,1),Movimenti!$A$6:$A$2005,"<"&DATE(Impostazioni!$C$4,J$4+1,1))) | ... N17: =IF($A17="",0,SUMIFS(Movimenti!$D$6:$D$2005,Movimenti!$C$6:$C$2005,$A17,Movimenti!$A$6:$A$2005,">="&DATE(Impostazioni!$C$4,N$4,1),Movimenti!$A$6:$A$2005,"<"&DATE(Impostazioni!$C$4,N$4+1,1))) | O17: =SUM(C17:N17) | P17: =Budget!P17 | Q17: =O17-P17 | R17: =IF(P17=0,"",O17/P17) | T17: =INDEX(Budget!$D17:$O17,Impostazioni!$C$12) | U17: =INDEX($C17:$N17,Impostazioni!$C$12) | V17: =U17-T17 | W17: =SUMIFS(Budget!$D17:$O17,Budget!$D$4:$O$4,"<="&Impostazioni!$C$12) | X17: =SUMIFS($C17:$N17,$C$4:$N$4,"<="&Impostazioni!$C$12) | Y17: =X17-W17 | Z17: =IF(AND(O17>0,LEFT(B17,5)="Spesa"),O17-ROW()/10000000,0)
A18: =IF(Categorie!$A10="","",Categorie!$A10) | B18: =IF(A18="","",Categorie!$B10&"") | C18: =IF($A18="",0,SUMIFS(Movimenti!$D$6:$D$2005,Movimenti!$C$6:$C$2005,$A18,Movimenti!$A$6:$A$2005,">="&DATE(Impostazioni!$C$4,C$4,1),Movimenti!$A$6:$A$2005,"<"&DATE(Impostazioni!$C$4,C$4+1,1))) | D18: =IF($A18="",0,SUMIFS(Movimenti!$D$6:$D$2005,Movimenti!$C$6:$C$2005,$A18,Movimenti!$A$6:$A$2005,">="&DATE(Impostazioni!$C$4,D$4,1),Movimenti!$A$6:$A$2005,"<"&DATE(Impostazioni!$C$4,D$4+1,1))) | E18: =IF($A18="",0,SUMIFS(Movimenti!$D$6:$D$2005,Movimenti!$C$6:$C$2005,$A18,Movimenti!$A$6:$A$2005,">="&DATE(Impostazioni!$C$4,E$4,1),Movimenti!$A$6:$A$2005,"<"&DATE(Impostazioni!$C$4,E$4+1,1))) | F18: =IF($A18="",0,SUMIFS(Movimenti!$D$6:$D$2005,Movimenti!$C$6:$C$2005,$A18,Movimenti!$A$6:$A$2005,">="&DATE(Impostazioni!$C$4,F$4,1),Movimenti!$A$6:$A$2005,"<"&DATE(Impostazioni!$C$4,F$4+1,1))) | G18: =IF($A18="",0,SUMIFS(Movimenti!$D$6:$D$2005,Movimenti!$C$6:$C$2005,$A18,Movimenti!$A$6:$A$2005,">="&DATE(Impostazioni!$C$4,G$4,1),Movimenti!$A$6:$A$2005,"<"&DATE(Impostazioni!$C$4,G$4+1,1))) | H18: =IF($A18="",0,SUMIFS(Movimenti!$D$6:$D$2005,Movimenti!$C$6:$C$2005,$A18,Movimenti!$A$6:$A$2005,">="&DATE(Impostazioni!$C$4,H$4,1),Movimenti!$A$6:$A$2005,"<"&DATE(Impostazioni!$C$4,H$4+1,1))) | I18: =IF($A18="",0,SUMIFS(Movimenti!$D$6:$D$2005,Movimenti!$C$6:$C$2005,$A18,Movimenti!$A$6:$A$2005,">="&DATE(Impostazioni!$C$4,I$4,1),Movimenti!$A$6:$A$2005,"<"&DATE(Impostazioni!$C$4,I$4+1,1))) | J18: =IF($A18="",0,SUMIFS(Movimenti!$D$6:$D$2005,Movimenti!$C$6:$C$2005,$A18,Movimenti!$A$6:$A$2005,">="&DATE(Impostazioni!$C$4,J$4,1),Movimenti!$A$6:$A$2005,"<"&DATE(Impostazioni!$C$4,J$4+1,1))) | ... N18: =IF($A18="",0,SUMIFS(Movimenti!$D$6:$D$2005,Movimenti!$C$6:$C$2005,$A18,Movimenti!$A$6:$A$2005,">="&DATE(Impostazioni!$C$4,N$4,1),Movimenti!$A$6:$A$2005,"<"&DATE(Impostazioni!$C$4,N$4+1,1))) | O18: =SUM(C18:N18) | P18: =Budget!P18 | Q18: =O18-P18 | R18: =IF(P18=0,"",O18/P18) | T18: =INDEX(Budget!$D18:$O18,Impostazioni!$C$12) | U18: =INDEX($C18:$N18,Impostazioni!$C$12) | V18: =U18-T18 | W18: =SUMIFS(Budget!$D18:$O18,Budget!$D$4:$O$4,"<="&Impostazioni!$C$12) | X18: =SUMIFS($C18:$N18,$C$4:$N$4,"<="&Impostazioni!$C$12) | Y18: =X18-W18 | Z18: =IF(AND(O18>0,LEFT(B18,5)="Spesa"),O18-ROW()/10000000,0)
A19: =IF(Categorie!$A11="","",Categorie!$A11) | B19: =IF(A19="","",Categorie!$B11&"") | C19: =IF($A19="",0,SUMIFS(Movimenti!$D$6:$D$2005,Movimenti!$C$6:$C$2005,$A19,Movimenti!$A$6:$A$2005,">="&DATE(Impostazioni!$C$4,C$4,1),Movimenti!$A$6:$A$2005,"<"&DATE(Impostazioni!$C$4,C$4+1,1))) | D19: =IF($A19="",0,SUMIFS(Movimenti!$D$6:$D$2005,Movimenti!$C$6:$C$2005,$A19,Movimenti!$A$6:$A$2005,">="&DATE(Impostazioni!$C$4,D$4,1),Movimenti!$A$6:$A$2005,"<"&DATE(Impostazioni!$C$4,D$4+1,1))) | E19: =IF($A19="",0,SUMIFS(Movimenti!$D$6:$D$2005,Movimenti!$C$6:$C$2005,$A19,Movimenti!$A$6:$A$2005,">="&DATE(Impostazioni!$C$4,E$4,1),Movimenti!$A$6:$A$2005,"<"&DATE(Impostazioni!$C$4,E$4+1,1))) | F19: =IF($A19="",0,SUMIFS(Movimenti!$D$6:$D$2005,Movimenti!$C$6:$C$2005,$A19,Movimenti!$A$6:$A$2005,">="&DATE(Impostazioni!$C$4,F$4,1),Movimenti!$A$6:$A$2005,"<"&DATE(Impostazioni!$C$4,F$4+1,1))) | G19: =IF($A19="",0,SUMIFS(Movimenti!$D$6:$D$2005,Movimenti!$C$6:$C$2005,$A19,Movimenti!$A$6:$A$2005,">="&DATE(Impostazioni!$C$4,G$4,1),Movimenti!$A$6:$A$2005,"<"&DATE(Impostazioni!$C$4,G$4+1,1))) | H19: =IF($A19="",0,SUMIFS(Movimenti!$D$6:$D$2005,Movimenti!$C$6:$C$2005,$A19,Movimenti!$A$6:$A$2005,">="&DATE(Impostazioni!$C$4,H$4,1),Movimenti!$A$6:$A$2005,"<"&DATE(Impostazioni!$C$4,H$4+1,1))) | I19: =IF($A19="",0,SUMIFS(Movimenti!$D$6:$D$2005,Movimenti!$C$6:$C$2005,$A19,Movimenti!$A$6:$A$2005,">="&DATE(Impostazioni!$C$4,I$4,1),Movimenti!$A$6:$A$2005,"<"&DATE(Impostazioni!$C$4,I$4+1,1))) | J19: =IF($A19="",0,SUMIFS(Movimenti!$D$6:$D$2005,Movimenti!$C$6:$C$2005,$A19,Movimenti!$A$6:$A$2005,">="&DATE(Impostazioni!$C$4,J$4,1),Movimenti!$A$6:$A$2005,"<"&DATE(Impostazioni!$C$4,J$4+1,1))) | ... N19: =IF($A19="",0,SUMIFS(Movimenti!$D$6:$D$2005,Movimenti!$C$6:$C$2005,$A19,Movimenti!$A$6:$A$2005,">="&DATE(Impostazioni!$C$4,N$4,1),Movimenti!$A$6:$A$2005,"<"&DATE(Impostazioni!$C$4,N$4+1,1))) | O19: =SUM(C19:N19) | P19: =Budget!P19 | Q19: =O19-P19 | R19: =IF(P19=0,"",O19/P19) | T19: =INDEX(Budget!$D19:$O19,Impostazioni!$C$12) | U19: =INDEX($C19:$N19,Impostazioni!$C$12) | V19: =U19-T19 | W19: =SUMIFS(Budget!$D19:$O19,Budget!$D$4:$O$4,"<="&Impostazioni!$C$12) | X19: =SUMIFS($C19:$N19,$C$4:$N$4,"<="&Impostazioni!$C$12) | Y19: =X19-W19 | Z19: =IF(AND(O19>0,LEFT(B19,5)="Spesa"),O19-ROW()/10000000,0)
A20: =IF(Categorie!$A12="","",Categorie!$A12) | B20: =IF(A20="","",Categorie!$B12&"") | C20: =IF($A20="",0,SUMIFS(Movimenti!$D$6:$D$2005,Movimenti!$C$6:$C$2005,$A20,Movimenti!$A$6:$A$2005,">="&DATE(Impostazioni!$C$4,C$4,1),Movimenti!$A$6:$A$2005,"<"&DATE(Impostazioni!$C$4,C$4+1,1))) | D20: =IF($A20="",0,SUMIFS(Movimenti!$D$6:$D$2005,Movimenti!$C$6:$C$2005,$A20,Movimenti!$A$6:$A$2005,">="&DATE(Impostazioni!$C$4,D$4,1),Movimenti!$A$6:$A$2005,"<"&DATE(Impostazioni!$C$4,D$4+1,1))) | E20: =IF($A20="",0,SUMIFS(Movimenti!$D$6:$D$2005,Movimenti!$C$6:$C$2005,$A20,Movimenti!$A$6:$A$2005,">="&DATE(Impostazioni!$C$4,E$4,1),Movimenti!$A$6:$A$2005,"<"&DATE(Impostazioni!$C$4,E$4+1,1))) | F20: =IF($A20="",0,SUMIFS(Movimenti!$D$6:$D$2005,Movimenti!$C$6:$C$2005,$A20,Movimenti!$A$6:$A$2005,">="&DATE(Impostazioni!$C$4,F$4,1),Movimenti!$A$6:$A$2005,"<"&DATE(Impostazioni!$C$4,F$4+1,1))) | G20: =IF($A20="",0,SUMIFS(Movimenti!$D$6:$D$2005,Movimenti!$C$6:$C$2005,$A20,Movimenti!$A$6:$A$2005,">="&DATE(Impostazioni!$C$4,G$4,1),Movimenti!$A$6:$A$2005,"<"&DATE(Impostazioni!$C$4,G$4+1,1))) | H20: =IF($A20="",0,SUMIFS(Movimenti!$D$6:$D$2005,Movimenti!$C$6:$C$2005,$A20,Movimenti!$A$6:$A$2005,">="&DATE(Impostazioni!$C$4,H$4,1),Movimenti!$A$6:$A$2005,"<"&DATE(Impostazioni!$C$4,H$4+1,1))) | I20: =IF($A20="",0,SUMIFS(Movimenti!$D$6:$D$2005,Movimenti!$C$6:$C$2005,$A20,Movimenti!$A$6:$A$2005,">="&DATE(Impostazioni!$C$4,I$4,1),Movimenti!$A$6:$A$2005,"<"&DATE(Impostazioni!$C$4,I$4+1,1))) | J20: =IF($A20="",0,SUMIFS(Movimenti!$D$6:$D$2005,Movimenti!$C$6:$C$2005,$A20,Movimenti!$A$6:$A$2005,">="&DATE(Impostazioni!$C$4,J$4,1),Movimenti!$A$6:$A$2005,"<"&DATE(Impostazioni!$C$4,J$4+1,1))) | ... N20: =IF($A20="",0,SUMIFS(Movimenti!$D$6:$D$2005,Movimenti!$C$6:$C$2005,$A20,Movimenti!$A$6:$A$2005,">="&DATE(Impostazioni!$C$4,N$4,1),Movimenti!$A$6:$A$2005,"<"&DATE(Impostazioni!$C$4,N$4+1,1))) | O20: =SUM(C20:N20) | P20: =Budget!P20 | Q20: =O20-P20 | R20: =IF(P20=0,"",O20/P20) | T20: =INDEX(Budget!$D20:$O20,Impostazioni!$C$12) | U20: =INDEX($C20:$N20,Impostazioni!$C$12) | V20: =U20-T20 | W20: =SUMIFS(Budget!$D20:$O20,Budget!$D$4:$O$4,"<="&Impostazioni!$C$12) | X20: =SUMIFS($C20:$N20,$C$4:$N$4,"<="&Impostazioni!$C$12) | Y20: =X20-W20 | Z20: =IF(AND(O20>0,LEFT(B20,5)="Spesa"),O20-ROW()/10000000,0)
A21: =IF(Categorie!$A13="","",Categorie!$A13) | B21: =IF(A21="","",Categorie!$B13&"") | C21: =IF($A21="",0,SUMIFS(Movimenti!$D$6:$D$2005,Movimenti!$C$6:$C$2005,$A21,Movimenti!$A$6:$A$2005,">="&DATE(Impostazioni!$C$4,C$4,1),Movimenti!$A$6:$A$2005,"<"&DATE(Impostazioni!$C$4,C$4+1,1))) | D21: =IF($A21="",0,SUMIFS(Movimenti!$D$6:$D$2005,Movimenti!$C$6:$C$2005,$A21,Movimenti!$A$6:$A$2005,">="&DATE(Impostazioni!$C$4,D$4,1),Movimenti!$A$6:$A$2005,"<"&DATE(Impostazioni!$C$4,D$4+1,1))) | E21: =IF($A21="",0,SUMIFS(Movimenti!$D$6:$D$2005,Movimenti!$C$6:$C$2005,$A21,Movimenti!$A$6:$A$2005,">="&DATE(Impostazioni!$C$4,E$4,1),Movimenti!$A$6:$A$2005,"<"&DATE(Impostazioni!$C$4,E$4+1,1))) | F21: =IF($A21="",0,SUMIFS(Movimenti!$D$6:$D$2005,Movimenti!$C$6:$C$2005,$A21,Movimenti!$A$6:$A$2005,">="&DATE(Impostazioni!$C$4,F$4,1),Movimenti!$A$6:$A$2005,"<"&DATE(Impostazioni!$C$4,F$4+1,1))) | G21: =IF($A21="",0,SUMIFS(Movimenti!$D$6:$D$2005,Movimenti!$C$6:$C$2005,$A21,Movimenti!$A$6:$A$2005,">="&DATE(Impostazioni!$C$4,G$4,1),Movimenti!$A$6:$A$2005,"<"&DATE(Impostazioni!$C$4,G$4+1,1))) | H21: =IF($A21="",0,SUMIFS(Movimenti!$D$6:$D$2005,Movimenti!$C$6:$C$2005,$A21,Movimenti!$A$6:$A$2005,">="&DATE(Impostazioni!$C$4,H$4,1),Movimenti!$A$6:$A$2005,"<"&DATE(Impostazioni!$C$4,H$4+1,1))) | I21: =IF($A21="",0,SUMIFS(Movimenti!$D$6:$D$2005,Movimenti!$C$6:$C$2005,$A21,Movimenti!$A$6:$A$2005,">="&DATE(Impostazioni!$C$4,I$4,1),Movimenti!$A$6:$A$2005,"<"&DATE(Impostazioni!$C$4,I$4+1,1))) | J21: =IF($A21="",0,SUMIFS(Movimenti!$D$6:$D$2005,Movimenti!$C$6:$C$2005,$A21,Movimenti!$A$6:$A$2005,">="&DATE(Impostazioni!$C$4,J$4,1),Movimenti!$A$6:$A$2005,"<"&DATE(Impostazioni!$C$4,J$4+1,1))) | ... N21: =IF($A21="",0,SUMIFS(Movimenti!$D$6:$D$2005,Movimenti!$C$6:$C$2005,$A21,Movimenti!$A$6:$A$2005,">="&DATE(Impostazioni!$C$4,N$4,1),Movimenti!$A$6:$A$2005,"<"&DATE(Impostazioni!$C$4,N$4+1,1))) | O21: =SUM(C21:N21) | P21: =Budget!P21 | Q21: =O21-P21 | R21: =IF(P21=0,"",O21/P21) | T21: =INDEX(Budget!$D21:$O21,Impostazioni!$C$12) | U21: =INDEX($C21:$N21,Impostazioni!$C$12) | V21: =U21-T21 | W21: =SUMIFS(Budget!$D21:$O21,Budget!$D$4:$O$4,"<="&Impostazioni!$C$12) | X21: =SUMIFS($C21:$N21,$C$4:$N$4,"<="&Impostazioni!$C$12) | Y21: =X21-W21 | Z21: =IF(AND(O21>0,LEFT(B21,5)="Spesa"),O21-ROW()/10000000,0)
A22: =IF(Categorie!$A14="","",Categorie!$A14) | B22: =IF(A22="","",Categorie!$B14&"") | C22: =IF($A22="",0,SUMIFS(Movimenti!$D$6:$D$2005,Movimenti!$C$6:$C$2005,$A22,Movimenti!$A$6:$A$2005,">="&DATE(Impostazioni!$C$4,C$4,1),Movimenti!$A$6:$A$2005,"<"&DATE(Impostazioni!$C$4,C$4+1,1))) | D22: =IF($A22="",0,SUMIFS(Movimenti!$D$6:$D$2005,Movimenti!$C$6:$C$2005,$A22,Movimenti!$A$6:$A$2005,">="&DATE(Impostazioni!$C$4,D$4,1),Movimenti!$A$6:$A$2005,"<"&DATE(Impostazioni!$C$4,D$4+1,1))) | E22: =IF($A22="",0,SUMIFS(Movimenti!$D$6:$D$2005,Movimenti!$C$6:$C$2005,$A22,Movimenti!$A$6:$A$2005,">="&DATE(Impostazioni!$C$4,E$4,1),Movimenti!$A$6:$A$2005,"<"&DATE(Impostazioni!$C$4,E$4+1,1))) | F22: =IF($A22="",0,SUMIFS(Movimenti!$D$6:$D$2005,Movimenti!$C$6:$C$2005,$A22,Movimenti!$A$6:$A$2005,">="&DATE(Impostazioni!$C$4,F$4,1),Movimenti!$A$6:$A$2005,"<"&DATE(Impostazioni!$C$4,F$4+1,1))) | G22: =IF($A22="",0,SUMIFS(Movimenti!$D$6:$D$2005,Movimenti!$C$6:$C$2005,$A22,Movimenti!$A$6:$A$2005,">="&DATE(Impostazioni!$C$4,G$4,1),Movimenti!$A$6:$A$2005,"<"&DATE(Impostazioni!$C$4,G$4+1,1))) | H22: =IF($A22="",0,SUMIFS(Movimenti!$D$6:$D$2005,Movimenti!$C$6:$C$2005,$A22,Movimenti!$A$6:$A$2005,">="&DATE(Impostazioni!$C$4,H$4,1),Movimenti!$A$6:$A$2005,"<"&DATE(Impostazioni!$C$4,H$4+1,1))) | I22: =IF($A22="",0,SUMIFS(Movimenti!$D$6:$D$2005,Movimenti!$C$6:$C$2005,$A22,Movimenti!$A$6:$A$2005,">="&DATE(Impostazioni!$C$4,I$4,1),Movimenti!$A$6:$A$2005,"<"&DATE(Impostazioni!$C$4,I$4+1,1))) | J22: =IF($A22="",0,SUMIFS(Movimenti!$D$6:$D$2005,Movimenti!$C$6:$C$2005,$A22,Movimenti!$A$6:$A$2005,">="&DATE(Impostazioni!$C$4,J$4,1),Movimenti!$A$6:$A$2005,"<"&DATE(Impostazioni!$C$4,J$4+1,1))) | ... N22: =IF($A22="",0,SUMIFS(Movimenti!$D$6:$D$2005,Movimenti!$C$6:$C$2005,$A22,Movimenti!$A$6:$A$2005,">="&DATE(Impostazioni!$C$4,N$4,1),Movimenti!$A$6:$A$2005,"<"&DATE(Impostazioni!$C$4,N$4+1,1))) | O22: =SUM(C22:N22) | P22: =Budget!P22 | Q22: =O22-P22 | R22: =IF(P22=0,"",O22/P22) | T22: =INDEX(Budget!$D22:$O22,Impostazioni!$C$12) | U22: =INDEX($C22:$N22,Impostazioni!$C$12) | V22: =U22-T22 | W22: =SUMIFS(Budget!$D22:$O22,Budget!$D$4:$O$4,"<="&Impostazioni!$C$12) | X22: =SUMIFS($C22:$N22,$C$4:$N$4,"<="&Impostazioni!$C$12) | Y22: =X22-W22 | Z22: =IF(AND(O22>0,LEFT(B22,5)="Spesa"),O22-ROW()/10000000,0)
A23: =IF(Categorie!$A15="","",Categorie!$A15) | B23: =IF(A23="","",Categorie!$B15&"") | C23: =IF($A23="",0,SUMIFS(Movimenti!$D$6:$D$2005,Movimenti!$C$6:$C$2005,$A23,Movimenti!$A$6:$A$2005,">="&DATE(Impostazioni!$C$4,C$4,1),Movimenti!$A$6:$A$2005,"<"&DATE(Impostazioni!$C$4,C$4+1,1))) | D23: =IF($A23="",0,SUMIFS(Movimenti!$D$6:$D$2005,Movimenti!$C$6:$C$2005,$A23,Movimenti!$A$6:$A$2005,">="&DATE(Impostazioni!$C$4,D$4,1),Movimenti!$A$6:$A$2005,"<"&DATE(Impostazioni!$C$4,D$4+1,1))) | E23: =IF($A23="",0,SUMIFS(Movimenti!$D$6:$D$2005,Movimenti!$C$6:$C$2005,$A23,Movimenti!$A$6:$A$2005,">="&DATE(Impostazioni!$C$4,E$4,1),Movimenti!$A$6:$A$2005,"<"&DATE(Impostazioni!$C$4,E$4+1,1))) | F23: =IF($A23="",0,SUMIFS(Movimenti!$D$6:$D$2005,Movimenti!$C$6:$C$2005,$A23,Movimenti!$A$6:$A$2005,">="&DATE(Impostazioni!$C$4,F$4,1),Movimenti!$A$6:$A$2005,"<"&DATE(Impostazioni!$C$4,F$4+1,1))) | G23: =IF($A23="",0,SUMIFS(Movimenti!$D$6:$D$2005,Movimenti!$C$6:$C$2005,$A23,Movimenti!$A$6:$A$2005,">="&DATE(Impostazioni!$C$4,G$4,1),Movimenti!$A$6:$A$2005,"<"&DATE(Impostazioni!$C$4,G$4+1,1))) | H23: =IF($A23="",0,SUMIFS(Movimenti!$D$6:$D$2005,Movimenti!$C$6:$C$2005,$A23,Movimenti!$A$6:$A$2005,">="&DATE(Impostazioni!$C$4,H$4,1),Movimenti!$A$6:$A$2005,"<"&DATE(Impostazioni!$C$4,H$4+1,1))) | I23: =IF($A23="",0,SUMIFS(Movimenti!$D$6:$D$2005,Movimenti!$C$6:$C$2005,$A23,Movimenti!$A$6:$A$2005,">="&DATE(Impostazioni!$C$4,I$4,1),Movimenti!$A$6:$A$2005,"<"&DATE(Impostazioni!$C$4,I$4+1,1))) | J23: =IF($A23="",0,SUMIFS(Movimenti!$D$6:$D$2005,Movimenti!$C$6:$C$2005,$A23,Movimenti!$A$6:$A$2005,">="&DATE(Impostazioni!$C$4,J$4,1),Movimenti!$A$6:$A$2005,"<"&DATE(Impostazioni!$C$4,J$4+1,1))) | ... N23: =IF($A23="",0,SUMIFS(Movimenti!$D$6:$D$2005,Movimenti!$C$6:$C$2005,$A23,Movimenti!$A$6:$A$2005,">="&DATE(Impostazioni!$C$4,N$4,1),Movimenti!$A$6:$A$2005,"<"&DATE(Impostazioni!$C$4,N$4+1,1))) | O23: =SUM(C23:N23) | P23: =Budget!P23 | Q23: =O23-P23 | R23: =IF(P23=0,"",O23/P23) | T23: =INDEX(Budget!$D23:$O23,Impostazioni!$C$12) | U23: =INDEX($C23:$N23,Impostazioni!$C$12) | V23: =U23-T23 | W23: =SUMIFS(Budget!$D23:$O23,Budget!$D$4:$O$4,"<="&Impostazioni!$C$12) | X23: =SUMIFS($C23:$N23,$C$4:$N$4,"<="&Impostazioni!$C$12) | Y23: =X23-W23 | Z23: =IF(AND(O23>0,LEFT(B23,5)="Spesa"),O23-ROW()/10000000,0)
A24: =IF(Categorie!$A16="","",Categorie!$A16) | B24: =IF(A24="","",Categorie!$B16&"") | C24: =IF($A24="",0,SUMIFS(Movimenti!$D$6:$D$2005,Movimenti!$C$6:$C$2005,$A24,Movimenti!$A$6:$A$2005,">="&DATE(Impostazioni!$C$4,C$4,1),Movimenti!$A$6:$A$2005,"<"&DATE(Impostazioni!$C$4,C$4+1,1))) | D24: =IF($A24="",0,SUMIFS(Movimenti!$D$6:$D$2005,Movimenti!$C$6:$C$2005,$A24,Movimenti!$A$6:$A$2005,">="&DATE(Impostazioni!$C$4,D$4,1),Movimenti!$A$6:$A$2005,"<"&DATE(Impostazioni!$C$4,D$4+1,1))) | E24: =IF($A24="",0,SUMIFS(Movimenti!$D$6:$D$2005,Movimenti!$C$6:$C$2005,$A24,Movimenti!$A$6:$A$2005,">="&DATE(Impostazioni!$C$4,E$4,1),Movimenti!$A$6:$A$2005,"<"&DATE(Impostazioni!$C$4,E$4+1,1))) | F24: =IF($A24="",0,SUMIFS(Movimenti!$D$6:$D$2005,Movimenti!$C$6:$C$2005,$A24,Movimenti!$A$6:$A$2005,">="&DATE(Impostazioni!$C$4,F$4,1),Movimenti!$A$6:$A$2005,"<"&DATE(Impostazioni!$C$4,F$4+1,1))) | G24: =IF($A24="",0,SUMIFS(Movimenti!$D$6:$D$2005,Movimenti!$C$6:$C$2005,$A24,Movimenti!$A$6:$A$2005,">="&DATE(Impostazioni!$C$4,G$4,1),Movimenti!$A$6:$A$2005,"<"&DATE(Impostazioni!$C$4,G$4+1,1))) | H24: =IF($A24="",0,SUMIFS(Movimenti!$D$6:$D$2005,Movimenti!$C$6:$C$2005,$A24,Movimenti!$A$6:$A$2005,">="&DATE(Impostazioni!$C$4,H$4,1),Movimenti!$A$6:$A$2005,"<"&DATE(Impostazioni!$C$4,H$4+1,1))) | I24: =IF($A24="",0,SUMIFS(Movimenti!$D$6:$D$2005,Movimenti!$C$6:$C$2005,$A24,Movimenti!$A$6:$A$2005,">="&DATE(Impostazioni!$C$4,I$4,1),Movimenti!$A$6:$A$2005,"<"&DATE(Impostazioni!$C$4,I$4+1,1))) | J24: =IF($A24="",0,SUMIFS(Movimenti!$D$6:$D$2005,Movimenti!$C$6:$C$2005,$A24,Movimenti!$A$6:$A$2005,">="&DATE(Impostazioni!$C$4,J$4,1),Movimenti!$A$6:$A$2005,"<"&DATE(Impostazioni!$C$4,J$4+1,1))) | ... N24: =IF($A24="",0,SUMIFS(Movimenti!$D$6:$D$2005,Movimenti!$C$6:$C$2005,$A24,Movimenti!$A$6:$A$2005,">="&DATE(Impostazioni!$C$4,N$4,1),Movimenti!$A$6:$A$2005,"<"&DATE(Impostazioni!$C$4,N$4+1,1))) | O24: =SUM(C24:N24) | P24: =Budget!P24 | Q24: =O24-P24 | R24: =IF(P24=0,"",O24/P24) | T24: =INDEX(Budget!$D24:$O24,Impostazioni!$C$12) | U24: =INDEX($C24:$N24,Impostazioni!$C$12) | V24: =U24-T24 | W24: =SUMIFS(Budget!$D24:$O24,Budget!$D$4:$O$4,"<="&Impostazioni!$C$12) | X24: =SUMIFS($C24:$N24,$C$4:$N$4,"<="&Impostazioni!$C$12) | Y24: =X24-W24 | Z24: =IF(AND(O24>0,LEFT(B24,5)="Spesa"),O24-ROW()/10000000,0)
A25: =IF(Categorie!$A17="","",Categorie!$A17) | B25: =IF(A25="","",Categorie!$B17&"") | C25: =IF($A25="",0,SUMIFS(Movimenti!$D$6:$D$2005,Movimenti!$C$6:$C$2005,$A25,Movimenti!$A$6:$A$2005,">="&DATE(Impostazioni!$C$4,C$4,1),Movimenti!$A$6:$A$2005,"<"&DATE(Impostazioni!$C$4,C$4+1,1))) | D25: =IF($A25="",0,SUMIFS(Movimenti!$D$6:$D$2005,Movimenti!$C$6:$C$2005,$A25,Movimenti!$A$6:$A$2005,">="&DATE(Impostazioni!$C$4,D$4,1),Movimenti!$A$6:$A$2005,"<"&DATE(Impostazioni!$C$4,D$4+1,1))) | E25: =IF($A25="",0,SUMIFS(Movimenti!$D$6:$D$2005,Movimenti!$C$6:$C$2005,$A25,Movimenti!$A$6:$A$2005,">="&DATE(Impostazioni!$C$4,E$4,1),Movimenti!$A$6:$A$2005,"<"&DATE(Impostazioni!$C$4,E$4+1,1))) | F25: =IF($A25="",0,SUMIFS(Movimenti!$D$6:$D$2005,Movimenti!$C$6:$C$2005,$A25,Movimenti!$A$6:$A$2005,">="&DATE(Impostazioni!$C$4,F$4,1),Movimenti!$A$6:$A$2005,"<"&DATE(Impostazioni!$C$4,F$4+1,1))) | G25: =IF($A25="",0,SUMIFS(Movimenti!$D$6:$D$2005,Movimenti!$C$6:$C$2005,$A25,Movimenti!$A$6:$A$2005,">="&DATE(Impostazioni!$C$4,G$4,1),Movimenti!$A$6:$A$2005,"<"&DATE(Impostazioni!$C$4,G$4+1,1))) | H25: =IF($A25="",0,SUMIFS(Movimenti!$D$6:$D$2005,Movimenti!$C$6:$C$2005,$A25,Movimenti!$A$6:$A$2005,">="&DATE(Impostazioni!$C$4,H$4,1),Movimenti!$A$6:$A$2005,"<"&DATE(Impostazioni!$C$4,H$4+1,1))) | I25: =IF($A25="",0,SUMIFS(Movimenti!$D$6:$D$2005,Movimenti!$C$6:$C$2005,$A25,Movimenti!$A$6:$A$2005,">="&DATE(Impostazioni!$C$4,I$4,1),Movimenti!$A$6:$A$2005,"<"&DATE(Impostazioni!$C$4,I$4+1,1))) | J25: =IF($A25="",0,SUMIFS(Movimenti!$D$6:$D$2005,Movimenti!$C$6:$C$2005,$A25,Movimenti!$A$6:$A$2005,">="&DATE(Impostazioni!$C$4,J$4,1),Movimenti!$A$6:$A$2005,"<"&DATE(Impostazioni!$C$4,J$4+1,1))) | ... N25: =IF($A25="",0,SUMIFS(Movimenti!$D$6:$D$2005,Movimenti!$C$6:$C$2005,$A25,Movimenti!$A$6:$A$2005,">="&DATE(Impostazioni!$C$4,N$4,1),Movimenti!$A$6:$A$2005,"<"&DATE(Impostazioni!$C$4,N$4+1,1))) | O25: =SUM(C25:N25) | P25: =Budget!P25 | Q25: =O25-P25 | R25: =IF(P25=0,"",O25/P25) | T25: =INDEX(Budget!$D25:$O25,Impostazioni!$C$12) | U25: =INDEX($C25:$N25,Impostazioni!$C$12) | V25: =U25-T25 | W25: =SUMIFS(Budget!$D25:$O25,Budget!$D$4:$O$4,"<="&Impostazioni!$C$12) | X25: =SUMIFS($C25:$N25,$C$4:$N$4,"<="&Impostazioni!$C$12) | Y25: =X25-W25 | Z25: =IF(AND(O25>0,LEFT(B25,5)="Spesa"),O25-ROW()/10000000,0)
... A73: =IF(Categorie!$A65="","",Categorie!$A65) | B73: =IF(A73="","",Categorie!$B65&"") | C73: =IF($A73="",0,SUMIFS(Movimenti!$D$6:$D$2005,Movimenti!$C$6:$C$2005,$A73,Movimenti!$A$6:$A$2005,">="&DATE(Impostazioni!$C$4,C$4,1),Movimenti!$A$6:$A$2005,"<"&DATE(Impostazioni!$C$4,C$4+1,1))) | D73: =IF($A73="",0,SUMIFS(Movimenti!$D$6:$D$2005,Movimenti!$C$6:$C$2005,$A73,Movimenti!$A$6:$A$2005,">="&DATE(Impostazioni!$C$4,D$4,1),Movimenti!$A$6:$A$2005,"<"&DATE(Impostazioni!$C$4,D$4+1,1))) | E73: =IF($A73="",0,SUMIFS(Movimenti!$D$6:$D$2005,Movimenti!$C$6:$C$2005,$A73,Movimenti!$A$6:$A$2005,">="&DATE(Impostazioni!$C$4,E$4,1),Movimenti!$A$6:$A$2005,"<"&DATE(Impostazioni!$C$4,E$4+1,1))) | F73: =IF($A73="",0,SUMIFS(Movimenti!$D$6:$D$2005,Movimenti!$C$6:$C$2005,$A73,Movimenti!$A$6:$A$2005,">="&DATE(Impostazioni!$C$4,F$4,1),Movimenti!$A$6:$A$2005,"<"&DATE(Impostazioni!$C$4,F$4+1,1))) | G73: =IF($A73="",0,SUMIFS(Movimenti!$D$6:$D$2005,Movimenti!$C$6:$C$2005,$A73,Movimenti!$A$6:$A$2005,">="&DATE(Impostazioni!$C$4,G$4,1),Movimenti!$A$6:$A$2005,"<"&DATE(Impostazioni!$C$4,G$4+1,1))) | H73: =IF($A73="",0,SUMIFS(Movimenti!$D$6:$D$2005,Movimenti!$C$6:$C$2005,$A73,Movimenti!$A$6:$A$2005,">="&DATE(Impostazioni!$C$4,H$4,1),Movimenti!$A$6:$A$2005,"<"&DATE(Impostazioni!$C$4,H$4+1,1))) | I73: =IF($A73="",0,SUMIFS(Movimenti!$D$6:$D$2005,Movimenti!$C$6:$C$2005,$A73,Movimenti!$A$6:$A$2005,">="&DATE(Impostazioni!$C$4,I$4,1),Movimenti!$A$6:$A$2005,"<"&DATE(Impostazioni!$C$4,I$4+1,1))) | J73: =IF($A73="",0,SUMIFS(Movimenti!$D$6:$D$2005,Movimenti!$C$6:$C$2005,$A73,Movimenti!$A$6:$A$2005,">="&DATE(Impostazioni!$C$4,J$4,1),Movimenti!$A$6:$A$2005,"<"&DATE(Impostazioni!$C$4,J$4+1,1))) | ... N73: =IF($A73="",0,SUMIFS(Movimenti!$D$6:$D$2005,Movimenti!$C$6:$C$2005,$A73,Movimenti!$A$6:$A$2005,">="&DATE(Impostazioni!$C$4,N$4,1),Movimenti!$A$6:$A$2005,"<"&DATE(Impostazioni!$C$4,N$4+1,1))) | O73: =SUM(C73:N73) | P73: =Budget!P73 | Q73: =O73-P73 | R73: =IF(P73=0,"",O73/P73) | T73: =INDEX(Budget!$D73:$O73,Impostazioni!$C$12) | U73: =INDEX($C73:$N73,Impostazioni!$C$12) | V73: =U73-T73 | W73: =SUMIFS(Budget!$D73:$O73,Budget!$D$4:$O$4,"<="&Impostazioni!$C$12) | X73: =SUMIFS($C73:$N73,$C$4:$N$4,"<="&Impostazioni!$C$12) | Y73: =X73-W73 | Z73: =IF(AND(O73>0,LEFT(B73,5)="Spesa"),O73-ROW()/10000000,0)

Sheet Dashboard
B1: ="Budget familiare "&Impostazioni!$C$4&IF(Impostazioni!$C$6="",""," · "&Impostazioni!$C$6)
B2: ="Totali dei movimenti registrati nell'anno. Confronti con il budget fino a "&LOWER(Impostazioni!$C$13)&"."
B4: Entrate | D4: Spese | F4: Risparmio | H4: Tasso di risparmio | J4: Saldo di cassa | L4: Debiti residui
B5: =Mensile!$O$6 | D5: =Mensile!$O$9 | F5: =Mensile!$O$6-Mensile!$O$9 | H5: =IF(Mensile!$O$6=0,0,(Mensile!$O$6-Mensile!$O$9)/Mensile!$O$6) | J5: =Mensile!$O$12 | L5: =Debiti!$C$18
B6: =IF(Mensile!$P$6=0,"",Mensile!$O$6/Mensile!$P$6) | D6: =IF(Mensile!$P$9=0,"",Mensile!$O$9/Mensile!$P$9) | F6: =Mensile!$O$10 | H6: risparmio / entrate | J6: =Impostazioni!$C$5 | L6: =Debiti!$E$18
B8: Andamento mensile
B9: Mese | C9: Entrate | D9: Spese | E9: Risparmio e investimenti | F9: Avanzo | G9: Saldo di cassa
B10: Gen | C10: =Mensile!C$6 | D10: =Mensile!C$9 | E10: =Mensile!C$10 | F10: =Mensile!C$11 | G10: =Mensile!C$12
B11: Feb | C11: =Mensile!D$6 | D11: =Mensile!D$9 | E11: =Mensile!D$10 | F11: =Mensile!D$11 | G11: =Mensile!D$12
B12: Mar | C12: =Mensile!E$6 | D12: =Mensile!E$9 | E12: =Mensile!E$10 | F12: =Mensile!E$11 | G12: =Mensile!E$12
B13: Apr | C13: =Mensile!F$6 | D13: =Mensile!F$9 | E13: =Mensile!F$10 | F13: =Mensile!F$11 | G13: =Mensile!F$12
B14: Mag | C14: =Mensile!G$6 | D14: =Mensile!G$9 | E14: =Mensile!G$10 | F14: =Mensile!G$11 | G14: =Mensile!G$12
B15: Giu | C15: =Mensile!H$6 | D15: =Mensile!H$9 | E15: =Mensile!H$10 | F15: =Mensile!H$11 | G15: =Mensile!H$12
B16: Lug | C16: =Mensile!I$6 | D16: =Mensile!I$9 | E16: =Mensile!I$10 | F16: =Mensile!I$11 | G16: =Mensile!I$12
B17: Ago | C17: =Mensile!J$6 | D17: =Mensile!J$9 | E17: =Mensile!J$10 | F17: =Mensile!J$11 | G17: =Mensile!J$12
B18: Set | C18: =Mensile!K$6 | D18: =Mensile!K$9 | E18: =Mensile!K$10 | F18: =Mensile!K$11 | G18: =Mensile!K$12
B19: Ott | C19: =Mensile!L$6 | D19: =Mensile!L$9 | E19: =Mensile!L$10 | F19: =Mensile!L$11 | G19: =Mensile!L$12
B20: Nov | C20: =Mensile!M$6 | D20: =Mensile!M$9 | E20: =Mensile!M$10 | F20: =Mensile!M$11 | G20: =Mensile!M$12
B21: Dic | C21: =Mensile!N$6 | D21: =Mensile!N$9 | E21: =Mensile!N$10 | F21: =Mensile!N$11 | G21: =Mensile!N$12
B22: Totale | C22: =SUM(C10:C21) | D22: =SUM(D10:D21) | E22: =SUM(E10:E21) | F22: =SUM(F10:F21) | G22: =G21
B24: Budget e consuntivo da inizio anno | I24: Controlli
B25: Voce | D25: Budget | E25: Consuntivo | F25: Differenza | G25: % del budget | I25: Movimenti registrati | M25: =COUNT(Movimenti!$D$6:$D$2005)
B26: Entrate | D26: =Mensile!$W$6 | E26: =Mensile!$X$6 | F26: =E26-D26 | G26: =IF(D26=0,"",E26/D26) | I26: Righe del registro da controllare | M26: =COUNTIF(Movimenti!$H$6:$H$2005,"?*") | N26: Entrata
B27: Spese fisse | D27: =Mensile!$W$7 | E27: =Mensile!$X$7 | F27: =E27-D27 | G27: =IF(D27=0,"",E27/D27) | I27: Categorie da controllare | M27: =COUNTIF(Categorie!$D$6:$D$65,"?*") | N27: Spesa fissa
B28: Spese variabili | D28: =Mensile!$W$8 | E28: =Mensile!$X$8 | F28: =E28-D28 | G28: =IF(D28=0,"",E28/D28) | I28: Debiti da controllare | M28: =COUNTIF(Debiti!$G$8:$G$17,"Manca*")+COUNTIF(Debiti!$G$8:$G$17,"Rata*") | N28: Spesa variabile
B29: Totale spese | D29: =Mensile!$W$9 | E29: =Mensile!$X$9 | F29: =E29-D29 | G29: =IF(D29=0,"",E29/D29) | I29: =IF(M26+M27+M28=0,"Nessun problema rilevato.","Ci sono dati da controllare: vedi le celle arancioni nei fogli Movimenti, Categorie e Debiti.") | N29: Spesa totale
B30: Risparmio e investimenti | D30: =Mensile!$W$10 | E30: =Mensile!$X$10 | F30: =E30-D30 | G30: =IF(D30=0,"",E30/D30) | N30: Risparmio
B31: Avanzo | D31: =Mensile!$W$11 | E31: =Mensile!$X$11 | F31: =E31-D31 | G31: =IF(D31=0,"",E31/D31) | N31: Risultato
B32: ="Da gennaio a "&LOWER(Impostazioni!$C$13)&". Differenza = consuntivo − budget."
B34: Le 10 categorie di spesa più alte (anno)
B35: # | C35: Categoria | F35: Totale anno | G35: % sulle spese
B36: 1 | C36: =IF(LARGE(Mensile!$Z$14:$Z$73,B36)<=0,"",INDEX(Mensile!$A$14:$A$73,MATCH(LARGE(Mensile!$Z$14:$Z$73,B36),Mensile!$Z$14:$Z$73,0))) | F36: =IF(C36="",0,INDEX(Mensile!$O$14:$O$73,MATCH(LARGE(Mensile!$Z$14:$Z$73,B36),Mensile!$Z$14:$Z$73,0))) | G36: =IF(OR(F36=0,Mensile!$O$9=0),"",F36/Mensile!$O$9)
B37: 2 | C37: =IF(LARGE(Mensile!$Z$14:$Z$73,B37)<=0,"",INDEX(Mensile!$A$14:$A$73,MATCH(LARGE(Mensile!$Z$14:$Z$73,B37),Mensile!$Z$14:$Z$73,0))) | F37: =IF(C37="",0,INDEX(Mensile!$O$14:$O$73,MATCH(LARGE(Mensile!$Z$14:$Z$73,B37),Mensile!$Z$14:$Z$73,0))) | G37: =IF(OR(F37=0,Mensile!$O$9=0),"",F37/Mensile!$O$9)
B38: 3 | C38: =IF(LARGE(Mensile!$Z$14:$Z$73,B38)<=0,"",INDEX(Mensile!$A$14:$A$73,MATCH(LARGE(Mensile!$Z$14:$Z$73,B38),Mensile!$Z$14:$Z$73,0))) | F38: =IF(C38="",0,INDEX(Mensile!$O$14:$O$73,MATCH(LARGE(Mensile!$Z$14:$Z$73,B38),Mensile!$Z$14:$Z$73,0))) | G38: =IF(OR(F38=0,Mensile!$O$9=0),"",F38/Mensile!$O$9)
B39: 4 | C39: =IF(LARGE(Mensile!$Z$14:$Z$73,B39)<=0,"",INDEX(Mensile!$A$14:$A$73,MATCH(LARGE(Mensile!$Z$14:$Z$73,B39),Mensile!$Z$14:$Z$73,0))) | F39: =IF(C39="",0,INDEX(Mensile!$O$14:$O$73,MATCH(LARGE(Mensile!$Z$14:$Z$73,B39),Mensile!$Z$14:$Z$73,0))) | G39: =IF(OR(F39=0,Mensile!$O$9=0),"",F39/Mensile!$O$9)
B40: 5 | C40: =IF(LARGE(Mensile!$Z$14:$Z$73,B40)<=0,"",INDEX(Mensile!$A$14:$A$73,MATCH(LARGE(Mensile!$Z$14:$Z$73,B40),Mensile!$Z$14:$Z$73,0))) | F40: =IF(C40="",0,INDEX(Mensile!$O$14:$O$73,MATCH(LARGE(Mensile!$Z$14:$Z$73,B40),Mensile!$Z$14:$Z$73,0))) | G40: =IF(OR(F40=0,Mensile!$O$9=0),"",F40/Mensile!$O$9)
B41: 6 | C41: =IF(LARGE(Mensile!$Z$14:$Z$73,B41)<=0,"",INDEX(Mensile!$A$14:$A$73,MATCH(LARGE(Mensile!$Z$14:$Z$73,B41),Mensile!$Z$14:$Z$73,0))) | F41: =IF(C41="",0,INDEX(Mensile!$O$14:$O$73,MATCH(LARGE(Mensile!$Z$14:$Z$73,B41),Mensile!$Z$14:$Z$73,0))) | G41: =IF(OR(F41=0,Mensile!$O$9=0),"",F41/Mensile!$O$9)
B42: 7 | C42: =IF(LARGE(Mensile!$Z$14:$Z$73,B42)<=0,"",INDEX(Mensile!$A$14:$A$73,MATCH(LARGE(Mensile!$Z$14:$Z$73,B42),Mensile!$Z$14:$Z$73,0))) | F42: =IF(C42="",0,INDEX(Mensile!$O$14:$O$73,MATCH(LARGE(Mensile!$Z$14:$Z$73,B42),Mensile!$Z$14:$Z$73,0))) | G42: =IF(OR(F42=0,Mensile!$O$9=0),"",F42/Mensile!$O$9)
B43: 8 | C43: =IF(LARGE(Mensile!$Z$14:$Z$73,B43)<=0,"",INDEX(Mensile!$A$14:$A$73,MATCH(LARGE(Mensile!$Z$14:$Z$73,B43),Mensile!$Z$14:$Z$73,0))) | F43: =IF(C43="",0,INDEX(Mensile!$O$14:$O$73,MATCH(LARGE(Mensile!$Z$14:$Z$73,B43),Mensile!$Z$14:$Z$73,0))) | G43: =IF(OR(F43=0,Mensile!$O$9=0),"",F43/Mensile!$O$9)
B44: 9 | C44: =IF(LARGE(Mensile!$Z$14:$Z$73,B44)<=0,"",INDEX(Mensile!$A$14:$A$73,MATCH(LARGE(Mensile!$Z$14:$Z$73,B44),Mensile!$Z$14:$Z$73,0))) | F44: =IF(C44="",0,INDEX(Mensile!$O$14:$O$73,MATCH(LARGE(Mensile!$Z$14:$Z$73,B44),Mensile!$Z$14:$Z$73,0))) | G44: =IF(OR(F44=0,Mensile!$O$9=0),"",F44/Mensile!$O$9)
B45: 10 | C45: =IF(LARGE(Mensile!$Z$14:$Z$73,B45)<=0,"",INDEX(Mensile!$A$14:$A$73,MATCH(LARGE(Mensile!$Z$14:$Z$73,B45),Mensile!$Z$14:$Z$73,0))) | F45: =IF(C45="",0,INDEX(Mensile!$O$14:$O$73,MATCH(LARGE(Mensile!$Z$14:$Z$73,B45),Mensile!$Z$14:$Z$73,0))) | G45: =IF(OR(F45=0,Mensile!$O$9=0),"",F45/Mensile!$O$9)
B48: Spese ed entrate per persona (anno)
B49: Persona | D49: Spese | E49: Entrate | F49: % sulle spese
B50: =IF(OR(Impostazioni!$C$16="",COUNTIF(Impostazioni!$C$15:$C$15,Impostazioni!$C$16)>0),"",Impostazioni!$C$16) | D50: =IF(B50="",0,SUMIFS(Movimenti!$D$6:$D$2005,Movimenti!$F$6:$F$2005,B50,Movimenti!$G$6:$G$2005,"Spesa*",Movimenti!$A$6:$A$2005,">="&DATE(Impostazioni!$C$4,1,1),Movimenti!$A$6:$A$2005,"<"&DATE(Impostazioni!$C$4+1,1,1))) | E50: =IF(B50="",0,SUMIFS(Movimenti!$D$6:$D$2005,Movimenti!$F$6:$F$2005,B50,Movimenti!$G$6:$G$2005,"Entrata",Movimenti!$A$6:$A$2005,">="&DATE(Impostazioni!$C$4,1,1),Movimenti!$A$6:$A$2005,"<"&DATE(Impostazioni!$C$4+1,1,1))) | F50: =IF(OR(D50=0,Mensile!$O$9=0),"",D50/Mensile!$O$9)
B51: =IF(OR(Impostazioni!$C$17="",COUNTIF(Impostazioni!$C$15:$C$16,Impostazioni!$C$17)>0),"",Impostazioni!$C$17) | D51: =IF(B51="",0,SUMIFS(Movimenti!$D$6:$D$2005,Movimenti!$F$6:$F$2005,B51,Movimenti!$G$6:$G$2005,"Spesa*",Movimenti!$A$6:$A$2005,">="&DATE(Impostazioni!$C$4,1,1),Movimenti!$A$6:$A$2005,"<"&DATE(Impostazioni!$C$4+1,1,1))) | E51: =IF(B51="",0,SUMIFS(Movimenti!$D$6:$D$2005,Movimenti!$F$6:$F$2005,B51,Movimenti!$G$6:$G$2005,"Entrata",Movimenti!$A$6:$A$2005,">="&DATE(Impostazioni!$C$4,1,1),Movimenti!$A$6:$A$2005,"<"&DATE(Impostazioni!$C$4+1,1,1))) | F51: =IF(OR(D51=0,Mensile!$O$9=0),"",D51/Mensile!$O$9)
B52: =IF(OR(Impostazioni!$C$18="",COUNTIF(Impostazioni!$C$15:$C$17,Impostazioni!$C$18)>0),"",Impostazioni!$C$18) | D52: =IF(B52="",0,SUMIFS(Movimenti!$D$6:$D$2005,Movimenti!$F$6:$F$2005,B52,Movimenti!$G$6:$G$2005,"Spesa*",Movimenti!$A$6:$A$2005,">="&DATE(Impostazioni!$C$4,1,1),Movimenti!$A$6:$A$2005,"<"&DATE(Impostazioni!$C$4+1,1,1))) | E52: =IF(B52="",0,SUMIFS(Movimenti!$D$6:$D$2005,Movimenti!$F$6:$F$2005,B52,Movimenti!$G$6:$G$2005,"Entrata",Movimenti!$A$6:$A$2005,">="&DATE(Impostazioni!$C$4,1,1),Movimenti!$A$6:$A$2005,"<"&DATE(Impostazioni!$C$4+1,1,1))) | F52: =IF(OR(D52=0,Mensile!$O$9=0),"",D52/Mensile!$O$9)
B53: =IF(OR(Impostazioni!$C$19="",COUNTIF(Impostazioni!$C$15:$C$18,Impostazioni!$C$19)>0),"",Impostazioni!$C$19) | D53: =IF(B53="",0,SUMIFS(Movimenti!$D$6:$D$2005,Movimenti!$F$6:$F$2005,B53,Movimenti!$G$6:$G$2005,"Spesa*",Movimenti!$A$6:$A$2005,">="&DATE(Impostazioni!$C$4,1,1),Movimenti!$A$6:$A$2005,"<"&DATE(Impostazioni!$C$4+1,1,1))) | E53: =IF(B53="",0,SUMIFS(Movimenti!$D$6:$D$2005,Movimenti!$F$6:$F$2005,B53,Movimenti!$G$6:$G$2005,"Entrata",Movimenti!$A$6:$A$2005,">="&DATE(Impostazioni!$C$4,1,1),Movimenti!$A$6:$A$2005,"<"&DATE(Impostazioni!$C$4+1,1,1))) | F53: =IF(OR(D53=0,Mensile!$O$9=0),"",D53/Mensile!$O$9)
B54: =IF(OR(Impostazioni!$C$20="",COUNTIF(Impostazioni!$C$15:$C$19,Impostazioni!$C$20)>0),"",Impostazioni!$C$20) | D54: =IF(B54="",0,SUMIFS(Movimenti!$D$6:$D$2005,Movimenti!$F$6:$F$2005,B54,Movimenti!$G$6:$G$2005,"Spesa*",Movimenti!$A$6:$A$2005,">="&DATE(Impostazioni!$C$4,1,1),Movimenti!$A$6:$A$2005,"<"&DATE(Impostazioni!$C$4+1,1,1))) | E54: =IF(B54="",0,SUMIFS(Movimenti!$D$6:$D$2005,Movimenti!$F$6:$F$2005,B54,Movimenti!$G$6:$G$2005,"Entrata",Movimenti!$A$6:$A$2005,">="&DATE(Impostazioni!$C$4,1,1),Movimenti!$A$6:$A$2005,"<"&DATE(Impostazioni!$C$4+1,1,1))) | F54: =IF(OR(D54=0,Mensile!$O$9=0),"",D54/Mensile!$O$9)
B55: =IF(OR(Impostazioni!$C$21="",COUNTIF(Impostazioni!$C$15:$C$20,Impostazioni!$C$21)>0),"",Impostazioni!$C$21) | D55: =IF(B55="",0,SUMIFS(Movimenti!$D$6:$D$2005,Movimenti!$F$6:$F$2005,B55,Movimenti!$G$6:$G$2005,"Spesa*",Movimenti!$A$6:$A$2005,">="&DATE(Impostazioni!$C$4,1,1),Movimenti!$A$6:$A$2005,"<"&DATE(Impostazioni!$C$4+1,1,1))) | E55: =IF(B55="",0,SUMIFS(Movimenti!$D$6:$D$2005,Movimenti!$F$6:$F$2005,B55,Movimenti!$G$6:$G$2005,"Entrata",Movimenti!$A$6:$A$2005,">="&DATE(Impostazioni!$C$4,1,1),Movimenti!$A$6:$A$2005,"<"&DATE(Impostazioni!$C$4+1,1,1))) | F55: =IF(OR(D55=0,Mensile!$O$9=0),"",D55/Mensile!$O$9)
B56: Comuni o senza nome | D56: =Mensile!$O$9-SUM(D50:D55) | E56: =Mensile!$O$6-SUM(E50:E55) | F56: =IF(OR(D56=0,Mensile!$O$9=0),"",D56/Mensile!$O$9)
B57: La persona è la colonna «Chi» dei Movimenti; i nomi si inseriscono in Impostazioni.

Sheet Obiettivi
B1: Obiettivi di risparmio
B2: Per ogni obiettivo indica importo, scadenza e quanto hai già messo da parte. La quota mensile parte dalla data di riferimento (Impostazioni).
B4: Obiettivo | C4: Importo obiettivo | D4: Scadenza | E4: Già versato | F4: Mancante | G4: % raggiunta | H4: Avanzamento | I4: Mesi rimanenti | J4: Quota mensile necessaria | K4: Stato
B5: Fondo per le emergenze | C5: 12000 | D5: 47118 | E5: 6300 | F5: =IF(B5="","",MAX(0,N(C5)-N(E5))) | G5: =IF(OR(B5="",N(C5)<=0),"",MIN(1,N(E5)/C5)) | H5: =IF(G5="","",REPT("█",ROUND(G5*20,0))&REPT("░",20-ROUND(G5*20,0))) | I5: =IF(OR(B5="",D5=""),"",MAX(0,(YEAR(D5)-YEAR(Impostazioni!$C$11))*12+MONTH(D5)-MONTH(Impostazioni!$C$11))) | J5: =IF(OR(B5="",N(C5)<=0),"",IF(F5=0,0,IF(I5="","",F5/MAX(1,I5)))) | K5: =IF(B5="","",IF(N(C5)<=0,"Manca l'importo",IF(F5=0,"Raggiunto",IF(D5="","Manca la scadenza",IF(D5<Impostazioni!$C$11,"Scaduto","In corso")))))
B6: Vacanza estate 2027 | C6: 2400 | D6: 46568 | E6: 1200 | F6: =IF(B6="","",MAX(0,N(C6)-N(E6))) | G6: =IF(OR(B6="",N(C6)<=0),"",MIN(1,N(E6)/C6)) | H6: =IF(G6="","",REPT("█",ROUND(G6*20,0))&REPT("░",20-ROUND(G6*20,0))) | I6: =IF(OR(B6="",D6=""),"",MAX(0,(YEAR(D6)-YEAR(Impostazioni!$C$11))*12+MONTH(D6)-MONTH(Impostazioni!$C$11))) | J6: =IF(OR(B6="",N(C6)<=0),"",IF(F6=0,0,IF(I6="","",F6/MAX(1,I6)))) | K6: =IF(B6="","",IF(N(C6)<=0,"Manca l'importo",IF(F6=0,"Raggiunto",IF(D6="","Manca la scadenza",IF(D6<Impostazioni!$C$11,"Scaduto","In corso")))))
B7: Auto nuova | C7: 9000 | D7: 47483 | E7: 2000 | F7: =IF(B7="","",MAX(0,N(C7)-N(E7))) | G7: =IF(OR(B7="",N(C7)<=0),"",MIN(1,N(E7)/C7)) | H7: =IF(G7="","",REPT("█",ROUND(G7*20,0))&REPT("░",20-ROUND(G7*20,0))) | I7: =IF(OR(B7="",D7=""),"",MAX(0,(YEAR(D7)-YEAR(Impostazioni!$C$11))*12+MONTH(D7)-MONTH(Impostazioni!$C$11))) | J7: =IF(OR(B7="",N(C7)<=0),"",IF(F7=0,0,IF(I7="","",F7/MAX(1,I7)))) | K7: =IF(B7="","",IF(N(C7)<=0,"Manca l'importo",IF(F7=0,"Raggiunto",IF(D7="","Manca la scadenza",IF(D7<Impostazioni!$C$11,"Scaduto","In corso")))))
B8: Regali di Natale 2026 | C8: 400 | D8: 46357 | E8: 400 | F8: =IF(B8="","",MAX(0,N(C8)-N(E8))) | G8: =IF(OR(B8="",N(C8)<=0),"",MIN(1,N(E8)/C8)) | H8: =IF(G8="","",REPT("█",ROUND(G8*20,0))&REPT("░",20-ROUND(G8*20,0))) | I8: =IF(OR(B8="",D8=""),"",MAX(0,(YEAR(D8)-YEAR(Impostazioni!$C$11))*12+MONTH(D8)-MONTH(Impostazioni!$C$11))) | J8: =IF(OR(B8="",N(C8)<=0),"",IF(F8=0,0,IF(I8="","",F8/MAX(1,I8)))) | K8: =IF(B8="","",IF(N(C8)<=0,"Manca l'importo",IF(F8=0,"Raggiunto",IF(D8="","Manca la scadenza",IF(D8<Impostazioni!$C$11,"Scaduto","In corso")))))
B9: Corso di inglese Sofia | C9: 600 | D9: 46630 | E9: 150 | F9: =IF(B9="","",MAX(0,N(C9)-N(E9))) | G9: =IF(OR(B9="",N(C9)<=0),"",MIN(1,N(E9)/C9)) | H9: =IF(G9="","",REPT("█",ROUND(G9*20,0))&REPT("░",20-ROUND(G9*20,0))) | I9: =IF(OR(B9="",D9=""),"",MAX(0,(YEAR(D9)-YEAR(Impostazioni!$C$11))*12+MONTH(D9)-MONTH(Impostazioni!$C$11))) | J9: =IF(OR(B9="",N(C9)<=0),"",IF(F9=0,0,IF(I9="","",F9/MAX(1,I9)))) | K9: =IF(B9="","",IF(N(C9)<=0,"Manca l'importo",IF(F9=0,"Raggiunto",IF(D9="","Manca la scadenza",IF(D9<Impostazioni!$C$11,"Scaduto","In corso")))))
F10: =IF(B10="","",MAX(0,N(C10)-N(E10))) | G10: =IF(OR(B10="",N(C10)<=0),"",MIN(1,N(E10)/C10)) | H10: =IF(G10="","",REPT("█",ROUND(G10*20,0))&REPT("░",20-ROUND(G10*20,0))) | I10: =IF(OR(B10="",D10=""),"",MAX(0,(YEAR(D10)-YEAR(Impostazioni!$C$11))*12+MONTH(D10)-MONTH(Impostazioni!$C$11))) | J10: =IF(OR(B10="",N(C10)<=0),"",IF(F10=0,0,IF(I10="","",F10/MAX(1,I10)))) | K10: =IF(B10="","",IF(N(C10)<=0,"Manca l'importo",IF(F10=0,"Raggiunto",IF(D10="","Manca la scadenza",IF(D10<Impostazioni!$C$11,"Scaduto","In corso")))))
F11: =IF(B11="","",MAX(0,N(C11)-N(E11))) | G11: =IF(OR(B11="",N(C11)<=0),"",MIN(1,N(E11)/C11)) | H11: =IF(G11="","",REPT("█",ROUND(G11*20,0))&REPT("░",20-ROUND(G11*20,0))) | I11: =IF(OR(B11="",D11=""),"",MAX(0,(YEAR(D11)-YEAR(Impostazioni!$C$11))*12+MONTH(D11)-MONTH(Impostazioni!$C$11))) | J11: =IF(OR(B11="",N(C11)<=0),"",IF(F11=0,0,IF(I11="","",F11/MAX(1,I11)))) | K11: =IF(B11="","",IF(N(C11)<=0,"Manca l'importo",IF(F11=0,"Raggiunto",IF(D11="","Manca la scadenza",IF(D11<Impostazioni!$C$11,"Scaduto","In corso")))))
F12: =IF(B12="","",MAX(0,N(C12)-N(E12))) | G12: =IF(OR(B12="",N(C12)<=0),"",MIN(1,N(E12)/C12)) | H12: =IF(G12="","",REPT("█",ROUND(G12*20,0))&REPT("░",20-ROUND(G12*20,0))) | I12: =IF(OR(B12="",D12=""),"",MAX(0,(YEAR(D12)-YEAR(Impostazioni!$C$11))*12+MONTH(D12)-MONTH(Impostazioni!$C$11))) | J12: =IF(OR(B12="",N(C12)<=0),"",IF(F12=0,0,IF(I12="","",F12/MAX(1,I12)))) | K12: =IF(B12="","",IF(N(C12)<=0,"Manca l'importo",IF(F12=0,"Raggiunto",IF(D12="","Manca la scadenza",IF(D12<Impostazioni!$C$11,"Scaduto","In corso")))))
F13: =IF(B13="","",MAX(0,N(C13)-N(E13))) | G13: =IF(OR(B13="",N(C13)<=0),"",MIN(1,N(E13)/C13)) | H13: =IF(G13="","",REPT("█",ROUND(G13*20,0))&REPT("░",20-ROUND(G13*20,0))) | I13: =IF(OR(B13="",D13=""),"",MAX(0,(YEAR(D13)-YEAR(Impostazioni!$C$11))*12+MONTH(D13)-MONTH(Impostazioni!$C$11))) | J13: =IF(OR(B13="",N(C13)<=0),"",IF(F13=0,0,IF(I13="","",F13/MAX(1,I13)))) | K13: =IF(B13="","",IF(N(C13)<=0,"Manca l'importo",IF(F13=0,"Raggiunto",IF(D13="","Manca la scadenza",IF(D13<Impostazioni!$C$11,"Scaduto","In corso")))))
F14: =IF(B14="","",MAX(0,N(C14)-N(E14))) | G14: =IF(OR(B14="",N(C14)<=0),"",MIN(1,N(E14)/C14)) | H14: =IF(G14="","",REPT("█",ROUND(G14*20,0))&REPT("░",20-ROUND(G14*20,0))) | I14: =IF(OR(B14="",D14=""),"",MAX(0,(YEAR(D14)-YEAR(Impostazioni!$C$11))*12+MONTH(D14)-MONTH(Impostazioni!$C$11))) | J14: =IF(OR(B14="",N(C14)<=0),"",IF(F14=0,0,IF(I14="","",F14/MAX(1,I14)))) | K14: =IF(B14="","",IF(N(C14)<=0,"Manca l'importo",IF(F14=0,"Raggiunto",IF(D14="","Manca la scadenza",IF(D14<Impostazioni!$C$11,"Scaduto","In corso")))))
F15: =IF(B15="","",MAX(0,N(C15)-N(E15))) | G15: =IF(OR(B15="",N(C15)<=0),"",MIN(1,N(E15)/C15)) | H15: =IF(G15="","",REPT("█",ROUND(G15*20,0))&REPT("░",20-ROUND(G15*20,0))) | I15: =IF(OR(B15="",D15=""),"",MAX(0,(YEAR(D15)-YEAR(Impostazioni!$C$11))*12+MONTH(D15)-MONTH(Impostazioni!$C$11))) | J15: =IF(OR(B15="",N(C15)<=0),"",IF(F15=0,0,IF(I15="","",F15/MAX(1,I15)))) | K15: =IF(B15="","",IF(N(C15)<=0,"Manca l'importo",IF(F15=0,"Raggiunto",IF(D15="","Manca la scadenza",IF(D15<Impostazioni!$C$11,"Scaduto","In corso")))))
F16: =IF(B16="","",MAX(0,N(C16)-N(E16))) | G16: =IF(OR(B16="",N(C16)<=0),"",MIN(1,N(E16)/C16)) | H16: =IF(G16="","",REPT("█",ROUND(G16*20,0))&REPT("░",20-ROUND(G16*20,0))) | I16: =IF(OR(B16="",D16=""),"",MAX(0,(YEAR(D16)-YEAR(Impostazioni!$C$11))*12+MONTH(D16)-MONTH(Impostazioni!$C$11))) | J16: =IF(OR(B16="",N(C16)<=0),"",IF(F16=0,0,IF(I16="","",F16/MAX(1,I16)))) | K16: =IF(B16="","",IF(N(C16)<=0,"Manca l'importo",IF(F16=0,"Raggiunto",IF(D16="","Manca la scadenza",IF(D16<Impostazioni!$C$11,"Scaduto","In corso")))))
B17: Totale | C17: =SUM(C5:C16) | E17: =SUM(E5:E16) | F17: =SUM(F5:F16) | G17: =IF(C17=0,"",E17/C17) | J17: =SUM(J5:J16)
B19: Confronto con il budget
B20: Quota mensile per tutti gli obiettivi | C20: =J17
B21: Risparmio previsto nel budget (al mese) | C21: =Budget!P10/12
B22: Versato a risparmio (media mensile) | C22: =IF(Impostazioni!$C$12=0,0,Mensile!X10/Impostazioni!$C$12)
B23: Margine del budget sugli obiettivi | C23: =C21-C20
B24: I mesi rimanenti vanno dal mese della data di riferimento a quello della scadenza. Se la scadenza è nel mese in corso, la quota è l'intero importo mancante.

Sheet Debiti
B1: Debiti e piano di estinzione
B2: Elenca mutuo, prestiti e carte rateali. TAN = tasso annuo nominale del contratto. Le stime ipotizzano rata e tasso costanti.
B4: Metodo di estinzione scelto | C4: Valanga | D4: Valanga: prima il debito con il tasso più alto (paghi meno interessi). Palla di neve: prima il debito più piccolo (lo chiudi prima).
B5: Somma extra al mese per i debiti | C5: 100 | D5: Si aggiunge alla rata del primo debito dell'ordine scelto. L'effetto è calcolato in fondo al foglio.
B7: Debito | C7: Saldo residuo | D7: TAN annuo | E7: Rata mensile | F7: Interessi del mese (stima) | G7: Mesi alla fine | H7: Fine prevista | I7: Interessi residui (stima) | J7: Ordine valanga | K7: Ordine palla di neve
B8: Mutuo casa | C8: 118400 | D8: 0.0295 | E8: 680 | F8: =IF(OR(B8="",N(C8)<=0),"",C8*N(D8)/12) | G8: =IF(B8="",IF(N(C8)>0,"Manca il nome",""),IF(C8="","Manca il saldo",IF(N(C8)<=0,"",IF(NOT(ISNUMBER(D8)),"Manca il TAN",IF(N(E8)<=0,"Manca la rata",IF(D8=0,ROUNDUP(C8/E8,0),IF(E8<=C8*D8/12,"Rata troppo bassa",ROUNDUP(NPER(D8/12,-E8,C8),0)))))))) | H8: =IF(ISNUMBER(G8),DATE(YEAR(Impostazioni!$C$11),MONTH(Impostazioni!$C$11)+G8,1),"") | I8: =IF(ISNUMBER(G8),IF(N(D8)=0,0,MAX(0,E8*NPER(D8/12,-E8,C8)-C8)),"") | J8: =IF(OR(B8="",N(C8)<=0,NOT(ISNUMBER(D8))),"",1+COUNTIFS($B$8:$B$17,"<>",$C$8:$C$17,">0",$D$8:$D$17,">=0",$D$8:$D$17,">"&D8)+COUNTIFS($B$8:$B$17,"<>",$C$8:$C$17,">0",$D$8:$D$17,">=0",$D$8:$D$17,D8,$C$8:$C$17,"<"&C8)+COUNTIFS($B$7:B7,"<>",$C$7:C7,C8,$D$7:D7,D8)) | K8: =IF(OR(B8="",N(C8)<=0,NOT(ISNUMBER(D8))),"",1+COUNTIFS($B$8:$B$17,"<>",$C$8:$C$17,">0",$D$8:$D$17,">=0",$C$8:$C$17,"<"&C8)+COUNTIFS($B$8:$B$17,"<>",$C$8:$C$17,">0",$D$8:$D$17,">=0",$C$8:$C$17,C8,$D$8:$D$17,">"&D8)+COUNTIFS($B$7:B7,"<>",$C$7:C7,C8,$D$7:D7,D8))
B9: Prestito auto | C9: 6150 | D9: 0.069 | E9: 210 | F9: =IF(OR(B9="",N(C9)<=0),"",C9*N(D9)/12) | G9: =IF(B9="",IF(N(C9)>0,"Manca il nome",""),IF(C9="","Manca il saldo",IF(N(C9)<=0,"",IF(NOT(ISNUMBER(D9)),"Manca il TAN",IF(N(E9)<=0,"Manca la rata",IF(D9=0,ROUNDUP(C9/E9,0),IF(E9<=C9*D9/12,"Rata troppo bassa",ROUNDUP(NPER(D9/12,-E9,C9),0)))))))) | H9: =IF(ISNUMBER(G9),DATE(YEAR(Impostazioni!$C$11),MONTH(Impostazioni!$C$11)+G9,1),"") | I9: =IF(ISNUMBER(G9),IF(N(D9)=0,0,MAX(0,E9*NPER(D9/12,-E9,C9)-C9)),"") | J9: =IF(OR(B9="",N(C9)<=0,NOT(ISNUMBER(D9))),"",1+COUNTIFS($B$8:$B$17,"<>",$C$8:$C$17,">0",$D$8:$D$17,">=0",$D$8:$D$17,">"&D9)+COUNTIFS($B$8:$B$17,"<>",$C$8:$C$17,">0",$D$8:$D$17,">=0",$D$8:$D$17,D9,$C$8:$C$17,"<"&C9)+COUNTIFS($B$7:B8,"<>",$C$7:C8,C9,$D$7:D8,D9)) | K9: =IF(OR(B9="",N(C9)<=0,NOT(ISNUMBER(D9))),"",1+COUNTIFS($B$8:$B$17,"<>",$C$8:$C$17,">0",$D$8:$D$17,">=0",$C$8:$C$17,"<"&C9)+COUNTIFS($B$8:$B$17,"<>",$C$8:$C$17,">0",$D$8:$D$17,">=0",$C$8:$C$17,C9,$D$8:$D$17,">"&D9)+COUNTIFS($B$7:B8,"<>",$C$7:C8,C9,$D$7:D8,D9))
B10: Carta revolving | C10: 1120 | D10: 0.159 | E10: 60 | F10: =IF(OR(B10="",N(C10)<=0),"",C10*N(D10)/12) | G10: =IF(B10="",IF(N(C10)>0,"Manca il nome",""),IF(C10="","Manca il saldo",IF(N(C10)<=0,"",IF(NOT(ISNUMBER(D10)),"Manca il TAN",IF(N(E10)<=0,"Manca la rata",IF(D10=0,ROUNDUP(C10/E10,0),IF(E10<=C10*D10/12,"Rata troppo bassa",ROUNDUP(NPER(D10/12,-E10,C10),0)))))))) | H10: =IF(ISNUMBER(G10),DATE(YEAR(Impostazioni!$C$11),MONTH(Impostazioni!$C$11)+G10,1),"") | I10: =IF(ISNUMBER(G10),IF(N(D10)=0,0,MAX(0,E10*NPER(D10/12,-E10,C10)-C10)),"") | J10: =IF(OR(B10="",N(C10)<=0,NOT(ISNUMBER(D10))),"",1+COUNTIFS($B$8:$B$17,"<>",$C$8:$C$17,">0",$D$8:$D$17,">=0",$D$8:$D$17,">"&D10)+COUNTIFS($B$8:$B$17,"<>",$C$8:$C$17,">0",$D$8:$D$17,">=0",$D$8:$D$17,D10,$C$8:$C$17,"<"&C10)+COUNTIFS($B$7:B9,"<>",$C$7:C9,C10,$D$7:D9,D10)) | K10: =IF(OR(B10="",N(C10)<=0,NOT(ISNUMBER(D10))),"",1+COUNTIFS($B$8:$B$17,"<>",$C$8:$C$17,">0",$D$8:$D$17,">=0",$C$8:$C$17,"<"&C10)+COUNTIFS($B$8:$B$17,"<>",$C$8:$C$17,">0",$D$8:$D$17,">=0",$C$8:$C$17,C10,$D$8:$D$17,">"&D10)+COUNTIFS($B$7:B9,"<>",$C$7:C9,C10,$D$7:D9,D10))
B11: Lavatrice a tasso zero | C11: 360 | D11: 0 | E11: 40 | F11: =IF(OR(B11="",N(C11)<=0),"",C11*N(D11)/12) | G11: =IF(B11="",IF(N(C11)>0,"Manca il nome",""),IF(C11="","Manca il saldo",IF(N(C11)<=0,"",IF(NOT(ISNUMBER(D11)),"Manca il TAN",IF(N(E11)<=0,"Manca la rata",IF(D11=0,ROUNDUP(C11/E11,0),IF(E11<=C11*D11/12,"Rata troppo bassa",ROUNDUP(NPER(D11/12,-E11,C11),0)))))))) | H11: =IF(ISNUMBER(G11),DATE(YEAR(Impostazioni!$C$11),MONTH(Impostazioni!$C$11)+G11,1),"") | I11: =IF(ISNUMBER(G11),IF(N(D11)=0,0,MAX(0,E11*NPER(D11/12,-E11,C11)-C11)),"") | J11: =IF(OR(B11="",N(C11)<=0,NOT(ISNUMBER(D11))),"",1+COUNTIFS($B$8:$B$17,"<>",$C$8:$C$17,">0",$D$8:$D$17,">=0",$D$8:$D$17,">"&D11)+COUNTIFS($B$8:$B$17,"<>",$C$8:$C$17,">0",$D$8:$D$17,">=0",$D$8:$D$17,D11,$C$8:$C$17,"<"&C11)+COUNTIFS($B$7:B10,"<>",$C$7:C10,C11,$D$7:D10,D11)) | K11: =IF(OR(B11="",N(C11)<=0,NOT(ISNUMBER(D11))),"",1+COUNTIFS($B$8:$B$17,"<>",$C$8:$C$17,">0",$D$8:$D$17,">=0",$C$8:$C$17,"<"&C11)+COUNTIFS($B$8:$B$17,"<>",$C$8:$C$17,">0",$D$8:$D$17,">=0",$C$8:$C$17,C11,$D$8:$D$17,">"&D11)+COUNTIFS($B$7:B10,"<>",$C$7:C10,C11,$D$7:D10,D11))
F12: =IF(OR(B12="",N(C12)<=0),"",C12*N(D12)/12) | G12: =IF(B12="",IF(N(C12)>0,"Manca il nome",""),IF(C12="","Manca il saldo",IF(N(C12)<=0,"",IF(NOT(ISNUMBER(D12)),"Manca il TAN",IF(N(E12)<=0,"Manca la rata",IF(D12=0,ROUNDUP(C12/E12,0),IF(E12<=C12*D12/12,"Rata troppo bassa",ROUNDUP(NPER(D12/12,-E12,C12),0)))))))) | H12: =IF(ISNUMBER(G12),DATE(YEAR(Impostazioni!$C$11),MONTH(Impostazioni!$C$11)+G12,1),"") | I12: =IF(ISNUMBER(G12),IF(N(D12)=0,0,MAX(0,E12*NPER(D12/12,-E12,C12)-C12)),"") | J12: =IF(OR(B12="",N(C12)<=0,NOT(ISNUMBER(D12))),"",1+COUNTIFS($B$8:$B$17,"<>",$C$8:$C$17,">0",$D$8:$D$17,">=0",$D$8:$D$17,">"&D12)+COUNTIFS($B$8:$B$17,"<>",$C$8:$C$17,">0",$D$8:$D$17,">=0",$D$8:$D$17,D12,$C$8:$C$17,"<"&C12)+COUNTIFS($B$7:B11,"<>",$C$7:C11,C12,$D$7:D11,D12)) | K12: =IF(OR(B12="",N(C12)<=0,NOT(ISNUMBER(D12))),"",1+COUNTIFS($B$8:$B$17,"<>",$C$8:$C$17,">0",$D$8:$D$17,">=0",$C$8:$C$17,"<"&C12)+COUNTIFS($B$8:$B$17,"<>",$C$8:$C$17,">0",$D$8:$D$17,">=0",$C$8:$C$17,C12,$D$8:$D$17,">"&D12)+COUNTIFS($B$7:B11,"<>",$C$7:C11,C12,$D$7:D11,D12))
F13: =IF(OR(B13="",N(C13)<=0),"",C13*N(D13)/12) | G13: =IF(B13="",IF(N(C13)>0,"Manca il nome",""),IF(C13="","Manca il saldo",IF(N(C13)<=0,"",IF(NOT(ISNUMBER(D13)),"Manca il TAN",IF(N(E13)<=0,"Manca la rata",IF(D13=0,ROUNDUP(C13/E13,0),IF(E13<=C13*D13/12,"Rata troppo bassa",ROUNDUP(NPER(D13/12,-E13,C13),0)))))))) | H13: =IF(ISNUMBER(G13),DATE(YEAR(Impostazioni!$C$11),MONTH(Impostazioni!$C$11)+G13,1),"") | I13: =IF(ISNUMBER(G13),IF(N(D13)=0,0,MAX(0,E13*NPER(D13/12,-E13,C13)-C13)),"") | J13: =IF(OR(B13="",N(C13)<=0,NOT(ISNUMBER(D13))),"",1+COUNTIFS($B$8:$B$17,"<>",$C$8:$C$17,">0",$D$8:$D$17,">=0",$D$8:$D$17,">"&D13)+COUNTIFS($B$8:$B$17,"<>",$C$8:$C$17,">0",$D$8:$D$17,">=0",$D$8:$D$17,D13,$C$8:$C$17,"<"&C13)+COUNTIFS($B$7:B12,"<>",$C$7:C12,C13,$D$7:D12,D13)) | K13: =IF(OR(B13="",N(C13)<=0,NOT(ISNUMBER(D13))),"",1+COUNTIFS($B$8:$B$17,"<>",$C$8:$C$17,">0",$D$8:$D$17,">=0",$C$8:$C$17,"<"&C13)+COUNTIFS($B$8:$B$17,"<>",$C$8:$C$17,">0",$D$8:$D$17,">=0",$C$8:$C$17,C13,$D$8:$D$17,">"&D13)+COUNTIFS($B$7:B12,"<>",$C$7:C12,C13,$D$7:D12,D13))
F14: =IF(OR(B14="",N(C14)<=0),"",C14*N(D14)/12) | G14: =IF(B14="",IF(N(C14)>0,"Manca il nome",""),IF(C14="","Manca il saldo",IF(N(C14)<=0,"",IF(NOT(ISNUMBER(D14)),"Manca il TAN",IF(N(E14)<=0,"Manca la rata",IF(D14=0,ROUNDUP(C14/E14,0),IF(E14<=C14*D14/12,"Rata troppo bassa",ROUNDUP(NPER(D14/12,-E14,C14),0)))))))) | H14: =IF(ISNUMBER(G14),DATE(YEAR(Impostazioni!$C$11),MONTH(Impostazioni!$C$11)+G14,1),"") | I14: =IF(ISNUMBER(G14),IF(N(D14)=0,0,MAX(0,E14*NPER(D14/12,-E14,C14)-C14)),"") | J14: =IF(OR(B14="",N(C14)<=0,NOT(ISNUMBER(D14))),"",1+COUNTIFS($B$8:$B$17,"<>",$C$8:$C$17,">0",$D$8:$D$17,">=0",$D$8:$D$17,">"&D14)+COUNTIFS($B$8:$B$17,"<>",$C$8:$C$17,">0",$D$8:$D$17,">=0",$D$8:$D$17,D14,$C$8:$C$17,"<"&C14)+COUNTIFS($B$7:B13,"<>",$C$7:C13,C14,$D$7:D13,D14)) | K14: =IF(OR(B14="",N(C14)<=0,NOT(ISNUMBER(D14))),"",1+COUNTIFS($B$8:$B$17,"<>",$C$8:$C$17,">0",$D$8:$D$17,">=0",$C$8:$C$17,"<"&C14)+COUNTIFS($B$8:$B$17,"<>",$C$8:$C$17,">0",$D$8:$D$17,">=0",$C$8:$C$17,C14,$D$8:$D$17,">"&D14)+COUNTIFS($B$7:B13,"<>",$C$7:C13,C14,$D$7:D13,D14))
F15: =IF(OR(B15="",N(C15)<=0),"",C15*N(D15)/12) | G15: =IF(B15="",IF(N(C15)>0,"Manca il nome",""),IF(C15="","Manca il saldo",IF(N(C15)<=0,"",IF(NOT(ISNUMBER(D15)),"Manca il TAN",IF(N(E15)<=0,"Manca la rata",IF(D15=0,ROUNDUP(C15/E15,0),IF(E15<=C15*D15/12,"Rata troppo bassa",ROUNDUP(NPER(D15/12,-E15,C15),0)))))))) | H15: =IF(ISNUMBER(G15),DATE(YEAR(Impostazioni!$C$11),MONTH(Impostazioni!$C$11)+G15,1),"") | I15: =IF(ISNUMBER(G15),IF(N(D15)=0,0,MAX(0,E15*NPER(D15/12,-E15,C15)-C15)),"") | J15: =IF(OR(B15="",N(C15)<=0,NOT(ISNUMBER(D15))),"",1+COUNTIFS($B$8:$B$17,"<>",$C$8:$C$17,">0",$D$8:$D$17,">=0",$D$8:$D$17,">"&D15)+COUNTIFS($B$8:$B$17,"<>",$C$8:$C$17,">0",$D$8:$D$17,">=0",$D$8:$D$17,D15,$C$8:$C$17,"<"&C15)+COUNTIFS($B$7:B14,"<>",$C$7:C14,C15,$D$7:D14,D15)) | K15: =IF(OR(B15="",N(C15)<=0,NOT(ISNUMBER(D15))),"",1+COUNTIFS($B$8:$B$17,"<>",$C$8:$C$17,">0",$D$8:$D$17,">=0",$C$8:$C$17,"<"&C15)+COUNTIFS($B$8:$B$17,"<>",$C$8:$C$17,">0",$D$8:$D$17,">=0",$C$8:$C$17,C15,$D$8:$D$17,">"&D15)+COUNTIFS($B$7:B14,"<>",$C$7:C14,C15,$D$7:D14,D15))
F16: =IF(OR(B16="",N(C16)<=0),"",C16*N(D16)/12) | G16: =IF(B16="",IF(N(C16)>0,"Manca il nome",""),IF(C16="","Manca il saldo",IF(N(C16)<=0,"",IF(NOT(ISNUMBER(D16)),"Manca il TAN",IF(N(E16)<=0,"Manca la rata",IF(D16=0,ROUNDUP(C16/E16,0),IF(E16<=C16*D16/12,"Rata troppo bassa",ROUNDUP(NPER(D16/12,-E16,C16),0)))))))) | H16: =IF(ISNUMBER(G16),DATE(YEAR(Impostazioni!$C$11),MONTH(Impostazioni!$C$11)+G16,1),"") | I16: =IF(ISNUMBER(G16),IF(N(D16)=0,0,MAX(0,E16*NPER(D16/12,-E16,C16)-C16)),"") | J16: =IF(OR(B16="",N(C16)<=0,NOT(ISNUMBER(D16))),"",1+COUNTIFS($B$8:$B$17,"<>",$C$8:$C$17,">0",$D$8:$D$17,">=0",$D$8:$D$17,">"&D16)+COUNTIFS($B$8:$B$17,"<>",$C$8:$C$17,">0",$D$8:$D$17,">=0",$D$8:$D$17,D16,$C$8:$C$17,"<"&C16)+COUNTIFS($B$7:B15,"<>",$C$7:C15,C16,$D$7:D15,D16)) | K16: =IF(OR(B16="",N(C16)<=0,NOT(ISNUMBER(D16))),"",1+COUNTIFS($B$8:$B$17,"<>",$C$8:$C$17,">0",$D$8:$D$17,">=0",$C$8:$C$17,"<"&C16)+COUNTIFS($B$8:$B$17,"<>",$C$8:$C$17,">0",$D$8:$D$17,">=0",$C$8:$C$17,C16,$D$8:$D$17,">"&D16)+COUNTIFS($B$7:B15,"<>",$C$7:C15,C16,$D$7:D15,D16))
F17: =IF(OR(B17="",N(C17)<=0),"",C17*N(D17)/12) | G17: =IF(B17="",IF(N(C17)>0,"Manca il nome",""),IF(C17="","Manca il saldo",IF(N(C17)<=0,"",IF(NOT(ISNUMBER(D17)),"Manca il TAN",IF(N(E17)<=0,"Manca la rata",IF(D17=0,ROUNDUP(C17/E17,0),IF(E17<=C17*D17/12,"Rata troppo bassa",ROUNDUP(NPER(D17/12,-E17,C17),0)))))))) | H17: =IF(ISNUMBER(G17),DATE(YEAR(Impostazioni!$C$11),MONTH(Impostazioni!$C$11)+G17,1),"") | I17: =IF(ISNUMBER(G17),IF(N(D17)=0,0,MAX(0,E17*NPER(D17/12,-E17,C17)-C17)),"") | J17: =IF(OR(B17="",N(C17)<=0,NOT(ISNUMBER(D17))),"",1+COUNTIFS($B$8:$B$17,"<>",$C$8:$C$17,">0",$D$8:$D$17,">=0",$D$8:$D$17,">"&D17)+COUNTIFS($B$8:$B$17,"<>",$C$8:$C$17,">0",$D$8:$D$17,">=0",$D$8:$D$17,D17,$C$8:$C$17,"<"&C17)+COUNTIFS($B$7:B16,"<>",$C$7:C16,C17,$D$7:D16,D17)) | K17: =IF(OR(B17="",N(C17)<=0,NOT(ISNUMBER(D17))),"",1+COUNTIFS($B$8:$B$17,"<>",$C$8:$C$17,">0",$D$8:$D$17,">=0",$C$8:$C$17,"<"&C17)+COUNTIFS($B$8:$B$17,"<>",$C$8:$C$17,">0",$D$8:$D$17,">=0",$C$8:$C$17,C17,$D$8:$D$17,">"&D17)+COUNTIFS($B$7:B16,"<>",$C$7:C16,C17,$D$7:D16,D17))
B18: Totale | C18: =SUM(C8:C17) | D18: =IF(C18=0,"",F18*12/C18) | E18: =SUM(E8:E17) | F18: =SUM(F8:F17) | I18: =SUM(I8:I17)
B19: Il TAN nella riga del totale è la media pesata sui saldi. Per un finanziamento a tasso zero scrivi 0%.
B21: Ordine di estinzione consigliato
B22: Valanga: prima il tasso più alto | C22: TAN | D22: Saldo | F22: Palla di neve: prima il saldo più basso | H22: Saldo | I22: TAN
A23: 1 | B23: =IFERROR(INDEX($B$8:$B$17,MATCH(1,$J$8:$J$17,0)),"") | C23: =IFERROR(INDEX($D$8:$D$17,MATCH(1,$J$8:$J$17,0)),"") | D23: =IFERROR(INDEX($C$8:$C$17,MATCH(1,$J$8:$J$17,0)),"") | F23: =IFERROR(INDEX($B$8:$B$17,MATCH(1,$K$8:$K$17,0)),"") | H23: =IFERROR(INDEX($C$8:$C$17,MATCH(1,$K$8:$K$17,0)),"") | I23: =IFERROR(INDEX($D$8:$D$17,MATCH(1,$K$8:$K$17,0)),"")
A24: 2 | B24: =IFERROR(INDEX($B$8:$B$17,MATCH(2,$J$8:$J$17,0)),"") | C24: =IFERROR(INDEX($D$8:$D$17,MATCH(2,$J$8:$J$17,0)),"") | D24: =IFERROR(INDEX($C$8:$C$17,MATCH(2,$J$8:$J$17,0)),"") | F24: =IFERROR(INDEX($B$8:$B$17,MATCH(2,$K$8:$K$17,0)),"") | H24: =IFERROR(INDEX($C$8:$C$17,MATCH(2,$K$8:$K$17,0)),"") | I24: =IFERROR(INDEX($D$8:$D$17,MATCH(2,$K$8:$K$17,0)),"")
A25: 3 | B25: =IFERROR(INDEX($B$8:$B$17,MATCH(3,$J$8:$J$17,0)),"") | C25: =IFERROR(INDEX($D$8:$D$17,MATCH(3,$J$8:$J$17,0)),"") | D25: =IFERROR(INDEX($C$8:$C$17,MATCH(3,$J$8:$J$17,0)),"") | F25: =IFERROR(INDEX($B$8:$B$17,MATCH(3,$K$8:$K$17,0)),"") | H25: =IFERROR(INDEX($C$8:$C$17,MATCH(3,$K$8:$K$17,0)),"") | I25: =IFERROR(INDEX($D$8:$D$17,MATCH(3,$K$8:$K$17,0)),"")
A26: 4 | B26: =IFERROR(INDEX($B$8:$B$17,MATCH(4,$J$8:$J$17,0)),"") | C26: =IFERROR(INDEX($D$8:$D$17,MATCH(4,$J$8:$J$17,0)),"") | D26: =IFERROR(INDEX($C$8:$C$17,MATCH(4,$J$8:$J$17,0)),"") | F26: =IFERROR(INDEX($B$8:$B$17,MATCH(4,$K$8:$K$17,0)),"") | H26: =IFERROR(INDEX($C$8:$C$17,MATCH(4,$K$8:$K$17,0)),"") | I26: =IFERROR(INDEX($D$8:$D$17,MATCH(4,$K$8:$K$17,0)),"")
A27: 5 | B27: =IFERROR(INDEX($B$8:$B$17,MATCH(5,$J$8:$J$17,0)),"") | C27: =IFERROR(INDEX($D$8:$D$17,MATCH(5,$J$8:$J$17,0)),"") | D27: =IFERROR(INDEX($C$8:$C$17,MATCH(5,$J$8:$J$17,0)),"") | F27: =IFERROR(INDEX($B$8:$B$17,MATCH(5,$K$8:$K$17,0)),"") | H27: =IFERROR(INDEX($C$8:$C$17,MATCH(5,$K$8:$K$17,0)),"") | I27: =IFERROR(INDEX($D$8:$D$17,MATCH(5,$K$8:$K$17,0)),"")
A28: 6 | B28: =IFERROR(INDEX($B$8:$B$17,MATCH(6,$J$8:$J$17,0)),"") | C28: =IFERROR(INDEX($D$8:$D$17,MATCH(6,$J$8:$J$17,0)),"") | D28: =IFERROR(INDEX($C$8:$C$17,MATCH(6,$J$8:$J$17,0)),"") | F28: =IFERROR(INDEX($B$8:$B$17,MATCH(6,$K$8:$K$17,0)),"") | H28: =IFERROR(INDEX($C$8:$C$17,MATCH(6,$K$8:$K$17,0)),"") | I28: =IFERROR(INDEX($D$8:$D$17,MATCH(6,$K$8:$K$17,0)),"")
A29: 7 | B29: =IFERROR(INDEX($B$8:$B$17,MATCH(7,$J$8:$J$17,0)),"") | C29: =IFERROR(INDEX($D$8:$D$17,MATCH(7,$J$8:$J$17,0)),"") | D29: =IFERROR(INDEX($C$8:$C$17,MATCH(7,$J$8:$J$17,0)),"") | F29: =IFERROR(INDEX($B$8:$B$17,MATCH(7,$K$8:$K$17,0)),"") | H29: =IFERROR(INDEX($C$8:$C$17,MATCH(7,$K$8:$K$17,0)),"") | I29: =IFERROR(INDEX($D$8:$D$17,MATCH(7,$K$8:$K$17,0)),"")
A30: 8 | B30: =IFERROR(INDEX($B$8:$B$17,MATCH(8,$J$8:$J$17,0)),"") | C30: =IFERROR(INDEX($D$8:$D$17,MATCH(8,$J$8:$J$17,0)),"") | D30: =IFERROR(INDEX($C$8:$C$17,MATCH(8,$J$8:$J$17,0)),"") | F30: =IFERROR(INDEX($B$8:$B$17,MATCH(8,$K$8:$K$17,0)),"") | H30: =IFERROR(INDEX($C$8:$C$17,MATCH(8,$K$8:$K$17,0)),"") | I30: =IFERROR(INDEX($D$8:$D$17,MATCH(8,$K$8:$K$17,0)),"")
A31: 9 | B31: =IFERROR(INDEX($B$8:$B$17,MATCH(9,$J$8:$J$17,0)),"") | C31: =IFERROR(INDEX($D$8:$D$17,MATCH(9,$J$8:$J$17,0)),"") | D31: =IFERROR(INDEX($C$8:$C$17,MATCH(9,$J$8:$J$17,0)),"") | F31: =IFERROR(INDEX($B$8:$B$17,MATCH(9,$K$8:$K$17,0)),"") | H31: =IFERROR(INDEX($C$8:$C$17,MATCH(9,$K$8:$K$17,0)),"") | I31: =IFERROR(INDEX($D$8:$D$17,MATCH(9,$K$8:$K$17,0)),"")
A32: 10 | B32: =IFERROR(INDEX($B$8:$B$17,MATCH(10,$J$8:$J$17,0)),"") | C32: =IFERROR(INDEX($D$8:$D$17,MATCH(10,$J$8:$J$17,0)),"") | D32: =IFERROR(INDEX($C$8:$C$17,MATCH(10,$J$8:$J$17,0)),"") | F32: =IFERROR(INDEX($B$8:$B$17,MATCH(10,$K$8:$K$17,0)),"") | H32: =IFERROR(INDEX($C$8:$C$17,MATCH(10,$K$8:$K$17,0)),"") | I32: =IFERROR(INDEX($D$8:$D$17,MATCH(10,$K$8:$K$17,0)),"")
B34: Effetto della somma extra sul primo debito
B35: Debito su cui concentrare l'extra | C35: =IF($C$4="Palla di neve",F23,B23)
B36: Saldo residuo | C36: =IF(C35="","",INDEX($C$8:$C$17,MATCH(C35,$B$8:$B$17,0)))
B37: TAN annuo | C37: =IF(C35="","",INDEX($D$8:$D$17,MATCH(C35,$B$8:$B$17,0)))
B38: Rata attuale più somma extra | C38: =IF(C35="","",INDEX($E$8:$E$17,MATCH(C35,$B$8:$B$17,0))+N($C$5))
B39: Mesi alla fine con la sola rata | C39: =IF(C35="","",INDEX($G$8:$G$17,MATCH(C35,$B$8:$B$17,0)))
B40: Mesi alla fine con rata più extra | C40: =IF(OR(C35="",N(C38)<=0),"",IF(C37=0,ROUNDUP(C36/C38,0),IF(C38<=C36*C37/12,"Rata troppo bassa",ROUNDUP(NPER(C37/12,-C38,C36),0))))
B41: Mesi in meno | C41: =IF(AND(ISNUMBER(C39),ISNUMBER(C40)),C39-C40,"")
B42: Interessi risparmiati (stima) | C42: =IF(AND(ISNUMBER(C39),ISNUMBER(C40)),IF(C37=0,0,MAX(0,INDEX($I$8:$I$17,MATCH(C35,$B$8:$B$17,0))-(C38*NPER(C37/12,-C38,C36)-C36))),"")
B43: Quando estingui il primo debito, aggiungi la sua rata a quella del debito successivo: è l'effetto «valanga» o «palla di neve».

Sheet Elenchi
A1: Mesi | B1: Mesi brevi | C1: Tipi | D1: Mese di riferimento | E1: Metodo | G1: Elenchi usati dai menu a tendina. Non modificare.
A2: Gennaio | B2: Gen | C2: Entrata | D2: Automatico | E2: Valanga
A3: Febbraio | B3: Feb | C3: Spesa fissa | D3: Gennaio | E3: Palla di neve
A4: Marzo | B4: Mar | C4: Spesa variabile | D4: Febbraio
A5: Aprile | B5: Apr | C5: Risparmio e investimenti | D5: Marzo
A6: Maggio | B6: Mag | D6: Aprile
A7: Giugno | B7: Giu | D7: Maggio
A8: Luglio | B8: Lug | D8: Giugno
A9: Agosto | B9: Ago | D9: Luglio
A10: Settembre | B10: Set | D10: Agosto
A11: Ottobre | B11: Ott | D11: Settembre
A12: Novembre | B12: Nov | D12: Ottobre
A13: Dicembre | B13: Dic | D13: Novembre
D14: Dicembre
