Workbook

Sheet Start Here
B1: 2026 Budget Planner
B2: Plan your money month by month, log every transaction and see your whole year at a glance.
B5: Start in 6 steps
B6: 1. Settings: check the year and choose your currency symbol ($, £, € ...). It appears in the column headings.
B7: 2. Categories: rename, delete or add categories (up to 60). Give each one a type: Income, Fixed bills, Variable expenses or Savings & debt.
B8: 3. Monthly Budget: type a typical monthly amount for each category. All 12 months fill in by themselves; type over a single month for costs that do not repeat every month (annual insurance, holiday gifts).
B9: 4. Transactions: log every payment and every income with date, description, category (from the drop-down list) and amount. Use positive amounts; for a refund, type a negative amount in the same category.
B10: 5. Monthly Summary and Annual Dashboard: nothing to type, they update by themselves. Pick the month to review at the top of Monthly Summary.
B11: 6. Optional: track your Savings Goals, Sinking Funds and Debt Payoff plan.
B13: Color key
B14: Yellow cells: your inputs. Type over them freely.
B15: White cells: formulas. The sheets are protected so you do not delete them by mistake.
... B37: Sheets in this file
B38: Settings | C38: Year, currency symbol, plan name, accounts and the date used for "months left".
B39: Categories | C39: Your categories and their types.
B40: Transactions | C40: One log for the whole year: 2,000 rows with drop-down lists and automatic checks.
B41: Monthly Budget | C41: Planned amounts per category and month, and "Left to budget".
B42: Monthly Summary | C42: Actual vs planned for the month you choose and the year to date, plus actuals for every month.
B43: Annual Dashboard | C43: Income, expenses, savings rate, top spending categories and charts.
B44: Savings Goals | C44: Targets, progress and how much to save each month.
B45: Sinking Funds | C45: Money set aside for irregular costs: balance, amount still needed, monthly amount.
B46: Debt Payoff | C46: Snowball or avalanche order, debt-free date and interest saved.
B47: Debt Schedule | C47: Month-by-month balances behind Debt Payoff (calculated, nothing to type).
B49: This planner is a personal organization tool. It is not financial, tax or legal advice.
B50: Made by NettoChiaro · version 2026.1 · Questions? Send us a message on Etsy.

Sheet Settings
B1: Settings
B2: Set these once. Yellow cells are inputs.
B3: Setting | C3: Your value | D3: Notes
B4: Budget year | C4: 2026 | D4: The calendar year of this planner. Transactions from other years are flagged.
B5: Currency symbol | C5: $ | D5: Shown in the column headings, for example "Amount ($)". Pick one from the list or type your own.
B6: Plan name (optional) | C6: Alex & Sam (sample data) | D6: Shown on the dashboard, for example "Smith household".
B7: As-of date (optional) | C7: 46387 | D7: Leave empty to use today's date. Used for "months left" and payoff dates.
B9: Values used by the formulas (calculated)
B10: Month to review | C10: ='Monthly Summary'!$B$3 | D10: Chosen at the top of Monthly Summary. Auto = the latest month.
B11: As-of date used | C11: =IF(ISNUMBER(C7),C7,TODAY())
B12: Month used (number) | C12: =IFERROR(MATCH('Monthly Summary'!$B$3,Lists!$A$2:$A$13,0),IF(YEAR(C11)<C4,1,IF(YEAR(C11)>C4,12,MONTH(C11)))) | D12: Auto: the month of the as-of date; December for a past year, January for a future year.
B13: Month used (name) | C13: =INDEX(Lists!$A$2:$A$13,C12)
B14: Currency in headings | C14: =IF(TRIM(C5)="",""," ("&TRIM(C5)&")")
B15: Month used (short) | C15: =LEFT(C13,3)
B17: Accounts and payment methods (drop-down in Transactions)
B18: Checking | C18: Optional. Rename or add up to 8.
B19: Savings
B20: Credit card
B21: Debit card
B22: Cash

Sheet Categories
A1: Categories
A2: Up to 60 categories. Each one needs a type. Changes show up everywhere, including the drop-down list in Transactions.
A3: Types: Income · Fixed bills (same amount every month) · Variable expenses · Savings & debt (savings, investing and debt payments). Avoid the characters * ? ~ in names.
A5: Category | B5: Type | C5: Notes | D5: Check
A6: Paycheck 1 | B6: Income | C6: Take-home pay after tax. Rename it, for example "Alex pay". | D6: =IF(A6="",IF(B6="","","Name missing"),IF(B6="","Choose a type",IF(COUNTIF($A$6:$A$65,A6)>1,"Name used twice",IF(ISNA(MATCH(B6,Lists!$D$2:$D$5,0)),"Unknown type",""))))
A7: Paycheck 2 | B7: Income | C7: Second earner, if any. | D7: =IF(A7="",IF(B7="","","Name missing"),IF(B7="","Choose a type",IF(COUNTIF($A$6:$A$65,A7)>1,"Name used twice",IF(ISNA(MATCH(B7,Lists!$D$2:$D$5,0)),"Unknown type",""))))
A8: Side income | B8: Income | C8: Freelance work, selling things, tips. | D8: =IF(A8="",IF(B8="","","Name missing"),IF(B8="","Choose a type",IF(COUNTIF($A$6:$A$65,A8)>1,"Name used twice",IF(ISNA(MATCH(B8,Lists!$D$2:$D$5,0)),"Unknown type",""))))
A9: Other income | B9: Income | C9: Tax refunds, gifts, interest, benefits. | D9: =IF(A9="",IF(B9="","","Name missing"),IF(B9="","Choose a type",IF(COUNTIF($A$6:$A$65,A9)>1,"Name used twice",IF(ISNA(MATCH(B9,Lists!$D$2:$D$5,0)),"Unknown type",""))))
A10: Rent / Mortgage | B10: Fixed bills | D10: =IF(A10="",IF(B10="","","Name missing"),IF(B10="","Choose a type",IF(COUNTIF($A$6:$A$65,A10)>1,"Name used twice",IF(ISNA(MATCH(B10,Lists!$D$2:$D$5,0)),"Unknown type",""))))
A11: Utilities | B11: Fixed bills | C11: Electricity, gas, water, trash. | D11: =IF(A11="",IF(B11="","","Name missing"),IF(B11="","Choose a type",IF(COUNTIF($A$6:$A$65,A11)>1,"Name used twice",IF(ISNA(MATCH(B11,Lists!$D$2:$D$5,0)),"Unknown type",""))))
A12: Internet & Phone | B12: Fixed bills | D12: =IF(A12="",IF(B12="","","Name missing"),IF(B12="","Choose a type",IF(COUNTIF($A$6:$A$65,A12)>1,"Name used twice",IF(ISNA(MATCH(B12,Lists!$D$2:$D$5,0)),"Unknown type",""))))
A13: Insurance | B13: Fixed bills | C13: Car, home or renters, life, health. | D13: =IF(A13="",IF(B13="","","Name missing"),IF(B13="","Choose a type",IF(COUNTIF($A$6:$A$65,A13)>1,"Name used twice",IF(ISNA(MATCH(B13,Lists!$D$2:$D$5,0)),"Unknown type",""))))
A14: Subscriptions | B14: Fixed bills | C14: Streaming, apps, gym, memberships. | D14: =IF(A14="",IF(B14="","","Name missing"),IF(B14="","Choose a type",IF(COUNTIF($A$6:$A$65,A14)>1,"Name used twice",IF(ISNA(MATCH(B14,Lists!$D$2:$D$5,0)),"Unknown type",""))))
A15: Car payment | B15: Fixed bills | C15: Car loan or lease. | D15: =IF(A15="",IF(B15="","","Name missing"),IF(B15="","Choose a type",IF(COUNTIF($A$6:$A$65,A15)>1,"Name used twice",IF(ISNA(MATCH(B15,Lists!$D$2:$D$5,0)),"Unknown type",""))))
A16: Groceries | B16: Variable expenses | C16: Food and household supplies. | D16: =IF(A16="",IF(B16="","","Name missing"),IF(B16="","Choose a type",IF(COUNTIF($A$6:$A$65,A16)>1,"Name used twice",IF(ISNA(MATCH(B16,Lists!$D$2:$D$5,0)),"Unknown type",""))))
A17: Dining out | B17: Variable expenses | C17: Restaurants, takeout, coffee. | D17: =IF(A17="",IF(B17="","","Name missing"),IF(B17="","Choose a type",IF(COUNTIF($A$6:$A$65,A17)>1,"Name used twice",IF(ISNA(MATCH(B17,Lists!$D$2:$D$5,0)),"Unknown type",""))))
A18: Transport / Gas | B18: Variable expenses | C18: Fuel, public transport, parking, tolls, car repairs. | D18: =IF(A18="",IF(B18="","","Name missing"),IF(B18="","Choose a type",IF(COUNTIF($A$6:$A$65,A18)>1,"Name used twice",IF(ISNA(MATCH(B18,Lists!$D$2:$D$5,0)),"Unknown type",""))))
A19: Health | B19: Variable expenses | C19: Pharmacy, doctor and dentist visits, copays. | D19: =IF(A19="",IF(B19="","","Name missing"),IF(B19="","Choose a type",IF(COUNTIF($A$6:$A$65,A19)>1,"Name used twice",IF(ISNA(MATCH(B19,Lists!$D$2:$D$5,0)),"Unknown type",""))))
A20: Kids | B20: Variable expenses | C20: Childcare, school, activities, clothes. | D20: =IF(A20="",IF(B20="","","Name missing"),IF(B20="","Choose a type",IF(COUNTIF($A$6:$A$65,A20)>1,"Name used twice",IF(ISNA(MATCH(B20,Lists!$D$2:$D$5,0)),"Unknown type",""))))
A21: Personal care | B21: Variable expenses | C21: Haircuts, toiletries, cosmetics. | D21: =IF(A21="",IF(B21="","","Name missing"),IF(B21="","Choose a type",IF(COUNTIF($A$6:$A$65,A21)>1,"Name used twice",IF(ISNA(MATCH(B21,Lists!$D$2:$D$5,0)),"Unknown type",""))))
A22: Entertainment | B22: Variable expenses | C22: Movies, events, hobbies, games. | D22: =IF(A22="",IF(B22="","","Name missing"),IF(B22="","Choose a type",IF(COUNTIF($A$6:$A$65,A22)>1,"Name used twice",IF(ISNA(MATCH(B22,Lists!$D$2:$D$5,0)),"Unknown type",""))))
A23: Gifts | B23: Variable expenses | C23: Birthdays, holidays, donations. | D23: =IF(A23="",IF(B23="","","Name missing"),IF(B23="","Choose a type",IF(COUNTIF($A$6:$A$65,A23)>1,"Name used twice",IF(ISNA(MATCH(B23,Lists!$D$2:$D$5,0)),"Unknown type",""))))
A24: Travel | B24: Variable expenses | C24: Trips and vacations. | D24: =IF(A24="",IF(B24="","","Name missing"),IF(B24="","Choose a type",IF(COUNTIF($A$6:$A$65,A24)>1,"Name used twice",IF(ISNA(MATCH(B24,Lists!$D$2:$D$5,0)),"Unknown type",""))))
A25: Clothing | B25: Variable expenses | D25: =IF(A25="",IF(B25="","","Name missing"),IF(B25="","Choose a type",IF(COUNTIF($A$6:$A$65,A25)>1,"Name used twice",IF(ISNA(MATCH(B25,Lists!$D$2:$D$5,0)),"Unknown type",""))))
A26: Home & repairs | B26: Variable expenses | C26: Furniture, tools, repairs, appliances. | D26: =IF(A26="",IF(B26="","","Name missing"),IF(B26="","Choose a type",IF(COUNTIF($A$6:$A$65,A26)>1,"Name used twice",IF(ISNA(MATCH(B26,Lists!$D$2:$D$5,0)),"Unknown type",""))))
A27: Pets | B27: Variable expenses | C27: Food, vet, grooming. | D27: =IF(A27="",IF(B27="","","Name missing"),IF(B27="","Choose a type",IF(COUNTIF($A$6:$A$65,A27)>1,"Name used twice",IF(ISNA(MATCH(B27,Lists!$D$2:$D$5,0)),"Unknown type",""))))
A28: Misc | B28: Variable expenses | C28: Anything that does not fit elsewhere. | D28: =IF(A28="",IF(B28="","","Name missing"),IF(B28="","Choose a type",IF(COUNTIF($A$6:$A$65,A28)>1,"Name used twice",IF(ISNA(MATCH(B28,Lists!$D$2:$D$5,0)),"Unknown type",""))))
A29: Emergency fund | B29: Savings & debt | C29: Money moved to your emergency savings. | D29: =IF(A29="",IF(B29="","","Name missing"),IF(B29="","Choose a type",IF(COUNTIF($A$6:$A$65,A29)>1,"Name used twice",IF(ISNA(MATCH(B29,Lists!$D$2:$D$5,0)),"Unknown type",""))))
A30: Savings goals | B30: Savings & debt | C30: Money moved to the goals in Savings Goals. | D30: =IF(A30="",IF(B30="","","Name missing"),IF(B30="","Choose a type",IF(COUNTIF($A$6:$A$65,A30)>1,"Name used twice",IF(ISNA(MATCH(B30,Lists!$D$2:$D$5,0)),"Unknown type",""))))
A31: Sinking funds | B31: Savings & debt | C31: Money set aside for the funds in Sinking Funds. | D31: =IF(A31="",IF(B31="","","Name missing"),IF(B31="","Choose a type",IF(COUNTIF($A$6:$A$65,A31)>1,"Name used twice",IF(ISNA(MATCH(B31,Lists!$D$2:$D$5,0)),"Unknown type",""))))
A32: Retirement & investing | B32: Savings & debt | C32: Pension or retirement account, investments. | D32: =IF(A32="",IF(B32="","","Name missing"),IF(B32="","Choose a type",IF(COUNTIF($A$6:$A$65,A32)>1,"Name used twice",IF(ISNA(MATCH(B32,Lists!$D$2:$D$5,0)),"Unknown type",""))))
A33: Debt payments | B33: Savings & debt | C33: Credit cards, student and personal loans (see Debt Payoff). | D33: =IF(A33="",IF(B33="","","Name missing"),IF(B33="","Choose a type",IF(COUNTIF($A$6:$A$65,A33)>1,"Name used twice",IF(ISNA(MATCH(B33,Lists!$D$2:$D$5,0)),"Unknown type",""))))
D34: =IF(A34="",IF(B34="","","Name missing"),IF(B34="","Choose a type",IF(COUNTIF($A$6:$A$65,A34)>1,"Name used twice",IF(ISNA(MATCH(B34,Lists!$D$2:$D$5,0)),"Unknown type",""))))
D35: =IF(A35="",IF(B35="","","Name missing"),IF(B35="","Choose a type",IF(COUNTIF($A$6:$A$65,A35)>1,"Name used twice",IF(ISNA(MATCH(B35,Lists!$D$2:$D$5,0)),"Unknown type",""))))
D36: =IF(A36="",IF(B36="","","Name missing"),IF(B36="","Choose a type",IF(COUNTIF($A$6:$A$65,A36)>1,"Name used twice",IF(ISNA(MATCH(B36,Lists!$D$2:$D$5,0)),"Unknown type",""))))
D37: =IF(A37="",IF(B37="","","Name missing"),IF(B37="","Choose a type",IF(COUNTIF($A$6:$A$65,A37)>1,"Name used twice",IF(ISNA(MATCH(B37,Lists!$D$2:$D$5,0)),"Unknown type",""))))
D38: =IF(A38="",IF(B38="","","Name missing"),IF(B38="","Choose a type",IF(COUNTIF($A$6:$A$65,A38)>1,"Name used twice",IF(ISNA(MATCH(B38,Lists!$D$2:$D$5,0)),"Unknown type",""))))
D39: =IF(A39="",IF(B39="","","Name missing"),IF(B39="","Choose a type",IF(COUNTIF($A$6:$A$65,A39)>1,"Name used twice",IF(ISNA(MATCH(B39,Lists!$D$2:$D$5,0)),"Unknown type",""))))
D40: =IF(A40="",IF(B40="","","Name missing"),IF(B40="","Choose a type",IF(COUNTIF($A$6:$A$65,A40)>1,"Name used twice",IF(ISNA(MATCH(B40,Lists!$D$2:$D$5,0)),"Unknown type",""))))
D41: =IF(A41="",IF(B41="","","Name missing"),IF(B41="","Choose a type",IF(COUNTIF($A$6:$A$65,A41)>1,"Name used twice",IF(ISNA(MATCH(B41,Lists!$D$2:$D$5,0)),"Unknown type",""))))
D42: =IF(A42="",IF(B42="","","Name missing"),IF(B42="","Choose a type",IF(COUNTIF($A$6:$A$65,A42)>1,"Name used twice",IF(ISNA(MATCH(B42,Lists!$D$2:$D$5,0)),"Unknown type",""))))
D43: =IF(A43="",IF(B43="","","Name missing"),IF(B43="","Choose a type",IF(COUNTIF($A$6:$A$65,A43)>1,"Name used twice",IF(ISNA(MATCH(B43,Lists!$D$2:$D$5,0)),"Unknown type",""))))
D44: =IF(A44="",IF(B44="","","Name missing"),IF(B44="","Choose a type",IF(COUNTIF($A$6:$A$65,A44)>1,"Name used twice",IF(ISNA(MATCH(B44,Lists!$D$2:$D$5,0)),"Unknown type",""))))
D45: =IF(A45="",IF(B45="","","Name missing"),IF(B45="","Choose a type",IF(COUNTIF($A$6:$A$65,A45)>1,"Name used twice",IF(ISNA(MATCH(B45,Lists!$D$2:$D$5,0)),"Unknown type",""))))
... D65: =IF(A65="",IF(B65="","","Name missing"),IF(B65="","Choose a type",IF(COUNTIF($A$6:$A$65,A65)>1,"Name used twice",IF(ISNA(MATCH(B65,Lists!$D$2:$D$5,0)),"Unknown type",""))))

Sheet Transactions
A1: Transactions
A2: One row per payment or income. Dates as year-month-day (2026-03-15). Positive amounts; a refund is a negative amount in the same category.
A3: ="Rows used: "&COUNT(D6:D2005)&" of 2,000 · Total income "&Settings!$C$4&": "&FIXED(SUMIFS(D6:D2005,H6:H2005,"Income",A6:A2005,">="&DATE(Settings!$C$4,1,1),A6:A2005,"<"&DATE(Settings!$C$4+1,1,1)),2)&" · Total expenses "&Settings!$C$4&": "&FIXED(SUMIFS(D6:D2005,H6:H2005,"Fixed bills",A6:A2005,">="&DATE(Settings!$C$4,1,1),A6:A2005,"<"&DATE(Settings!$C$4+1,1,1))+SUMIFS(D6:D2005,H6:H2005,"Variable expenses",A6:A2005,">="&DATE(Settings!$C$4,1,1),A6:A2005,"<"&DATE(Settings!$C$4+1,1,1)),2)
A5: Date | B5: Description | C5: Category | D5: ="Amount"&Settings!$C$14 | E5: Account | F5: Goal / fund (optional) | G5: Notes | H5: Type | I5: Check
A6: 46023 | B6: Alex paycheck | C6: Paycheck 1 | D6: 2100 | E6: Checking | H6: =IF(C6="","",IFERROR(INDEX(Categories!$B$6:$B$65,MATCH(C6,Categories!$A$6:$A$65,0))&"","")) | I6: =IF(AND(A6="",C6="",D6=""),"",IF(A6="","Date missing",IF(NOT(ISNUMBER(A6)),"Date not recognized",IF(YEAR(A6)<>Settings!$C$4,"Not in "&Settings!$C$4,IF(C6="","Category missing",IF(H6="",IF(COUNTIF(Categories!$A$6:$A$65,C6)>0,"Category has no type","Category not in list"),IF(D6="","Amount missing",IF(NOT(ISNUMBER(D6)),"Amount is not a number",IF(F6="","",IF(ISNA(MATCH(F6,Lists!$G$2:$G$25,0)),"Goal / fund not in list",IF(H6="Income","Fund tag ignored on income","")))))))))))
A7: 46023 | B7: Rent | C7: Rent / Mortgage | D7: 1850 | E7: Checking | H7: =IF(C7="","",IFERROR(INDEX(Categories!$B$6:$B$65,MATCH(C7,Categories!$A$6:$A$65,0))&"","")) | I7: =IF(AND(A7="",C7="",D7=""),"",IF(A7="","Date missing",IF(NOT(ISNUMBER(A7)),"Date not recognized",IF(YEAR(A7)<>Settings!$C$4,"Not in "&Settings!$C$4,IF(C7="","Category missing",IF(H7="",IF(COUNTIF(Categories!$A$6:$A$65,C7)>0,"Category has no type","Category not in list"),IF(D7="","Amount missing",IF(NOT(ISNUMBER(D7)),"Amount is not a number",IF(F7="","",IF(ISNA(MATCH(F7,Lists!$G$2:$G$25,0)),"Goal / fund not in list",IF(H7="Income","Fund tag ignored on income","")))))))))))
A8: 46023 | B8: Dentist copay | C8: Health | D8: 53.73 | E8: Debit card | H8: =IF(C8="","",IFERROR(INDEX(Categories!$B$6:$B$65,MATCH(C8,Categories!$A$6:$A$65,0))&"","")) | I8: =IF(AND(A8="",C8="",D8=""),"",IF(A8="","Date missing",IF(NOT(ISNUMBER(A8)),"Date not recognized",IF(YEAR(A8)<>Settings!$C$4,"Not in "&Settings!$C$4,IF(C8="","Category missing",IF(H8="",IF(COUNTIF(Categories!$A$6:$A$65,C8)>0,"Category has no type","Category not in list"),IF(D8="","Amount missing",IF(NOT(ISNUMBER(D8)),"Amount is not a number",IF(F8="","",IF(ISNA(MATCH(F8,Lists!$G$2:$G$25,0)),"Goal / fund not in list",IF(H8="Income","Fund tag ignored on income","")))))))))))
A9: 46023 | B9: After-school program | C9: Kids | D9: 320 | E9: Checking | H9: =IF(C9="","",IFERROR(INDEX(Categories!$B$6:$B$65,MATCH(C9,Categories!$A$6:$A$65,0))&"","")) | I9: =IF(AND(A9="",C9="",D9=""),"",IF(A9="","Date missing",IF(NOT(ISNUMBER(A9)),"Date not recognized",IF(YEAR(A9)<>Settings!$C$4,"Not in "&Settings!$C$4,IF(C9="","Category missing",IF(H9="",IF(COUNTIF(Categories!$A$6:$A$65,C9)>0,"Category has no type","Category not in list"),IF(D9="","Amount missing",IF(NOT(ISNUMBER(D9)),"Amount is not a number",IF(F9="","",IF(ISNA(MATCH(F9,Lists!$G$2:$G$25,0)),"Goal / fund not in list",IF(H9="Income","Fund tag ignored on income","")))))))))))
A10: 46024 | B10: Gym membership | C10: Subscriptions | D10: 45 | E10: Checking | H10: =IF(C10="","",IFERROR(INDEX(Categories!$B$6:$B$65,MATCH(C10,Categories!$A$6:$A$65,0))&"","")) | I10: =IF(AND(A10="",C10="",D10=""),"",IF(A10="","Date missing",IF(NOT(ISNUMBER(A10)),"Date not recognized",IF(YEAR(A10)<>Settings!$C$4,"Not in "&Settings!$C$4,IF(C10="","Category missing",IF(H10="",IF(COUNTIF(Categories!$A$6:$A$65,C10)>0,"Category has no type","Category not in list"),IF(D10="","Amount missing",IF(NOT(ISNUMBER(D10)),"Amount is not a number",IF(F10="","",IF(ISNA(MATCH(F10,Lists!$G$2:$G$25,0)),"Goal / fund not in list",IF(H10="Income","Fund tag ignored on income","")))))))))))
A11: 46024 | B11: Transfer to emergency fund | C11: Emergency fund | D11: 300 | E11: Savings | F11: Emergency fund | H11: =IF(C11="","",IFERROR(INDEX(Categories!$B$6:$B$65,MATCH(C11,Categories!$A$6:$A$65,0))&"","")) | I11: =IF(AND(A11="",C11="",D11=""),"",IF(A11="","Date missing",IF(NOT(ISNUMBER(A11)),"Date not recognized",IF(YEAR(A11)<>Settings!$C$4,"Not in "&Settings!$C$4,IF(C11="","Category missing",IF(H11="",IF(COUNTIF(Categories!$A$6:$A$65,C11)>0,"Category has no type","Category not in list"),IF(D11="","Amount missing",IF(NOT(ISNUMBER(D11)),"Amount is not a number",IF(F11="","",IF(ISNA(MATCH(F11,Lists!$G$2:$G$25,0)),"Goal / fund not in list",IF(H11="Income","Fund tag ignored on income","")))))))))))
A12: 46024 | B12: Transfer: house fund | C12: Savings goals | D12: 300 | E12: Savings | F12: House down payment | H12: =IF(C12="","",IFERROR(INDEX(Categories!$B$6:$B$65,MATCH(C12,Categories!$A$6:$A$65,0))&"","")) | I12: =IF(AND(A12="",C12="",D12=""),"",IF(A12="","Date missing",IF(NOT(ISNUMBER(A12)),"Date not recognized",IF(YEAR(A12)<>Settings!$C$4,"Not in "&Settings!$C$4,IF(C12="","Category missing",IF(H12="",IF(COUNTIF(Categories!$A$6:$A$65,C12)>0,"Category has no type","Category not in list"),IF(D12="","Amount missing",IF(NOT(ISNUMBER(D12)),"Amount is not a number",IF(F12="","",IF(ISNA(MATCH(F12,Lists!$G$2:$G$25,0)),"Goal / fund not in list",IF(H12="Income","Fund tag ignored on income","")))))))))))
A13: 46024 | B13: Transfer: laptop | C13: Savings goals | D13: 100 | E13: Savings | F13: New laptop | H13: =IF(C13="","",IFERROR(INDEX(Categories!$B$6:$B$65,MATCH(C13,Categories!$A$6:$A$65,0))&"","")) | I13: =IF(AND(A13="",C13="",D13=""),"",IF(A13="","Date missing",IF(NOT(ISNUMBER(A13)),"Date not recognized",IF(YEAR(A13)<>Settings!$C$4,"Not in "&Settings!$C$4,IF(C13="","Category missing",IF(H13="",IF(COUNTIF(Categories!$A$6:$A$65,C13)>0,"Category has no type","Category not in list"),IF(D13="","Amount missing",IF(NOT(ISNUMBER(D13)),"Amount is not a number",IF(F13="","",IF(ISNA(MATCH(F13,Lists!$G$2:$G$25,0)),"Goal / fund not in list",IF(H13="Income","Fund tag ignored on income","")))))))))))
A14: 46024 | B14: Set aside: car maintenance | C14: Sinking funds | D14: 60 | E14: Savings | F14: Car maintenance | H14: =IF(C14="","",IFERROR(INDEX(Categories!$B$6:$B$65,MATCH(C14,Categories!$A$6:$A$65,0))&"","")) | I14: =IF(AND(A14="",C14="",D14=""),"",IF(A14="","Date missing",IF(NOT(ISNUMBER(A14)),"Date not recognized",IF(YEAR(A14)<>Settings!$C$4,"Not in "&Settings!$C$4,IF(C14="","Category missing",IF(H14="",IF(COUNTIF(Categories!$A$6:$A$65,C14)>0,"Category has no type","Category not in list"),IF(D14="","Amount missing",IF(NOT(ISNUMBER(D14)),"Amount is not a number",IF(F14="","",IF(ISNA(MATCH(F14,Lists!$G$2:$G$25,0)),"Goal / fund not in list",IF(H14="Income","Fund tag ignored on income","")))))))))))
A15: 46024 | B15: Set aside: holiday gifts | C15: Sinking funds | D15: 50 | E15: Savings | F15: Holiday gifts | H15: =IF(C15="","",IFERROR(INDEX(Categories!$B$6:$B$65,MATCH(C15,Categories!$A$6:$A$65,0))&"","")) | I15: =IF(AND(A15="",C15="",D15=""),"",IF(A15="","Date missing",IF(NOT(ISNUMBER(A15)),"Date not recognized",IF(YEAR(A15)<>Settings!$C$4,"Not in "&Settings!$C$4,IF(C15="","Category missing",IF(H15="",IF(COUNTIF(Categories!$A$6:$A$65,C15)>0,"Category has no type","Category not in list"),IF(D15="","Amount missing",IF(NOT(ISNUMBER(D15)),"Amount is not a number",IF(F15="","",IF(ISNA(MATCH(F15,Lists!$G$2:$G$25,0)),"Goal / fund not in list",IF(H15="Income","Fund tag ignored on income","")))))))))))
A16: 46024 | B16: Set aside: summer vacation | C16: Sinking funds | D16: 150 | E16: Savings | F16: Summer vacation | H16: =IF(C16="","",IFERROR(INDEX(Categories!$B$6:$B$65,MATCH(C16,Categories!$A$6:$A$65,0))&"","")) | I16: =IF(AND(A16="",C16="",D16=""),"",IF(A16="","Date missing",IF(NOT(ISNUMBER(A16)),"Date not recognized",IF(YEAR(A16)<>Settings!$C$4,"Not in "&Settings!$C$4,IF(C16="","Category missing",IF(H16="",IF(COUNTIF(Categories!$A$6:$A$65,C16)>0,"Category has no type","Category not in list"),IF(D16="","Amount missing",IF(NOT(ISNUMBER(D16)),"Amount is not a number",IF(F16="","",IF(ISNA(MATCH(F16,Lists!$G$2:$G$25,0)),"Goal / fund not in list",IF(H16="Income","Fund tag ignored on income","")))))))))))
A17: 46024 | B17: Set aside: home repairs | C17: Sinking funds | D17: 40 | E17: Savings | F17: Home repairs | H17: =IF(C17="","",IFERROR(INDEX(Categories!$B$6:$B$65,MATCH(C17,Categories!$A$6:$A$65,0))&"","")) | I17: =IF(AND(A17="",C17="",D17=""),"",IF(A17="","Date missing",IF(NOT(ISNUMBER(A17)),"Date not recognized",IF(YEAR(A17)<>Settings!$C$4,"Not in "&Settings!$C$4,IF(C17="","Category missing",IF(H17="",IF(COUNTIF(Categories!$A$6:$A$65,C17)>0,"Category has no type","Category not in list"),IF(D17="","Amount missing",IF(NOT(ISNUMBER(D17)),"Amount is not a number",IF(F17="","",IF(ISNA(MATCH(F17,Lists!$G$2:$G$25,0)),"Goal / fund not in list",IF(H17="Income","Fund tag ignored on income","")))))))))))
A18: 46025 | B18: Video streaming | C18: Subscriptions | D18: 15.49 | E18: Credit card | H18: =IF(C18="","",IFERROR(INDEX(Categories!$B$6:$B$65,MATCH(C18,Categories!$A$6:$A$65,0))&"","")) | I18: =IF(AND(A18="",C18="",D18=""),"",IF(A18="","Date missing",IF(NOT(ISNUMBER(A18)),"Date not recognized",IF(YEAR(A18)<>Settings!$C$4,"Not in "&Settings!$C$4,IF(C18="","Category missing",IF(H18="",IF(COUNTIF(Categories!$A$6:$A$65,C18)>0,"Category has no type","Category not in list"),IF(D18="","Amount missing",IF(NOT(ISNUMBER(D18)),"Amount is not a number",IF(F18="","",IF(ISNA(MATCH(F18,Lists!$G$2:$G$25,0)),"Goal / fund not in list",IF(H18="Income","Fund tag ignored on income","")))))))))))
A19: 46025 | B19: Supermarket | C19: Groceries | D19: 191.42 | E19: Debit card | H19: =IF(C19="","",IFERROR(INDEX(Categories!$B$6:$B$65,MATCH(C19,Categories!$A$6:$A$65,0))&"","")) | I19: =IF(AND(A19="",C19="",D19=""),"",IF(A19="","Date missing",IF(NOT(ISNUMBER(A19)),"Date not recognized",IF(YEAR(A19)<>Settings!$C$4,"Not in "&Settings!$C$4,IF(C19="","Category missing",IF(H19="",IF(COUNTIF(Categories!$A$6:$A$65,C19)>0,"Category has no type","Category not in list"),IF(D19="","Amount missing",IF(NOT(ISNUMBER(D19)),"Amount is not a number",IF(F19="","",IF(ISNA(MATCH(F19,Lists!$G$2:$G$25,0)),"Goal / fund not in list",IF(H19="Income","Fund tag ignored on income","")))))))))))
A20: 46025 | B20: Retirement contribution | C20: Retirement & investing | D20: 600 | E20: Checking | H20: =IF(C20="","",IFERROR(INDEX(Categories!$B$6:$B$65,MATCH(C20,Categories!$A$6:$A$65,0))&"","")) | I20: =IF(AND(A20="",C20="",D20=""),"",IF(A20="","Date missing",IF(NOT(ISNUMBER(A20)),"Date not recognized",IF(YEAR(A20)<>Settings!$C$4,"Not in "&Settings!$C$4,IF(C20="","Category missing",IF(H20="",IF(COUNTIF(Categories!$A$6:$A$65,C20)>0,"Category has no type","Category not in list"),IF(D20="","Amount missing",IF(NOT(ISNUMBER(D20)),"Amount is not a number",IF(F20="","",IF(ISNA(MATCH(F20,Lists!$G$2:$G$25,0)),"Goal / fund not in list",IF(H20="Income","Fund tag ignored on income","")))))))))))
A21: 46026 | B21: Gas station | C21: Transport / Gas | D21: 44.13 | E21: Credit card | H21: =IF(C21="","",IFERROR(INDEX(Categories!$B$6:$B$65,MATCH(C21,Categories!$A$6:$A$65,0))&"","")) | I21: =IF(AND(A21="",C21="",D21=""),"",IF(A21="","Date missing",IF(NOT(ISNUMBER(A21)),"Date not recognized",IF(YEAR(A21)<>Settings!$C$4,"Not in "&Settings!$C$4,IF(C21="","Category missing",IF(H21="",IF(COUNTIF(Categories!$A$6:$A$65,C21)>0,"Category has no type","Category not in list"),IF(D21="","Amount missing",IF(NOT(ISNUMBER(D21)),"Amount is not a number",IF(F21="","",IF(ISNA(MATCH(F21,Lists!$G$2:$G$25,0)),"Goal / fund not in list",IF(H21="Income","Fund tag ignored on income","")))))))))))
A22: 46027 | B22: Car insurance | C22: Insurance | D22: 128 | E22: Checking | H22: =IF(C22="","",IFERROR(INDEX(Categories!$B$6:$B$65,MATCH(C22,Categories!$A$6:$A$65,0))&"","")) | I22: =IF(AND(A22="",C22="",D22=""),"",IF(A22="","Date missing",IF(NOT(ISNUMBER(A22)),"Date not recognized",IF(YEAR(A22)<>Settings!$C$4,"Not in "&Settings!$C$4,IF(C22="","Category missing",IF(H22="",IF(COUNTIF(Categories!$A$6:$A$65,C22)>0,"Category has no type","Category not in list"),IF(D22="","Amount missing",IF(NOT(ISNUMBER(D22)),"Amount is not a number",IF(F22="","",IF(ISNA(MATCH(F22,Lists!$G$2:$G$25,0)),"Goal / fund not in list",IF(H22="Income","Fund tag ignored on income","")))))))))))
A23: 46027 | B23: Renters insurance | C23: Insurance | D23: 18 | E23: Checking | H23: =IF(C23="","",IFERROR(INDEX(Categories!$B$6:$B$65,MATCH(C23,Categories!$A$6:$A$65,0))&"","")) | I23: =IF(AND(A23="",C23="",D23=""),"",IF(A23="","Date missing",IF(NOT(ISNUMBER(A23)),"Date not recognized",IF(YEAR(A23)<>Settings!$C$4,"Not in "&Settings!$C$4,IF(C23="","Category missing",IF(H23="",IF(COUNTIF(Categories!$A$6:$A$65,C23)>0,"Category has no type","Category not in list"),IF(D23="","Amount missing",IF(NOT(ISNUMBER(D23)),"Amount is not a number",IF(F23="","",IF(ISNA(MATCH(F23,Lists!$G$2:$G$25,0)),"Goal / fund not in list",IF(H23="Income","Fund tag ignored on income","")))))))))))
A24: 46029 | B24: Music streaming | C24: Subscriptions | D24: 10.99 | E24: Credit card | H24: =IF(C24="","",IFERROR(INDEX(Categories!$B$6:$B$65,MATCH(C24,Categories!$A$6:$A$65,0))&"","")) | I24: =IF(AND(A24="",C24="",D24=""),"",IF(A24="","Date missing",IF(NOT(ISNUMBER(A24)),"Date not recognized",IF(YEAR(A24)<>Settings!$C$4,"Not in "&Settings!$C$4,IF(C24="","Category missing",IF(H24="",IF(COUNTIF(Categories!$A$6:$A$65,C24)>0,"Category has no type","Category not in list"),IF(D24="","Amount missing",IF(NOT(ISNUMBER(D24)),"Amount is not a number",IF(F24="","",IF(ISNA(MATCH(F24,Lists!$G$2:$G$25,0)),"Goal / fund not in list",IF(H24="Income","Fund tag ignored on income","")))))))))))
A25: 46029 | B25: Takeout | C25: Dining out | D25: 23.84 | E25: Credit card | H25: =IF(C25="","",IFERROR(INDEX(Categories!$B$6:$B$65,MATCH(C25,Categories!$A$6:$A$65,0))&"","")) | I25: =IF(AND(A25="",C25="",D25=""),"",IF(A25="","Date missing",IF(NOT(ISNUMBER(A25)),"Date not recognized",IF(YEAR(A25)<>Settings!$C$4,"Not in "&Settings!$C$4,IF(C25="","Category missing",IF(H25="",IF(COUNTIF(Categories!$A$6:$A$65,C25)>0,"Category has no type","Category not in list"),IF(D25="","Amount missing",IF(NOT(ISNUMBER(D25)),"Amount is not a number",IF(F25="","",IF(ISNA(MATCH(F25,Lists!$G$2:$G$25,0)),"Goal / fund not in list",IF(H25="Income","Fund tag ignored on income","")))))))))))
A26: 46031 | B26: Pet food | C26: Pets | D26: 46.29 | E26: Debit card | H26: =IF(C26="","",IFERROR(INDEX(Categories!$B$6:$B$65,MATCH(C26,Categories!$A$6:$A$65,0))&"","")) | I26: =IF(AND(A26="",C26="",D26=""),"",IF(A26="","Date missing",IF(NOT(ISNUMBER(A26)),"Date not recognized",IF(YEAR(A26)<>Settings!$C$4,"Not in "&Settings!$C$4,IF(C26="","Category missing",IF(H26="",IF(COUNTIF(Categories!$A$6:$A$65,C26)>0,"Category has no type","Category not in list"),IF(D26="","Amount missing",IF(NOT(ISNUMBER(D26)),"Amount is not a number",IF(F26="","",IF(ISNA(MATCH(F26,Lists!$G$2:$G$25,0)),"Goal / fund not in list",IF(H26="Income","Fund tag ignored on income","")))))))))))
A27: 46032 | B27: Car loan payment | C27: Car payment | D27: 389 | E27: Checking | H27: =IF(C27="","",IFERROR(INDEX(Categories!$B$6:$B$65,MATCH(C27,Categories!$A$6:$A$65,0))&"","")) | I27: =IF(AND(A27="",C27="",D27=""),"",IF(A27="","Date missing",IF(NOT(ISNUMBER(A27)),"Date not recognized",IF(YEAR(A27)<>Settings!$C$4,"Not in "&Settings!$C$4,IF(C27="","Category missing",IF(H27="",IF(COUNTIF(Categories!$A$6:$A$65,C27)>0,"Category has no type","Category not in list"),IF(D27="","Amount missing",IF(NOT(ISNUMBER(D27)),"Amount is not a number",IF(F27="","",IF(ISNA(MATCH(F27,Lists!$G$2:$G$25,0)),"Goal / fund not in list",IF(H27="Income","Fund tag ignored on income","")))))))))))
A28: 46032 | B28: Warehouse store | C28: Groceries | D28: 183.97 | E28: Debit card | H28: =IF(C28="","",IFERROR(INDEX(Categories!$B$6:$B$65,MATCH(C28,Categories!$A$6:$A$65,0))&"","")) | I28: =IF(AND(A28="",C28="",D28=""),"",IF(A28="","Date missing",IF(NOT(ISNUMBER(A28)),"Date not recognized",IF(YEAR(A28)<>Settings!$C$4,"Not in "&Settings!$C$4,IF(C28="","Category missing",IF(H28="",IF(COUNTIF(Categories!$A$6:$A$65,C28)>0,"Category has no type","Category not in list"),IF(D28="","Amount missing",IF(NOT(ISNUMBER(D28)),"Amount is not a number",IF(F28="","",IF(ISNA(MATCH(F28,Lists!$G$2:$G$25,0)),"Goal / fund not in list",IF(H28="Income","Fund tag ignored on income","")))))))))))
A29: 46034 | B29: Internet | C29: Internet & Phone | D29: 65 | E29: Checking | H29: =IF(C29="","",IFERROR(INDEX(Categories!$B$6:$B$65,MATCH(C29,Categories!$A$6:$A$65,0))&"","")) | I29: =IF(AND(A29="",C29="",D29=""),"",IF(A29="","Date missing",IF(NOT(ISNUMBER(A29)),"Date not recognized",IF(YEAR(A29)<>Settings!$C$4,"Not in "&Settings!$C$4,IF(C29="","Category missing",IF(H29="",IF(COUNTIF(Categories!$A$6:$A$65,C29)>0,"Category has no type","Category not in list"),IF(D29="","Amount missing",IF(NOT(ISNUMBER(D29)),"Amount is not a number",IF(F29="","",IF(ISNA(MATCH(F29,Lists!$G$2:$G$25,0)),"Goal / fund not in list",IF(H29="Income","Fund tag ignored on income","")))))))))))
... A62: 46055 | B62: Gym membership | C62: Subscriptions | D62: 45 | E62: Checking | H62: =IF(C62="","",IFERROR(INDEX(Categories!$B$6:$B$65,MATCH(C62,Categories!$A$6:$A$65,0))&"","")) | I62: =IF(AND(A62="",C62="",D62=""),"",IF(A62="","Date missing",IF(NOT(ISNUMBER(A62)),"Date not recognized",IF(YEAR(A62)<>Settings!$C$4,"Not in "&Settings!$C$4,IF(C62="","Category missing",IF(H62="",IF(COUNTIF(Categories!$A$6:$A$65,C62)>0,"Category has no type","Category not in list"),IF(D62="","Amount missing",IF(NOT(ISNUMBER(D62)),"Amount is not a number",IF(F62="","",IF(ISNA(MATCH(F62,Lists!$G$2:$G$25,0)),"Goal / fund not in list",IF(H62="Income","Fund tag ignored on income","")))))))))))
A63: 46055 | B63: Transfer to emergency fund | C63: Emergency fund | D63: 300 | E63: Savings | F63: Emergency fund | H63: =IF(C63="","",IFERROR(INDEX(Categories!$B$6:$B$65,MATCH(C63,Categories!$A$6:$A$65,0))&"","")) | I63: =IF(AND(A63="",C63="",D63=""),"",IF(A63="","Date missing",IF(NOT(ISNUMBER(A63)),"Date not recognized",IF(YEAR(A63)<>Settings!$C$4,"Not in "&Settings!$C$4,IF(C63="","Category missing",IF(H63="",IF(COUNTIF(Categories!$A$6:$A$65,C63)>0,"Category has no type","Category not in list"),IF(D63="","Amount missing",IF(NOT(ISNUMBER(D63)),"Amount is not a number",IF(F63="","",IF(ISNA(MATCH(F63,Lists!$G$2:$G$25,0)),"Goal / fund not in list",IF(H63="Income","Fund tag ignored on income","")))))))))))
A64: 46055 | B64: Transfer: house fund | C64: Savings goals | D64: 300 | E64: Savings | F64: House down payment | H64: =IF(C64="","",IFERROR(INDEX(Categories!$B$6:$B$65,MATCH(C64,Categories!$A$6:$A$65,0))&"","")) | I64: =IF(AND(A64="",C64="",D64=""),"",IF(A64="","Date missing",IF(NOT(ISNUMBER(A64)),"Date not recognized",IF(YEAR(A64)<>Settings!$C$4,"Not in "&Settings!$C$4,IF(C64="","Category missing",IF(H64="",IF(COUNTIF(Categories!$A$6:$A$65,C64)>0,"Category has no type","Category not in list"),IF(D64="","Amount missing",IF(NOT(ISNUMBER(D64)),"Amount is not a number",IF(F64="","",IF(ISNA(MATCH(F64,Lists!$G$2:$G$25,0)),"Goal / fund not in list",IF(H64="Income","Fund tag ignored on income","")))))))))))
A65: 46055 | B65: Transfer: laptop | C65: Savings goals | D65: 100 | E65: Savings | F65: New laptop | H65: =IF(C65="","",IFERROR(INDEX(Categories!$B$6:$B$65,MATCH(C65,Categories!$A$6:$A$65,0))&"","")) | I65: =IF(AND(A65="",C65="",D65=""),"",IF(A65="","Date missing",IF(NOT(ISNUMBER(A65)),"Date not recognized",IF(YEAR(A65)<>Settings!$C$4,"Not in "&Settings!$C$4,IF(C65="","Category missing",IF(H65="",IF(COUNTIF(Categories!$A$6:$A$65,C65)>0,"Category has no type","Category not in list"),IF(D65="","Amount missing",IF(NOT(ISNUMBER(D65)),"Amount is not a number",IF(F65="","",IF(ISNA(MATCH(F65,Lists!$G$2:$G$25,0)),"Goal / fund not in list",IF(H65="Income","Fund tag ignored on income","")))))))))))
A66: 46055 | B66: Set aside: car maintenance | C66: Sinking funds | D66: 60 | E66: Savings | F66: Car maintenance | H66: =IF(C66="","",IFERROR(INDEX(Categories!$B$6:$B$65,MATCH(C66,Categories!$A$6:$A$65,0))&"","")) | I66: =IF(AND(A66="",C66="",D66=""),"",IF(A66="","Date missing",IF(NOT(ISNUMBER(A66)),"Date not recognized",IF(YEAR(A66)<>Settings!$C$4,"Not in "&Settings!$C$4,IF(C66="","Category missing",IF(H66="",IF(COUNTIF(Categories!$A$6:$A$65,C66)>0,"Category has no type","Category not in list"),IF(D66="","Amount missing",IF(NOT(ISNUMBER(D66)),"Amount is not a number",IF(F66="","",IF(ISNA(MATCH(F66,Lists!$G$2:$G$25,0)),"Goal / fund not in list",IF(H66="Income","Fund tag ignored on income","")))))))))))
A67: 46055 | B67: Set aside: holiday gifts | C67: Sinking funds | D67: 50 | E67: Savings | F67: Holiday gifts | H67: =IF(C67="","",IFERROR(INDEX(Categories!$B$6:$B$65,MATCH(C67,Categories!$A$6:$A$65,0))&"","")) | I67: =IF(AND(A67="",C67="",D67=""),"",IF(A67="","Date missing",IF(NOT(ISNUMBER(A67)),"Date not recognized",IF(YEAR(A67)<>Settings!$C$4,"Not in "&Settings!$C$4,IF(C67="","Category missing",IF(H67="",IF(COUNTIF(Categories!$A$6:$A$65,C67)>0,"Category has no type","Category not in list"),IF(D67="","Amount missing",IF(NOT(ISNUMBER(D67)),"Amount is not a number",IF(F67="","",IF(ISNA(MATCH(F67,Lists!$G$2:$G$25,0)),"Goal / fund not in list",IF(H67="Income","Fund tag ignored on income","")))))))))))
A68: 46055 | B68: Set aside: summer vacation | C68: Sinking funds | D68: 150 | E68: Savings | F68: Summer vacation | H68: =IF(C68="","",IFERROR(INDEX(Categories!$B$6:$B$65,MATCH(C68,Categories!$A$6:$A$65,0))&"","")) | I68: =IF(AND(A68="",C68="",D68=""),"",IF(A68="","Date missing",IF(NOT(ISNUMBER(A68)),"Date not recognized",IF(YEAR(A68)<>Settings!$C$4,"Not in "&Settings!$C$4,IF(C68="","Category missing",IF(H68="",IF(COUNTIF(Categories!$A$6:$A$65,C68)>0,"Category has no type","Category not in list"),IF(D68="","Amount missing",IF(NOT(ISNUMBER(D68)),"Amount is not a number",IF(F68="","",IF(ISNA(MATCH(F68,Lists!$G$2:$G$25,0)),"Goal / fund not in list",IF(H68="Income","Fund tag ignored on income","")))))))))))
A69: 46055 | B69: Set aside: home repairs | C69: Sinking funds | D69: 40 | E69: Savings | F69: Home repairs | H69: =IF(C69="","",IFERROR(INDEX(Categories!$B$6:$B$65,MATCH(C69,Categories!$A$6:$A$65,0))&"","")) | I69: =IF(AND(A69="",C69="",D69=""),"",IF(A69="","Date missing",IF(NOT(ISNUMBER(A69)),"Date not recognized",IF(YEAR(A69)<>Settings!$C$4,"Not in "&Settings!$C$4,IF(C69="","Category missing",IF(H69="",IF(COUNTIF(Categories!$A$6:$A$65,C69)>0,"Category has no type","Category not in list"),IF(D69="","Amount missing",IF(NOT(ISNUMBER(D69)),"Amount is not a number",IF(F69="","",IF(ISNA(MATCH(F69,Lists!$G$2:$G$25,0)),"Goal / fund not in list",IF(H69="Income","Fund tag ignored on income","")))))))))))
A70: 46056 | B70: Video streaming | C70: Subscriptions | D70: 15.49 | E70: Credit card | H70: =IF(C70="","",IFERROR(INDEX(Categories!$B$6:$B$65,MATCH(C70,Categories!$A$6:$A$65,0))&"","")) | I70: =IF(AND(A70="",C70="",D70=""),"",IF(A70="","Date missing",IF(NOT(ISNUMBER(A70)),"Date not recognized",IF(YEAR(A70)<>Settings!$C$4,"Not in "&Settings!$C$4,IF(C70="","Category missing",IF(H70="",IF(COUNTIF(Categories!$A$6:$A$65,C70)>0,"Category has no type","Category not in list"),IF(D70="","Amount missing",IF(NOT(ISNUMBER(D70)),"Amount is not a number",IF(F70="","",IF(ISNA(MATCH(F70,Lists!$G$2:$G$25,0)),"Goal / fund not in list",IF(H70="Income","Fund tag ignored on income","")))))))))))
A71: 46056 | B71: Farmers market | C71: Groceries | D71: 167.42 | E71: Debit card | H71: =IF(C71="","",IFERROR(INDEX(Categories!$B$6:$B$65,MATCH(C71,Categories!$A$6:$A$65,0))&"","")) | I71: =IF(AND(A71="",C71="",D71=""),"",IF(A71="","Date missing",IF(NOT(ISNUMBER(A71)),"Date not recognized",IF(YEAR(A71)<>Settings!$C$4,"Not in "&Settings!$C$4,IF(C71="","Category missing",IF(H71="",IF(COUNTIF(Categories!$A$6:$A$65,C71)>0,"Category has no type","Category not in list"),IF(D71="","Amount missing",IF(NOT(ISNUMBER(D71)),"Amount is not a number",IF(F71="","",IF(ISNA(MATCH(F71,Lists!$G$2:$G$25,0)),"Goal / fund not in list",IF(H71="Income","Fund tag ignored on income","")))))))))))
A72: 46056 | B72: Movie tickets | C72: Entertainment | D72: 32.76 | E72: Credit card | H72: =IF(C72="","",IFERROR(INDEX(Categories!$B$6:$B$65,MATCH(C72,Categories!$A$6:$A$65,0))&"","")) | I72: =IF(AND(A72="",C72="",D72=""),"",IF(A72="","Date missing",IF(NOT(ISNUMBER(A72)),"Date not recognized",IF(YEAR(A72)<>Settings!$C$4,"Not in "&Settings!$C$4,IF(C72="","Category missing",IF(H72="",IF(COUNTIF(Categories!$A$6:$A$65,C72)>0,"Category has no type","Category not in list"),IF(D72="","Amount missing",IF(NOT(ISNUMBER(D72)),"Amount is not a number",IF(F72="","",IF(ISNA(MATCH(F72,Lists!$G$2:$G$25,0)),"Goal / fund not in list",IF(H72="Income","Fund tag ignored on income","")))))))))))
A73: 46056 | B73: Retirement contribution | C73: Retirement & investing | D73: 600 | E73: Checking | H73: =IF(C73="","",IFERROR(INDEX(Categories!$B$6:$B$65,MATCH(C73,Categories!$A$6:$A$65,0))&"","")) | I73: =IF(AND(A73="",C73="",D73=""),"",IF(A73="","Date missing",IF(NOT(ISNUMBER(A73)),"Date not recognized",IF(YEAR(A73)<>Settings!$C$4,"Not in "&Settings!$C$4,IF(C73="","Category missing",IF(H73="",IF(COUNTIF(Categories!$A$6:$A$65,C73)>0,"Category has no type","Category not in list"),IF(D73="","Amount missing",IF(NOT(ISNUMBER(D73)),"Amount is not a number",IF(F73="","",IF(ISNA(MATCH(F73,Lists!$G$2:$G$25,0)),"Goal / fund not in list",IF(H73="Income","Fund tag ignored on income","")))))))))))
A74: 46057 | B74: Gas station | C74: Transport / Gas | D74: 52.97 | E74: Credit card | H74: =IF(C74="","",IFERROR(INDEX(Categories!$B$6:$B$65,MATCH(C74,Categories!$A$6:$A$65,0))&"","")) | I74: =IF(AND(A74="",C74="",D74=""),"",IF(A74="","Date missing",IF(NOT(ISNUMBER(A74)),"Date not recognized",IF(YEAR(A74)<>Settings!$C$4,"Not in "&Settings!$C$4,IF(C74="","Category missing",IF(H74="",IF(COUNTIF(Categories!$A$6:$A$65,C74)>0,"Category has no type","Category not in list"),IF(D74="","Amount missing",IF(NOT(ISNUMBER(D74)),"Amount is not a number",IF(F74="","",IF(ISNA(MATCH(F74,Lists!$G$2:$G$25,0)),"Goal / fund not in list",IF(H74="Income","Fund tag ignored on income","")))))))))))
A75: 46057 | B75: Jeans | C75: Clothing | D75: 96.43 | E75: Credit card | H75: =IF(C75="","",IFERROR(INDEX(Categories!$B$6:$B$65,MATCH(C75,Categories!$A$6:$A$65,0))&"","")) | I75: =IF(AND(A75="",C75="",D75=""),"",IF(A75="","Date missing",IF(NOT(ISNUMBER(A75)),"Date not recognized",IF(YEAR(A75)<>Settings!$C$4,"Not in "&Settings!$C$4,IF(C75="","Category missing",IF(H75="",IF(COUNTIF(Categories!$A$6:$A$65,C75)>0,"Category has no type","Category not in list"),IF(D75="","Amount missing",IF(NOT(ISNUMBER(D75)),"Amount is not a number",IF(F75="","",IF(ISNA(MATCH(F75,Lists!$G$2:$G$25,0)),"Goal / fund not in list",IF(H75="Income","Fund tag ignored on income","")))))))))))
A76: 46058 | B76: Car insurance | C76: Insurance | D76: 128 | E76: Checking | H76: =IF(C76="","",IFERROR(INDEX(Categories!$B$6:$B$65,MATCH(C76,Categories!$A$6:$A$65,0))&"","")) | I76: =IF(AND(A76="",C76="",D76=""),"",IF(A76="","Date missing",IF(NOT(ISNUMBER(A76)),"Date not recognized",IF(YEAR(A76)<>Settings!$C$4,"Not in "&Settings!$C$4,IF(C76="","Category missing",IF(H76="",IF(COUNTIF(Categories!$A$6:$A$65,C76)>0,"Category has no type","Category not in list"),IF(D76="","Amount missing",IF(NOT(ISNUMBER(D76)),"Amount is not a number",IF(F76="","",IF(ISNA(MATCH(F76,Lists!$G$2:$G$25,0)),"Goal / fund not in list",IF(H76="Income","Fund tag ignored on income","")))))))))))
A77: 46058 | B77: Renters insurance | C77: Insurance | D77: 18 | E77: Checking | H77: =IF(C77="","",IFERROR(INDEX(Categories!$B$6:$B$65,MATCH(C77,Categories!$A$6:$A$65,0))&"","")) | I77: =IF(AND(A77="",C77="",D77=""),"",IF(A77="","Date missing",IF(NOT(ISNUMBER(A77)),"Date not recognized",IF(YEAR(A77)<>Settings!$C$4,"Not in "&Settings!$C$4,IF(C77="","Category missing",IF(H77="",IF(COUNTIF(Categories!$A$6:$A$65,C77)>0,"Category has no type","Category not in list"),IF(D77="","Amount missing",IF(NOT(ISNUMBER(D77)),"Amount is not a number",IF(F77="","",IF(ISNA(MATCH(F77,Lists!$G$2:$G$25,0)),"Goal / fund not in list",IF(H77="Income","Fund tag ignored on income","")))))))))))
A78: 46058 | B78: Dinner out | C78: Dining out | D78: 61.04 | E78: Credit card | H78: =IF(C78="","",IFERROR(INDEX(Categories!$B$6:$B$65,MATCH(C78,Categories!$A$6:$A$65,0))&"","")) | I78: =IF(AND(A78="",C78="",D78=""),"",IF(A78="","Date missing",IF(NOT(ISNUMBER(A78)),"Date not recognized",IF(YEAR(A78)<>Settings!$C$4,"Not in "&Settings!$C$4,IF(C78="","Category missing",IF(H78="",IF(COUNTIF(Categories!$A$6:$A$65,C78)>0,"Category has no type","Category not in list"),IF(D78="","Amount missing",IF(NOT(ISNUMBER(D78)),"Amount is not a number",IF(F78="","",IF(ISNA(MATCH(F78,Lists!$G$2:$G$25,0)),"Goal / fund not in list",IF(H78="Income","Fund tag ignored on income","")))))))))))
A79: 46060 | B79: Music streaming | C79: Subscriptions | D79: 10.99 | E79: Credit card | H79: =IF(C79="","",IFERROR(INDEX(Categories!$B$6:$B$65,MATCH(C79,Categories!$A$6:$A$65,0))&"","")) | I79: =IF(AND(A79="",C79="",D79=""),"",IF(A79="","Date missing",IF(NOT(ISNUMBER(A79)),"Date not recognized",IF(YEAR(A79)<>Settings!$C$4,"Not in "&Settings!$C$4,IF(C79="","Category missing",IF(H79="",IF(COUNTIF(Categories!$A$6:$A$65,C79)>0,"Category has no type","Category not in list"),IF(D79="","Amount missing",IF(NOT(ISNUMBER(D79)),"Amount is not a number",IF(F79="","",IF(ISNA(MATCH(F79,Lists!$G$2:$G$25,0)),"Goal / fund not in list",IF(H79="Income","Fund tag ignored on income","")))))))))))
A80: 46062 | B80: Weekend tutoring | C80: Side income | D80: 340.53 | E80: Checking | H80: =IF(C80="","",IFERROR(INDEX(Categories!$B$6:$B$65,MATCH(C80,Categories!$A$6:$A$65,0))&"","")) | I80: =IF(AND(A80="",C80="",D80=""),"",IF(A80="","Date missing",IF(NOT(ISNUMBER(A80)),"Date not recognized",IF(YEAR(A80)<>Settings!$C$4,"Not in "&Settings!$C$4,IF(C80="","Category missing",IF(H80="",IF(COUNTIF(Categories!$A$6:$A$65,C80)>0,"Category has no type","Category not in list"),IF(D80="","Amount missing",IF(NOT(ISNUMBER(D80)),"Amount is not a number",IF(F80="","",IF(ISNA(MATCH(F80,Lists!$G$2:$G$25,0)),"Goal / fund not in list",IF(H80="Income","Fund tag ignored on income","")))))))))))
A81: 46062 | B81: Kitchen items | C81: Home & repairs | D81: 29.92 | E81: Debit card | H81: =IF(C81="","",IFERROR(INDEX(Categories!$B$6:$B$65,MATCH(C81,Categories!$A$6:$A$65,0))&"","")) | I81: =IF(AND(A81="",C81="",D81=""),"",IF(A81="","Date missing",IF(NOT(ISNUMBER(A81)),"Date not recognized",IF(YEAR(A81)<>Settings!$C$4,"Not in "&Settings!$C$4,IF(C81="","Category missing",IF(H81="",IF(COUNTIF(Categories!$A$6:$A$65,C81)>0,"Category has no type","Category not in list"),IF(D81="","Amount missing",IF(NOT(ISNUMBER(D81)),"Amount is not a number",IF(F81="","",IF(ISNA(MATCH(F81,Lists!$G$2:$G$25,0)),"Goal / fund not in list",IF(H81="Income","Fund tag ignored on income","")))))))))))
... A120: 46083 | B120: Haircut | C120: Personal care | D120: 32.52 | E120: Debit card | H120: =IF(C120="","",IFERROR(INDEX(Categories!$B$6:$B$65,MATCH(C120,Categories!$A$6:$A$65,0))&"","")) | I120: =IF(AND(A120="",C120="",D120=""),"",IF(A120="","Date missing",IF(NOT(ISNUMBER(A120)),"Date not recognized",IF(YEAR(A120)<>Settings!$C$4,"Not in "&Settings!$C$4,IF(C120="","Category missing",IF(H120="",IF(COUNTIF(Categories!$A$6:$A$65,C120)>0,"Category has no type","Category not in list"),IF(D120="","Amount missing",IF(NOT(ISNUMBER(D120)),"Amount is not a number",IF(F120="","",IF(ISNA(MATCH(F120,Lists!$G$2:$G$25,0)),"Goal / fund not in list",IF(H120="Income","Fund tag ignored on income","")))))))))))
A121: 46083 | B121: Transfer to emergency fund | C121: Emergency fund | D121: 300 | E121: Savings | F121: Emergency fund | H121: =IF(C121="","",IFERROR(INDEX(Categories!$B$6:$B$65,MATCH(C121,Categories!$A$6:$A$65,0))&"","")) | I121: =IF(AND(A121="",C121="",D121=""),"",IF(A121="","Date missing",IF(NOT(ISNUMBER(A121)),"Date not recognized",IF(YEAR(A121)<>Settings!$C$4,"Not in "&Settings!$C$4,IF(C121="","Category missing",IF(H121="",IF(COUNTIF(Categories!$A$6:$A$65,C121)>0,"Category has no type","Category not in list"),IF(D121="","Amount missing",IF(NOT(ISNUMBER(D121)),"Amount is not a number",IF(F121="","",IF(ISNA(MATCH(F121,Lists!$G$2:$G$25,0)),"Goal / fund not in list",IF(H121="Income","Fund tag ignored on income","")))))))))))
A122: 46083 | B122: Transfer: house fund | C122: Savings goals | D122: 300 | E122: Savings | F122: House down payment | H122: =IF(C122="","",IFERROR(INDEX(Categories!$B$6:$B$65,MATCH(C122,Categories!$A$6:$A$65,0))&"","")) | I122: =IF(AND(A122="",C122="",D122=""),"",IF(A122="","Date missing",IF(NOT(ISNUMBER(A122)),"Date not recognized",IF(YEAR(A122)<>Settings!$C$4,"Not in "&Settings!$C$4,IF(C122="","Category missing",IF(H122="",IF(COUNTIF(Categories!$A$6:$A$65,C122)>0,"Category has no type","Category not in list"),IF(D122="","Amount missing",IF(NOT(ISNUMBER(D122)),"Amount is not a number",IF(F122="","",IF(ISNA(MATCH(F122,Lists!$G$2:$G$25,0)),"Goal / fund not in list",IF(H122="Income","Fund tag ignored on income","")))))))))))
A123: 46083 | B123: Transfer: laptop | C123: Savings goals | D123: 100 | E123: Savings | F123: New laptop | H123: =IF(C123="","",IFERROR(INDEX(Categories!$B$6:$B$65,MATCH(C123,Categories!$A$6:$A$65,0))&"","")) | I123: =IF(AND(A123="",C123="",D123=""),"",IF(A123="","Date missing",IF(NOT(ISNUMBER(A123)),"Date not recognized",IF(YEAR(A123)<>Settings!$C$4,"Not in "&Settings!$C$4,IF(C123="","Category missing",IF(H123="",IF(COUNTIF(Categories!$A$6:$A$65,C123)>0,"Category has no type","Category not in list"),IF(D123="","Amount missing",IF(NOT(ISNUMBER(D123)),"Amount is not a number",IF(F123="","",IF(ISNA(MATCH(F123,Lists!$G$2:$G$25,0)),"Goal / fund not in list",IF(H123="Income","Fund tag ignored on income","")))))))))))
A124: 46083 | B124: Set aside: car maintenance | C124: Sinking funds | D124: 60 | E124: Savings | F124: Car maintenance | H124: =IF(C124="","",IFERROR(INDEX(Categories!$B$6:$B$65,MATCH(C124,Categories!$A$6:$A$65,0))&"","")) | I124: =IF(AND(A124="",C124="",D124=""),"",IF(A124="","Date missing",IF(NOT(ISNUMBER(A124)),"Date not recognized",IF(YEAR(A124)<>Settings!$C$4,"Not in "&Settings!$C$4,IF(C124="","Category missing",IF(H124="",IF(COUNTIF(Categories!$A$6:$A$65,C124)>0,"Category has no type","Category not in list"),IF(D124="","Amount missing",IF(NOT(ISNUMBER(D124)),"Amount is not a number",IF(F124="","",IF(ISNA(MATCH(F124,Lists!$G$2:$G$25,0)),"Goal / fund not in list",IF(H124="Income","Fund tag ignored on income","")))))))))))
A125: 46083 | B125: Set aside: holiday gifts | C125: Sinking funds | D125: 50 | E125: Savings | F125: Holiday gifts | H125: =IF(C125="","",IFERROR(INDEX(Categories!$B$6:$B$65,MATCH(C125,Categories!$A$6:$A$65,0))&"","")) | I125: =IF(AND(A125="",C125="",D125=""),"",IF(A125="","Date missing",IF(NOT(ISNUMBER(A125)),"Date not recognized",IF(YEAR(A125)<>Settings!$C$4,"Not in "&Settings!$C$4,IF(C125="","Category missing",IF(H125="",IF(COUNTIF(Categories!$A$6:$A$65,C125)>0,"Category has no type","Category not in list"),IF(D125="","Amount missing",IF(NOT(ISNUMBER(D125)),"Amount is not a number",IF(F125="","",IF(ISNA(MATCH(F125,Lists!$G$2:$G$25,0)),"Goal / fund not in list",IF(H125="Income","Fund tag ignored on income","")))))))))))
A126: 46083 | B126: Set aside: summer vacation | C126: Sinking funds | D126: 150 | E126: Savings | F126: Summer vacation | H126: =IF(C126="","",IFERROR(INDEX(Categories!$B$6:$B$65,MATCH(C126,Categories!$A$6:$A$65,0))&"","")) | I126: =IF(AND(A126="",C126="",D126=""),"",IF(A126="","Date missing",IF(NOT(ISNUMBER(A126)),"Date not recognized",IF(YEAR(A126)<>Settings!$C$4,"Not in "&Settings!$C$4,IF(C126="","Category missing",IF(H126="",IF(COUNTIF(Categories!$A$6:$A$65,C126)>0,"Category has no type","Category not in list"),IF(D126="","Amount missing",IF(NOT(ISNUMBER(D126)),"Amount is not a number",IF(F126="","",IF(ISNA(MATCH(F126,Lists!$G$2:$G$25,0)),"Goal / fund not in list",IF(H126="Income","Fund tag ignored on income","")))))))))))
A127: 46083 | B127: Set aside: home repairs | C127: Sinking funds | D127: 40 | E127: Savings | F127: Home repairs | H127: =IF(C127="","",IFERROR(INDEX(Categories!$B$6:$B$65,MATCH(C127,Categories!$A$6:$A$65,0))&"","")) | I127: =IF(AND(A127="",C127="",D127=""),"",IF(A127="","Date missing",IF(NOT(ISNUMBER(A127)),"Date not recognized",IF(YEAR(A127)<>Settings!$C$4,"Not in "&Settings!$C$4,IF(C127="","Category missing",IF(H127="",IF(COUNTIF(Categories!$A$6:$A$65,C127)>0,"Category has no type","Category not in list"),IF(D127="","Amount missing",IF(NOT(ISNUMBER(D127)),"Amount is not a number",IF(F127="","",IF(ISNA(MATCH(F127,Lists!$G$2:$G$25,0)),"Goal / fund not in list",IF(H127="Income","Fund tag ignored on income","")))))))))))
A128: 46084 | B128: Video streaming | C128: Subscriptions | D128: 15.49 | E128: Credit card | H128: =IF(C128="","",IFERROR(INDEX(Categories!$B$6:$B$65,MATCH(C128,Categories!$A$6:$A$65,0))&"","")) | I128: =IF(AND(A128="",C128="",D128=""),"",IF(A128="","Date missing",IF(NOT(ISNUMBER(A128)),"Date not recognized",IF(YEAR(A128)<>Settings!$C$4,"Not in "&Settings!$C$4,IF(C128="","Category missing",IF(H128="",IF(COUNTIF(Categories!$A$6:$A$65,C128)>0,"Category has no type","Category not in list"),IF(D128="","Amount missing",IF(NOT(ISNUMBER(D128)),"Amount is not a number",IF(F128="","",IF(ISNA(MATCH(F128,Lists!$G$2:$G$25,0)),"Goal / fund not in list",IF(H128="Income","Fund tag ignored on income","")))))))))))
A129: 46084 | B129: Supermarket | C129: Groceries | D129: 183.97 | E129: Debit card | H129: =IF(C129="","",IFERROR(INDEX(Categories!$B$6:$B$65,MATCH(C129,Categories!$A$6:$A$65,0))&"","")) | I129: =IF(AND(A129="",C129="",D129=""),"",IF(A129="","Date missing",IF(NOT(ISNUMBER(A129)),"Date not recognized",IF(YEAR(A129)<>Settings!$C$4,"Not in "&Settings!$C$4,IF(C129="","Category missing",IF(H129="",IF(COUNTIF(Categories!$A$6:$A$65,C129)>0,"Category has no type","Category not in list"),IF(D129="","Amount missing",IF(NOT(ISNUMBER(D129)),"Amount is not a number",IF(F129="","",IF(ISNA(MATCH(F129,Lists!$G$2:$G$25,0)),"Goal / fund not in list",IF(H129="Income","Fund tag ignored on income","")))))))))))
A130: 46084 | B130: Retirement contribution | C130: Retirement & investing | D130: 600 | E130: Checking | H130: =IF(C130="","",IFERROR(INDEX(Categories!$B$6:$B$65,MATCH(C130,Categories!$A$6:$A$65,0))&"","")) | I130: =IF(AND(A130="",C130="",D130=""),"",IF(A130="","Date missing",IF(NOT(ISNUMBER(A130)),"Date not recognized",IF(YEAR(A130)<>Settings!$C$4,"Not in "&Settings!$C$4,IF(C130="","Category missing",IF(H130="",IF(COUNTIF(Categories!$A$6:$A$65,C130)>0,"Category has no type","Category not in list"),IF(D130="","Amount missing",IF(NOT(ISNUMBER(D130)),"Amount is not a number",IF(F130="","",IF(ISNA(MATCH(F130,Lists!$G$2:$G$25,0)),"Goal / fund not in list",IF(H130="Income","Fund tag ignored on income","")))))))))))
A131: 46085 | B131: Gas station | C131: Transport / Gas | D131: 52.49 | E131: Credit card | H131: =IF(C131="","",IFERROR(INDEX(Categories!$B$6:$B$65,MATCH(C131,Categories!$A$6:$A$65,0))&"","")) | I131: =IF(AND(A131="",C131="",D131=""),"",IF(A131="","Date missing",IF(NOT(ISNUMBER(A131)),"Date not recognized",IF(YEAR(A131)<>Settings!$C$4,"Not in "&Settings!$C$4,IF(C131="","Category missing",IF(H131="",IF(COUNTIF(Categories!$A$6:$A$65,C131)>0,"Category has no type","Category not in list"),IF(D131="","Amount missing",IF(NOT(ISNUMBER(D131)),"Amount is not a number",IF(F131="","",IF(ISNA(MATCH(F131,Lists!$G$2:$G$25,0)),"Goal / fund not in list",IF(H131="Income","Fund tag ignored on income","")))))))))))
A132: 46086 | B132: Car insurance | C132: Insurance | D132: 128 | E132: Checking | H132: =IF(C132="","",IFERROR(INDEX(Categories!$B$6:$B$65,MATCH(C132,Categories!$A$6:$A$65,0))&"","")) | I132: =IF(AND(A132="",C132="",D132=""),"",IF(A132="","Date missing",IF(NOT(ISNUMBER(A132)),"Date not recognized",IF(YEAR(A132)<>Settings!$C$4,"Not in "&Settings!$C$4,IF(C132="","Category missing",IF(H132="",IF(COUNTIF(Categories!$A$6:$A$65,C132)>0,"Category has no type","Category not in list"),IF(D132="","Amount missing",IF(NOT(ISNUMBER(D132)),"Amount is not a number",IF(F132="","",IF(ISNA(MATCH(F132,Lists!$G$2:$G$25,0)),"Goal / fund not in list",IF(H132="Income","Fund tag ignored on income","")))))))))))
A133: 46086 | B133: Renters insurance | C133: Insurance | D133: 18 | E133: Checking | H133: =IF(C133="","",IFERROR(INDEX(Categories!$B$6:$B$65,MATCH(C133,Categories!$A$6:$A$65,0))&"","")) | I133: =IF(AND(A133="",C133="",D133=""),"",IF(A133="","Date missing",IF(NOT(ISNUMBER(A133)),"Date not recognized",IF(YEAR(A133)<>Settings!$C$4,"Not in "&Settings!$C$4,IF(C133="","Category missing",IF(H133="",IF(COUNTIF(Categories!$A$6:$A$65,C133)>0,"Category has no type","Category not in list"),IF(D133="","Amount missing",IF(NOT(ISNUMBER(D133)),"Amount is not a number",IF(F133="","",IF(ISNA(MATCH(F133,Lists!$G$2:$G$25,0)),"Goal / fund not in list",IF(H133="Income","Fund tag ignored on income","")))))))))))
A134: 46087 | B134: Bank fee | C134: Misc | D134: 13.24 | E134: Cash | H134: =IF(C134="","",IFERROR(INDEX(Categories!$B$6:$B$65,MATCH(C134,Categories!$A$6:$A$65,0))&"","")) | I134: =IF(AND(A134="",C134="",D134=""),"",IF(A134="","Date missing",IF(NOT(ISNUMBER(A134)),"Date not recognized",IF(YEAR(A134)<>Settings!$C$4,"Not in "&Settings!$C$4,IF(C134="","Category missing",IF(H134="",IF(COUNTIF(Categories!$A$6:$A$65,C134)>0,"Category has no type","Category not in list"),IF(D134="","Amount missing",IF(NOT(ISNUMBER(D134)),"Amount is not a number",IF(F134="","",IF(ISNA(MATCH(F134,Lists!$G$2:$G$25,0)),"Goal / fund not in list",IF(H134="Income","Fund tag ignored on income","")))))))))))
A135: 46088 | B135: Music streaming | C135: Subscriptions | D135: 10.99 | E135: Credit card | H135: =IF(C135="","",IFERROR(INDEX(Categories!$B$6:$B$65,MATCH(C135,Categories!$A$6:$A$65,0))&"","")) | I135: =IF(AND(A135="",C135="",D135=""),"",IF(A135="","Date missing",IF(NOT(ISNUMBER(A135)),"Date not recognized",IF(YEAR(A135)<>Settings!$C$4,"Not in "&Settings!$C$4,IF(C135="","Category missing",IF(H135="",IF(COUNTIF(Categories!$A$6:$A$65,C135)>0,"Category has no type","Category not in list"),IF(D135="","Amount missing",IF(NOT(ISNUMBER(D135)),"Amount is not a number",IF(F135="","",IF(ISNA(MATCH(F135,Lists!$G$2:$G$25,0)),"Goal / fund not in list",IF(H135="Income","Fund tag ignored on income","")))))))))))
A136: 46090 | B136: Cloud storage (yearly) | C136: Subscriptions | D136: 29.99 | E136: Credit card | H136: =IF(C136="","",IFERROR(INDEX(Categories!$B$6:$B$65,MATCH(C136,Categories!$A$6:$A$65,0))&"","")) | I136: =IF(AND(A136="",C136="",D136=""),"",IF(A136="","Date missing",IF(NOT(ISNUMBER(A136)),"Date not recognized",IF(YEAR(A136)<>Settings!$C$4,"Not in "&Settings!$C$4,IF(C136="","Category missing",IF(H136="",IF(COUNTIF(Categories!$A$6:$A$65,C136)>0,"Category has no type","Category not in list"),IF(D136="","Amount missing",IF(NOT(ISNUMBER(D136)),"Amount is not a number",IF(F136="","",IF(ISNA(MATCH(F136,Lists!$G$2:$G$25,0)),"Goal / fund not in list",IF(H136="Income","Fund tag ignored on income","")))))))))))
A137: 46090 | B137: Pet food | C137: Pets | D137: 46.25 | E137: Debit card | H137: =IF(C137="","",IFERROR(INDEX(Categories!$B$6:$B$65,MATCH(C137,Categories!$A$6:$A$65,0))&"","")) | I137: =IF(AND(A137="",C137="",D137=""),"",IF(A137="","Date missing",IF(NOT(ISNUMBER(A137)),"Date not recognized",IF(YEAR(A137)<>Settings!$C$4,"Not in "&Settings!$C$4,IF(C137="","Category missing",IF(H137="",IF(COUNTIF(Categories!$A$6:$A$65,C137)>0,"Category has no type","Category not in list"),IF(D137="","Amount missing",IF(NOT(ISNUMBER(D137)),"Amount is not a number",IF(F137="","",IF(ISNA(MATCH(F137,Lists!$G$2:$G$25,0)),"Goal / fund not in list",IF(H137="Income","Fund tag ignored on income","")))))))))))
A138: 46091 | B138: Car loan payment | C138: Car payment | D138: 389 | E138: Checking | H138: =IF(C138="","",IFERROR(INDEX(Categories!$B$6:$B$65,MATCH(C138,Categories!$A$6:$A$65,0))&"","")) | I138: =IF(AND(A138="",C138="",D138=""),"",IF(A138="","Date missing",IF(NOT(ISNUMBER(A138)),"Date not recognized",IF(YEAR(A138)<>Settings!$C$4,"Not in "&Settings!$C$4,IF(C138="","Category missing",IF(H138="",IF(COUNTIF(Categories!$A$6:$A$65,C138)>0,"Category has no type","Category not in list"),IF(D138="","Amount missing",IF(NOT(ISNUMBER(D138)),"Amount is not a number",IF(F138="","",IF(ISNA(MATCH(F138,Lists!$G$2:$G$25,0)),"Goal / fund not in list",IF(H138="Income","Fund tag ignored on income","")))))))))))
A139: 46091 | B139: Farmers market | C139: Groceries | D139: 163.57 | E139: Debit card | H139: =IF(C139="","",IFERROR(INDEX(Categories!$B$6:$B$65,MATCH(C139,Categories!$A$6:$A$65,0))&"","")) | I139: =IF(AND(A139="",C139="",D139=""),"",IF(A139="","Date missing",IF(NOT(ISNUMBER(A139)),"Date not recognized",IF(YEAR(A139)<>Settings!$C$4,"Not in "&Settings!$C$4,IF(C139="","Category missing",IF(H139="",IF(COUNTIF(Categories!$A$6:$A$65,C139)>0,"Category has no type","Category not in list"),IF(D139="","Amount missing",IF(NOT(ISNUMBER(D139)),"Amount is not a number",IF(F139="","",IF(ISNA(MATCH(F139,Lists!$G$2:$G$25,0)),"Goal / fund not in list",IF(H139="Income","Fund tag ignored on income","")))))))))))
... A157: 46101 | B157: Medical bill installment | C157: Debt payments | D157: 40 | E157: Checking | H157: =IF(C157="","",IFERROR(INDEX(Categories!$B$6:$B$65,MATCH(C157,Categories!$A$6:$A$65,0))&"","")) | I157: =IF(AND(A157="",C157="",D157=""),"",IF(A157="","Date missing",IF(NOT(ISNUMBER(A157)),"Date not recognized",IF(YEAR(A157)<>Settings!$C$4,"Not in "&Settings!$C$4,IF(C157="","Category missing",IF(H157="",IF(COUNTIF(Categories!$A$6:$A$65,C157)>0,"Category has no type","Category not in list"),IF(D157="","Amount missing",IF(NOT(ISNUMBER(D157)),"Amount is not a number",IF(F157="","",IF(ISNA(MATCH(F157,Lists!$G$2:$G$25,0)),"Goal / fund not in list",IF(H157="Income","Fund tag ignored on income","")))))))))))
A158: 46102 | B158: Oil change | C158: Transport / Gas | D158: 69.99 | E158: Debit card | F158: Car maintenance | H158: =IF(C158="","",IFERROR(INDEX(Categories!$B$6:$B$65,MATCH(C158,Categories!$A$6:$A$65,0))&"","")) | I158: =IF(AND(A158="",C158="",D158=""),"",IF(A158="","Date missing",IF(NOT(ISNUMBER(A158)),"Date not recognized",IF(YEAR(A158)<>Settings!$C$4,"Not in "&Settings!$C$4,IF(C158="","Category missing",IF(H158="",IF(COUNTIF(Categories!$A$6:$A$65,C158)>0,"Category has no type","Category not in list"),IF(D158="","Amount missing",IF(NOT(ISNUMBER(D158)),"Amount is not a number",IF(F158="","",IF(ISNA(MATCH(F158,Lists!$G$2:$G$25,0)),"Goal / fund not in list",IF(H158="Income","Fund tag ignored on income","")))))))))))
A159: 46102 | B159: Personal loan payment | C159: Debt payments | D159: 210 | E159: Checking | H159: =IF(C159="","",IFERROR(INDEX(Categories!$B$6:$B$65,MATCH(C159,Categories!$A$6:$A$65,0))&"","")) | I159: =IF(AND(A159="",C159="",D159=""),"",IF(A159="","Date missing",IF(NOT(ISNUMBER(A159)),"Date not recognized",IF(YEAR(A159)<>Settings!$C$4,"Not in "&Settings!$C$4,IF(C159="","Category missing",IF(H159="",IF(COUNTIF(Categories!$A$6:$A$65,C159)>0,"Category has no type","Category not in list"),IF(D159="","Amount missing",IF(NOT(ISNUMBER(D159)),"Amount is not a number",IF(F159="","",IF(ISNA(MATCH(F159,Lists!$G$2:$G$25,0)),"Goal / fund not in list",IF(H159="Income","Fund tag ignored on income","")))))))))))
A160: 46103 | B160: Freelance logo | C160: Side income | D160: 233.02 | E160: Checking | H160: =IF(C160="","",IFERROR(INDEX(Categories!$B$6:$B$65,MATCH(C160,Categories!$A$6:$A$65,0))&"","")) | I160: =IF(AND(A160="",C160="",D160=""),"",IF(A160="","Date missing",IF(NOT(ISNUMBER(A160)),"Date not recognized",IF(YEAR(A160)<>Settings!$C$4,"Not in "&Settings!$C$4,IF(C160="","Category missing",IF(H160="",IF(COUNTIF(Categories!$A$6:$A$65,C160)>0,"Category has no type","Category not in list"),IF(D160="","Amount missing",IF(NOT(ISNUMBER(D160)),"Amount is not a number",IF(F160="","",IF(ISNA(MATCH(F160,Lists!$G$2:$G$25,0)),"Goal / fund not in list",IF(H160="Income","Fund tag ignored on income","")))))))))))
A161: 46103 | B161: Water & trash | C161: Utilities | D161: 54.3 | E161: Checking | H161: =IF(C161="","",IFERROR(INDEX(Categories!$B$6:$B$65,MATCH(C161,Categories!$A$6:$A$65,0))&"","")) | I161: =IF(AND(A161="",C161="",D161=""),"",IF(A161="","Date missing",IF(NOT(ISNUMBER(A161)),"Date not recognized",IF(YEAR(A161)<>Settings!$C$4,"Not in "&Settings!$C$4,IF(C161="","Category missing",IF(H161="",IF(COUNTIF(Categories!$A$6:$A$65,C161)>0,"Category has no type","Category not in list"),IF(D161="","Amount missing",IF(NOT(ISNUMBER(D161)),"Amount is not a number",IF(F161="","",IF(ISNA(MATCH(F161,Lists!$G$2:$G$25,0)),"Goal / fund not in list",IF(H161="Income","Fund tag ignored on income","")))))))))))
A162: 46105 | B162: Supermarket | C162: Groceries | D162: 153.82 | E162: Debit card | H162: =IF(C162="","",IFERROR(INDEX(Categories!$B$6:$B$65,MATCH(C162,Categories!$A$6:$A$65,0))&"","")) | I162: =IF(AND(A162="",C162="",D162=""),"",IF(A162="","Date missing",IF(NOT(ISNUMBER(A162)),"Date not recognized",IF(YEAR(A162)<>Settings!$C$4,"Not in "&Settings!$C$4,IF(C162="","Category missing",IF(H162="",IF(COUNTIF(Categories!$A$6:$A$65,C162)>0,"Category has no type","Category not in list"),IF(D162="","Amount missing",IF(NOT(ISNUMBER(D162)),"Amount is not a number",IF(F162="","",IF(ISNA(MATCH(F162,Lists!$G$2:$G$25,0)),"Goal / fund not in list",IF(H162="Income","Fund tag ignored on income","")))))))))))
A163: 46106 | B163: Pizza night | C163: Dining out | D163: 10.51 | E163: Credit card | H163: =IF(C163="","",IFERROR(INDEX(Categories!$B$6:$B$65,MATCH(C163,Categories!$A$6:$A$65,0))&"","")) | I163: =IF(AND(A163="",C163="",D163=""),"",IF(A163="","Date missing",IF(NOT(ISNUMBER(A163)),"Date not recognized",IF(YEAR(A163)<>Settings!$C$4,"Not in "&Settings!$C$4,IF(C163="","Category missing",IF(H163="",IF(COUNTIF(Categories!$A$6:$A$65,C163)>0,"Category has no type","Category not in list"),IF(D163="","Amount missing",IF(NOT(ISNUMBER(D163)),"Amount is not a number",IF(F163="","",IF(ISNA(MATCH(F163,Lists!$G$2:$G$25,0)),"Goal / fund not in list",IF(H163="Income","Fund tag ignored on income","")))))))))))
A164: 46106 | B164: Student loan payment | C164: Debt payments | D164: 165 | E164: Checking | H164: =IF(C164="","",IFERROR(INDEX(Categories!$B$6:$B$65,MATCH(C164,Categories!$A$6:$A$65,0))&"","")) | I164: =IF(AND(A164="",C164="",D164=""),"",IF(A164="","Date missing",IF(NOT(ISNUMBER(A164)),"Date not recognized",IF(YEAR(A164)<>Settings!$C$4,"Not in "&Settings!$C$4,IF(C164="","Category missing",IF(H164="",IF(COUNTIF(Categories!$A$6:$A$65,C164)>0,"Category has no type","Category not in list"),IF(D164="","Amount missing",IF(NOT(ISNUMBER(D164)),"Amount is not a number",IF(F164="","",IF(ISNA(MATCH(F164,Lists!$G$2:$G$25,0)),"Goal / fund not in list",IF(H164="Income","Fund tag ignored on income","")))))))))))
A165: 46108 | B165: Gas station | C165: Transport / Gas | D165: 45.8 | E165: Credit card | H165: =IF(C165="","",IFERROR(INDEX(Categories!$B$6:$B$65,MATCH(C165,Categories!$A$6:$A$65,0))&"","")) | I165: =IF(AND(A165="",C165="",D165=""),"",IF(A165="","Date missing",IF(NOT(ISNUMBER(A165)),"Date not recognized",IF(YEAR(A165)<>Settings!$C$4,"Not in "&Settings!$C$4,IF(C165="","Category missing",IF(H165="",IF(COUNTIF(Categories!$A$6:$A$65,C165)>0,"Category has no type","Category not in list"),IF(D165="","Amount missing",IF(NOT(ISNUMBER(D165)),"Amount is not a number",IF(F165="","",IF(ISNA(MATCH(F165,Lists!$G$2:$G$25,0)),"Goal / fund not in list",IF(H165="Income","Fund tag ignored on income","")))))))))))
A166: 46109 | B166: Sam paycheck | C166: Paycheck 2 | D166: 2950 | E166: Checking | H166: =IF(C166="","",IFERROR(INDEX(Categories!$B$6:$B$65,MATCH(C166,Categories!$A$6:$A$65,0))&"","")) | I166: =IF(AND(A166="",C166="",D166=""),"",IF(A166="","Date missing",IF(NOT(ISNUMBER(A166)),"Date not recognized",IF(YEAR(A166)<>Settings!$C$4,"Not in "&Settings!$C$4,IF(C166="","Category missing",IF(H166="",IF(COUNTIF(Categories!$A$6:$A$65,C166)>0,"Category has no type","Category not in list"),IF(D166="","Amount missing",IF(NOT(ISNUMBER(D166)),"Amount is not a number",IF(F166="","",IF(ISNA(MATCH(F166,Lists!$G$2:$G$25,0)),"Goal / fund not in list",IF(H166="Income","Fund tag ignored on income","")))))))))))
A167: 46109 | B167: Light bulbs | C167: Home & repairs | D167: 48.03 | E167: Debit card | H167: =IF(C167="","",IFERROR(INDEX(Categories!$B$6:$B$65,MATCH(C167,Categories!$A$6:$A$65,0))&"","")) | I167: =IF(AND(A167="",C167="",D167=""),"",IF(A167="","Date missing",IF(NOT(ISNUMBER(A167)),"Date not recognized",IF(YEAR(A167)<>Settings!$C$4,"Not in "&Settings!$C$4,IF(C167="","Category missing",IF(H167="",IF(COUNTIF(Categories!$A$6:$A$65,C167)>0,"Category has no type","Category not in list"),IF(D167="","Amount missing",IF(NOT(ISNUMBER(D167)),"Amount is not a number",IF(F167="","",IF(ISNA(MATCH(F167,Lists!$G$2:$G$25,0)),"Goal / fund not in list",IF(H167="Income","Fund tag ignored on income","")))))))))))
A168: 46109 | B168: Post office | C168: Misc | D168: 19.5 | E168: Cash | H168: =IF(C168="","",IFERROR(INDEX(Categories!$B$6:$B$65,MATCH(C168,Categories!$A$6:$A$65,0))&"","")) | I168: =IF(AND(A168="",C168="",D168=""),"",IF(A168="","Date missing",IF(NOT(ISNUMBER(A168)),"Date not recognized",IF(YEAR(A168)<>Settings!$C$4,"Not in "&Settings!$C$4,IF(C168="","Category missing",IF(H168="",IF(COUNTIF(Categories!$A$6:$A$65,C168)>0,"Category has no type","Category not in list"),IF(D168="","Amount missing",IF(NOT(ISNUMBER(D168)),"Amount is not a number",IF(F168="","",IF(ISNA(MATCH(F168,Lists!$G$2:$G$25,0)),"Goal / fund not in list",IF(H168="Income","Fund tag ignored on income","")))))))))))
A169: 46111 | B169: Supermarket | C169: Groceries | D169: 154.81 | E169: Debit card | H169: =IF(C169="","",IFERROR(INDEX(Categories!$B$6:$B$65,MATCH(C169,Categories!$A$6:$A$65,0))&"","")) | I169: =IF(AND(A169="",C169="",D169=""),"",IF(A169="","Date missing",IF(NOT(ISNUMBER(A169)),"Date not recognized",IF(YEAR(A169)<>Settings!$C$4,"Not in "&Settings!$C$4,IF(C169="","Category missing",IF(H169="",IF(COUNTIF(Categories!$A$6:$A$65,C169)>0,"Category has no type","Category not in list"),IF(D169="","Amount missing",IF(NOT(ISNUMBER(D169)),"Amount is not a number",IF(F169="","",IF(ISNA(MATCH(F169,Lists!$G$2:$G$25,0)),"Goal / fund not in list",IF(H169="Income","Fund tag ignored on income","")))))))))))
A170: 46113 | B170: Alex paycheck | C170: Paycheck 1 | D170: 2100 | E170: Checking | H170: =IF(C170="","",IFERROR(INDEX(Categories!$B$6:$B$65,MATCH(C170,Categories!$A$6:$A$65,0))&"","")) | I170: =IF(AND(A170="",C170="",D170=""),"",IF(A170="","Date missing",IF(NOT(ISNUMBER(A170)),"Date not recognized",IF(YEAR(A170)<>Settings!$C$4,"Not in "&Settings!$C$4,IF(C170="","Category missing",IF(H170="",IF(COUNTIF(Categories!$A$6:$A$65,C170)>0,"Category has no type","Category not in list"),IF(D170="","Amount missing",IF(NOT(ISNUMBER(D170)),"Amount is not a number",IF(F170="","",IF(ISNA(MATCH(F170,Lists!$G$2:$G$25,0)),"Goal / fund not in list",IF(H170="Income","Fund tag ignored on income","")))))))))))
... A174: 46114 | B174: Gym membership | C174: Subscriptions | D174: 45 | E174: Checking | H174: =IF(C174="","",IFERROR(INDEX(Categories!$B$6:$B$65,MATCH(C174,Categories!$A$6:$A$65,0))&"","")) | I174: =IF(AND(A174="",C174="",D174=""),"",IF(A174="","Date missing",IF(NOT(ISNUMBER(A174)),"Date not recognized",IF(YEAR(A174)<>Settings!$C$4,"Not in "&Settings!$C$4,IF(C174="","Category missing",IF(H174="",IF(COUNTIF(Categories!$A$6:$A$65,C174)>0,"Category has no type","Category not in list"),IF(D174="","Amount missing",IF(NOT(ISNUMBER(D174)),"Amount is not a number",IF(F174="","",IF(ISNA(MATCH(F174,Lists!$G$2:$G$25,0)),"Goal / fund not in list",IF(H174="Income","Fund tag ignored on income","")))))))))))
A175: 46114 | B175: Transfer to emergency fund | C175: Emergency fund | D175: 300 | E175: Savings | F175: Emergency fund | H175: =IF(C175="","",IFERROR(INDEX(Categories!$B$6:$B$65,MATCH(C175,Categories!$A$6:$A$65,0))&"","")) | I175: =IF(AND(A175="",C175="",D175=""),"",IF(A175="","Date missing",IF(NOT(ISNUMBER(A175)),"Date not recognized",IF(YEAR(A175)<>Settings!$C$4,"Not in "&Settings!$C$4,IF(C175="","Category missing",IF(H175="",IF(COUNTIF(Categories!$A$6:$A$65,C175)>0,"Category has no type","Category not in list"),IF(D175="","Amount missing",IF(NOT(ISNUMBER(D175)),"Amount is not a number",IF(F175="","",IF(ISNA(MATCH(F175,Lists!$G$2:$G$25,0)),"Goal / fund not in list",IF(H175="Income","Fund tag ignored on income","")))))))))))
A176: 46114 | B176: Transfer: house fund | C176: Savings goals | D176: 300 | E176: Savings | F176: House down payment | H176: =IF(C176="","",IFERROR(INDEX(Categories!$B$6:$B$65,MATCH(C176,Categories!$A$6:$A$65,0))&"","")) | I176: =IF(AND(A176="",C176="",D176=""),"",IF(A176="","Date missing",IF(NOT(ISNUMBER(A176)),"Date not recognized",IF(YEAR(A176)<>Settings!$C$4,"Not in "&Settings!$C$4,IF(C176="","Category missing",IF(H176="",IF(COUNTIF(Categories!$A$6:$A$65,C176)>0,"Category has no type","Category not in list"),IF(D176="","Amount missing",IF(NOT(ISNUMBER(D176)),"Amount is not a number",IF(F176="","",IF(ISNA(MATCH(F176,Lists!$G$2:$G$25,0)),"Goal / fund not in list",IF(H176="Income","Fund tag ignored on income","")))))))))))
A177: 46114 | B177: Transfer: laptop | C177: Savings goals | D177: 100 | E177: Savings | F177: New laptop | H177: =IF(C177="","",IFERROR(INDEX(Categories!$B$6:$B$65,MATCH(C177,Categories!$A$6:$A$65,0))&"","")) | I177: =IF(AND(A177="",C177="",D177=""),"",IF(A177="","Date missing",IF(NOT(ISNUMBER(A177)),"Date not recognized",IF(YEAR(A177)<>Settings!$C$4,"Not in "&Settings!$C$4,IF(C177="","Category missing",IF(H177="",IF(COUNTIF(Categories!$A$6:$A$65,C177)>0,"Category has no type","Category not in list"),IF(D177="","Amount missing",IF(NOT(ISNUMBER(D177)),"Amount is not a number",IF(F177="","",IF(ISNA(MATCH(F177,Lists!$G$2:$G$25,0)),"Goal / fund not in list",IF(H177="Income","Fund tag ignored on income","")))))))))))
A178: 46114 | B178: Set aside: car maintenance | C178: Sinking funds | D178: 60 | E178: Savings | F178: Car maintenance | H178: =IF(C178="","",IFERROR(INDEX(Categories!$B$6:$B$65,MATCH(C178,Categories!$A$6:$A$65,0))&"","")) | I178: =IF(AND(A178="",C178="",D178=""),"",IF(A178="","Date missing",IF(NOT(ISNUMBER(A178)),"Date not recognized",IF(YEAR(A178)<>Settings!$C$4,"Not in "&Settings!$C$4,IF(C178="","Category missing",IF(H178="",IF(COUNTIF(Categories!$A$6:$A$65,C178)>0,"Category has no type","Category not in list"),IF(D178="","Amount missing",IF(NOT(ISNUMBER(D178)),"Amount is not a number",IF(F178="","",IF(ISNA(MATCH(F178,Lists!$G$2:$G$25,0)),"Goal / fund not in list",IF(H178="Income","Fund tag ignored on income","")))))))))))
A179: 46114 | B179: Set aside: holiday gifts | C179: Sinking funds | D179: 50 | E179: Savings | F179: Holiday gifts | H179: =IF(C179="","",IFERROR(INDEX(Categories!$B$6:$B$65,MATCH(C179,Categories!$A$6:$A$65,0))&"","")) | I179: =IF(AND(A179="",C179="",D179=""),"",IF(A179="","Date missing",IF(NOT(ISNUMBER(A179)),"Date not recognized",IF(YEAR(A179)<>Settings!$C$4,"Not in "&Settings!$C$4,IF(C179="","Category missing",IF(H179="",IF(COUNTIF(Categories!$A$6:$A$65,C179)>0,"Category has no type","Category not in list"),IF(D179="","Amount missing",IF(NOT(ISNUMBER(D179)),"Amount is not a number",IF(F179="","",IF(ISNA(MATCH(F179,Lists!$G$2:$G$25,0)),"Goal / fund not in list",IF(H179="Income","Fund tag ignored on income","")))))))))))
A180: 46114 | B180: Set aside: summer vacation | C180: Sinking funds | D180: 150 | E180: Savings | F180: Summer vacation | H180: =IF(C180="","",IFERROR(INDEX(Categories!$B$6:$B$65,MATCH(C180,Categories!$A$6:$A$65,0))&"","")) | I180: =IF(AND(A180="",C180="",D180=""),"",IF(A180="","Date missing",IF(NOT(ISNUMBER(A180)),"Date not recognized",IF(YEAR(A180)<>Settings!$C$4,"Not in "&Settings!$C$4,IF(C180="","Category missing",IF(H180="",IF(COUNTIF(Categories!$A$6:$A$65,C180)>0,"Category has no type","Category not in list"),IF(D180="","Amount missing",IF(NOT(ISNUMBER(D180)),"Amount is not a number",IF(F180="","",IF(ISNA(MATCH(F180,Lists!$G$2:$G$25,0)),"Goal / fund not in list",IF(H180="Income","Fund tag ignored on income","")))))))))))
A181: 46114 | B181: Set aside: home repairs | C181: Sinking funds | D181: 40 | E181: Savings | F181: Home repairs | H181: =IF(C181="","",IFERROR(INDEX(Categories!$B$6:$B$65,MATCH(C181,Categories!$A$6:$A$65,0))&"","")) | I181: =IF(AND(A181="",C181="",D181=""),"",IF(A181="","Date missing",IF(NOT(ISNUMBER(A181)),"Date not recognized",IF(YEAR(A181)<>Settings!$C$4,"Not in "&Settings!$C$4,IF(C181="","Category missing",IF(H181="",IF(COUNTIF(Categories!$A$6:$A$65,C181)>0,"Category has no type","Category not in list"),IF(D181="","Amount missing",IF(NOT(ISNUMBER(D181)),"Amount is not a number",IF(F181="","",IF(ISNA(MATCH(F181,Lists!$G$2:$G$25,0)),"Goal / fund not in list",IF(H181="Income","Fund tag ignored on income","")))))))))))
A182: 46115 | B182: Video streaming | C182: Subscriptions | D182: 15.49 | E182: Credit card | H182: =IF(C182="","",IFERROR(INDEX(Categories!$B$6:$B$65,MATCH(C182,Categories!$A$6:$A$65,0))&"","")) | I182: =IF(AND(A182="",C182="",D182=""),"",IF(A182="","Date missing",IF(NOT(ISNUMBER(A182)),"Date not recognized",IF(YEAR(A182)<>Settings!$C$4,"Not in "&Settings!$C$4,IF(C182="","Category missing",IF(H182="",IF(COUNTIF(Categories!$A$6:$A$65,C182)>0,"Category has no type","Category not in list"),IF(D182="","Amount missing",IF(NOT(ISNUMBER(D182)),"Amount is not a number",IF(F182="","",IF(ISNA(MATCH(F182,Lists!$G$2:$G$25,0)),"Goal / fund not in list",IF(H182="Income","Fund tag ignored on income","")))))))))))
A183: 46115 | B183: Warehouse store | C183: Groceries | D183: 147.29 | E183: Debit card | H183: =IF(C183="","",IFERROR(INDEX(Categories!$B$6:$B$65,MATCH(C183,Categories!$A$6:$A$65,0))&"","")) | I183: =IF(AND(A183="",C183="",D183=""),"",IF(A183="","Date missing",IF(NOT(ISNUMBER(A183)),"Date not recognized",IF(YEAR(A183)<>Settings!$C$4,"Not in "&Settings!$C$4,IF(C183="","Category missing",IF(H183="",IF(COUNTIF(Categories!$A$6:$A$65,C183)>0,"Category has no type","Category not in list"),IF(D183="","Amount missing",IF(NOT(ISNUMBER(D183)),"Amount is not a number",IF(F183="","",IF(ISNA(MATCH(F183,Lists!$G$2:$G$25,0)),"Goal / fund not in list",IF(H183="Income","Fund tag ignored on income","")))))))))))
A184: 46115 | B184: Charity donation | C184: Gifts | D184: 66.93 | E184: Credit card | H184: =IF(C184="","",IFERROR(INDEX(Categories!$B$6:$B$65,MATCH(C184,Categories!$A$6:$A$65,0))&"","")) | I184: =IF(AND(A184="",C184="",D184=""),"",IF(A184="","Date missing",IF(NOT(ISNUMBER(A184)),"Date not recognized",IF(YEAR(A184)<>Settings!$C$4,"Not in "&Settings!$C$4,IF(C184="","Category missing",IF(H184="",IF(COUNTIF(Categories!$A$6:$A$65,C184)>0,"Category has no type","Category not in list"),IF(D184="","Amount missing",IF(NOT(ISNUMBER(D184)),"Amount is not a number",IF(F184="","",IF(ISNA(MATCH(F184,Lists!$G$2:$G$25,0)),"Goal / fund not in list",IF(H184="Income","Fund tag ignored on income","")))))))))))
A185: 46115 | B185: Retirement contribution | C185: Retirement & investing | D185: 600 | E185: Checking | H185: =IF(C185="","",IFERROR(INDEX(Categories!$B$6:$B$65,MATCH(C185,Categories!$A$6:$A$65,0))&"","")) | I185: =IF(AND(A185="",C185="",D185=""),"",IF(A185="","Date missing",IF(NOT(ISNUMBER(A185)),"Date not recognized",IF(YEAR(A185)<>Settings!$C$4,"Not in "&Settings!$C$4,IF(C185="","Category missing",IF(H185="",IF(COUNTIF(Categories!$A$6:$A$65,C185)>0,"Category has no type","Category not in list"),IF(D185="","Amount missing",IF(NOT(ISNUMBER(D185)),"Amount is not a number",IF(F185="","",IF(ISNA(MATCH(F185,Lists!$G$2:$G$25,0)),"Goal / fund not in list",IF(H185="Income","Fund tag ignored on income","")))))))))))
A186: 46116 | B186: Gas station | C186: Transport / Gas | D186: 49.17 | E186: Credit card | H186: =IF(C186="","",IFERROR(INDEX(Categories!$B$6:$B$65,MATCH(C186,Categories!$A$6:$A$65,0))&"","")) | I186: =IF(AND(A186="",C186="",D186=""),"",IF(A186="","Date missing",IF(NOT(ISNUMBER(A186)),"Date not recognized",IF(YEAR(A186)<>Settings!$C$4,"Not in "&Settings!$C$4,IF(C186="","Category missing",IF(H186="",IF(COUNTIF(Categories!$A$6:$A$65,C186)>0,"Category has no type","Category not in list"),IF(D186="","Amount missing",IF(NOT(ISNUMBER(D186)),"Amount is not a number",IF(F186="","",IF(ISNA(MATCH(F186,Lists!$G$2:$G$25,0)),"Goal / fund not in list",IF(H186="Income","Fund tag ignored on income","")))))))))))
A187: 46116 | B187: Haircut | C187: Personal care | D187: 16.05 | E187: Debit card | H187: =IF(C187="","",IFERROR(INDEX(Categories!$B$6:$B$65,MATCH(C187,Categories!$A$6:$A$65,0))&"","")) | I187: =IF(AND(A187="",C187="",D187=""),"",IF(A187="","Date missing",IF(NOT(ISNUMBER(A187)),"Date not recognized",IF(YEAR(A187)<>Settings!$C$4,"Not in "&Settings!$C$4,IF(C187="","Category missing",IF(H187="",IF(COUNTIF(Categories!$A$6:$A$65,C187)>0,"Category has no type","Category not in list"),IF(D187="","Amount missing",IF(NOT(ISNUMBER(D187)),"Amount is not a number",IF(F187="","",IF(ISNA(MATCH(F187,Lists!$G$2:$G$25,0)),"Goal / fund not in list",IF(H187="Income","Fund tag ignored on income","")))))))))))
A188: 46116 | B188: Bowling | C188: Entertainment | D188: 26.42 | E188: Credit card | H188: =IF(C188="","",IFERROR(INDEX(Categories!$B$6:$B$65,MATCH(C188,Categories!$A$6:$A$65,0))&"","")) | I188: =IF(AND(A188="",C188="",D188=""),"",IF(A188="","Date missing",IF(NOT(ISNUMBER(A188)),"Date not recognized",IF(YEAR(A188)<>Settings!$C$4,"Not in "&Settings!$C$4,IF(C188="","Category missing",IF(H188="",IF(COUNTIF(Categories!$A$6:$A$65,C188)>0,"Category has no type","Category not in list"),IF(D188="","Amount missing",IF(NOT(ISNUMBER(D188)),"Amount is not a number",IF(F188="","",IF(ISNA(MATCH(F188,Lists!$G$2:$G$25,0)),"Goal / fund not in list",IF(H188="Income","Fund tag ignored on income","")))))))))))
A189: 46117 | B189: Car insurance | C189: Insurance | D189: 128 | E189: Checking | H189: =IF(C189="","",IFERROR(INDEX(Categories!$B$6:$B$65,MATCH(C189,Categories!$A$6:$A$65,0))&"","")) | I189: =IF(AND(A189="",C189="",D189=""),"",IF(A189="","Date missing",IF(NOT(ISNUMBER(A189)),"Date not recognized",IF(YEAR(A189)<>Settings!$C$4,"Not in "&Settings!$C$4,IF(C189="","Category missing",IF(H189="",IF(COUNTIF(Categories!$A$6:$A$65,C189)>0,"Category has no type","Category not in list"),IF(D189="","Amount missing",IF(NOT(ISNUMBER(D189)),"Amount is not a number",IF(F189="","",IF(ISNA(MATCH(F189,Lists!$G$2:$G$25,0)),"Goal / fund not in list",IF(H189="Income","Fund tag ignored on income","")))))))))))
A190: 46117 | B190: Renters insurance | C190: Insurance | D190: 18 | E190: Checking | H190: =IF(C190="","",IFERROR(INDEX(Categories!$B$6:$B$65,MATCH(C190,Categories!$A$6:$A$65,0))&"","")) | I190: =IF(AND(A190="",C190="",D190=""),"",IF(A190="","Date missing",IF(NOT(ISNUMBER(A190)),"Date not recognized",IF(YEAR(A190)<>Settings!$C$4,"Not in "&Settings!$C$4,IF(C190="","Category missing",IF(H190="",IF(COUNTIF(Categories!$A$6:$A$65,C190)>0,"Category has no type","Category not in list"),IF(D190="","Amount missing",IF(NOT(ISNUMBER(D190)),"Amount is not a number",IF(F190="","",IF(ISNA(MATCH(F190,Lists!$G$2:$G$25,0)),"Goal / fund not in list",IF(H190="Income","Fund tag ignored on income","")))))))))))
A191: 46119 | B191: Music streaming | C191: Subscriptions | D191: 10.99 | E191: Credit card | H191: =IF(C191="","",IFERROR(INDEX(Categories!$B$6:$B$65,MATCH(C191,Categories!$A$6:$A$65,0))&"","")) | I191: =IF(AND(A191="",C191="",D191=""),"",IF(A191="","Date missing",IF(NOT(ISNUMBER(A191)),"Date not recognized",IF(YEAR(A191)<>Settings!$C$4,"Not in "&Settings!$C$4,IF(C191="","Category missing",IF(H191="",IF(COUNTIF(Categories!$A$6:$A$65,C191)>0,"Category has no type","Category not in list"),IF(D191="","Amount missing",IF(NOT(ISNUMBER(D191)),"Amount is not a number",IF(F191="","",IF(ISNA(MATCH(F191,Lists!$G$2:$G$25,0)),"Goal / fund not in list",IF(H191="Income","Fund tag ignored on income","")))))))))))
...

Sheet Monthly Budget
A1: Monthly Budget
A2: Type a typical monthly amount in column C: the 12 months fill in by themselves. For a month that is different (annual bills, holidays), type over that month.
A3: To go back to the typical amount, copy a month that you did not change. The summary rows at the top are calculated.
D4: ="Planned by month"&Settings!$C$14
A5: Category | B5: Type | C5: ="Typical month"&Settings!$C$14 | D5: Jan | E5: Feb | F5: Mar | G5: Apr | H5: May | I5: Jun | J5: Jul | K5: Aug | L5: Sep | M5: Oct | N5: Nov | O5: Dec | P5: ="Year total"&Settings!$C$14
A6: Income | B6: Income | C6: =SUMIFS(C$14:C$73,$B$14:$B$73,"Income") | D6: =SUMIFS(D$14:D$73,$B$14:$B$73,"Income") | E6: =SUMIFS(E$14:E$73,$B$14:$B$73,"Income") | F6: =SUMIFS(F$14:F$73,$B$14:$B$73,"Income") | G6: =SUMIFS(G$14:G$73,$B$14:$B$73,"Income") | H6: =SUMIFS(H$14:H$73,$B$14:$B$73,"Income") | I6: =SUMIFS(I$14:I$73,$B$14:$B$73,"Income") | J6: =SUMIFS(J$14:J$73,$B$14:$B$73,"Income") | ... P6: =SUMIFS(P$14:P$73,$B$14:$B$73,"Income")
A7: Fixed bills | B7: Fixed bills | C7: =SUMIFS(C$14:C$73,$B$14:$B$73,"Fixed bills") | D7: =SUMIFS(D$14:D$73,$B$14:$B$73,"Fixed bills") | E7: =SUMIFS(E$14:E$73,$B$14:$B$73,"Fixed bills") | F7: =SUMIFS(F$14:F$73,$B$14:$B$73,"Fixed bills") | G7: =SUMIFS(G$14:G$73,$B$14:$B$73,"Fixed bills") | H7: =SUMIFS(H$14:H$73,$B$14:$B$73,"Fixed bills") | I7: =SUMIFS(I$14:I$73,$B$14:$B$73,"Fixed bills") | J7: =SUMIFS(J$14:J$73,$B$14:$B$73,"Fixed bills") | ... P7: =SUMIFS(P$14:P$73,$B$14:$B$73,"Fixed bills")
A8: Variable expenses | B8: Variable expenses | C8: =SUMIFS(C$14:C$73,$B$14:$B$73,"Variable expenses") | D8: =SUMIFS(D$14:D$73,$B$14:$B$73,"Variable expenses") | E8: =SUMIFS(E$14:E$73,$B$14:$B$73,"Variable expenses") | F8: =SUMIFS(F$14:F$73,$B$14:$B$73,"Variable expenses") | G8: =SUMIFS(G$14:G$73,$B$14:$B$73,"Variable expenses") | H8: =SUMIFS(H$14:H$73,$B$14:$B$73,"Variable expenses") | I8: =SUMIFS(I$14:I$73,$B$14:$B$73,"Variable expenses") | J8: =SUMIFS(J$14:J$73,$B$14:$B$73,"Variable expenses") | ... P8: =SUMIFS(P$14:P$73,$B$14:$B$73,"Variable expenses")
A9: Total expenses | B9: All expenses | C9: =C7+C8 | D9: =D7+D8 | E9: =E7+E8 | F9: =F7+F8 | G9: =G7+G8 | H9: =H7+H8 | I9: =I7+I8 | J9: =J7+J8 | ... P9: =P7+P8
A10: Savings & debt payments | B10: Savings & debt | C10: =SUMIFS(C$14:C$73,$B$14:$B$73,"Savings & debt") | D10: =SUMIFS(D$14:D$73,$B$14:$B$73,"Savings & debt") | E10: =SUMIFS(E$14:E$73,$B$14:$B$73,"Savings & debt") | F10: =SUMIFS(F$14:F$73,$B$14:$B$73,"Savings & debt") | G10: =SUMIFS(G$14:G$73,$B$14:$B$73,"Savings & debt") | H10: =SUMIFS(H$14:H$73,$B$14:$B$73,"Savings & debt") | I10: =SUMIFS(I$14:I$73,$B$14:$B$73,"Savings & debt") | J10: =SUMIFS(J$14:J$73,$B$14:$B$73,"Savings & debt") | ... P10: =SUMIFS(P$14:P$73,$B$14:$B$73,"Savings & debt")
A11: Paid from goals & funds | B11: Funds | J11: 1500 | L11: 500 | O11: 600 | P11: =SUM(D11:O11)
A12: Left to budget | B12: Result | C12: =C6-C9-C10+N(C11) | D12: =D6-D9-D10+N(D11) | E12: =E6-E9-E10+N(E11) | F12: =F6-F9-F10+N(F11) | G12: =G6-G9-G10+N(G11) | H12: =H6-H9-H10+N(H11) | I12: =I6-I9-I10+N(I11) | J12: =J6-J9-J10+N(J11) | ... P12: =P6-P9-P10+N(P11)
A13: Categories
A14: =IF(Categories!$A6="","",Categories!$A6) | B14: =IF(A14="","",Categories!$B6&"") | C14: 4200 | D14: =$C14 | E14: =$C14 | F14: =$C14 | G14: =$C14 | H14: =$C14 | I14: =$C14 | J14: =$C14 | K14: =$C14 | ... O14: =$C14 | P14: =SUM(D14:O14)
A15: =IF(Categories!$A7="","",Categories!$A7) | B15: =IF(A15="","",Categories!$B7&"") | C15: 2950 | D15: =$C15 | E15: =$C15 | F15: =$C15 | G15: =$C15 | H15: =$C15 | I15: =$C15 | J15: =$C15 | K15: =$C15 | ... O15: =$C15 | P15: =SUM(D15:O15)
A16: =IF(Categories!$A8="","",Categories!$A8) | B16: =IF(A16="","",Categories!$B8&"") | C16: 250 | D16: =$C16 | E16: =$C16 | F16: =$C16 | G16: =$C16 | H16: =$C16 | I16: =$C16 | J16: =$C16 | K16: =$C16 | ... O16: =$C16 | P16: =SUM(D16:O16)
A17: =IF(Categories!$A9="","",Categories!$A9) | B17: =IF(A17="","",Categories!$B9&"") | C17: 0 | D17: =$C17 | E17: =$C17 | F17: =$C17 | G17: 1200 | H17: =$C17 | I17: =$C17 | J17: =$C17 | K17: =$C17 | L17: =$C17 | M17: =$C17 | N17: =$C17 | O17: 300 | P17: =SUM(D17:O17)
A18: =IF(Categories!$A10="","",Categories!$A10) | B18: =IF(A18="","",Categories!$B10&"") | C18: 1850 | D18: =$C18 | E18: =$C18 | F18: =$C18 | G18: =$C18 | H18: =$C18 | I18: =$C18 | J18: =$C18 | K18: =$C18 | ... O18: =$C18 | P18: =SUM(D18:O18)
A19: =IF(Categories!$A11="","",Categories!$A11) | B19: =IF(A19="","",Categories!$B11&"") | C19: 200 | D19: 260 | E19: 250 | F19: =$C19 | G19: =$C19 | H19: =$C19 | I19: =$C19 | J19: 240 | K19: 245 | L19: =$C19 | M19: =$C19 | N19: =$C19 | O19: 260 | P19: =SUM(D19:O19)
A20: =IF(Categories!$A12="","",Categories!$A12) | B20: =IF(A20="","",Categories!$B12&"") | C20: 135 | D20: =$C20 | E20: =$C20 | F20: =$C20 | G20: =$C20 | H20: =$C20 | I20: =$C20 | J20: =$C20 | K20: =$C20 | ... O20: =$C20 | P20: =SUM(D20:O20)
A21: =IF(Categories!$A13="","",Categories!$A13) | B21: =IF(A21="","",Categories!$B13&"") | C21: 146 | D21: =$C21 | E21: =$C21 | F21: =$C21 | G21: =$C21 | H21: =$C21 | I21: =$C21 | J21: =$C21 | K21: =$C21 | ... O21: =$C21 | P21: =SUM(D21:O21)
A22: =IF(Categories!$A14="","",Categories!$A14) | B22: =IF(A22="","",Categories!$B14&"") | C22: 72 | D22: =$C22 | E22: =$C22 | F22: 102 | G22: =$C22 | H22: =$C22 | I22: =$C22 | J22: =$C22 | K22: =$C22 | L22: =$C22 | M22: =$C22 | N22: =$C22 | O22: =$C22 | P22: =SUM(D22:O22)
A23: =IF(Categories!$A15="","",Categories!$A15) | B23: =IF(A23="","",Categories!$B15&"") | C23: 389 | D23: =$C23 | E23: =$C23 | F23: =$C23 | G23: =$C23 | H23: =$C23 | I23: =$C23 | J23: =$C23 | K23: =$C23 | ... O23: =$C23 | P23: =SUM(D23:O23)
A24: =IF(Categories!$A16="","",Categories!$A16) | B24: =IF(A24="","",Categories!$B16&"") | C24: 720 | D24: =$C24 | E24: =$C24 | F24: =$C24 | G24: =$C24 | H24: =$C24 | I24: =$C24 | J24: =$C24 | K24: =$C24 | ... M24: =$C24 | N24: 760 | O24: 820 | P24: =SUM(D24:O24)
A25: =IF(Categories!$A17="","",Categories!$A17) | B25: =IF(A25="","",Categories!$B17&"") | C25: 240 | D25: =$C25 | E25: =$C25 | F25: =$C25 | G25: =$C25 | H25: =$C25 | I25: =$C25 | J25: =$C25 | K25: =$C25 | ... O25: =$C25 | P25: =SUM(D25:O25)
A26: =IF(Categories!$A18="","",Categories!$A18) | B26: =IF(A26="","",Categories!$B18&"") | C26: 200 | D26: =$C26 | E26: =$C26 | F26: =$C26 | G26: =$C26 | H26: =$C26 | I26: =$C26 | J26: =$C26 | K26: =$C26 | L26: 750 | M26: =$C26 | N26: =$C26 | O26: =$C26 | P26: =SUM(D26:O26)
A27: =IF(Categories!$A19="","",Categories!$A19) | B27: =IF(A27="","",Categories!$B19&"") | C27: 60 | D27: =$C27 | E27: =$C27 | F27: =$C27 | G27: =$C27 | H27: =$C27 | I27: =$C27 | J27: =$C27 | K27: =$C27 | ... O27: =$C27 | P27: =SUM(D27:O27)
A28: =IF(Categories!$A20="","",Categories!$A20) | B28: =IF(A28="","",Categories!$B20&"") | C28: 390 | D28: =$C28 | E28: =$C28 | F28: =$C28 | G28: =$C28 | H28: =$C28 | I28: =$C28 | J28: 500 | K28: 640 | L28: =$C28 | M28: =$C28 | N28: =$C28 | O28: =$C28 | P28: =SUM(D28:O28)
A29: =IF(Categories!$A21="","",Categories!$A21) | B29: =IF(A29="","",Categories!$B21&"") | C29: 45 | D29: =$C29 | E29: =$C29 | F29: =$C29 | G29: =$C29 | H29: =$C29 | I29: =$C29 | J29: =$C29 | K29: =$C29 | ... O29: =$C29 | P29: =SUM(D29:O29)
A30: =IF(Categories!$A22="","",Categories!$A22) | B30: =IF(A30="","",Categories!$B22&"") | C30: 80 | D30: =$C30 | E30: =$C30 | F30: =$C30 | G30: =$C30 | H30: =$C30 | I30: =$C30 | J30: =$C30 | K30: =$C30 | ... O30: =$C30 | P30: =SUM(D30:O30)
A31: =IF(Categories!$A23="","",Categories!$A23) | B31: =IF(A31="","",Categories!$B23&"") | C31: 40 | D31: =$C31 | E31: =$C31 | F31: =$C31 | G31: =$C31 | H31: =$C31 | I31: =$C31 | J31: =$C31 | K31: =$C31 | ... N31: =$C31 | O31: 650 | P31: =SUM(D31:O31)
A32: =IF(Categories!$A24="","",Categories!$A24) | B32: =IF(A32="","",Categories!$B24&"") | C32: 0 | D32: =$C32 | E32: =$C32 | F32: =$C32 | G32: =$C32 | H32: 200 | I32: =$C32 | J32: 1600 | K32: =$C32 | L32: =$C32 | M32: =$C32 | N32: =$C32 | O32: =$C32 | P32: =SUM(D32:O32)
A33: =IF(Categories!$A25="","",Categories!$A25) | B33: =IF(A33="","",Categories!$B25&"") | C33: 60 | D33: =$C33 | E33: =$C33 | F33: =$C33 | G33: =$C33 | H33: =$C33 | I33: =$C33 | J33: =$C33 | K33: =$C33 | ... O33: =$C33 | P33: =SUM(D33:O33)
A34: =IF(Categories!$A26="","",Categories!$A26) | B34: =IF(A34="","",Categories!$B26&"") | C34: 60 | D34: =$C34 | E34: =$C34 | F34: =$C34 | G34: =$C34 | H34: =$C34 | I34: =$C34 | J34: =$C34 | K34: =$C34 | ... O34: =$C34 | P34: =SUM(D34:O34)
A35: =IF(Categories!$A27="","",Categories!$A27) | B35: =IF(A35="","",Categories!$B27&"") | C35: 50 | D35: =$C35 | E35: =$C35 | F35: 210 | G35: =$C35 | H35: =$C35 | I35: =$C35 | J35: =$C35 | K35: =$C35 | L35: =$C35 | M35: =$C35 | N35: =$C35 | O35: =$C35 | P35: =SUM(D35:O35)
A36: =IF(Categories!$A28="","",Categories!$A28) | B36: =IF(A36="","",Categories!$B28&"") | C36: 40 | D36: =$C36 | E36: =$C36 | F36: =$C36 | G36: =$C36 | H36: =$C36 | I36: =$C36 | J36: =$C36 | K36: =$C36 | ... O36: =$C36 | P36: =SUM(D36:O36)
A37: =IF(Categories!$A29="","",Categories!$A29) | B37: =IF(A37="","",Categories!$B29&"") | C37: 300 | D37: =$C37 | E37: =$C37 | F37: =$C37 | G37: =$C37 | H37: =$C37 | I37: =$C37 | J37: =$C37 | K37: =$C37 | ... O37: =$C37 | P37: =SUM(D37:O37)
A38: =IF(Categories!$A30="","",Categories!$A30) | B38: =IF(A38="","",Categories!$B30&"") | C38: 400 | D38: =$C38 | E38: =$C38 | F38: =$C38 | G38: =$C38 | H38: =$C38 | I38: =$C38 | J38: =$C38 | K38: =$C38 | ... O38: =$C38 | P38: =SUM(D38:O38)
A39: =IF(Categories!$A31="","",Categories!$A31) | B39: =IF(A39="","",Categories!$B31&"") | C39: 300 | D39: =$C39 | E39: =$C39 | F39: =$C39 | G39: =$C39 | H39: =$C39 | I39: =$C39 | J39: =$C39 | K39: =$C39 | ... O39: =$C39 | P39: =SUM(D39:O39)
A40: =IF(Categories!$A32="","",Categories!$A32) | B40: =IF(A40="","",Categories!$B32&"") | C40: 600 | D40: =$C40 | E40: =$C40 | F40: =$C40 | G40: =$C40 | H40: =$C40 | I40: =$C40 | J40: =$C40 | K40: =$C40 | ... O40: =$C40 | P40: =SUM(D40:O40)
A41: =IF(Categories!$A33="","",Categories!$A33) | B41: =IF(A41="","",Categories!$B33&"") | C41: 675 | D41: =$C41 | E41: =$C41 | F41: =$C41 | G41: =$C41 | H41: =$C41 | I41: =$C41 | J41: =$C41 | K41: =$C41 | ... O41: =$C41 | P41: =SUM(D41:O41)
A42: =IF(Categories!$A34="","",Categories!$A34) | B42: =IF(A42="","",Categories!$B34&"") | D42: =$C42 | E42: =$C42 | F42: =$C42 | G42: =$C42 | H42: =$C42 | I42: =$C42 | J42: =$C42 | K42: =$C42 | ... O42: =$C42 | P42: =SUM(D42:O42)
A43: =IF(Categories!$A35="","",Categories!$A35) | B43: =IF(A43="","",Categories!$B35&"") | D43: =$C43 | E43: =$C43 | F43: =$C43 | G43: =$C43 | H43: =$C43 | I43: =$C43 | J43: =$C43 | K43: =$C43 | ... O43: =$C43 | P43: =SUM(D43:O43)
A44: =IF(Categories!$A36="","",Categories!$A36) | B44: =IF(A44="","",Categories!$B36&"") | D44: =$C44 | E44: =$C44 | F44: =$C44 | G44: =$C44 | H44: =$C44 | I44: =$C44 | J44: =$C44 | K44: =$C44 | ... O44: =$C44 | P44: =SUM(D44:O44)
A45: =IF(Categories!$A37="","",Categories!$A37) | B45: =IF(A45="","",Categories!$B37&"") | D45: =$C45 | E45: =$C45 | F45: =$C45 | G45: =$C45 | H45: =$C45 | I45: =$C45 | J45: =$C45 | K45: =$C45 | ... O45: =$C45 | P45: =SUM(D45:O45)
A46: =IF(Categories!$A38="","",Categories!$A38) | B46: =IF(A46="","",Categories!$B38&"") | D46: =$C46 | E46: =$C46 | F46: =$C46 | G46: =$C46 | H46: =$C46 | I46: =$C46 | J46: =$C46 | K46: =$C46 | ... O46: =$C46 | P46: =SUM(D46:O46)
A47: =IF(Categories!$A39="","",Categories!$A39) | B47: =IF(A47="","",Categories!$B39&"") | D47: =$C47 | E47: =$C47 | F47: =$C47 | G47: =$C47 | H47: =$C47 | I47: =$C47 | J47: =$C47 | K47: =$C47 | ... O47: =$C47 | P47: =SUM(D47:O47)
A48: =IF(Categories!$A40="","",Categories!$A40) | B48: =IF(A48="","",Categories!$B40&"") | D48: =$C48 | E48: =$C48 | F48: =$C48 | G48: =$C48 | H48: =$C48 | I48: =$C48 | J48: =$C48 | K48: =$C48 | ... O48: =$C48 | P48: =SUM(D48:O48)
A49: =IF(Categories!$A41="","",Categories!$A41) | B49: =IF(A49="","",Categories!$B41&"") | D49: =$C49 | E49: =$C49 | F49: =$C49 | G49: =$C49 | H49: =$C49 | I49: =$C49 | J49: =$C49 | K49: =$C49 | ... O49: =$C49 | P49: =SUM(D49:O49)
A50: =IF(Categories!$A42="","",Categories!$A42) | B50: =IF(A50="","",Categories!$B42&"") | D50: =$C50 | E50: =$C50 | F50: =$C50 | G50: =$C50 | H50: =$C50 | I50: =$C50 | J50: =$C50 | K50: =$C50 | ... O50: =$C50 | P50: =SUM(D50:O50)
A51: =IF(Categories!$A43="","",Categories!$A43) | B51: =IF(A51="","",Categories!$B43&"") | D51: =$C51 | E51: =$C51 | F51: =$C51 | G51: =$C51 | H51: =$C51 | I51: =$C51 | J51: =$C51 | K51: =$C51 | ... O51: =$C51 | P51: =SUM(D51:O51)
A52: =IF(Categories!$A44="","",Categories!$A44) | B52: =IF(A52="","",Categories!$B44&"") | D52: =$C52 | E52: =$C52 | F52: =$C52 | G52: =$C52 | H52: =$C52 | I52: =$C52 | J52: =$C52 | K52: =$C52 | ... O52: =$C52 | P52: =SUM(D52:O52)
A53: =IF(Categories!$A45="","",Categories!$A45) | B53: =IF(A53="","",Categories!$B45&"") | D53: =$C53 | E53: =$C53 | F53: =$C53 | G53: =$C53 | H53: =$C53 | I53: =$C53 | J53: =$C53 | K53: =$C53 | ... O53: =$C53 | P53: =SUM(D53:O53)
... A73: =IF(Categories!$A65="","",Categories!$A65) | B73: =IF(A73="","",Categories!$B65&"") | D73: =$C73 | E73: =$C73 | F73: =$C73 | G73: =$C73 | H73: =$C73 | I73: =$C73 | J73: =$C73 | K73: =$C73 | ... O73: =$C73 | P73: =SUM(D73:O73)
A75: Left to budget = income − expenses − savings & debt + paid from goals & funds. Below zero means you planned to spend more than you earn.

Sheet Monthly Summary
A1: Monthly Summary
A2: Actual amounts from Transactions compared with Monthly Budget. Difference = actual − planned: green is better than planned, red is worse.
A3: Month to review ▸ | B3: Auto | C3: ="Showing "&Settings!$C$13&" "&Settings!$C$4&". Auto = the latest month (today, or the as-of date in Settings)."
C4: =Settings!$C$13&" "&Settings!$C$4&Settings!$C$14 | H4: ="Year to date ("&IF(Settings!$C$12=1,"Jan","Jan–"&Settings!$C$15)&")"&Settings!$C$14 | L4: ="Actual by month"&Settings!$C$14 | X4: ="Full year"&Settings!$C$14
A5: Category | B5: Type | C5: Planned | D5: Actual | E5: Difference | F5: % of plan | H5: Planned | I5: Actual | J5: Difference | L5: Jan | M5: Feb | N5: Mar | O5: Apr | P5: May | Q5: Jun | R5: Jul | S5: Aug | T5: Sep | U5: Oct | V5: Nov | W5: Dec | X5: Actual | Y5: Planned | Z5: Difference | AA5: Rank key
A6: Income | B6: Income | C6: =SUMIFS(C$14:C$73,$B$14:$B$73,"Income") | D6: =SUMIFS(D$14:D$73,$B$14:$B$73,"Income") | E6: =D6-C6 | F6: =IF(C6=0,"",D6/C6) | H6: =SUMIFS(H$14:H$73,$B$14:$B$73,"Income") | I6: =SUMIFS(I$14:I$73,$B$14:$B$73,"Income") | J6: =I6-H6 | L6: =SUMIFS(L$14:L$73,$B$14:$B$73,"Income") | M6: =SUMIFS(M$14:M$73,$B$14:$B$73,"Income") | N6: =SUMIFS(N$14:N$73,$B$14:$B$73,"Income") | O6: =SUMIFS(O$14:O$73,$B$14:$B$73,"Income") | P6: =SUMIFS(P$14:P$73,$B$14:$B$73,"Income") | Q6: =SUMIFS(Q$14:Q$73,$B$14:$B$73,"Income") | R6: =SUMIFS(R$14:R$73,$B$14:$B$73,"Income") | S6: =SUMIFS(S$14:S$73,$B$14:$B$73,"Income") | ... Y6: =SUMIFS(Y$14:Y$73,$B$14:$B$73,"Income") | Z6: =X6-Y6
A7: Fixed bills | B7: Fixed bills | C7: =SUMIFS(C$14:C$73,$B$14:$B$73,"Fixed bills") | D7: =SUMIFS(D$14:D$73,$B$14:$B$73,"Fixed bills") | E7: =D7-C7 | F7: =IF(C7=0,"",D7/C7) | H7: =SUMIFS(H$14:H$73,$B$14:$B$73,"Fixed bills") | I7: =SUMIFS(I$14:I$73,$B$14:$B$73,"Fixed bills") | J7: =I7-H7 | L7: =SUMIFS(L$14:L$73,$B$14:$B$73,"Fixed bills") | M7: =SUMIFS(M$14:M$73,$B$14:$B$73,"Fixed bills") | N7: =SUMIFS(N$14:N$73,$B$14:$B$73,"Fixed bills") | O7: =SUMIFS(O$14:O$73,$B$14:$B$73,"Fixed bills") | P7: =SUMIFS(P$14:P$73,$B$14:$B$73,"Fixed bills") | Q7: =SUMIFS(Q$14:Q$73,$B$14:$B$73,"Fixed bills") | R7: =SUMIFS(R$14:R$73,$B$14:$B$73,"Fixed bills") | S7: =SUMIFS(S$14:S$73,$B$14:$B$73,"Fixed bills") | ... Y7: =SUMIFS(Y$14:Y$73,$B$14:$B$73,"Fixed bills") | Z7: =X7-Y7
A8: Variable expenses | B8: Variable expenses | C8: =SUMIFS(C$14:C$73,$B$14:$B$73,"Variable expenses") | D8: =SUMIFS(D$14:D$73,$B$14:$B$73,"Variable expenses") | E8: =D8-C8 | F8: =IF(C8=0,"",D8/C8) | H8: =SUMIFS(H$14:H$73,$B$14:$B$73,"Variable expenses") | I8: =SUMIFS(I$14:I$73,$B$14:$B$73,"Variable expenses") | J8: =I8-H8 | L8: =SUMIFS(L$14:L$73,$B$14:$B$73,"Variable expenses") | M8: =SUMIFS(M$14:M$73,$B$14:$B$73,"Variable expenses") | N8: =SUMIFS(N$14:N$73,$B$14:$B$73,"Variable expenses") | O8: =SUMIFS(O$14:O$73,$B$14:$B$73,"Variable expenses") | P8: =SUMIFS(P$14:P$73,$B$14:$B$73,"Variable expenses") | Q8: =SUMIFS(Q$14:Q$73,$B$14:$B$73,"Variable expenses") | R8: =SUMIFS(R$14:R$73,$B$14:$B$73,"Variable expenses") | S8: =SUMIFS(S$14:S$73,$B$14:$B$73,"Variable expenses") | ... Y8: =SUMIFS(Y$14:Y$73,$B$14:$B$73,"Variable expenses") | Z8: =X8-Y8
A9: Total expenses | B9: All expenses | C9: =C7+C8 | D9: =D7+D8 | E9: =D9-C9 | F9: =IF(C9=0,"",D9/C9) | H9: =H7+H8 | I9: =I7+I8 | J9: =I9-H9 | L9: =L7+L8 | M9: =M7+M8 | N9: =N7+N8 | O9: =O7+O8 | P9: =P7+P8 | Q9: =Q7+Q8 | R9: =R7+R8 | S9: =S7+S8 | ... Y9: =Y7+Y8 | Z9: =X9-Y9
A10: Savings & debt payments | B10: Savings & debt | C10: =SUMIFS(C$14:C$73,$B$14:$B$73,"Savings & debt") | D10: =SUMIFS(D$14:D$73,$B$14:$B$73,"Savings & debt") | E10: =D10-C10 | F10: =IF(C10=0,"",D10/C10) | H10: =SUMIFS(H$14:H$73,$B$14:$B$73,"Savings & debt") | I10: =SUMIFS(I$14:I$73,$B$14:$B$73,"Savings & debt") | J10: =I10-H10 | L10: =SUMIFS(L$14:L$73,$B$14:$B$73,"Savings & debt") | M10: =SUMIFS(M$14:M$73,$B$14:$B$73,"Savings & debt") | N10: =SUMIFS(N$14:N$73,$B$14:$B$73,"Savings & debt") | O10: =SUMIFS(O$14:O$73,$B$14:$B$73,"Savings & debt") | P10: =SUMIFS(P$14:P$73,$B$14:$B$73,"Savings & debt") | Q10: =SUMIFS(Q$14:Q$73,$B$14:$B$73,"Savings & debt") | R10: =SUMIFS(R$14:R$73,$B$14:$B$73,"Savings & debt") | S10: =SUMIFS(S$14:S$73,$B$14:$B$73,"Savings & debt") | ... Y10: =SUMIFS(Y$14:Y$73,$B$14:$B$73,"Savings & debt") | Z10: =X10-Y10
A11: Paid from goals & funds | B11: Funds | C11: =INDEX('Monthly Budget'!$D$11:$O$11,1,Settings!$C$12) | D11: =INDEX($L$11:$W$11,1,Settings!$C$12) | E11: =D11-C11 | H11: =SUMIFS('Monthly Budget'!$D$11:$O$11,Lists!$I$2:$T$2,"<="&Settings!$C$12) | I11: =SUMIFS($L$11:$W$11,Lists!$I$2:$T$2,"<="&Settings!$C$12) | J11: =I11-H11 | L11: =SUMIFS(Transactions!$D$6:$D$2005,Transactions!$F$6:$F$2005,"<>",Transactions!$H$6:$H$2005,"Fixed bills",Transactions!$A$6:$A$2005,">="&DATE(Settings!$C$4,1,1),Transactions!$A$6:$A$2005,"<"&DATE(Settings!$C$4,2,1))+SUMIFS(Transactions!$D$6:$D$2005,Transactions!$F$6:$F$2005,"<>",Transactions!$H$6:$H$2005,"Variable expenses",Transactions!$A$6:$A$2005,">="&DATE(Settings!$C$4,1,1),Transactions!$A$6:$A$2005,"<"&DATE(Settings!$C$4,2,1)) | M11: =SUMIFS(Transactions!$D$6:$D$2005,Transactions!$F$6:$F$2005,"<>",Transactions!$H$6:$H$2005,"Fixed bills",Transactions!$A$6:$A$2005,">="&DATE(Settings!$C$4,2,1),Transactions!$A$6:$A$2005,"<"&DATE(Settings!$C$4,3,1))+SUMIFS(Transactions!$D$6:$D$2005,Transactions!$F$6:$F$2005,"<>",Transactions!$H$6:$H$2005,"Variable expenses",Transactions!$A$6:$A$2005,">="&DATE(Settings!$C$4,2,1),Transactions!$A$6:$A$2005,"<"&DATE(Settings!$C$4,3,1)) | N11: =SUMIFS(Transactions!$D$6:$D$2005,Transactions!$F$6:$F$2005,"<>",Transactions!$H$6:$H$2005,"Fixed bills",Transactions!$A$6:$A$2005,">="&DATE(Settings!$C$4,3,1),Transactions!$A$6:$A$2005,"<"&DATE(Settings!$C$4,4,1))+SUMIFS(Transactions!$D$6:$D$2005,Transactions!$F$6:$F$2005,"<>",Transactions!$H$6:$H$2005,"Variable expenses",Transactions!$A$6:$A$2005,">="&DATE(Settings!$C$4,3,1),Transactions!$A$6:$A$2005,"<"&DATE(Settings!$C$4,4,1)) | O11: =SUMIFS(Transactions!$D$6:$D$2005,Transactions!$F$6:$F$2005,"<>",Transactions!$H$6:$H$2005,"Fixed bills",Transactions!$A$6:$A$2005,">="&DATE(Settings!$C$4,4,1),Transactions!$A$6:$A$2005,"<"&DATE(Settings!$C$4,5,1))+SUMIFS(Transactions!$D$6:$D$2005,Transactions!$F$6:$F$2005,"<>",Transactions!$H$6:$H$2005,"Variable expenses",Transactions!$A$6:$A$2005,">="&DATE(Settings!$C$4,4,1),Transactions!$A$6:$A$2005,"<"&DATE(Settings!$C$4,5,1)) | P11: =SUMIFS(Transactions!$D$6:$D$2005,Transactions!$F$6:$F$2005,"<>",Transactions!$H$6:$H$2005,"Fixed bills",Transactions!$A$6:$A$2005,">="&DATE(Settings!$C$4,5,1),Transactions!$A$6:$A$2005,"<"&DATE(Settings!$C$4,6,1))+SUMIFS(Transactions!$D$6:$D$2005,Transactions!$F$6:$F$2005,"<>",Transactions!$H$6:$H$2005,"Variable expenses",Transactions!$A$6:$A$2005,">="&DATE(Settings!$C$4,5,1),Transactions!$A$6:$A$2005,"<"&DATE(Settings!$C$4,6,1)) | Q11: =SUMIFS(Transactions!$D$6:$D$2005,Transactions!$F$6:$F$2005,"<>",Transactions!$H$6:$H$2005,"Fixed bills",Transactions!$A$6:$A$2005,">="&DATE(Settings!$C$4,6,1),Transactions!$A$6:$A$2005,"<"&DATE(Settings!$C$4,7,1))+SUMIFS(Transactions!$D$6:$D$2005,Transactions!$F$6:$F$2005,"<>",Transactions!$H$6:$H$2005,"Variable expenses",Transactions!$A$6:$A$2005,">="&DATE(Settings!$C$4,6,1),Transactions!$A$6:$A$2005,"<"&DATE(Settings!$C$4,7,1)) | R11: =SUMIFS(Transactions!$D$6:$D$2005,Transactions!$F$6:$F$2005,"<>",Transactions!$H$6:$H$2005,"Fixed bills",Transactions!$A$6:$A$2005,">="&DATE(Settings!$C$4,7,1),Transactions!$A$6:$A$2005,"<"&DATE(Settings!$C$4,8,1))+SUMIFS(Transactions!$D$6:$D$2005,Transactions!$F$6:$F$2005,"<>",Transactions!$H$6:$H$2005,"Variable expenses",Transactions!$A$6:$A$2005,">="&DATE(Settings!$C$4,7,1),Transactions!$A$6:$A$2005,"<"&DATE(Settings!$C$4,8,1)) | S11: =SUMIFS(Transactions!$D$6:$D$2005,Transactions!$F$6:$F$2005,"<>",Transactions!$H$6:$H$2005,"Fixed bills",Transactions!$A$6:$A$2005,">="&DATE(Settings!$C$4,8,1),Transactions!$A$6:$A$2005,"<"&DATE(Settings!$C$4,9,1))+SUMIFS(Transactions!$D$6:$D$2005,Transactions!$F$6:$F$2005,"<>",Transactions!$H$6:$H$2005,"Variable expenses",Transactions!$A$6:$A$2005,">="&DATE(Settings!$C$4,8,1),Transactions!$A$6:$A$2005,"<"&DATE(Settings!$C$4,9,1)) | T11: =SUMIFS(Transactions!$D$6:$D$2005,Transactions!$F$6:$F$2005,"<>",Transactions!$H$6:$H$2005,"Fixed bills",Transactions!$A$6:$A$2005,">="&DATE(Settings!$C$4,9,1),Transactions!$A$6:$A$2005,"<"&DATE(Settings!$C$4,10,1))+SUMIFS(Transactions!$D$6:$D$2005,Transactions!$F$6:$F$2005,"<>",Transactions!$H$6:$H$2005,"Variable expenses",Transactions!$A$6:$A$2005,">="&DATE(Settings!$C$4,9,1),Transactions!$A$6:$A$2005,"<"&DATE(Settings!$C$4,10,1)) | U11: =SUMIFS(Transactions!$D$6:$D$2005,Transactions!$F$6:$F$2005,"<>",Transactions!$H$6:$H$2005,"Fixed bills",Transactions!$A$6:$A$2005,">="&DATE(Settings!$C$4,10,1),Transactions!$A$6:$A$2005,"<"&DATE(Settings!$C$4,11,1))+SUMIFS(Transactions!$D$6:$D$2005,Transactions!$F$6:$F$2005,"<>",Transactions!$H$6:$H$2005,"Variable expenses",Transactions!$A$6:$A$2005,">="&DATE(Settings!$C$4,10,1),Transactions!$A$6:$A$2005,"<"&DATE(Settings!$C$4,11,1)) | V11: =SUMIFS(Transactions!$D$6:$D$2005,Transactions!$F$6:$F$2005,"<>",Transactions!$H$6:$H$2005,"Fixed bills",Transactions!$A$6:$A$2005,">="&DATE(Settings!$C$4,11,1),Transactions!$A$6:$A$2005,"<"&DATE(Settings!$C$4,12,1))+SUMIFS(Transactions!$D$6:$D$2005,Transactions!$F$6:$F$2005,"<>",Transactions!$H$6:$H$2005,"Variable expenses",Transactions!$A$6:$A$2005,">="&DATE(Settings!$C$4,11,1),Transactions!$A$6:$A$2005,"<"&DATE(Settings!$C$4,12,1)) | W11: =SUMIFS(Transactions!$D$6:$D$2005,Transactions!$F$6:$F$2005,"<>",Transactions!$H$6:$H$2005,"Fixed bills",Transactions!$A$6:$A$2005,">="&DATE(Settings!$C$4,12,1),Transactions!$A$6:$A$2005,"<"&DATE(Settings!$C$4,13,1))+SUMIFS(Transactions!$D$6:$D$2005,Transactions!$F$6:$F$2005,"<>",Transactions!$H$6:$H$2005,"Variable expenses",Transactions!$A$6:$A$2005,">="&DATE(Settings!$C$4,12,1),Transactions!$A$6:$A$2005,"<"&DATE(Settings!$C$4,13,1)) | X11: =SUM(L11:W11) | Y11: ='Monthly Budget'!$P$11 | Z11: =X11-Y11
A12: Left over | B12: Result | C12: =C6-C9-C10+C11 | D12: =D6-D9-D10+D11 | E12: =D12-C12 | H12: =H6-H9-H10+H11 | I12: =I6-I9-I10+I11 | J12: =I12-H12 | L12: =L6-L9-L10+L11 | M12: =M6-M9-M10+M11 | N12: =N6-N9-N10+N11 | O12: =O6-O9-O10+O11 | P12: =P6-P9-P10+P11 | Q12: =Q6-Q9-Q10+Q11 | R12: =R6-R9-R10+R11 | S12: =S6-S9-S10+S11 | ... Y12: =Y6-Y9-Y10+Y11 | Z12: =X12-Y12
A13: Categories
A14: =IF(Categories!$A6="","",Categories!$A6) | B14: =IF(A14="","",Categories!$B6&"") | C14: =IF($A14="",0,INDEX('Monthly Budget'!$D14:$O14,1,Settings!$C$12)) | D14: =INDEX($L14:$W14,1,Settings!$C$12) | E14: =D14-C14 | F14: =IF(C14=0,"",D14/C14) | H14: =IF($A14="",0,SUMIFS('Monthly Budget'!$D14:$O14,Lists!$I$2:$T$2,"<="&Settings!$C$12)) | I14: =SUMIFS($L14:$W14,Lists!$I$2:$T$2,"<="&Settings!$C$12) | J14: =I14-H14 | L14: =IF($A14="",0,SUMIFS(Transactions!$D$6:$D$2005,Transactions!$C$6:$C$2005,$A14,Transactions!$A$6:$A$2005,">="&DATE(Settings!$C$4,1,1),Transactions!$A$6:$A$2005,"<"&DATE(Settings!$C$4,2,1))) | M14: =IF($A14="",0,SUMIFS(Transactions!$D$6:$D$2005,Transactions!$C$6:$C$2005,$A14,Transactions!$A$6:$A$2005,">="&DATE(Settings!$C$4,2,1),Transactions!$A$6:$A$2005,"<"&DATE(Settings!$C$4,3,1))) | N14: =IF($A14="",0,SUMIFS(Transactions!$D$6:$D$2005,Transactions!$C$6:$C$2005,$A14,Transactions!$A$6:$A$2005,">="&DATE(Settings!$C$4,3,1),Transactions!$A$6:$A$2005,"<"&DATE(Settings!$C$4,4,1))) | O14: =IF($A14="",0,SUMIFS(Transactions!$D$6:$D$2005,Transactions!$C$6:$C$2005,$A14,Transactions!$A$6:$A$2005,">="&DATE(Settings!$C$4,4,1),Transactions!$A$6:$A$2005,"<"&DATE(Settings!$C$4,5,1))) | P14: =IF($A14="",0,SUMIFS(Transactions!$D$6:$D$2005,Transactions!$C$6:$C$2005,$A14,Transactions!$A$6:$A$2005,">="&DATE(Settings!$C$4,5,1),Transactions!$A$6:$A$2005,"<"&DATE(Settings!$C$4,6,1))) | Q14: =IF($A14="",0,SUMIFS(Transactions!$D$6:$D$2005,Transactions!$C$6:$C$2005,$A14,Transactions!$A$6:$A$2005,">="&DATE(Settings!$C$4,6,1),Transactions!$A$6:$A$2005,"<"&DATE(Settings!$C$4,7,1))) | R14: =IF($A14="",0,SUMIFS(Transactions!$D$6:$D$2005,Transactions!$C$6:$C$2005,$A14,Transactions!$A$6:$A$2005,">="&DATE(Settings!$C$4,7,1),Transactions!$A$6:$A$2005,"<"&DATE(Settings!$C$4,8,1))) | S14: =IF($A14="",0,SUMIFS(Transactions!$D$6:$D$2005,Transactions!$C$6:$C$2005,$A14,Transactions!$A$6:$A$2005,">="&DATE(Settings!$C$4,8,1),Transactions!$A$6:$A$2005,"<"&DATE(Settings!$C$4,9,1))) | T14: =IF($A14="",0,SUMIFS(Transactions!$D$6:$D$2005,Transactions!$C$6:$C$2005,$A14,Transactions!$A$6:$A$2005,">="&DATE(Settings!$C$4,9,1),Transactions!$A$6:$A$2005,"<"&DATE(Settings!$C$4,10,1))) | U14: =IF($A14="",0,SUMIFS(Transactions!$D$6:$D$2005,Transactions!$C$6:$C$2005,$A14,Transactions!$A$6:$A$2005,">="&DATE(Settings!$C$4,10,1),Transactions!$A$6:$A$2005,"<"&DATE(Settings!$C$4,11,1))) | V14: =IF($A14="",0,SUMIFS(Transactions!$D$6:$D$2005,Transactions!$C$6:$C$2005,$A14,Transactions!$A$6:$A$2005,">="&DATE(Settings!$C$4,11,1),Transactions!$A$6:$A$2005,"<"&DATE(Settings!$C$4,12,1))) | W14: =IF($A14="",0,SUMIFS(Transactions!$D$6:$D$2005,Transactions!$C$6:$C$2005,$A14,Transactions!$A$6:$A$2005,">="&DATE(Settings!$C$4,12,1),Transactions!$A$6:$A$2005,"<"&DATE(Settings!$C$4,13,1))) | X14: =SUM(L14:W14) | Y14: =IF($A14="",0,'Monthly Budget'!$P14) | Z14: =X14-Y14 | AA14: =IF(AND(X14>0,OR(B14="Fixed bills",B14="Variable expenses")),X14+ROW()/10000000,0)
A15: =IF(Categories!$A7="","",Categories!$A7) | B15: =IF(A15="","",Categories!$B7&"") | C15: =IF($A15="",0,INDEX('Monthly Budget'!$D15:$O15,1,Settings!$C$12)) | D15: =INDEX($L15:$W15,1,Settings!$C$12) | E15: =D15-C15 | F15: =IF(C15=0,"",D15/C15) | H15: =IF($A15="",0,SUMIFS('Monthly Budget'!$D15:$O15,Lists!$I$2:$T$2,"<="&Settings!$C$12)) | I15: =SUMIFS($L15:$W15,Lists!$I$2:$T$2,"<="&Settings!$C$12) | J15: =I15-H15 | L15: =IF($A15="",0,SUMIFS(Transactions!$D$6:$D$2005,Transactions!$C$6:$C$2005,$A15,Transactions!$A$6:$A$2005,">="&DATE(Settings!$C$4,1,1),Transactions!$A$6:$A$2005,"<"&DATE(Settings!$C$4,2,1))) | M15: =IF($A15="",0,SUMIFS(Transactions!$D$6:$D$2005,Transactions!$C$6:$C$2005,$A15,Transactions!$A$6:$A$2005,">="&DATE(Settings!$C$4,2,1),Transactions!$A$6:$A$2005,"<"&DATE(Settings!$C$4,3,1))) | N15: =IF($A15="",0,SUMIFS(Transactions!$D$6:$D$2005,Transactions!$C$6:$C$2005,$A15,Transactions!$A$6:$A$2005,">="&DATE(Settings!$C$4,3,1),Transactions!$A$6:$A$2005,"<"&DATE(Settings!$C$4,4,1))) | O15: =IF($A15="",0,SUMIFS(Transactions!$D$6:$D$2005,Transactions!$C$6:$C$2005,$A15,Transactions!$A$6:$A$2005,">="&DATE(Settings!$C$4,4,1),Transactions!$A$6:$A$2005,"<"&DATE(Settings!$C$4,5,1))) | P15: =IF($A15="",0,SUMIFS(Transactions!$D$6:$D$2005,Transactions!$C$6:$C$2005,$A15,Transactions!$A$6:$A$2005,">="&DATE(Settings!$C$4,5,1),Transactions!$A$6:$A$2005,"<"&DATE(Settings!$C$4,6,1))) | Q15: =IF($A15="",0,SUMIFS(Transactions!$D$6:$D$2005,Transactions!$C$6:$C$2005,$A15,Transactions!$A$6:$A$2005,">="&DATE(Settings!$C$4,6,1),Transactions!$A$6:$A$2005,"<"&DATE(Settings!$C$4,7,1))) | R15: =IF($A15="",0,SUMIFS(Transactions!$D$6:$D$2005,Transactions!$C$6:$C$2005,$A15,Transactions!$A$6:$A$2005,">="&DATE(Settings!$C$4,7,1),Transactions!$A$6:$A$2005,"<"&DATE(Settings!$C$4,8,1))) | S15: =IF($A15="",0,SUMIFS(Transactions!$D$6:$D$2005,Transactions!$C$6:$C$2005,$A15,Transactions!$A$6:$A$2005,">="&DATE(Settings!$C$4,8,1),Transactions!$A$6:$A$2005,"<"&DATE(Settings!$C$4,9,1))) | T15: =IF($A15="",0,SUMIFS(Transactions!$D$6:$D$2005,Transactions!$C$6:$C$2005,$A15,Transactions!$A$6:$A$2005,">="&DATE(Settings!$C$4,9,1),Transactions!$A$6:$A$2005,"<"&DATE(Settings!$C$4,10,1))) | U15: =IF($A15="",0,SUMIFS(Transactions!$D$6:$D$2005,Transactions!$C$6:$C$2005,$A15,Transactions!$A$6:$A$2005,">="&DATE(Settings!$C$4,10,1),Transactions!$A$6:$A$2005,"<"&DATE(Settings!$C$4,11,1))) | V15: =IF($A15="",0,SUMIFS(Transactions!$D$6:$D$2005,Transactions!$C$6:$C$2005,$A15,Transactions!$A$6:$A$2005,">="&DATE(Settings!$C$4,11,1),Transactions!$A$6:$A$2005,"<"&DATE(Settings!$C$4,12,1))) | W15: =IF($A15="",0,SUMIFS(Transactions!$D$6:$D$2005,Transactions!$C$6:$C$2005,$A15,Transactions!$A$6:$A$2005,">="&DATE(Settings!$C$4,12,1),Transactions!$A$6:$A$2005,"<"&DATE(Settings!$C$4,13,1))) | X15: =SUM(L15:W15) | Y15: =IF($A15="",0,'Monthly Budget'!$P15) | Z15: =X15-Y15 | AA15: =IF(AND(X15>0,OR(B15="Fixed bills",B15="Variable expenses")),X15+ROW()/10000000,0)
A16: =IF(Categories!$A8="","",Categories!$A8) | B16: =IF(A16="","",Categories!$B8&"") | C16: =IF($A16="",0,INDEX('Monthly Budget'!$D16:$O16,1,Settings!$C$12)) | D16: =INDEX($L16:$W16,1,Settings!$C$12) | E16: =D16-C16 | F16: =IF(C16=0,"",D16/C16) | H16: =IF($A16="",0,SUMIFS('Monthly Budget'!$D16:$O16,Lists!$I$2:$T$2,"<="&Settings!$C$12)) | I16: =SUMIFS($L16:$W16,Lists!$I$2:$T$2,"<="&Settings!$C$12) | J16: =I16-H16 | L16: =IF($A16="",0,SUMIFS(Transactions!$D$6:$D$2005,Transactions!$C$6:$C$2005,$A16,Transactions!$A$6:$A$2005,">="&DATE(Settings!$C$4,1,1),Transactions!$A$6:$A$2005,"<"&DATE(Settings!$C$4,2,1))) | M16: =IF($A16="",0,SUMIFS(Transactions!$D$6:$D$2005,Transactions!$C$6:$C$2005,$A16,Transactions!$A$6:$A$2005,">="&DATE(Settings!$C$4,2,1),Transactions!$A$6:$A$2005,"<"&DATE(Settings!$C$4,3,1))) | N16: =IF($A16="",0,SUMIFS(Transactions!$D$6:$D$2005,Transactions!$C$6:$C$2005,$A16,Transactions!$A$6:$A$2005,">="&DATE(Settings!$C$4,3,1),Transactions!$A$6:$A$2005,"<"&DATE(Settings!$C$4,4,1))) | O16: =IF($A16="",0,SUMIFS(Transactions!$D$6:$D$2005,Transactions!$C$6:$C$2005,$A16,Transactions!$A$6:$A$2005,">="&DATE(Settings!$C$4,4,1),Transactions!$A$6:$A$2005,"<"&DATE(Settings!$C$4,5,1))) | P16: =IF($A16="",0,SUMIFS(Transactions!$D$6:$D$2005,Transactions!$C$6:$C$2005,$A16,Transactions!$A$6:$A$2005,">="&DATE(Settings!$C$4,5,1),Transactions!$A$6:$A$2005,"<"&DATE(Settings!$C$4,6,1))) | Q16: =IF($A16="",0,SUMIFS(Transactions!$D$6:$D$2005,Transactions!$C$6:$C$2005,$A16,Transactions!$A$6:$A$2005,">="&DATE(Settings!$C$4,6,1),Transactions!$A$6:$A$2005,"<"&DATE(Settings!$C$4,7,1))) | R16: =IF($A16="",0,SUMIFS(Transactions!$D$6:$D$2005,Transactions!$C$6:$C$2005,$A16,Transactions!$A$6:$A$2005,">="&DATE(Settings!$C$4,7,1),Transactions!$A$6:$A$2005,"<"&DATE(Settings!$C$4,8,1))) | S16: =IF($A16="",0,SUMIFS(Transactions!$D$6:$D$2005,Transactions!$C$6:$C$2005,$A16,Transactions!$A$6:$A$2005,">="&DATE(Settings!$C$4,8,1),Transactions!$A$6:$A$2005,"<"&DATE(Settings!$C$4,9,1))) | T16: =IF($A16="",0,SUMIFS(Transactions!$D$6:$D$2005,Transactions!$C$6:$C$2005,$A16,Transactions!$A$6:$A$2005,">="&DATE(Settings!$C$4,9,1),Transactions!$A$6:$A$2005,"<"&DATE(Settings!$C$4,10,1))) | U16: =IF($A16="",0,SUMIFS(Transactions!$D$6:$D$2005,Transactions!$C$6:$C$2005,$A16,Transactions!$A$6:$A$2005,">="&DATE(Settings!$C$4,10,1),Transactions!$A$6:$A$2005,"<"&DATE(Settings!$C$4,11,1))) | V16: =IF($A16="",0,SUMIFS(Transactions!$D$6:$D$2005,Transactions!$C$6:$C$2005,$A16,Transactions!$A$6:$A$2005,">="&DATE(Settings!$C$4,11,1),Transactions!$A$6:$A$2005,"<"&DATE(Settings!$C$4,12,1))) | W16: =IF($A16="",0,SUMIFS(Transactions!$D$6:$D$2005,Transactions!$C$6:$C$2005,$A16,Transactions!$A$6:$A$2005,">="&DATE(Settings!$C$4,12,1),Transactions!$A$6:$A$2005,"<"&DATE(Settings!$C$4,13,1))) | X16: =SUM(L16:W16) | Y16: =IF($A16="",0,'Monthly Budget'!$P16) | Z16: =X16-Y16 | AA16: =IF(AND(X16>0,OR(B16="Fixed bills",B16="Variable expenses")),X16+ROW()/10000000,0)
A17: =IF(Categories!$A9="","",Categories!$A9) | B17: =IF(A17="","",Categories!$B9&"") | C17: =IF($A17="",0,INDEX('Monthly Budget'!$D17:$O17,1,Settings!$C$12)) | D17: =INDEX($L17:$W17,1,Settings!$C$12) | E17: =D17-C17 | F17: =IF(C17=0,"",D17/C17) | H17: =IF($A17="",0,SUMIFS('Monthly Budget'!$D17:$O17,Lists!$I$2:$T$2,"<="&Settings!$C$12)) | I17: =SUMIFS($L17:$W17,Lists!$I$2:$T$2,"<="&Settings!$C$12) | J17: =I17-H17 | L17: =IF($A17="",0,SUMIFS(Transactions!$D$6:$D$2005,Transactions!$C$6:$C$2005,$A17,Transactions!$A$6:$A$2005,">="&DATE(Settings!$C$4,1,1),Transactions!$A$6:$A$2005,"<"&DATE(Settings!$C$4,2,1))) | M17: =IF($A17="",0,SUMIFS(Transactions!$D$6:$D$2005,Transactions!$C$6:$C$2005,$A17,Transactions!$A$6:$A$2005,">="&DATE(Settings!$C$4,2,1),Transactions!$A$6:$A$2005,"<"&DATE(Settings!$C$4,3,1))) | N17: =IF($A17="",0,SUMIFS(Transactions!$D$6:$D$2005,Transactions!$C$6:$C$2005,$A17,Transactions!$A$6:$A$2005,">="&DATE(Settings!$C$4,3,1),Transactions!$A$6:$A$2005,"<"&DATE(Settings!$C$4,4,1))) | O17: =IF($A17="",0,SUMIFS(Transactions!$D$6:$D$2005,Transactions!$C$6:$C$2005,$A17,Transactions!$A$6:$A$2005,">="&DATE(Settings!$C$4,4,1),Transactions!$A$6:$A$2005,"<"&DATE(Settings!$C$4,5,1))) | P17: =IF($A17="",0,SUMIFS(Transactions!$D$6:$D$2005,Transactions!$C$6:$C$2005,$A17,Transactions!$A$6:$A$2005,">="&DATE(Settings!$C$4,5,1),Transactions!$A$6:$A$2005,"<"&DATE(Settings!$C$4,6,1))) | Q17: =IF($A17="",0,SUMIFS(Transactions!$D$6:$D$2005,Transactions!$C$6:$C$2005,$A17,Transactions!$A$6:$A$2005,">="&DATE(Settings!$C$4,6,1),Transactions!$A$6:$A$2005,"<"&DATE(Settings!$C$4,7,1))) | R17: =IF($A17="",0,SUMIFS(Transactions!$D$6:$D$2005,Transactions!$C$6:$C$2005,$A17,Transactions!$A$6:$A$2005,">="&DATE(Settings!$C$4,7,1),Transactions!$A$6:$A$2005,"<"&DATE(Settings!$C$4,8,1))) | S17: =IF($A17="",0,SUMIFS(Transactions!$D$6:$D$2005,Transactions!$C$6:$C$2005,$A17,Transactions!$A$6:$A$2005,">="&DATE(Settings!$C$4,8,1),Transactions!$A$6:$A$2005,"<"&DATE(Settings!$C$4,9,1))) | T17: =IF($A17="",0,SUMIFS(Transactions!$D$6:$D$2005,Transactions!$C$6:$C$2005,$A17,Transactions!$A$6:$A$2005,">="&DATE(Settings!$C$4,9,1),Transactions!$A$6:$A$2005,"<"&DATE(Settings!$C$4,10,1))) | U17: =IF($A17="",0,SUMIFS(Transactions!$D$6:$D$2005,Transactions!$C$6:$C$2005,$A17,Transactions!$A$6:$A$2005,">="&DATE(Settings!$C$4,10,1),Transactions!$A$6:$A$2005,"<"&DATE(Settings!$C$4,11,1))) | V17: =IF($A17="",0,SUMIFS(Transactions!$D$6:$D$2005,Transactions!$C$6:$C$2005,$A17,Transactions!$A$6:$A$2005,">="&DATE(Settings!$C$4,11,1),Transactions!$A$6:$A$2005,"<"&DATE(Settings!$C$4,12,1))) | W17: =IF($A17="",0,SUMIFS(Transactions!$D$6:$D$2005,Transactions!$C$6:$C$2005,$A17,Transactions!$A$6:$A$2005,">="&DATE(Settings!$C$4,12,1),Transactions!$A$6:$A$2005,"<"&DATE(Settings!$C$4,13,1))) | X17: =SUM(L17:W17) | Y17: =IF($A17="",0,'Monthly Budget'!$P17) | Z17: =X17-Y17 | AA17: =IF(AND(X17>0,OR(B17="Fixed bills",B17="Variable expenses")),X17+ROW()/10000000,0)
A18: =IF(Categories!$A10="","",Categories!$A10) | B18: =IF(A18="","",Categories!$B10&"") | C18: =IF($A18="",0,INDEX('Monthly Budget'!$D18:$O18,1,Settings!$C$12)) | D18: =INDEX($L18:$W18,1,Settings!$C$12) | E18: =D18-C18 | F18: =IF(C18=0,"",D18/C18) | H18: =IF($A18="",0,SUMIFS('Monthly Budget'!$D18:$O18,Lists!$I$2:$T$2,"<="&Settings!$C$12)) | I18: =SUMIFS($L18:$W18,Lists!$I$2:$T$2,"<="&Settings!$C$12) | J18: =I18-H18 | L18: =IF($A18="",0,SUMIFS(Transactions!$D$6:$D$2005,Transactions!$C$6:$C$2005,$A18,Transactions!$A$6:$A$2005,">="&DATE(Settings!$C$4,1,1),Transactions!$A$6:$A$2005,"<"&DATE(Settings!$C$4,2,1))) | M18: =IF($A18="",0,SUMIFS(Transactions!$D$6:$D$2005,Transactions!$C$6:$C$2005,$A18,Transactions!$A$6:$A$2005,">="&DATE(Settings!$C$4,2,1),Transactions!$A$6:$A$2005,"<"&DATE(Settings!$C$4,3,1))) | N18: =IF($A18="",0,SUMIFS(Transactions!$D$6:$D$2005,Transactions!$C$6:$C$2005,$A18,Transactions!$A$6:$A$2005,">="&DATE(Settings!$C$4,3,1),Transactions!$A$6:$A$2005,"<"&DATE(Settings!$C$4,4,1))) | O18: =IF($A18="",0,SUMIFS(Transactions!$D$6:$D$2005,Transactions!$C$6:$C$2005,$A18,Transactions!$A$6:$A$2005,">="&DATE(Settings!$C$4,4,1),Transactions!$A$6:$A$2005,"<"&DATE(Settings!$C$4,5,1))) | P18: =IF($A18="",0,SUMIFS(Transactions!$D$6:$D$2005,Transactions!$C$6:$C$2005,$A18,Transactions!$A$6:$A$2005,">="&DATE(Settings!$C$4,5,1),Transactions!$A$6:$A$2005,"<"&DATE(Settings!$C$4,6,1))) | Q18: =IF($A18="",0,SUMIFS(Transactions!$D$6:$D$2005,Transactions!$C$6:$C$2005,$A18,Transactions!$A$6:$A$2005,">="&DATE(Settings!$C$4,6,1),Transactions!$A$6:$A$2005,"<"&DATE(Settings!$C$4,7,1))) | R18: =IF($A18="",0,SUMIFS(Transactions!$D$6:$D$2005,Transactions!$C$6:$C$2005,$A18,Transactions!$A$6:$A$2005,">="&DATE(Settings!$C$4,7,1),Transactions!$A$6:$A$2005,"<"&DATE(Settings!$C$4,8,1))) | S18: =IF($A18="",0,SUMIFS(Transactions!$D$6:$D$2005,Transactions!$C$6:$C$2005,$A18,Transactions!$A$6:$A$2005,">="&DATE(Settings!$C$4,8,1),Transactions!$A$6:$A$2005,"<"&DATE(Settings!$C$4,9,1))) | T18: =IF($A18="",0,SUMIFS(Transactions!$D$6:$D$2005,Transactions!$C$6:$C$2005,$A18,Transactions!$A$6:$A$2005,">="&DATE(Settings!$C$4,9,1),Transactions!$A$6:$A$2005,"<"&DATE(Settings!$C$4,10,1))) | U18: =IF($A18="",0,SUMIFS(Transactions!$D$6:$D$2005,Transactions!$C$6:$C$2005,$A18,Transactions!$A$6:$A$2005,">="&DATE(Settings!$C$4,10,1),Transactions!$A$6:$A$2005,"<"&DATE(Settings!$C$4,11,1))) | V18: =IF($A18="",0,SUMIFS(Transactions!$D$6:$D$2005,Transactions!$C$6:$C$2005,$A18,Transactions!$A$6:$A$2005,">="&DATE(Settings!$C$4,11,1),Transactions!$A$6:$A$2005,"<"&DATE(Settings!$C$4,12,1))) | W18: =IF($A18="",0,SUMIFS(Transactions!$D$6:$D$2005,Transactions!$C$6:$C$2005,$A18,Transactions!$A$6:$A$2005,">="&DATE(Settings!$C$4,12,1),Transactions!$A$6:$A$2005,"<"&DATE(Settings!$C$4,13,1))) | X18: =SUM(L18:W18) | Y18: =IF($A18="",0,'Monthly Budget'!$P18) | Z18: =X18-Y18 | AA18: =IF(AND(X18>0,OR(B18="Fixed bills",B18="Variable expenses")),X18+ROW()/10000000,0)
A19: =IF(Categories!$A11="","",Categories!$A11) | B19: =IF(A19="","",Categories!$B11&"") | C19: =IF($A19="",0,INDEX('Monthly Budget'!$D19:$O19,1,Settings!$C$12)) | D19: =INDEX($L19:$W19,1,Settings!$C$12) | E19: =D19-C19 | F19: =IF(C19=0,"",D19/C19) | H19: =IF($A19="",0,SUMIFS('Monthly Budget'!$D19:$O19,Lists!$I$2:$T$2,"<="&Settings!$C$12)) | I19: =SUMIFS($L19:$W19,Lists!$I$2:$T$2,"<="&Settings!$C$12) | J19: =I19-H19 | L19: =IF($A19="",0,SUMIFS(Transactions!$D$6:$D$2005,Transactions!$C$6:$C$2005,$A19,Transactions!$A$6:$A$2005,">="&DATE(Settings!$C$4,1,1),Transactions!$A$6:$A$2005,"<"&DATE(Settings!$C$4,2,1))) | M19: =IF($A19="",0,SUMIFS(Transactions!$D$6:$D$2005,Transactions!$C$6:$C$2005,$A19,Transactions!$A$6:$A$2005,">="&DATE(Settings!$C$4,2,1),Transactions!$A$6:$A$2005,"<"&DATE(Settings!$C$4,3,1))) | N19: =IF($A19="",0,SUMIFS(Transactions!$D$6:$D$2005,Transactions!$C$6:$C$2005,$A19,Transactions!$A$6:$A$2005,">="&DATE(Settings!$C$4,3,1),Transactions!$A$6:$A$2005,"<"&DATE(Settings!$C$4,4,1))) | O19: =IF($A19="",0,SUMIFS(Transactions!$D$6:$D$2005,Transactions!$C$6:$C$2005,$A19,Transactions!$A$6:$A$2005,">="&DATE(Settings!$C$4,4,1),Transactions!$A$6:$A$2005,"<"&DATE(Settings!$C$4,5,1))) | P19: =IF($A19="",0,SUMIFS(Transactions!$D$6:$D$2005,Transactions!$C$6:$C$2005,$A19,Transactions!$A$6:$A$2005,">="&DATE(Settings!$C$4,5,1),Transactions!$A$6:$A$2005,"<"&DATE(Settings!$C$4,6,1))) | Q19: =IF($A19="",0,SUMIFS(Transactions!$D$6:$D$2005,Transactions!$C$6:$C$2005,$A19,Transactions!$A$6:$A$2005,">="&DATE(Settings!$C$4,6,1),Transactions!$A$6:$A$2005,"<"&DATE(Settings!$C$4,7,1))) | R19: =IF($A19="",0,SUMIFS(Transactions!$D$6:$D$2005,Transactions!$C$6:$C$2005,$A19,Transactions!$A$6:$A$2005,">="&DATE(Settings!$C$4,7,1),Transactions!$A$6:$A$2005,"<"&DATE(Settings!$C$4,8,1))) | S19: =IF($A19="",0,SUMIFS(Transactions!$D$6:$D$2005,Transactions!$C$6:$C$2005,$A19,Transactions!$A$6:$A$2005,">="&DATE(Settings!$C$4,8,1),Transactions!$A$6:$A$2005,"<"&DATE(Settings!$C$4,9,1))) | T19: =IF($A19="",0,SUMIFS(Transactions!$D$6:$D$2005,Transactions!$C$6:$C$2005,$A19,Transactions!$A$6:$A$2005,">="&DATE(Settings!$C$4,9,1),Transactions!$A$6:$A$2005,"<"&DATE(Settings!$C$4,10,1))) | U19: =IF($A19="",0,SUMIFS(Transactions!$D$6:$D$2005,Transactions!$C$6:$C$2005,$A19,Transactions!$A$6:$A$2005,">="&DATE(Settings!$C$4,10,1),Transactions!$A$6:$A$2005,"<"&DATE(Settings!$C$4,11,1))) | V19: =IF($A19="",0,SUMIFS(Transactions!$D$6:$D$2005,Transactions!$C$6:$C$2005,$A19,Transactions!$A$6:$A$2005,">="&DATE(Settings!$C$4,11,1),Transactions!$A$6:$A$2005,"<"&DATE(Settings!$C$4,12,1))) | W19: =IF($A19="",0,SUMIFS(Transactions!$D$6:$D$2005,Transactions!$C$6:$C$2005,$A19,Transactions!$A$6:$A$2005,">="&DATE(Settings!$C$4,12,1),Transactions!$A$6:$A$2005,"<"&DATE(Settings!$C$4,13,1))) | X19: =SUM(L19:W19) | Y19: =IF($A19="",0,'Monthly Budget'!$P19) | Z19: =X19-Y19 | AA19: =IF(AND(X19>0,OR(B19="Fixed bills",B19="Variable expenses")),X19+ROW()/10000000,0)
A20: =IF(Categories!$A12="","",Categories!$A12) | B20: =IF(A20="","",Categories!$B12&"") | C20: =IF($A20="",0,INDEX('Monthly Budget'!$D20:$O20,1,Settings!$C$12)) | D20: =INDEX($L20:$W20,1,Settings!$C$12) | E20: =D20-C20 | F20: =IF(C20=0,"",D20/C20) | H20: =IF($A20="",0,SUMIFS('Monthly Budget'!$D20:$O20,Lists!$I$2:$T$2,"<="&Settings!$C$12)) | I20: =SUMIFS($L20:$W20,Lists!$I$2:$T$2,"<="&Settings!$C$12) | J20: =I20-H20 | L20: =IF($A20="",0,SUMIFS(Transactions!$D$6:$D$2005,Transactions!$C$6:$C$2005,$A20,Transactions!$A$6:$A$2005,">="&DATE(Settings!$C$4,1,1),Transactions!$A$6:$A$2005,"<"&DATE(Settings!$C$4,2,1))) | M20: =IF($A20="",0,SUMIFS(Transactions!$D$6:$D$2005,Transactions!$C$6:$C$2005,$A20,Transactions!$A$6:$A$2005,">="&DATE(Settings!$C$4,2,1),Transactions!$A$6:$A$2005,"<"&DATE(Settings!$C$4,3,1))) | N20: =IF($A20="",0,SUMIFS(Transactions!$D$6:$D$2005,Transactions!$C$6:$C$2005,$A20,Transactions!$A$6:$A$2005,">="&DATE(Settings!$C$4,3,1),Transactions!$A$6:$A$2005,"<"&DATE(Settings!$C$4,4,1))) | O20: =IF($A20="",0,SUMIFS(Transactions!$D$6:$D$2005,Transactions!$C$6:$C$2005,$A20,Transactions!$A$6:$A$2005,">="&DATE(Settings!$C$4,4,1),Transactions!$A$6:$A$2005,"<"&DATE(Settings!$C$4,5,1))) | P20: =IF($A20="",0,SUMIFS(Transactions!$D$6:$D$2005,Transactions!$C$6:$C$2005,$A20,Transactions!$A$6:$A$2005,">="&DATE(Settings!$C$4,5,1),Transactions!$A$6:$A$2005,"<"&DATE(Settings!$C$4,6,1))) | Q20: =IF($A20="",0,SUMIFS(Transactions!$D$6:$D$2005,Transactions!$C$6:$C$2005,$A20,Transactions!$A$6:$A$2005,">="&DATE(Settings!$C$4,6,1),Transactions!$A$6:$A$2005,"<"&DATE(Settings!$C$4,7,1))) | R20: =IF($A20="",0,SUMIFS(Transactions!$D$6:$D$2005,Transactions!$C$6:$C$2005,$A20,Transactions!$A$6:$A$2005,">="&DATE(Settings!$C$4,7,1),Transactions!$A$6:$A$2005,"<"&DATE(Settings!$C$4,8,1))) | S20: =IF($A20="",0,SUMIFS(Transactions!$D$6:$D$2005,Transactions!$C$6:$C$2005,$A20,Transactions!$A$6:$A$2005,">="&DATE(Settings!$C$4,8,1),Transactions!$A$6:$A$2005,"<"&DATE(Settings!$C$4,9,1))) | T20: =IF($A20="",0,SUMIFS(Transactions!$D$6:$D$2005,Transactions!$C$6:$C$2005,$A20,Transactions!$A$6:$A$2005,">="&DATE(Settings!$C$4,9,1),Transactions!$A$6:$A$2005,"<"&DATE(Settings!$C$4,10,1))) | U20: =IF($A20="",0,SUMIFS(Transactions!$D$6:$D$2005,Transactions!$C$6:$C$2005,$A20,Transactions!$A$6:$A$2005,">="&DATE(Settings!$C$4,10,1),Transactions!$A$6:$A$2005,"<"&DATE(Settings!$C$4,11,1))) | V20: =IF($A20="",0,SUMIFS(Transactions!$D$6:$D$2005,Transactions!$C$6:$C$2005,$A20,Transactions!$A$6:$A$2005,">="&DATE(Settings!$C$4,11,1),Transactions!$A$6:$A$2005,"<"&DATE(Settings!$C$4,12,1))) | W20: =IF($A20="",0,SUMIFS(Transactions!$D$6:$D$2005,Transactions!$C$6:$C$2005,$A20,Transactions!$A$6:$A$2005,">="&DATE(Settings!$C$4,12,1),Transactions!$A$6:$A$2005,"<"&DATE(Settings!$C$4,13,1))) | X20: =SUM(L20:W20) | Y20: =IF($A20="",0,'Monthly Budget'!$P20) | Z20: =X20-Y20 | AA20: =IF(AND(X20>0,OR(B20="Fixed bills",B20="Variable expenses")),X20+ROW()/10000000,0)
A21: =IF(Categories!$A13="","",Categories!$A13) | B21: =IF(A21="","",Categories!$B13&"") | C21: =IF($A21="",0,INDEX('Monthly Budget'!$D21:$O21,1,Settings!$C$12)) | D21: =INDEX($L21:$W21,1,Settings!$C$12) | E21: =D21-C21 | F21: =IF(C21=0,"",D21/C21) | H21: =IF($A21="",0,SUMIFS('Monthly Budget'!$D21:$O21,Lists!$I$2:$T$2,"<="&Settings!$C$12)) | I21: =SUMIFS($L21:$W21,Lists!$I$2:$T$2,"<="&Settings!$C$12) | J21: =I21-H21 | L21: =IF($A21="",0,SUMIFS(Transactions!$D$6:$D$2005,Transactions!$C$6:$C$2005,$A21,Transactions!$A$6:$A$2005,">="&DATE(Settings!$C$4,1,1),Transactions!$A$6:$A$2005,"<"&DATE(Settings!$C$4,2,1))) | M21: =IF($A21="",0,SUMIFS(Transactions!$D$6:$D$2005,Transactions!$C$6:$C$2005,$A21,Transactions!$A$6:$A$2005,">="&DATE(Settings!$C$4,2,1),Transactions!$A$6:$A$2005,"<"&DATE(Settings!$C$4,3,1))) | N21: =IF($A21="",0,SUMIFS(Transactions!$D$6:$D$2005,Transactions!$C$6:$C$2005,$A21,Transactions!$A$6:$A$2005,">="&DATE(Settings!$C$4,3,1),Transactions!$A$6:$A$2005,"<"&DATE(Settings!$C$4,4,1))) | O21: =IF($A21="",0,SUMIFS(Transactions!$D$6:$D$2005,Transactions!$C$6:$C$2005,$A21,Transactions!$A$6:$A$2005,">="&DATE(Settings!$C$4,4,1),Transactions!$A$6:$A$2005,"<"&DATE(Settings!$C$4,5,1))) | P21: =IF($A21="",0,SUMIFS(Transactions!$D$6:$D$2005,Transactions!$C$6:$C$2005,$A21,Transactions!$A$6:$A$2005,">="&DATE(Settings!$C$4,5,1),Transactions!$A$6:$A$2005,"<"&DATE(Settings!$C$4,6,1))) | Q21: =IF($A21="",0,SUMIFS(Transactions!$D$6:$D$2005,Transactions!$C$6:$C$2005,$A21,Transactions!$A$6:$A$2005,">="&DATE(Settings!$C$4,6,1),Transactions!$A$6:$A$2005,"<"&DATE(Settings!$C$4,7,1))) | R21: =IF($A21="",0,SUMIFS(Transactions!$D$6:$D$2005,Transactions!$C$6:$C$2005,$A21,Transactions!$A$6:$A$2005,">="&DATE(Settings!$C$4,7,1),Transactions!$A$6:$A$2005,"<"&DATE(Settings!$C$4,8,1))) | S21: =IF($A21="",0,SUMIFS(Transactions!$D$6:$D$2005,Transactions!$C$6:$C$2005,$A21,Transactions!$A$6:$A$2005,">="&DATE(Settings!$C$4,8,1),Transactions!$A$6:$A$2005,"<"&DATE(Settings!$C$4,9,1))) | T21: =IF($A21="",0,SUMIFS(Transactions!$D$6:$D$2005,Transactions!$C$6:$C$2005,$A21,Transactions!$A$6:$A$2005,">="&DATE(Settings!$C$4,9,1),Transactions!$A$6:$A$2005,"<"&DATE(Settings!$C$4,10,1))) | U21: =IF($A21="",0,SUMIFS(Transactions!$D$6:$D$2005,Transactions!$C$6:$C$2005,$A21,Transactions!$A$6:$A$2005,">="&DATE(Settings!$C$4,10,1),Transactions!$A$6:$A$2005,"<"&DATE(Settings!$C$4,11,1))) | V21: =IF($A21="",0,SUMIFS(Transactions!$D$6:$D$2005,Transactions!$C$6:$C$2005,$A21,Transactions!$A$6:$A$2005,">="&DATE(Settings!$C$4,11,1),Transactions!$A$6:$A$2005,"<"&DATE(Settings!$C$4,12,1))) | W21: =IF($A21="",0,SUMIFS(Transactions!$D$6:$D$2005,Transactions!$C$6:$C$2005,$A21,Transactions!$A$6:$A$2005,">="&DATE(Settings!$C$4,12,1),Transactions!$A$6:$A$2005,"<"&DATE(Settings!$C$4,13,1))) | X21: =SUM(L21:W21) | Y21: =IF($A21="",0,'Monthly Budget'!$P21) | Z21: =X21-Y21 | AA21: =IF(AND(X21>0,OR(B21="Fixed bills",B21="Variable expenses")),X21+ROW()/10000000,0)
A22: =IF(Categories!$A14="","",Categories!$A14) | B22: =IF(A22="","",Categories!$B14&"") | C22: =IF($A22="",0,INDEX('Monthly Budget'!$D22:$O22,1,Settings!$C$12)) | D22: =INDEX($L22:$W22,1,Settings!$C$12) | E22: =D22-C22 | F22: =IF(C22=0,"",D22/C22) | H22: =IF($A22="",0,SUMIFS('Monthly Budget'!$D22:$O22,Lists!$I$2:$T$2,"<="&Settings!$C$12)) | I22: =SUMIFS($L22:$W22,Lists!$I$2:$T$2,"<="&Settings!$C$12) | J22: =I22-H22 | L22: =IF($A22="",0,SUMIFS(Transactions!$D$6:$D$2005,Transactions!$C$6:$C$2005,$A22,Transactions!$A$6:$A$2005,">="&DATE(Settings!$C$4,1,1),Transactions!$A$6:$A$2005,"<"&DATE(Settings!$C$4,2,1))) | M22: =IF($A22="",0,SUMIFS(Transactions!$D$6:$D$2005,Transactions!$C$6:$C$2005,$A22,Transactions!$A$6:$A$2005,">="&DATE(Settings!$C$4,2,1),Transactions!$A$6:$A$2005,"<"&DATE(Settings!$C$4,3,1))) | N22: =IF($A22="",0,SUMIFS(Transactions!$D$6:$D$2005,Transactions!$C$6:$C$2005,$A22,Transactions!$A$6:$A$2005,">="&DATE(Settings!$C$4,3,1),Transactions!$A$6:$A$2005,"<"&DATE(Settings!$C$4,4,1))) | O22: =IF($A22="",0,SUMIFS(Transactions!$D$6:$D$2005,Transactions!$C$6:$C$2005,$A22,Transactions!$A$6:$A$2005,">="&DATE(Settings!$C$4,4,1),Transactions!$A$6:$A$2005,"<"&DATE(Settings!$C$4,5,1))) | P22: =IF($A22="",0,SUMIFS(Transactions!$D$6:$D$2005,Transactions!$C$6:$C$2005,$A22,Transactions!$A$6:$A$2005,">="&DATE(Settings!$C$4,5,1),Transactions!$A$6:$A$2005,"<"&DATE(Settings!$C$4,6,1))) | Q22: =IF($A22="",0,SUMIFS(Transactions!$D$6:$D$2005,Transactions!$C$6:$C$2005,$A22,Transactions!$A$6:$A$2005,">="&DATE(Settings!$C$4,6,1),Transactions!$A$6:$A$2005,"<"&DATE(Settings!$C$4,7,1))) | R22: =IF($A22="",0,SUMIFS(Transactions!$D$6:$D$2005,Transactions!$C$6:$C$2005,$A22,Transactions!$A$6:$A$2005,">="&DATE(Settings!$C$4,7,1),Transactions!$A$6:$A$2005,"<"&DATE(Settings!$C$4,8,1))) | S22: =IF($A22="",0,SUMIFS(Transactions!$D$6:$D$2005,Transactions!$C$6:$C$2005,$A22,Transactions!$A$6:$A$2005,">="&DATE(Settings!$C$4,8,1),Transactions!$A$6:$A$2005,"<"&DATE(Settings!$C$4,9,1))) | T22: =IF($A22="",0,SUMIFS(Transactions!$D$6:$D$2005,Transactions!$C$6:$C$2005,$A22,Transactions!$A$6:$A$2005,">="&DATE(Settings!$C$4,9,1),Transactions!$A$6:$A$2005,"<"&DATE(Settings!$C$4,10,1))) | U22: =IF($A22="",0,SUMIFS(Transactions!$D$6:$D$2005,Transactions!$C$6:$C$2005,$A22,Transactions!$A$6:$A$2005,">="&DATE(Settings!$C$4,10,1),Transactions!$A$6:$A$2005,"<"&DATE(Settings!$C$4,11,1))) | V22: =IF($A22="",0,SUMIFS(Transactions!$D$6:$D$2005,Transactions!$C$6:$C$2005,$A22,Transactions!$A$6:$A$2005,">="&DATE(Settings!$C$4,11,1),Transactions!$A$6:$A$2005,"<"&DATE(Settings!$C$4,12,1))) | W22: =IF($A22="",0,SUMIFS(Transactions!$D$6:$D$2005,Transactions!$C$6:$C$2005,$A22,Transactions!$A$6:$A$2005,">="&DATE(Settings!$C$4,12,1),Transactions!$A$6:$A$2005,"<"&DATE(Settings!$C$4,13,1))) | X22: =SUM(L22:W22) | Y22: =IF($A22="",0,'Monthly Budget'!$P22) | Z22: =X22-Y22 | AA22: =IF(AND(X22>0,OR(B22="Fixed bills",B22="Variable expenses")),X22+ROW()/10000000,0)
A23: =IF(Categories!$A15="","",Categories!$A15) | B23: =IF(A23="","",Categories!$B15&"") | C23: =IF($A23="",0,INDEX('Monthly Budget'!$D23:$O23,1,Settings!$C$12)) | D23: =INDEX($L23:$W23,1,Settings!$C$12) | E23: =D23-C23 | F23: =IF(C23=0,"",D23/C23) | H23: =IF($A23="",0,SUMIFS('Monthly Budget'!$D23:$O23,Lists!$I$2:$T$2,"<="&Settings!$C$12)) | I23: =SUMIFS($L23:$W23,Lists!$I$2:$T$2,"<="&Settings!$C$12) | J23: =I23-H23 | L23: =IF($A23="",0,SUMIFS(Transactions!$D$6:$D$2005,Transactions!$C$6:$C$2005,$A23,Transactions!$A$6:$A$2005,">="&DATE(Settings!$C$4,1,1),Transactions!$A$6:$A$2005,"<"&DATE(Settings!$C$4,2,1))) | M23: =IF($A23="",0,SUMIFS(Transactions!$D$6:$D$2005,Transactions!$C$6:$C$2005,$A23,Transactions!$A$6:$A$2005,">="&DATE(Settings!$C$4,2,1),Transactions!$A$6:$A$2005,"<"&DATE(Settings!$C$4,3,1))) | N23: =IF($A23="",0,SUMIFS(Transactions!$D$6:$D$2005,Transactions!$C$6:$C$2005,$A23,Transactions!$A$6:$A$2005,">="&DATE(Settings!$C$4,3,1),Transactions!$A$6:$A$2005,"<"&DATE(Settings!$C$4,4,1))) | O23: =IF($A23="",0,SUMIFS(Transactions!$D$6:$D$2005,Transactions!$C$6:$C$2005,$A23,Transactions!$A$6:$A$2005,">="&DATE(Settings!$C$4,4,1),Transactions!$A$6:$A$2005,"<"&DATE(Settings!$C$4,5,1))) | P23: =IF($A23="",0,SUMIFS(Transactions!$D$6:$D$2005,Transactions!$C$6:$C$2005,$A23,Transactions!$A$6:$A$2005,">="&DATE(Settings!$C$4,5,1),Transactions!$A$6:$A$2005,"<"&DATE(Settings!$C$4,6,1))) | Q23: =IF($A23="",0,SUMIFS(Transactions!$D$6:$D$2005,Transactions!$C$6:$C$2005,$A23,Transactions!$A$6:$A$2005,">="&DATE(Settings!$C$4,6,1),Transactions!$A$6:$A$2005,"<"&DATE(Settings!$C$4,7,1))) | R23: =IF($A23="",0,SUMIFS(Transactions!$D$6:$D$2005,Transactions!$C$6:$C$2005,$A23,Transactions!$A$6:$A$2005,">="&DATE(Settings!$C$4,7,1),Transactions!$A$6:$A$2005,"<"&DATE(Settings!$C$4,8,1))) | S23: =IF($A23="",0,SUMIFS(Transactions!$D$6:$D$2005,Transactions!$C$6:$C$2005,$A23,Transactions!$A$6:$A$2005,">="&DATE(Settings!$C$4,8,1),Transactions!$A$6:$A$2005,"<"&DATE(Settings!$C$4,9,1))) | T23: =IF($A23="",0,SUMIFS(Transactions!$D$6:$D$2005,Transactions!$C$6:$C$2005,$A23,Transactions!$A$6:$A$2005,">="&DATE(Settings!$C$4,9,1),Transactions!$A$6:$A$2005,"<"&DATE(Settings!$C$4,10,1))) | U23: =IF($A23="",0,SUMIFS(Transactions!$D$6:$D$2005,Transactions!$C$6:$C$2005,$A23,Transactions!$A$6:$A$2005,">="&DATE(Settings!$C$4,10,1),Transactions!$A$6:$A$2005,"<"&DATE(Settings!$C$4,11,1))) | V23: =IF($A23="",0,SUMIFS(Transactions!$D$6:$D$2005,Transactions!$C$6:$C$2005,$A23,Transactions!$A$6:$A$2005,">="&DATE(Settings!$C$4,11,1),Transactions!$A$6:$A$2005,"<"&DATE(Settings!$C$4,12,1))) | W23: =IF($A23="",0,SUMIFS(Transactions!$D$6:$D$2005,Transactions!$C$6:$C$2005,$A23,Transactions!$A$6:$A$2005,">="&DATE(Settings!$C$4,12,1),Transactions!$A$6:$A$2005,"<"&DATE(Settings!$C$4,13,1))) | X23: =SUM(L23:W23) | Y23: =IF($A23="",0,'Monthly Budget'!$P23) | Z23: =X23-Y23 | AA23: =IF(AND(X23>0,OR(B23="Fixed bills",B23="Variable expenses")),X23+ROW()/10000000,0)
A24: =IF(Categories!$A16="","",Categories!$A16) | B24: =IF(A24="","",Categories!$B16&"") | C24: =IF($A24="",0,INDEX('Monthly Budget'!$D24:$O24,1,Settings!$C$12)) | D24: =INDEX($L24:$W24,1,Settings!$C$12) | E24: =D24-C24 | F24: =IF(C24=0,"",D24/C24) | H24: =IF($A24="",0,SUMIFS('Monthly Budget'!$D24:$O24,Lists!$I$2:$T$2,"<="&Settings!$C$12)) | I24: =SUMIFS($L24:$W24,Lists!$I$2:$T$2,"<="&Settings!$C$12) | J24: =I24-H24 | L24: =IF($A24="",0,SUMIFS(Transactions!$D$6:$D$2005,Transactions!$C$6:$C$2005,$A24,Transactions!$A$6:$A$2005,">="&DATE(Settings!$C$4,1,1),Transactions!$A$6:$A$2005,"<"&DATE(Settings!$C$4,2,1))) | M24: =IF($A24="",0,SUMIFS(Transactions!$D$6:$D$2005,Transactions!$C$6:$C$2005,$A24,Transactions!$A$6:$A$2005,">="&DATE(Settings!$C$4,2,1),Transactions!$A$6:$A$2005,"<"&DATE(Settings!$C$4,3,1))) | N24: =IF($A24="",0,SUMIFS(Transactions!$D$6:$D$2005,Transactions!$C$6:$C$2005,$A24,Transactions!$A$6:$A$2005,">="&DATE(Settings!$C$4,3,1),Transactions!$A$6:$A$2005,"<"&DATE(Settings!$C$4,4,1))) | O24: =IF($A24="",0,SUMIFS(Transactions!$D$6:$D$2005,Transactions!$C$6:$C$2005,$A24,Transactions!$A$6:$A$2005,">="&DATE(Settings!$C$4,4,1),Transactions!$A$6:$A$2005,"<"&DATE(Settings!$C$4,5,1))) | P24: =IF($A24="",0,SUMIFS(Transactions!$D$6:$D$2005,Transactions!$C$6:$C$2005,$A24,Transactions!$A$6:$A$2005,">="&DATE(Settings!$C$4,5,1),Transactions!$A$6:$A$2005,"<"&DATE(Settings!$C$4,6,1))) | Q24: =IF($A24="",0,SUMIFS(Transactions!$D$6:$D$2005,Transactions!$C$6:$C$2005,$A24,Transactions!$A$6:$A$2005,">="&DATE(Settings!$C$4,6,1),Transactions!$A$6:$A$2005,"<"&DATE(Settings!$C$4,7,1))) | R24: =IF($A24="",0,SUMIFS(Transactions!$D$6:$D$2005,Transactions!$C$6:$C$2005,$A24,Transactions!$A$6:$A$2005,">="&DATE(Settings!$C$4,7,1),Transactions!$A$6:$A$2005,"<"&DATE(Settings!$C$4,8,1))) | S24: =IF($A24="",0,SUMIFS(Transactions!$D$6:$D$2005,Transactions!$C$6:$C$2005,$A24,Transactions!$A$6:$A$2005,">="&DATE(Settings!$C$4,8,1),Transactions!$A$6:$A$2005,"<"&DATE(Settings!$C$4,9,1))) | T24: =IF($A24="",0,SUMIFS(Transactions!$D$6:$D$2005,Transactions!$C$6:$C$2005,$A24,Transactions!$A$6:$A$2005,">="&DATE(Settings!$C$4,9,1),Transactions!$A$6:$A$2005,"<"&DATE(Settings!$C$4,10,1))) | U24: =IF($A24="",0,SUMIFS(Transactions!$D$6:$D$2005,Transactions!$C$6:$C$2005,$A24,Transactions!$A$6:$A$2005,">="&DATE(Settings!$C$4,10,1),Transactions!$A$6:$A$2005,"<"&DATE(Settings!$C$4,11,1))) | V24: =IF($A24="",0,SUMIFS(Transactions!$D$6:$D$2005,Transactions!$C$6:$C$2005,$A24,Transactions!$A$6:$A$2005,">="&DATE(Settings!$C$4,11,1),Transactions!$A$6:$A$2005,"<"&DATE(Settings!$C$4,12,1))) | W24: =IF($A24="",0,SUMIFS(Transactions!$D$6:$D$2005,Transactions!$C$6:$C$2005,$A24,Transactions!$A$6:$A$2005,">="&DATE(Settings!$C$4,12,1),Transactions!$A$6:$A$2005,"<"&DATE(Settings!$C$4,13,1))) | X24: =SUM(L24:W24) | Y24: =IF($A24="",0,'Monthly Budget'!$P24) | Z24: =X24-Y24 | AA24: =IF(AND(X24>0,OR(B24="Fixed bills",B24="Variable expenses")),X24+ROW()/10000000,0)
A25: =IF(Categories!$A17="","",Categories!$A17) | B25: =IF(A25="","",Categories!$B17&"") | C25: =IF($A25="",0,INDEX('Monthly Budget'!$D25:$O25,1,Settings!$C$12)) | D25: =INDEX($L25:$W25,1,Settings!$C$12) | E25: =D25-C25 | F25: =IF(C25=0,"",D25/C25) | H25: =IF($A25="",0,SUMIFS('Monthly Budget'!$D25:$O25,Lists!$I$2:$T$2,"<="&Settings!$C$12)) | I25: =SUMIFS($L25:$W25,Lists!$I$2:$T$2,"<="&Settings!$C$12) | J25: =I25-H25 | L25: =IF($A25="",0,SUMIFS(Transactions!$D$6:$D$2005,Transactions!$C$6:$C$2005,$A25,Transactions!$A$6:$A$2005,">="&DATE(Settings!$C$4,1,1),Transactions!$A$6:$A$2005,"<"&DATE(Settings!$C$4,2,1))) | M25: =IF($A25="",0,SUMIFS(Transactions!$D$6:$D$2005,Transactions!$C$6:$C$2005,$A25,Transactions!$A$6:$A$2005,">="&DATE(Settings!$C$4,2,1),Transactions!$A$6:$A$2005,"<"&DATE(Settings!$C$4,3,1))) | N25: =IF($A25="",0,SUMIFS(Transactions!$D$6:$D$2005,Transactions!$C$6:$C$2005,$A25,Transactions!$A$6:$A$2005,">="&DATE(Settings!$C$4,3,1),Transactions!$A$6:$A$2005,"<"&DATE(Settings!$C$4,4,1))) | O25: =IF($A25="",0,SUMIFS(Transactions!$D$6:$D$2005,Transactions!$C$6:$C$2005,$A25,Transactions!$A$6:$A$2005,">="&DATE(Settings!$C$4,4,1),Transactions!$A$6:$A$2005,"<"&DATE(Settings!$C$4,5,1))) | P25: =IF($A25="",0,SUMIFS(Transactions!$D$6:$D$2005,Transactions!$C$6:$C$2005,$A25,Transactions!$A$6:$A$2005,">="&DATE(Settings!$C$4,5,1),Transactions!$A$6:$A$2005,"<"&DATE(Settings!$C$4,6,1))) | Q25: =IF($A25="",0,SUMIFS(Transactions!$D$6:$D$2005,Transactions!$C$6:$C$2005,$A25,Transactions!$A$6:$A$2005,">="&DATE(Settings!$C$4,6,1),Transactions!$A$6:$A$2005,"<"&DATE(Settings!$C$4,7,1))) | R25: =IF($A25="",0,SUMIFS(Transactions!$D$6:$D$2005,Transactions!$C$6:$C$2005,$A25,Transactions!$A$6:$A$2005,">="&DATE(Settings!$C$4,7,1),Transactions!$A$6:$A$2005,"<"&DATE(Settings!$C$4,8,1))) | S25: =IF($A25="",0,SUMIFS(Transactions!$D$6:$D$2005,Transactions!$C$6:$C$2005,$A25,Transactions!$A$6:$A$2005,">="&DATE(Settings!$C$4,8,1),Transactions!$A$6:$A$2005,"<"&DATE(Settings!$C$4,9,1))) | T25: =IF($A25="",0,SUMIFS(Transactions!$D$6:$D$2005,Transactions!$C$6:$C$2005,$A25,Transactions!$A$6:$A$2005,">="&DATE(Settings!$C$4,9,1),Transactions!$A$6:$A$2005,"<"&DATE(Settings!$C$4,10,1))) | U25: =IF($A25="",0,SUMIFS(Transactions!$D$6:$D$2005,Transactions!$C$6:$C$2005,$A25,Transactions!$A$6:$A$2005,">="&DATE(Settings!$C$4,10,1),Transactions!$A$6:$A$2005,"<"&DATE(Settings!$C$4,11,1))) | V25: =IF($A25="",0,SUMIFS(Transactions!$D$6:$D$2005,Transactions!$C$6:$C$2005,$A25,Transactions!$A$6:$A$2005,">="&DATE(Settings!$C$4,11,1),Transactions!$A$6:$A$2005,"<"&DATE(Settings!$C$4,12,1))) | W25: =IF($A25="",0,SUMIFS(Transactions!$D$6:$D$2005,Transactions!$C$6:$C$2005,$A25,Transactions!$A$6:$A$2005,">="&DATE(Settings!$C$4,12,1),Transactions!$A$6:$A$2005,"<"&DATE(Settings!$C$4,13,1))) | X25: =SUM(L25:W25) | Y25: =IF($A25="",0,'Monthly Budget'!$P25) | Z25: =X25-Y25 | AA25: =IF(AND(X25>0,OR(B25="Fixed bills",B25="Variable expenses")),X25+ROW()/10000000,0)
... A73: =IF(Categories!$A65="","",Categories!$A65) | B73: =IF(A73="","",Categories!$B65&"") | C73: =IF($A73="",0,INDEX('Monthly Budget'!$D73:$O73,1,Settings!$C$12)) | D73: =INDEX($L73:$W73,1,Settings!$C$12) | E73: =D73-C73 | F73: =IF(C73=0,"",D73/C73) | H73: =IF($A73="",0,SUMIFS('Monthly Budget'!$D73:$O73,Lists!$I$2:$T$2,"<="&Settings!$C$12)) | I73: =SUMIFS($L73:$W73,Lists!$I$2:$T$2,"<="&Settings!$C$12) | J73: =I73-H73 | L73: =IF($A73="",0,SUMIFS(Transactions!$D$6:$D$2005,Transactions!$C$6:$C$2005,$A73,Transactions!$A$6:$A$2005,">="&DATE(Settings!$C$4,1,1),Transactions!$A$6:$A$2005,"<"&DATE(Settings!$C$4,2,1))) | M73: =IF($A73="",0,SUMIFS(Transactions!$D$6:$D$2005,Transactions!$C$6:$C$2005,$A73,Transactions!$A$6:$A$2005,">="&DATE(Settings!$C$4,2,1),Transactions!$A$6:$A$2005,"<"&DATE(Settings!$C$4,3,1))) | N73: =IF($A73="",0,SUMIFS(Transactions!$D$6:$D$2005,Transactions!$C$6:$C$2005,$A73,Transactions!$A$6:$A$2005,">="&DATE(Settings!$C$4,3,1),Transactions!$A$6:$A$2005,"<"&DATE(Settings!$C$4,4,1))) | O73: =IF($A73="",0,SUMIFS(Transactions!$D$6:$D$2005,Transactions!$C$6:$C$2005,$A73,Transactions!$A$6:$A$2005,">="&DATE(Settings!$C$4,4,1),Transactions!$A$6:$A$2005,"<"&DATE(Settings!$C$4,5,1))) | P73: =IF($A73="",0,SUMIFS(Transactions!$D$6:$D$2005,Transactions!$C$6:$C$2005,$A73,Transactions!$A$6:$A$2005,">="&DATE(Settings!$C$4,5,1),Transactions!$A$6:$A$2005,"<"&DATE(Settings!$C$4,6,1))) | Q73: =IF($A73="",0,SUMIFS(Transactions!$D$6:$D$2005,Transactions!$C$6:$C$2005,$A73,Transactions!$A$6:$A$2005,">="&DATE(Settings!$C$4,6,1),Transactions!$A$6:$A$2005,"<"&DATE(Settings!$C$4,7,1))) | R73: =IF($A73="",0,SUMIFS(Transactions!$D$6:$D$2005,Transactions!$C$6:$C$2005,$A73,Transactions!$A$6:$A$2005,">="&DATE(Settings!$C$4,7,1),Transactions!$A$6:$A$2005,"<"&DATE(Settings!$C$4,8,1))) | S73: =IF($A73="",0,SUMIFS(Transactions!$D$6:$D$2005,Transactions!$C$6:$C$2005,$A73,Transactions!$A$6:$A$2005,">="&DATE(Settings!$C$4,8,1),Transactions!$A$6:$A$2005,"<"&DATE(Settings!$C$4,9,1))) | T73: =IF($A73="",0,SUMIFS(Transactions!$D$6:$D$2005,Transactions!$C$6:$C$2005,$A73,Transactions!$A$6:$A$2005,">="&DATE(Settings!$C$4,9,1),Transactions!$A$6:$A$2005,"<"&DATE(Settings!$C$4,10,1))) | U73: =IF($A73="",0,SUMIFS(Transactions!$D$6:$D$2005,Transactions!$C$6:$C$2005,$A73,Transactions!$A$6:$A$2005,">="&DATE(Settings!$C$4,10,1),Transactions!$A$6:$A$2005,"<"&DATE(Settings!$C$4,11,1))) | V73: =IF($A73="",0,SUMIFS(Transactions!$D$6:$D$2005,Transactions!$C$6:$C$2005,$A73,Transactions!$A$6:$A$2005,">="&DATE(Settings!$C$4,11,1),Transactions!$A$6:$A$2005,"<"&DATE(Settings!$C$4,12,1))) | W73: =IF($A73="",0,SUMIFS(Transactions!$D$6:$D$2005,Transactions!$C$6:$C$2005,$A73,Transactions!$A$6:$A$2005,">="&DATE(Settings!$C$4,12,1),Transactions!$A$6:$A$2005,"<"&DATE(Settings!$C$4,13,1))) | X73: =SUM(L73:W73) | Y73: =IF($A73="",0,'Monthly Budget'!$P73) | Z73: =X73-Y73 | AA73: =IF(AND(X73>0,OR(B73="Fixed bills",B73="Variable expenses")),X73+ROW()/10000000,0)

Sheet Annual Dashboard
B1: ="Budget Planner "&Settings!$C$4&IF(Settings!$C$6="",""," · "&Settings!$C$6)
B2: ="Actual totals for "&Settings!$C$4&" from Transactions. Year-to-date comparisons through "&Settings!$C$13&"."&IF(Settings!$C$14="",""," Amounts in "&TRIM(Settings!$C$5)&".")
B4: Income | D4: Expenses | F4: Savings & debt | H4: Savings rate | J4: Left over | L4: Total debt
B5: ='Monthly Summary'!$X$6 | D5: ='Monthly Summary'!$X$9 | F5: ='Monthly Summary'!$X$10 | H5: =IF('Monthly Summary'!$X$6=0,0,('Monthly Summary'!$X$6-'Monthly Summary'!$X$9)/'Monthly Summary'!$X$6) | J5: ='Monthly Summary'!$X$12 | L5: ='Debt Payoff'!$C$18
B6: =IF('Monthly Summary'!$Y$6=0,"No plan yet",ROUND('Monthly Summary'!$X$6/'Monthly Summary'!$Y$6*100,0)&"% of the yearly plan") | D6: =IF('Monthly Summary'!$Y$9=0,"No plan yet",ROUND('Monthly Summary'!$X$9/'Monthly Summary'!$Y$9*100,0)&"% of the yearly plan") | F6: =IF('Monthly Summary'!$Y$10=0,"No plan yet",ROUND('Monthly Summary'!$X$10/'Monthly Summary'!$Y$10*100,0)&"% of the yearly plan") | H6: ="Planned: "&IF('Monthly Summary'!$Y$6=0,"–",ROUND(('Monthly Summary'!$Y$6-'Monthly Summary'!$Y$9)/'Monthly Summary'!$Y$6*100,1)&"%") | J6: ="Planned: "&FIXED('Monthly Summary'!$Y$12,2) | L6: ="Minimums: "&FIXED('Debt Payoff'!$E$18,2)&" a month"
B8: Savings goals: saved so far | F8: Sinking funds: balance | J8: Debt-free (your plan)
B9: ='Savings Goals'!$G$18 | F9: ='Sinking Funds'!$H$18 | J9: ='Debt Payoff'!$K$18
B10: =IF('Savings Goals'!$C$18=0,"No goals yet","of "&FIXED('Savings Goals'!$C$18,2)&" in targets ("&ROUND('Savings Goals'!$I$18*100,0)&"%)") | F10: =IF('Sinking Funds'!$C$18=0,"No funds yet","Set aside "&FIXED('Sinking Funds'!$M$18,2)&" a month to be ready on time") | J10: =IF('Debt Payoff'!$C$18=0,"No debts entered",'Debt Payoff'!$C$4&" · interest saved: "&IF(ISNUMBER('Debt Payoff'!$M$28),FIXED('Debt Payoff'!$M$28,2),"–"))
B12: Month by month
B13: Month | C13: ="Income"&Settings!$C$14 | D13: ="Expenses"&Settings!$C$14 | E13: ="Savings & debt"&Settings!$C$14 | F13: ="Left over"&Settings!$C$14 | G13: Savings rate
B14: Jan | C14: ='Monthly Summary'!L$6 | D14: ='Monthly Summary'!L$9 | E14: ='Monthly Summary'!L$10 | F14: ='Monthly Summary'!L$12 | G14: =IF(C14=0,"",(C14-D14)/C14)
B15: Feb | C15: ='Monthly Summary'!M$6 | D15: ='Monthly Summary'!M$9 | E15: ='Monthly Summary'!M$10 | F15: ='Monthly Summary'!M$12 | G15: =IF(C15=0,"",(C15-D15)/C15)
B16: Mar | C16: ='Monthly Summary'!N$6 | D16: ='Monthly Summary'!N$9 | E16: ='Monthly Summary'!N$10 | F16: ='Monthly Summary'!N$12 | G16: =IF(C16=0,"",(C16-D16)/C16)
B17: Apr | C17: ='Monthly Summary'!O$6 | D17: ='Monthly Summary'!O$9 | E17: ='Monthly Summary'!O$10 | F17: ='Monthly Summary'!O$12 | G17: =IF(C17=0,"",(C17-D17)/C17)
B18: May | C18: ='Monthly Summary'!P$6 | D18: ='Monthly Summary'!P$9 | E18: ='Monthly Summary'!P$10 | F18: ='Monthly Summary'!P$12 | G18: =IF(C18=0,"",(C18-D18)/C18)
B19: Jun | C19: ='Monthly Summary'!Q$6 | D19: ='Monthly Summary'!Q$9 | E19: ='Monthly Summary'!Q$10 | F19: ='Monthly Summary'!Q$12 | G19: =IF(C19=0,"",(C19-D19)/C19)
B20: Jul | C20: ='Monthly Summary'!R$6 | D20: ='Monthly Summary'!R$9 | E20: ='Monthly Summary'!R$10 | F20: ='Monthly Summary'!R$12 | G20: =IF(C20=0,"",(C20-D20)/C20)
B21: Aug | C21: ='Monthly Summary'!S$6 | D21: ='Monthly Summary'!S$9 | E21: ='Monthly Summary'!S$10 | F21: ='Monthly Summary'!S$12 | G21: =IF(C21=0,"",(C21-D21)/C21)
B22: Sep | C22: ='Monthly Summary'!T$6 | D22: ='Monthly Summary'!T$9 | E22: ='Monthly Summary'!T$10 | F22: ='Monthly Summary'!T$12 | G22: =IF(C22=0,"",(C22-D22)/C22)
B23: Oct | C23: ='Monthly Summary'!U$6 | D23: ='Monthly Summary'!U$9 | E23: ='Monthly Summary'!U$10 | F23: ='Monthly Summary'!U$12 | G23: =IF(C23=0,"",(C23-D23)/C23)
B24: Nov | C24: ='Monthly Summary'!V$6 | D24: ='Monthly Summary'!V$9 | E24: ='Monthly Summary'!V$10 | F24: ='Monthly Summary'!V$12 | G24: =IF(C24=0,"",(C24-D24)/C24)
B25: Dec | C25: ='Monthly Summary'!W$6 | D25: ='Monthly Summary'!W$9 | E25: ='Monthly Summary'!W$10 | F25: ='Monthly Summary'!W$12 | G25: =IF(C25=0,"",(C25-D25)/C25)
B26: Year | C26: =SUM(C14:C25) | D26: =SUM(D14:D25) | E26: =SUM(E14:E25) | F26: =SUM(F14:F25) | G26: =IF(C26=0,"",(C26-D26)/C26)
B28: ="Year to date: planned vs actual ("&IF(Settings!$C$12=1,"Jan","Jan–"&Settings!$C$15)&")" | I28: Checks
B29: Line | D29: Planned | E29: Actual | F29: Difference | G29: % of plan | I29: Transactions logged | M29: =COUNT(Transactions!$D$6:$D$2005)
B30: Income | D30: ='Monthly Summary'!$H$6 | E30: ='Monthly Summary'!$I$6 | F30: =E30-D30 | G30: =IF(OR(D30=0,6>10),"",E30/D30) | I30: Transaction rows to check | M30: =COUNTIF(Transactions!$I$6:$I$2005,"?*") | N30: Income
B31: Fixed bills | D31: ='Monthly Summary'!$H$7 | E31: ='Monthly Summary'!$I$7 | F31: =E31-D31 | G31: =IF(OR(D31=0,7>10),"",E31/D31) | I31: Categories to check | M31: =COUNTIF(Categories!$D$6:$D$65,"?*") | N31: Fixed bills
B32: Variable expenses | D32: ='Monthly Summary'!$H$8 | E32: ='Monthly Summary'!$I$8 | F32: =E32-D32 | G32: =IF(OR(D32=0,8>10),"",E32/D32) | I32: Goals and funds to check | M32: =COUNTIF('Savings Goals'!$O$6:$O$17,"Name*")+COUNTIF('Sinking Funds'!$N$6:$N$17,"Name*") | N32: Variable expenses
B33: Total expenses | D33: ='Monthly Summary'!$H$9 | E33: ='Monthly Summary'!$I$9 | F33: =E33-D33 | G33: =IF(OR(D33=0,9>10),"",E33/D33) | I33: Debts to check | M33: =COUNTIF('Debt Payoff'!$L$8:$L$17,"?*") | N33: All expenses
B34: Savings & debt | D34: ='Monthly Summary'!$H$10 | E34: ='Monthly Summary'!$I$10 | F34: =E34-D34 | G34: =IF(OR(D34=0,10>10),"",E34/D34) | I34: =IF(SUM(M30:M33)=0,"No problems found.","Some rows need a look: see the Check column in Transactions, Categories, Savings Goals, Sinking Funds or Debt Payoff.") | N34: Savings & debt
B35: Paid from funds | D35: ='Monthly Summary'!$H$11 | E35: ='Monthly Summary'!$I$11 | F35: =E35-D35 | G35: =IF(OR(D35=0,11>10),"",E35/D35) | N35: Funds
B36: Left over | D36: ='Monthly Summary'!$H$12 | E36: ='Monthly Summary'!$I$12 | F36: =E36-D36 | G36: =IF(OR(D36=0,12>10),"",E36/D36) | N36: Result
B37: Difference = actual − planned. Green is better than planned, red is worse.
B39: Top 10 spending categories (year)
B40: # | C40: Category | F40: ="Actual"&Settings!$C$14 | G40: % of expenses
B41: 1 | C41: =IF(LARGE('Monthly Summary'!$AA$14:$AA$73,B41)<=0,"",INDEX('Monthly Summary'!$A$14:$A$73,MATCH(LARGE('Monthly Summary'!$AA$14:$AA$73,B41),'Monthly Summary'!$AA$14:$AA$73,0))) | F41: =IF(C41="",0,INDEX('Monthly Summary'!$X$14:$X$73,MATCH(LARGE('Monthly Summary'!$AA$14:$AA$73,B41),'Monthly Summary'!$AA$14:$AA$73,0))) | G41: =IF(OR(F41=0,'Monthly Summary'!$X$9=0),"",F41/'Monthly Summary'!$X$9)
B42: 2 | C42: =IF(LARGE('Monthly Summary'!$AA$14:$AA$73,B42)<=0,"",INDEX('Monthly Summary'!$A$14:$A$73,MATCH(LARGE('Monthly Summary'!$AA$14:$AA$73,B42),'Monthly Summary'!$AA$14:$AA$73,0))) | F42: =IF(C42="",0,INDEX('Monthly Summary'!$X$14:$X$73,MATCH(LARGE('Monthly Summary'!$AA$14:$AA$73,B42),'Monthly Summary'!$AA$14:$AA$73,0))) | G42: =IF(OR(F42=0,'Monthly Summary'!$X$9=0),"",F42/'Monthly Summary'!$X$9)
B43: 3 | C43: =IF(LARGE('Monthly Summary'!$AA$14:$AA$73,B43)<=0,"",INDEX('Monthly Summary'!$A$14:$A$73,MATCH(LARGE('Monthly Summary'!$AA$14:$AA$73,B43),'Monthly Summary'!$AA$14:$AA$73,0))) | F43: =IF(C43="",0,INDEX('Monthly Summary'!$X$14:$X$73,MATCH(LARGE('Monthly Summary'!$AA$14:$AA$73,B43),'Monthly Summary'!$AA$14:$AA$73,0))) | G43: =IF(OR(F43=0,'Monthly Summary'!$X$9=0),"",F43/'Monthly Summary'!$X$9)
B44: 4 | C44: =IF(LARGE('Monthly Summary'!$AA$14:$AA$73,B44)<=0,"",INDEX('Monthly Summary'!$A$14:$A$73,MATCH(LARGE('Monthly Summary'!$AA$14:$AA$73,B44),'Monthly Summary'!$AA$14:$AA$73,0))) | F44: =IF(C44="",0,INDEX('Monthly Summary'!$X$14:$X$73,MATCH(LARGE('Monthly Summary'!$AA$14:$AA$73,B44),'Monthly Summary'!$AA$14:$AA$73,0))) | G44: =IF(OR(F44=0,'Monthly Summary'!$X$9=0),"",F44/'Monthly Summary'!$X$9)
B45: 5 | C45: =IF(LARGE('Monthly Summary'!$AA$14:$AA$73,B45)<=0,"",INDEX('Monthly Summary'!$A$14:$A$73,MATCH(LARGE('Monthly Summary'!$AA$14:$AA$73,B45),'Monthly Summary'!$AA$14:$AA$73,0))) | F45: =IF(C45="",0,INDEX('Monthly Summary'!$X$14:$X$73,MATCH(LARGE('Monthly Summary'!$AA$14:$AA$73,B45),'Monthly Summary'!$AA$14:$AA$73,0))) | G45: =IF(OR(F45=0,'Monthly Summary'!$X$9=0),"",F45/'Monthly Summary'!$X$9)
B46: 6 | C46: =IF(LARGE('Monthly Summary'!$AA$14:$AA$73,B46)<=0,"",INDEX('Monthly Summary'!$A$14:$A$73,MATCH(LARGE('Monthly Summary'!$AA$14:$AA$73,B46),'Monthly Summary'!$AA$14:$AA$73,0))) | F46: =IF(C46="",0,INDEX('Monthly Summary'!$X$14:$X$73,MATCH(LARGE('Monthly Summary'!$AA$14:$AA$73,B46),'Monthly Summary'!$AA$14:$AA$73,0))) | G46: =IF(OR(F46=0,'Monthly Summary'!$X$9=0),"",F46/'Monthly Summary'!$X$9)
B47: 7 | C47: =IF(LARGE('Monthly Summary'!$AA$14:$AA$73,B47)<=0,"",INDEX('Monthly Summary'!$A$14:$A$73,MATCH(LARGE('Monthly Summary'!$AA$14:$AA$73,B47),'Monthly Summary'!$AA$14:$AA$73,0))) | F47: =IF(C47="",0,INDEX('Monthly Summary'!$X$14:$X$73,MATCH(LARGE('Monthly Summary'!$AA$14:$AA$73,B47),'Monthly Summary'!$AA$14:$AA$73,0))) | G47: =IF(OR(F47=0,'Monthly Summary'!$X$9=0),"",F47/'Monthly Summary'!$X$9)
B48: 8 | C48: =IF(LARGE('Monthly Summary'!$AA$14:$AA$73,B48)<=0,"",INDEX('Monthly Summary'!$A$14:$A$73,MATCH(LARGE('Monthly Summary'!$AA$14:$AA$73,B48),'Monthly Summary'!$AA$14:$AA$73,0))) | F48: =IF(C48="",0,INDEX('Monthly Summary'!$X$14:$X$73,MATCH(LARGE('Monthly Summary'!$AA$14:$AA$73,B48),'Monthly Summary'!$AA$14:$AA$73,0))) | G48: =IF(OR(F48=0,'Monthly Summary'!$X$9=0),"",F48/'Monthly Summary'!$X$9)
B49: 9 | C49: =IF(LARGE('Monthly Summary'!$AA$14:$AA$73,B49)<=0,"",INDEX('Monthly Summary'!$A$14:$A$73,MATCH(LARGE('Monthly Summary'!$AA$14:$AA$73,B49),'Monthly Summary'!$AA$14:$AA$73,0))) | F49: =IF(C49="",0,INDEX('Monthly Summary'!$X$14:$X$73,MATCH(LARGE('Monthly Summary'!$AA$14:$AA$73,B49),'Monthly Summary'!$AA$14:$AA$73,0))) | G49: =IF(OR(F49=0,'Monthly Summary'!$X$9=0),"",F49/'Monthly Summary'!$X$9)
B50: 10 | C50: =IF(LARGE('Monthly Summary'!$AA$14:$AA$73,B50)<=0,"",INDEX('Monthly Summary'!$A$14:$A$73,MATCH(LARGE('Monthly Summary'!$AA$14:$AA$73,B50),'Monthly Summary'!$AA$14:$AA$73,0))) | F50: =IF(C50="",0,INDEX('Monthly Summary'!$X$14:$X$73,MATCH(LARGE('Monthly Summary'!$AA$14:$AA$73,B50),'Monthly Summary'!$AA$14:$AA$73,0))) | G50: =IF(OR(F50=0,'Monthly Summary'!$X$9=0),"",F50/'Monthly Summary'!$X$9)

Sheet Savings Goals
B1: Savings Goals
B2: Long-term goals: emergency fund, a home, a car. To add money, log a Savings & debt transaction and pick the goal in the "Goal / fund" column of Transactions.
B3: ="Months left are counted from "&YEAR(Settings!$C$11)&"-"&RIGHT("0"&MONTH(Settings!$C$11),2)&" (as-of date in Settings)."
B5: Goal | C5: ="Target"&Settings!$C$14 | D5: Target date | E5: ="Starting amount"&Settings!$C$14 | F5: ="Added in Transactions"&Settings!$C$14 | G5: ="Saved so far"&Settings!$C$14 | H5: ="Still needed"&Settings!$C$14 | I5: Progress | K5: Months left | L5: ="Needed per month"&Settings!$C$14 | M5: ="Your monthly plan"&Settings!$C$14 | N5: Reached by (your plan) | O5: Status
B6: Emergency fund | C6: 12000 | D6: 46752 | E6: 6500 | F6: =IF(B6="",0,SUMIFS(Transactions!$D$6:$D$2005,Transactions!$F$6:$F$2005,B6,Transactions!$H$6:$H$2005,"Savings & debt")-SUMIFS(Transactions!$D$6:$D$2005,Transactions!$F$6:$F$2005,B6,Transactions!$H$6:$H$2005,"Fixed bills")-SUMIFS(Transactions!$D$6:$D$2005,Transactions!$F$6:$F$2005,B6,Transactions!$H$6:$H$2005,"Variable expenses")) | G6: =IF(B6="",0,N(E6)+F6) | H6: =IF(B6="",0,MAX(0,N(C6)-G6)) | I6: =IF(N(C6)<=0,"",MIN(1,MAX(0,G6/C6))) | J6: =IF(I6="","",REPT("■",ROUND(MIN(1,MAX(0,N(I6)))*10,0))&REPT("□",10-ROUND(MIN(1,MAX(0,N(I6)))*10,0))) | K6: =IF(OR(B6="",NOT(ISNUMBER(D6))),"",MAX(0,(YEAR(D6)-YEAR(Settings!$C$11))*12+MONTH(D6)-MONTH(Settings!$C$11))) | L6: =IF(OR(B6="",K6=""),"",IF(H6<=0,0,H6/MAX(1,K6))) | M6: 300 | N6: =IF(OR(B6="",N(C6)<=0),"",IF(H6<=0,"Reached",IF(N(M6)<=0,"",DATE(YEAR(Settings!$C$11),MONTH(Settings!$C$11)+ROUNDUP(H6/M6,0),1)))) | O6: =IF(B6="",IF(OR(N(C6)<>0,N(E6)<>0),"Name missing",""),IF(COUNTIF(Lists!$G$2:$G$25,B6)>1,"Name used twice",IF(N(C6)<=0,"Enter a target",IF(H6<=0,"Reached",IF(K6="","Enter a target date",IF(K6=0,"Target date reached",IF(N(M6)<=0,"Enter a monthly plan",IF(M6>=L6-0.005,"On track","Behind"))))))))
B7: House down payment | C7: 30000 | D7: 47483 | E7: 12000 | F7: =IF(B7="",0,SUMIFS(Transactions!$D$6:$D$2005,Transactions!$F$6:$F$2005,B7,Transactions!$H$6:$H$2005,"Savings & debt")-SUMIFS(Transactions!$D$6:$D$2005,Transactions!$F$6:$F$2005,B7,Transactions!$H$6:$H$2005,"Fixed bills")-SUMIFS(Transactions!$D$6:$D$2005,Transactions!$F$6:$F$2005,B7,Transactions!$H$6:$H$2005,"Variable expenses")) | G7: =IF(B7="",0,N(E7)+F7) | H7: =IF(B7="",0,MAX(0,N(C7)-G7)) | I7: =IF(N(C7)<=0,"",MIN(1,MAX(0,G7/C7))) | J7: =IF(I7="","",REPT("■",ROUND(MIN(1,MAX(0,N(I7)))*10,0))&REPT("□",10-ROUND(MIN(1,MAX(0,N(I7)))*10,0))) | K7: =IF(OR(B7="",NOT(ISNUMBER(D7))),"",MAX(0,(YEAR(D7)-YEAR(Settings!$C$11))*12+MONTH(D7)-MONTH(Settings!$C$11))) | L7: =IF(OR(B7="",K7=""),"",IF(H7<=0,0,H7/MAX(1,K7))) | M7: 300 | N7: =IF(OR(B7="",N(C7)<=0),"",IF(H7<=0,"Reached",IF(N(M7)<=0,"",DATE(YEAR(Settings!$C$11),MONTH(Settings!$C$11)+ROUNDUP(H7/M7,0),1)))) | O7: =IF(B7="",IF(OR(N(C7)<>0,N(E7)<>0),"Name missing",""),IF(COUNTIF(Lists!$G$2:$G$25,B7)>1,"Name used twice",IF(N(C7)<=0,"Enter a target",IF(H7<=0,"Reached",IF(K7="","Enter a target date",IF(K7=0,"Target date reached",IF(N(M7)<=0,"Enter a monthly plan",IF(M7>=L7-0.005,"On track","Behind"))))))))
B8: New laptop | C8: 1500 | D8: 46477 | E8: 200 | F8: =IF(B8="",0,SUMIFS(Transactions!$D$6:$D$2005,Transactions!$F$6:$F$2005,B8,Transactions!$H$6:$H$2005,"Savings & debt")-SUMIFS(Transactions!$D$6:$D$2005,Transactions!$F$6:$F$2005,B8,Transactions!$H$6:$H$2005,"Fixed bills")-SUMIFS(Transactions!$D$6:$D$2005,Transactions!$F$6:$F$2005,B8,Transactions!$H$6:$H$2005,"Variable expenses")) | G8: =IF(B8="",0,N(E8)+F8) | H8: =IF(B8="",0,MAX(0,N(C8)-G8)) | I8: =IF(N(C8)<=0,"",MIN(1,MAX(0,G8/C8))) | J8: =IF(I8="","",REPT("■",ROUND(MIN(1,MAX(0,N(I8)))*10,0))&REPT("□",10-ROUND(MIN(1,MAX(0,N(I8)))*10,0))) | K8: =IF(OR(B8="",NOT(ISNUMBER(D8))),"",MAX(0,(YEAR(D8)-YEAR(Settings!$C$11))*12+MONTH(D8)-MONTH(Settings!$C$11))) | L8: =IF(OR(B8="",K8=""),"",IF(H8<=0,0,H8/MAX(1,K8))) | M8: 100 | N8: =IF(OR(B8="",N(C8)<=0),"",IF(H8<=0,"Reached",IF(N(M8)<=0,"",DATE(YEAR(Settings!$C$11),MONTH(Settings!$C$11)+ROUNDUP(H8/M8,0),1)))) | O8: =IF(B8="",IF(OR(N(C8)<>0,N(E8)<>0),"Name missing",""),IF(COUNTIF(Lists!$G$2:$G$25,B8)>1,"Name used twice",IF(N(C8)<=0,"Enter a target",IF(H8<=0,"Reached",IF(K8="","Enter a target date",IF(K8=0,"Target date reached",IF(N(M8)<=0,"Enter a monthly plan",IF(M8>=L8-0.005,"On track","Behind"))))))))
B9: Anniversary trip | C9: 2500 | D9: 46691 | E9: 0 | F9: =IF(B9="",0,SUMIFS(Transactions!$D$6:$D$2005,Transactions!$F$6:$F$2005,B9,Transactions!$H$6:$H$2005,"Savings & debt")-SUMIFS(Transactions!$D$6:$D$2005,Transactions!$F$6:$F$2005,B9,Transactions!$H$6:$H$2005,"Fixed bills")-SUMIFS(Transactions!$D$6:$D$2005,Transactions!$F$6:$F$2005,B9,Transactions!$H$6:$H$2005,"Variable expenses")) | G9: =IF(B9="",0,N(E9)+F9) | H9: =IF(B9="",0,MAX(0,N(C9)-G9)) | I9: =IF(N(C9)<=0,"",MIN(1,MAX(0,G9/C9))) | J9: =IF(I9="","",REPT("■",ROUND(MIN(1,MAX(0,N(I9)))*10,0))&REPT("□",10-ROUND(MIN(1,MAX(0,N(I9)))*10,0))) | K9: =IF(OR(B9="",NOT(ISNUMBER(D9))),"",MAX(0,(YEAR(D9)-YEAR(Settings!$C$11))*12+MONTH(D9)-MONTH(Settings!$C$11))) | L9: =IF(OR(B9="",K9=""),"",IF(H9<=0,0,H9/MAX(1,K9))) | M9: 250 | N9: =IF(OR(B9="",N(C9)<=0),"",IF(H9<=0,"Reached",IF(N(M9)<=0,"",DATE(YEAR(Settings!$C$11),MONTH(Settings!$C$11)+ROUNDUP(H9/M9,0),1)))) | O9: =IF(B9="",IF(OR(N(C9)<>0,N(E9)<>0),"Name missing",""),IF(COUNTIF(Lists!$G$2:$G$25,B9)>1,"Name used twice",IF(N(C9)<=0,"Enter a target",IF(H9<=0,"Reached",IF(K9="","Enter a target date",IF(K9=0,"Target date reached",IF(N(M9)<=0,"Enter a monthly plan",IF(M9>=L9-0.005,"On track","Behind"))))))))
F10: =IF(B10="",0,SUMIFS(Transactions!$D$6:$D$2005,Transactions!$F$6:$F$2005,B10,Transactions!$H$6:$H$2005,"Savings & debt")-SUMIFS(Transactions!$D$6:$D$2005,Transactions!$F$6:$F$2005,B10,Transactions!$H$6:$H$2005,"Fixed bills")-SUMIFS(Transactions!$D$6:$D$2005,Transactions!$F$6:$F$2005,B10,Transactions!$H$6:$H$2005,"Variable expenses")) | G10: =IF(B10="",0,N(E10)+F10) | H10: =IF(B10="",0,MAX(0,N(C10)-G10)) | I10: =IF(N(C10)<=0,"",MIN(1,MAX(0,G10/C10))) | J10: =IF(I10="","",REPT("■",ROUND(MIN(1,MAX(0,N(I10)))*10,0))&REPT("□",10-ROUND(MIN(1,MAX(0,N(I10)))*10,0))) | K10: =IF(OR(B10="",NOT(ISNUMBER(D10))),"",MAX(0,(YEAR(D10)-YEAR(Settings!$C$11))*12+MONTH(D10)-MONTH(Settings!$C$11))) | L10: =IF(OR(B10="",K10=""),"",IF(H10<=0,0,H10/MAX(1,K10))) | N10: =IF(OR(B10="",N(C10)<=0),"",IF(H10<=0,"Reached",IF(N(M10)<=0,"",DATE(YEAR(Settings!$C$11),MONTH(Settings!$C$11)+ROUNDUP(H10/M10,0),1)))) | O10: =IF(B10="",IF(OR(N(C10)<>0,N(E10)<>0),"Name missing",""),IF(COUNTIF(Lists!$G$2:$G$25,B10)>1,"Name used twice",IF(N(C10)<=0,"Enter a target",IF(H10<=0,"Reached",IF(K10="","Enter a target date",IF(K10=0,"Target date reached",IF(N(M10)<=0,"Enter a monthly plan",IF(M10>=L10-0.005,"On track","Behind"))))))))
F11: =IF(B11="",0,SUMIFS(Transactions!$D$6:$D$2005,Transactions!$F$6:$F$2005,B11,Transactions!$H$6:$H$2005,"Savings & debt")-SUMIFS(Transactions!$D$6:$D$2005,Transactions!$F$6:$F$2005,B11,Transactions!$H$6:$H$2005,"Fixed bills")-SUMIFS(Transactions!$D$6:$D$2005,Transactions!$F$6:$F$2005,B11,Transactions!$H$6:$H$2005,"Variable expenses")) | G11: =IF(B11="",0,N(E11)+F11) | H11: =IF(B11="",0,MAX(0,N(C11)-G11)) | I11: =IF(N(C11)<=0,"",MIN(1,MAX(0,G11/C11))) | J11: =IF(I11="","",REPT("■",ROUND(MIN(1,MAX(0,N(I11)))*10,0))&REPT("□",10-ROUND(MIN(1,MAX(0,N(I11)))*10,0))) | K11: =IF(OR(B11="",NOT(ISNUMBER(D11))),"",MAX(0,(YEAR(D11)-YEAR(Settings!$C$11))*12+MONTH(D11)-MONTH(Settings!$C$11))) | L11: =IF(OR(B11="",K11=""),"",IF(H11<=0,0,H11/MAX(1,K11))) | N11: =IF(OR(B11="",N(C11)<=0),"",IF(H11<=0,"Reached",IF(N(M11)<=0,"",DATE(YEAR(Settings!$C$11),MONTH(Settings!$C$11)+ROUNDUP(H11/M11,0),1)))) | O11: =IF(B11="",IF(OR(N(C11)<>0,N(E11)<>0),"Name missing",""),IF(COUNTIF(Lists!$G$2:$G$25,B11)>1,"Name used twice",IF(N(C11)<=0,"Enter a target",IF(H11<=0,"Reached",IF(K11="","Enter a target date",IF(K11=0,"Target date reached",IF(N(M11)<=0,"Enter a monthly plan",IF(M11>=L11-0.005,"On track","Behind"))))))))
F12: =IF(B12="",0,SUMIFS(Transactions!$D$6:$D$2005,Transactions!$F$6:$F$2005,B12,Transactions!$H$6:$H$2005,"Savings & debt")-SUMIFS(Transactions!$D$6:$D$2005,Transactions!$F$6:$F$2005,B12,Transactions!$H$6:$H$2005,"Fixed bills")-SUMIFS(Transactions!$D$6:$D$2005,Transactions!$F$6:$F$2005,B12,Transactions!$H$6:$H$2005,"Variable expenses")) | G12: =IF(B12="",0,N(E12)+F12) | H12: =IF(B12="",0,MAX(0,N(C12)-G12)) | I12: =IF(N(C12)<=0,"",MIN(1,MAX(0,G12/C12))) | J12: =IF(I12="","",REPT("■",ROUND(MIN(1,MAX(0,N(I12)))*10,0))&REPT("□",10-ROUND(MIN(1,MAX(0,N(I12)))*10,0))) | K12: =IF(OR(B12="",NOT(ISNUMBER(D12))),"",MAX(0,(YEAR(D12)-YEAR(Settings!$C$11))*12+MONTH(D12)-MONTH(Settings!$C$11))) | L12: =IF(OR(B12="",K12=""),"",IF(H12<=0,0,H12/MAX(1,K12))) | N12: =IF(OR(B12="",N(C12)<=0),"",IF(H12<=0,"Reached",IF(N(M12)<=0,"",DATE(YEAR(Settings!$C$11),MONTH(Settings!$C$11)+ROUNDUP(H12/M12,0),1)))) | O12: =IF(B12="",IF(OR(N(C12)<>0,N(E12)<>0),"Name missing",""),IF(COUNTIF(Lists!$G$2:$G$25,B12)>1,"Name used twice",IF(N(C12)<=0,"Enter a target",IF(H12<=0,"Reached",IF(K12="","Enter a target date",IF(K12=0,"Target date reached",IF(N(M12)<=0,"Enter a monthly plan",IF(M12>=L12-0.005,"On track","Behind"))))))))
F13: =IF(B13="",0,SUMIFS(Transactions!$D$6:$D$2005,Transactions!$F$6:$F$2005,B13,Transactions!$H$6:$H$2005,"Savings & debt")-SUMIFS(Transactions!$D$6:$D$2005,Transactions!$F$6:$F$2005,B13,Transactions!$H$6:$H$2005,"Fixed bills")-SUMIFS(Transactions!$D$6:$D$2005,Transactions!$F$6:$F$2005,B13,Transactions!$H$6:$H$2005,"Variable expenses")) | G13: =IF(B13="",0,N(E13)+F13) | H13: =IF(B13="",0,MAX(0,N(C13)-G13)) | I13: =IF(N(C13)<=0,"",MIN(1,MAX(0,G13/C13))) | J13: =IF(I13="","",REPT("■",ROUND(MIN(1,MAX(0,N(I13)))*10,0))&REPT("□",10-ROUND(MIN(1,MAX(0,N(I13)))*10,0))) | K13: =IF(OR(B13="",NOT(ISNUMBER(D13))),"",MAX(0,(YEAR(D13)-YEAR(Settings!$C$11))*12+MONTH(D13)-MONTH(Settings!$C$11))) | L13: =IF(OR(B13="",K13=""),"",IF(H13<=0,0,H13/MAX(1,K13))) | N13: =IF(OR(B13="",N(C13)<=0),"",IF(H13<=0,"Reached",IF(N(M13)<=0,"",DATE(YEAR(Settings!$C$11),MONTH(Settings!$C$11)+ROUNDUP(H13/M13,0),1)))) | O13: =IF(B13="",IF(OR(N(C13)<>0,N(E13)<>0),"Name missing",""),IF(COUNTIF(Lists!$G$2:$G$25,B13)>1,"Name used twice",IF(N(C13)<=0,"Enter a target",IF(H13<=0,"Reached",IF(K13="","Enter a target date",IF(K13=0,"Target date reached",IF(N(M13)<=0,"Enter a monthly plan",IF(M13>=L13-0.005,"On track","Behind"))))))))
F14: =IF(B14="",0,SUMIFS(Transactions!$D$6:$D$2005,Transactions!$F$6:$F$2005,B14,Transactions!$H$6:$H$2005,"Savings & debt")-SUMIFS(Transactions!$D$6:$D$2005,Transactions!$F$6:$F$2005,B14,Transactions!$H$6:$H$2005,"Fixed bills")-SUMIFS(Transactions!$D$6:$D$2005,Transactions!$F$6:$F$2005,B14,Transactions!$H$6:$H$2005,"Variable expenses")) | G14: =IF(B14="",0,N(E14)+F14) | H14: =IF(B14="",0,MAX(0,N(C14)-G14)) | I14: =IF(N(C14)<=0,"",MIN(1,MAX(0,G14/C14))) | J14: =IF(I14="","",REPT("■",ROUND(MIN(1,MAX(0,N(I14)))*10,0))&REPT("□",10-ROUND(MIN(1,MAX(0,N(I14)))*10,0))) | K14: =IF(OR(B14="",NOT(ISNUMBER(D14))),"",MAX(0,(YEAR(D14)-YEAR(Settings!$C$11))*12+MONTH(D14)-MONTH(Settings!$C$11))) | L14: =IF(OR(B14="",K14=""),"",IF(H14<=0,0,H14/MAX(1,K14))) | N14: =IF(OR(B14="",N(C14)<=0),"",IF(H14<=0,"Reached",IF(N(M14)<=0,"",DATE(YEAR(Settings!$C$11),MONTH(Settings!$C$11)+ROUNDUP(H14/M14,0),1)))) | O14: =IF(B14="",IF(OR(N(C14)<>0,N(E14)<>0),"Name missing",""),IF(COUNTIF(Lists!$G$2:$G$25,B14)>1,"Name used twice",IF(N(C14)<=0,"Enter a target",IF(H14<=0,"Reached",IF(K14="","Enter a target date",IF(K14=0,"Target date reached",IF(N(M14)<=0,"Enter a monthly plan",IF(M14>=L14-0.005,"On track","Behind"))))))))
F15: =IF(B15="",0,SUMIFS(Transactions!$D$6:$D$2005,Transactions!$F$6:$F$2005,B15,Transactions!$H$6:$H$2005,"Savings & debt")-SUMIFS(Transactions!$D$6:$D$2005,Transactions!$F$6:$F$2005,B15,Transactions!$H$6:$H$2005,"Fixed bills")-SUMIFS(Transactions!$D$6:$D$2005,Transactions!$F$6:$F$2005,B15,Transactions!$H$6:$H$2005,"Variable expenses")) | G15: =IF(B15="",0,N(E15)+F15) | H15: =IF(B15="",0,MAX(0,N(C15)-G15)) | I15: =IF(N(C15)<=0,"",MIN(1,MAX(0,G15/C15))) | J15: =IF(I15="","",REPT("■",ROUND(MIN(1,MAX(0,N(I15)))*10,0))&REPT("□",10-ROUND(MIN(1,MAX(0,N(I15)))*10,0))) | K15: =IF(OR(B15="",NOT(ISNUMBER(D15))),"",MAX(0,(YEAR(D15)-YEAR(Settings!$C$11))*12+MONTH(D15)-MONTH(Settings!$C$11))) | L15: =IF(OR(B15="",K15=""),"",IF(H15<=0,0,H15/MAX(1,K15))) | N15: =IF(OR(B15="",N(C15)<=0),"",IF(H15<=0,"Reached",IF(N(M15)<=0,"",DATE(YEAR(Settings!$C$11),MONTH(Settings!$C$11)+ROUNDUP(H15/M15,0),1)))) | O15: =IF(B15="",IF(OR(N(C15)<>0,N(E15)<>0),"Name missing",""),IF(COUNTIF(Lists!$G$2:$G$25,B15)>1,"Name used twice",IF(N(C15)<=0,"Enter a target",IF(H15<=0,"Reached",IF(K15="","Enter a target date",IF(K15=0,"Target date reached",IF(N(M15)<=0,"Enter a monthly plan",IF(M15>=L15-0.005,"On track","Behind"))))))))
F16: =IF(B16="",0,SUMIFS(Transactions!$D$6:$D$2005,Transactions!$F$6:$F$2005,B16,Transactions!$H$6:$H$2005,"Savings & debt")-SUMIFS(Transactions!$D$6:$D$2005,Transactions!$F$6:$F$2005,B16,Transactions!$H$6:$H$2005,"Fixed bills")-SUMIFS(Transactions!$D$6:$D$2005,Transactions!$F$6:$F$2005,B16,Transactions!$H$6:$H$2005,"Variable expenses")) | G16: =IF(B16="",0,N(E16)+F16) | H16: =IF(B16="",0,MAX(0,N(C16)-G16)) | I16: =IF(N(C16)<=0,"",MIN(1,MAX(0,G16/C16))) | J16: =IF(I16="","",REPT("■",ROUND(MIN(1,MAX(0,N(I16)))*10,0))&REPT("□",10-ROUND(MIN(1,MAX(0,N(I16)))*10,0))) | K16: =IF(OR(B16="",NOT(ISNUMBER(D16))),"",MAX(0,(YEAR(D16)-YEAR(Settings!$C$11))*12+MONTH(D16)-MONTH(Settings!$C$11))) | L16: =IF(OR(B16="",K16=""),"",IF(H16<=0,0,H16/MAX(1,K16))) | N16: =IF(OR(B16="",N(C16)<=0),"",IF(H16<=0,"Reached",IF(N(M16)<=0,"",DATE(YEAR(Settings!$C$11),MONTH(Settings!$C$11)+ROUNDUP(H16/M16,0),1)))) | O16: =IF(B16="",IF(OR(N(C16)<>0,N(E16)<>0),"Name missing",""),IF(COUNTIF(Lists!$G$2:$G$25,B16)>1,"Name used twice",IF(N(C16)<=0,"Enter a target",IF(H16<=0,"Reached",IF(K16="","Enter a target date",IF(K16=0,"Target date reached",IF(N(M16)<=0,"Enter a monthly plan",IF(M16>=L16-0.005,"On track","Behind"))))))))
F17: =IF(B17="",0,SUMIFS(Transactions!$D$6:$D$2005,Transactions!$F$6:$F$2005,B17,Transactions!$H$6:$H$2005,"Savings & debt")-SUMIFS(Transactions!$D$6:$D$2005,Transactions!$F$6:$F$2005,B17,Transactions!$H$6:$H$2005,"Fixed bills")-SUMIFS(Transactions!$D$6:$D$2005,Transactions!$F$6:$F$2005,B17,Transactions!$H$6:$H$2005,"Variable expenses")) | G17: =IF(B17="",0,N(E17)+F17) | H17: =IF(B17="",0,MAX(0,N(C17)-G17)) | I17: =IF(N(C17)<=0,"",MIN(1,MAX(0,G17/C17))) | J17: =IF(I17="","",REPT("■",ROUND(MIN(1,MAX(0,N(I17)))*10,0))&REPT("□",10-ROUND(MIN(1,MAX(0,N(I17)))*10,0))) | K17: =IF(OR(B17="",NOT(ISNUMBER(D17))),"",MAX(0,(YEAR(D17)-YEAR(Settings!$C$11))*12+MONTH(D17)-MONTH(Settings!$C$11))) | L17: =IF(OR(B17="",K17=""),"",IF(H17<=0,0,H17/MAX(1,K17))) | N17: =IF(OR(B17="",N(C17)<=0),"",IF(H17<=0,"Reached",IF(N(M17)<=0,"",DATE(YEAR(Settings!$C$11),MONTH(Settings!$C$11)+ROUNDUP(H17/M17,0),1)))) | O17: =IF(B17="",IF(OR(N(C17)<>0,N(E17)<>0),"Name missing",""),IF(COUNTIF(Lists!$G$2:$G$25,B17)>1,"Name used twice",IF(N(C17)<=0,"Enter a target",IF(H17<=0,"Reached",IF(K17="","Enter a target date",IF(K17=0,"Target date reached",IF(N(M17)<=0,"Enter a monthly plan",IF(M17>=L17-0.005,"On track","Behind"))))))))
B18: Total | C18: =SUM(C6:C17) | E18: =SUM(E6:E17) | F18: =SUM(F6:F17) | G18: =SUM(G6:G17) | H18: =SUM(H6:H17) | I18: =IF(C18=0,0,MIN(1,G18/C18)) | J18: =IF(C18=0,"",REPT("■",ROUND(MIN(1,MAX(0,N(I18)))*10,0))&REPT("□",10-ROUND(MIN(1,MAX(0,N(I18)))*10,0))) | L18: =SUM(L6:L17) | M18: =SUM(M6:M17)
B20: Saved so far = starting amount + Savings & debt transactions tagged with the goal − expenses tagged with it. Needed per month = still needed ÷ months left.
B21: Starting amount: what the goal already had before you started logging it here. Type the goal name exactly as in Transactions (the drop-down list uses these names).

Sheet Sinking Funds
B1: Sinking Funds
B2: Money you set aside every month for costs you know are coming: car repairs, gifts, vacations, annual bills.
B3: Put money in: a Sinking funds transaction tagged with the fund. Spend it: log the expense in its own category and tag the same fund.
B5: Fund | C5: ="Amount needed"&Settings!$C$14 | D5: Due date | E5: ="Starting balance"&Settings!$C$14 | F5: ="Added"&Settings!$C$14 | G5: ="Spent"&Settings!$C$14 | H5: ="Balance"&Settings!$C$14 | I5: ="Still needed"&Settings!$C$14 | J5: Progress | L5: Months left | M5: ="Set aside per month"&Settings!$C$14 | N5: Status
B6: Car maintenance | C6: 900 | D6: 46660 | E6: 350 | F6: =IF(B6="",0,SUMIFS(Transactions!$D$6:$D$2005,Transactions!$F$6:$F$2005,B6,Transactions!$H$6:$H$2005,"Savings & debt")) | G6: =IF(B6="",0,SUMIFS(Transactions!$D$6:$D$2005,Transactions!$F$6:$F$2005,B6,Transactions!$H$6:$H$2005,"Fixed bills")+SUMIFS(Transactions!$D$6:$D$2005,Transactions!$F$6:$F$2005,B6,Transactions!$H$6:$H$2005,"Variable expenses")) | H6: =IF(B6="",0,N(E6)+F6-G6) | I6: =IF(B6="",0,MAX(0,N(C6)-H6)) | J6: =IF(N(C6)<=0,"",MIN(1,MAX(0,H6/C6))) | K6: =IF(J6="","",REPT("■",ROUND(MIN(1,MAX(0,N(J6)))*10,0))&REPT("□",10-ROUND(MIN(1,MAX(0,N(J6)))*10,0))) | L6: =IF(OR(B6="",NOT(ISNUMBER(D6))),"",MAX(0,(YEAR(D6)-YEAR(Settings!$C$11))*12+MONTH(D6)-MONTH(Settings!$C$11))) | M6: =IF(OR(B6="",L6=""),"",IF(I6<=0,0,I6/MAX(1,L6))) | N6: =IF(B6="",IF(OR(N(C6)<>0,N(E6)<>0),"Name missing",""),IF(COUNTIF(Lists!$G$2:$G$25,B6)>1,"Name used twice",IF(N(C6)<=0,"Enter an amount",IF(H6<-0.004,"Overspent",IF(I6<=0.004,"Ready",IF(L6="","Enter a due date",IF(L6=0,"Due now","Saving")))))))
B7: Holiday gifts | C7: 700 | D7: 46722 | E7: 80 | F7: =IF(B7="",0,SUMIFS(Transactions!$D$6:$D$2005,Transactions!$F$6:$F$2005,B7,Transactions!$H$6:$H$2005,"Savings & debt")) | G7: =IF(B7="",0,SUMIFS(Transactions!$D$6:$D$2005,Transactions!$F$6:$F$2005,B7,Transactions!$H$6:$H$2005,"Fixed bills")+SUMIFS(Transactions!$D$6:$D$2005,Transactions!$F$6:$F$2005,B7,Transactions!$H$6:$H$2005,"Variable expenses")) | H7: =IF(B7="",0,N(E7)+F7-G7) | I7: =IF(B7="",0,MAX(0,N(C7)-H7)) | J7: =IF(N(C7)<=0,"",MIN(1,MAX(0,H7/C7))) | K7: =IF(J7="","",REPT("■",ROUND(MIN(1,MAX(0,N(J7)))*10,0))&REPT("□",10-ROUND(MIN(1,MAX(0,N(J7)))*10,0))) | L7: =IF(OR(B7="",NOT(ISNUMBER(D7))),"",MAX(0,(YEAR(D7)-YEAR(Settings!$C$11))*12+MONTH(D7)-MONTH(Settings!$C$11))) | M7: =IF(OR(B7="",L7=""),"",IF(I7<=0,0,I7/MAX(1,L7))) | N7: =IF(B7="",IF(OR(N(C7)<>0,N(E7)<>0),"Name missing",""),IF(COUNTIF(Lists!$G$2:$G$25,B7)>1,"Name used twice",IF(N(C7)<=0,"Enter an amount",IF(H7<-0.004,"Overspent",IF(I7<=0.004,"Ready",IF(L7="","Enter a due date",IF(L7=0,"Due now","Saving")))))))
B8: Summer vacation | C8: 1800 | D8: 46569 | E8: 400 | F8: =IF(B8="",0,SUMIFS(Transactions!$D$6:$D$2005,Transactions!$F$6:$F$2005,B8,Transactions!$H$6:$H$2005,"Savings & debt")) | G8: =IF(B8="",0,SUMIFS(Transactions!$D$6:$D$2005,Transactions!$F$6:$F$2005,B8,Transactions!$H$6:$H$2005,"Fixed bills")+SUMIFS(Transactions!$D$6:$D$2005,Transactions!$F$6:$F$2005,B8,Transactions!$H$6:$H$2005,"Variable expenses")) | H8: =IF(B8="",0,N(E8)+F8-G8) | I8: =IF(B8="",0,MAX(0,N(C8)-H8)) | J8: =IF(N(C8)<=0,"",MIN(1,MAX(0,H8/C8))) | K8: =IF(J8="","",REPT("■",ROUND(MIN(1,MAX(0,N(J8)))*10,0))&REPT("□",10-ROUND(MIN(1,MAX(0,N(J8)))*10,0))) | L8: =IF(OR(B8="",NOT(ISNUMBER(D8))),"",MAX(0,(YEAR(D8)-YEAR(Settings!$C$11))*12+MONTH(D8)-MONTH(Settings!$C$11))) | M8: =IF(OR(B8="",L8=""),"",IF(I8<=0,0,I8/MAX(1,L8))) | N8: =IF(B8="",IF(OR(N(C8)<>0,N(E8)<>0),"Name missing",""),IF(COUNTIF(Lists!$G$2:$G$25,B8)>1,"Name used twice",IF(N(C8)<=0,"Enter an amount",IF(H8<-0.004,"Overspent",IF(I8<=0.004,"Ready",IF(L8="","Enter a due date",IF(L8=0,"Due now","Saving")))))))
B9: Home repairs | C9: 600 | D9: 46752 | E9: 150 | F9: =IF(B9="",0,SUMIFS(Transactions!$D$6:$D$2005,Transactions!$F$6:$F$2005,B9,Transactions!$H$6:$H$2005,"Savings & debt")) | G9: =IF(B9="",0,SUMIFS(Transactions!$D$6:$D$2005,Transactions!$F$6:$F$2005,B9,Transactions!$H$6:$H$2005,"Fixed bills")+SUMIFS(Transactions!$D$6:$D$2005,Transactions!$F$6:$F$2005,B9,Transactions!$H$6:$H$2005,"Variable expenses")) | H9: =IF(B9="",0,N(E9)+F9-G9) | I9: =IF(B9="",0,MAX(0,N(C9)-H9)) | J9: =IF(N(C9)<=0,"",MIN(1,MAX(0,H9/C9))) | K9: =IF(J9="","",REPT("■",ROUND(MIN(1,MAX(0,N(J9)))*10,0))&REPT("□",10-ROUND(MIN(1,MAX(0,N(J9)))*10,0))) | L9: =IF(OR(B9="",NOT(ISNUMBER(D9))),"",MAX(0,(YEAR(D9)-YEAR(Settings!$C$11))*12+MONTH(D9)-MONTH(Settings!$C$11))) | M9: =IF(OR(B9="",L9=""),"",IF(I9<=0,0,I9/MAX(1,L9))) | N9: =IF(B9="",IF(OR(N(C9)<>0,N(E9)<>0),"Name missing",""),IF(COUNTIF(Lists!$G$2:$G$25,B9)>1,"Name used twice",IF(N(C9)<=0,"Enter an amount",IF(H9<-0.004,"Overspent",IF(I9<=0.004,"Ready",IF(L9="","Enter a due date",IF(L9=0,"Due now","Saving")))))))
F10: =IF(B10="",0,SUMIFS(Transactions!$D$6:$D$2005,Transactions!$F$6:$F$2005,B10,Transactions!$H$6:$H$2005,"Savings & debt")) | G10: =IF(B10="",0,SUMIFS(Transactions!$D$6:$D$2005,Transactions!$F$6:$F$2005,B10,Transactions!$H$6:$H$2005,"Fixed bills")+SUMIFS(Transactions!$D$6:$D$2005,Transactions!$F$6:$F$2005,B10,Transactions!$H$6:$H$2005,"Variable expenses")) | H10: =IF(B10="",0,N(E10)+F10-G10) | I10: =IF(B10="",0,MAX(0,N(C10)-H10)) | J10: =IF(N(C10)<=0,"",MIN(1,MAX(0,H10/C10))) | K10: =IF(J10="","",REPT("■",ROUND(MIN(1,MAX(0,N(J10)))*10,0))&REPT("□",10-ROUND(MIN(1,MAX(0,N(J10)))*10,0))) | L10: =IF(OR(B10="",NOT(ISNUMBER(D10))),"",MAX(0,(YEAR(D10)-YEAR(Settings!$C$11))*12+MONTH(D10)-MONTH(Settings!$C$11))) | M10: =IF(OR(B10="",L10=""),"",IF(I10<=0,0,I10/MAX(1,L10))) | N10: =IF(B10="",IF(OR(N(C10)<>0,N(E10)<>0),"Name missing",""),IF(COUNTIF(Lists!$G$2:$G$25,B10)>1,"Name used twice",IF(N(C10)<=0,"Enter an amount",IF(H10<-0.004,"Overspent",IF(I10<=0.004,"Ready",IF(L10="","Enter a due date",IF(L10=0,"Due now","Saving")))))))
F11: =IF(B11="",0,SUMIFS(Transactions!$D$6:$D$2005,Transactions!$F$6:$F$2005,B11,Transactions!$H$6:$H$2005,"Savings & debt")) | G11: =IF(B11="",0,SUMIFS(Transactions!$D$6:$D$2005,Transactions!$F$6:$F$2005,B11,Transactions!$H$6:$H$2005,"Fixed bills")+SUMIFS(Transactions!$D$6:$D$2005,Transactions!$F$6:$F$2005,B11,Transactions!$H$6:$H$2005,"Variable expenses")) | H11: =IF(B11="",0,N(E11)+F11-G11) | I11: =IF(B11="",0,MAX(0,N(C11)-H11)) | J11: =IF(N(C11)<=0,"",MIN(1,MAX(0,H11/C11))) | K11: =IF(J11="","",REPT("■",ROUND(MIN(1,MAX(0,N(J11)))*10,0))&REPT("□",10-ROUND(MIN(1,MAX(0,N(J11)))*10,0))) | L11: =IF(OR(B11="",NOT(ISNUMBER(D11))),"",MAX(0,(YEAR(D11)-YEAR(Settings!$C$11))*12+MONTH(D11)-MONTH(Settings!$C$11))) | M11: =IF(OR(B11="",L11=""),"",IF(I11<=0,0,I11/MAX(1,L11))) | N11: =IF(B11="",IF(OR(N(C11)<>0,N(E11)<>0),"Name missing",""),IF(COUNTIF(Lists!$G$2:$G$25,B11)>1,"Name used twice",IF(N(C11)<=0,"Enter an amount",IF(H11<-0.004,"Overspent",IF(I11<=0.004,"Ready",IF(L11="","Enter a due date",IF(L11=0,"Due now","Saving")))))))
F12: =IF(B12="",0,SUMIFS(Transactions!$D$6:$D$2005,Transactions!$F$6:$F$2005,B12,Transactions!$H$6:$H$2005,"Savings & debt")) | G12: =IF(B12="",0,SUMIFS(Transactions!$D$6:$D$2005,Transactions!$F$6:$F$2005,B12,Transactions!$H$6:$H$2005,"Fixed bills")+SUMIFS(Transactions!$D$6:$D$2005,Transactions!$F$6:$F$2005,B12,Transactions!$H$6:$H$2005,"Variable expenses")) | H12: =IF(B12="",0,N(E12)+F12-G12) | I12: =IF(B12="",0,MAX(0,N(C12)-H12)) | J12: =IF(N(C12)<=0,"",MIN(1,MAX(0,H12/C12))) | K12: =IF(J12="","",REPT("■",ROUND(MIN(1,MAX(0,N(J12)))*10,0))&REPT("□",10-ROUND(MIN(1,MAX(0,N(J12)))*10,0))) | L12: =IF(OR(B12="",NOT(ISNUMBER(D12))),"",MAX(0,(YEAR(D12)-YEAR(Settings!$C$11))*12+MONTH(D12)-MONTH(Settings!$C$11))) | M12: =IF(OR(B12="",L12=""),"",IF(I12<=0,0,I12/MAX(1,L12))) | N12: =IF(B12="",IF(OR(N(C12)<>0,N(E12)<>0),"Name missing",""),IF(COUNTIF(Lists!$G$2:$G$25,B12)>1,"Name used twice",IF(N(C12)<=0,"Enter an amount",IF(H12<-0.004,"Overspent",IF(I12<=0.004,"Ready",IF(L12="","Enter a due date",IF(L12=0,"Due now","Saving")))))))
F13: =IF(B13="",0,SUMIFS(Transactions!$D$6:$D$2005,Transactions!$F$6:$F$2005,B13,Transactions!$H$6:$H$2005,"Savings & debt")) | G13: =IF(B13="",0,SUMIFS(Transactions!$D$6:$D$2005,Transactions!$F$6:$F$2005,B13,Transactions!$H$6:$H$2005,"Fixed bills")+SUMIFS(Transactions!$D$6:$D$2005,Transactions!$F$6:$F$2005,B13,Transactions!$H$6:$H$2005,"Variable expenses")) | H13: =IF(B13="",0,N(E13)+F13-G13) | I13: =IF(B13="",0,MAX(0,N(C13)-H13)) | J13: =IF(N(C13)<=0,"",MIN(1,MAX(0,H13/C13))) | K13: =IF(J13="","",REPT("■",ROUND(MIN(1,MAX(0,N(J13)))*10,0))&REPT("□",10-ROUND(MIN(1,MAX(0,N(J13)))*10,0))) | L13: =IF(OR(B13="",NOT(ISNUMBER(D13))),"",MAX(0,(YEAR(D13)-YEAR(Settings!$C$11))*12+MONTH(D13)-MONTH(Settings!$C$11))) | M13: =IF(OR(B13="",L13=""),"",IF(I13<=0,0,I13/MAX(1,L13))) | N13: =IF(B13="",IF(OR(N(C13)<>0,N(E13)<>0),"Name missing",""),IF(COUNTIF(Lists!$G$2:$G$25,B13)>1,"Name used twice",IF(N(C13)<=0,"Enter an amount",IF(H13<-0.004,"Overspent",IF(I13<=0.004,"Ready",IF(L13="","Enter a due date",IF(L13=0,"Due now","Saving")))))))
F14: =IF(B14="",0,SUMIFS(Transactions!$D$6:$D$2005,Transactions!$F$6:$F$2005,B14,Transactions!$H$6:$H$2005,"Savings & debt")) | G14: =IF(B14="",0,SUMIFS(Transactions!$D$6:$D$2005,Transactions!$F$6:$F$2005,B14,Transactions!$H$6:$H$2005,"Fixed bills")+SUMIFS(Transactions!$D$6:$D$2005,Transactions!$F$6:$F$2005,B14,Transactions!$H$6:$H$2005,"Variable expenses")) | H14: =IF(B14="",0,N(E14)+F14-G14) | I14: =IF(B14="",0,MAX(0,N(C14)-H14)) | J14: =IF(N(C14)<=0,"",MIN(1,MAX(0,H14/C14))) | K14: =IF(J14="","",REPT("■",ROUND(MIN(1,MAX(0,N(J14)))*10,0))&REPT("□",10-ROUND(MIN(1,MAX(0,N(J14)))*10,0))) | L14: =IF(OR(B14="",NOT(ISNUMBER(D14))),"",MAX(0,(YEAR(D14)-YEAR(Settings!$C$11))*12+MONTH(D14)-MONTH(Settings!$C$11))) | M14: =IF(OR(B14="",L14=""),"",IF(I14<=0,0,I14/MAX(1,L14))) | N14: =IF(B14="",IF(OR(N(C14)<>0,N(E14)<>0),"Name missing",""),IF(COUNTIF(Lists!$G$2:$G$25,B14)>1,"Name used twice",IF(N(C14)<=0,"Enter an amount",IF(H14<-0.004,"Overspent",IF(I14<=0.004,"Ready",IF(L14="","Enter a due date",IF(L14=0,"Due now","Saving")))))))
F15: =IF(B15="",0,SUMIFS(Transactions!$D$6:$D$2005,Transactions!$F$6:$F$2005,B15,Transactions!$H$6:$H$2005,"Savings & debt")) | G15: =IF(B15="",0,SUMIFS(Transactions!$D$6:$D$2005,Transactions!$F$6:$F$2005,B15,Transactions!$H$6:$H$2005,"Fixed bills")+SUMIFS(Transactions!$D$6:$D$2005,Transactions!$F$6:$F$2005,B15,Transactions!$H$6:$H$2005,"Variable expenses")) | H15: =IF(B15="",0,N(E15)+F15-G15) | I15: =IF(B15="",0,MAX(0,N(C15)-H15)) | J15: =IF(N(C15)<=0,"",MIN(1,MAX(0,H15/C15))) | K15: =IF(J15="","",REPT("■",ROUND(MIN(1,MAX(0,N(J15)))*10,0))&REPT("□",10-ROUND(MIN(1,MAX(0,N(J15)))*10,0))) | L15: =IF(OR(B15="",NOT(ISNUMBER(D15))),"",MAX(0,(YEAR(D15)-YEAR(Settings!$C$11))*12+MONTH(D15)-MONTH(Settings!$C$11))) | M15: =IF(OR(B15="",L15=""),"",IF(I15<=0,0,I15/MAX(1,L15))) | N15: =IF(B15="",IF(OR(N(C15)<>0,N(E15)<>0),"Name missing",""),IF(COUNTIF(Lists!$G$2:$G$25,B15)>1,"Name used twice",IF(N(C15)<=0,"Enter an amount",IF(H15<-0.004,"Overspent",IF(I15<=0.004,"Ready",IF(L15="","Enter a due date",IF(L15=0,"Due now","Saving")))))))
F16: =IF(B16="",0,SUMIFS(Transactions!$D$6:$D$2005,Transactions!$F$6:$F$2005,B16,Transactions!$H$6:$H$2005,"Savings & debt")) | G16: =IF(B16="",0,SUMIFS(Transactions!$D$6:$D$2005,Transactions!$F$6:$F$2005,B16,Transactions!$H$6:$H$2005,"Fixed bills")+SUMIFS(Transactions!$D$6:$D$2005,Transactions!$F$6:$F$2005,B16,Transactions!$H$6:$H$2005,"Variable expenses")) | H16: =IF(B16="",0,N(E16)+F16-G16) | I16: =IF(B16="",0,MAX(0,N(C16)-H16)) | J16: =IF(N(C16)<=0,"",MIN(1,MAX(0,H16/C16))) | K16: =IF(J16="","",REPT("■",ROUND(MIN(1,MAX(0,N(J16)))*10,0))&REPT("□",10-ROUND(MIN(1,MAX(0,N(J16)))*10,0))) | L16: =IF(OR(B16="",NOT(ISNUMBER(D16))),"",MAX(0,(YEAR(D16)-YEAR(Settings!$C$11))*12+MONTH(D16)-MONTH(Settings!$C$11))) | M16: =IF(OR(B16="",L16=""),"",IF(I16<=0,0,I16/MAX(1,L16))) | N16: =IF(B16="",IF(OR(N(C16)<>0,N(E16)<>0),"Name missing",""),IF(COUNTIF(Lists!$G$2:$G$25,B16)>1,"Name used twice",IF(N(C16)<=0,"Enter an amount",IF(H16<-0.004,"Overspent",IF(I16<=0.004,"Ready",IF(L16="","Enter a due date",IF(L16=0,"Due now","Saving")))))))
F17: =IF(B17="",0,SUMIFS(Transactions!$D$6:$D$2005,Transactions!$F$6:$F$2005,B17,Transactions!$H$6:$H$2005,"Savings & debt")) | G17: =IF(B17="",0,SUMIFS(Transactions!$D$6:$D$2005,Transactions!$F$6:$F$2005,B17,Transactions!$H$6:$H$2005,"Fixed bills")+SUMIFS(Transactions!$D$6:$D$2005,Transactions!$F$6:$F$2005,B17,Transactions!$H$6:$H$2005,"Variable expenses")) | H17: =IF(B17="",0,N(E17)+F17-G17) | I17: =IF(B17="",0,MAX(0,N(C17)-H17)) | J17: =IF(N(C17)<=0,"",MIN(1,MAX(0,H17/C17))) | K17: =IF(J17="","",REPT("■",ROUND(MIN(1,MAX(0,N(J17)))*10,0))&REPT("□",10-ROUND(MIN(1,MAX(0,N(J17)))*10,0))) | L17: =IF(OR(B17="",NOT(ISNUMBER(D17))),"",MAX(0,(YEAR(D17)-YEAR(Settings!$C$11))*12+MONTH(D17)-MONTH(Settings!$C$11))) | M17: =IF(OR(B17="",L17=""),"",IF(I17<=0,0,I17/MAX(1,L17))) | N17: =IF(B17="",IF(OR(N(C17)<>0,N(E17)<>0),"Name missing",""),IF(COUNTIF(Lists!$G$2:$G$25,B17)>1,"Name used twice",IF(N(C17)<=0,"Enter an amount",IF(H17<-0.004,"Overspent",IF(I17<=0.004,"Ready",IF(L17="","Enter a due date",IF(L17=0,"Due now","Saving")))))))
B18: Total | C18: =SUM(C6:C17) | E18: =SUM(E6:E17) | F18: =SUM(F6:F17) | G18: =SUM(G6:G17) | H18: =SUM(H6:H17) | I18: =SUM(I6:I17) | J18: =IF(C18=0,0,MIN(1,MAX(0,H18/C18))) | K18: =IF(C18=0,"",REPT("■",ROUND(MIN(1,MAX(0,N(J18)))*10,0))&REPT("□",10-ROUND(MIN(1,MAX(0,N(J18)))*10,0))) | M18: =SUM(M6:M17)
B20: ="Planned in Monthly Budget for the Sinking funds category in "&Settings!$C$13&":" | M20: =IFERROR(INDEX('Monthly Budget'!$D$14:$O$73,MATCH("Sinking funds",'Monthly Budget'!$A$14:$A$73,0),Settings!$C$12),"") | N20: =IF(OR(M18<=0,M20=""),"",IF(M20>=M18-0.005,"Enough","Plan more"))
B22: Balance = starting balance + money added − money spent (transactions tagged with the fund). Set aside per month = still needed ÷ months left.
B23: After the due date, change it to the next one (for example next year): the fund starts filling up again.

Sheet Debt Payoff
B1: Debt Payoff
B2: List your debts. Pay the minimum on every debt and put anything extra on the first one in the order. When a debt is paid off, its payment rolls over to the next.
B4: Payoff method | C4: Avalanche | D4: Avalanche: highest APR first (usually the least interest). Snowball: smallest balance first (quick wins).
B5: ="Extra payment each month"&Settings!$C$14 | C5: 150 | D5: On top of all the minimum payments. The total you pay each month stays the same until you are debt-free.
B7: Debt | C7: ="Balance"&Settings!$C$14 | D7: APR (yearly rate) | E7: ="Minimum payment"&Settings!$C$14 | F7: ="Interest this month"&Settings!$C$14 | G7: Months (minimums only) | H7: Paid off (minimums only) | I7: Avalanche order | J7: Snowball order | K7: Paid off (your plan) | L7: Check | M7: Months (your plan)
B8: Credit card | C8: 4200 | D8: 0.2499 | E8: 110 | F8: =IF(OR(B8="",N(C8)<=0,NOT(ISNUMBER(D8))),"",C8*D8/12) | G8: =IF(I8="","",'Debt Schedule'!C$8) | H8: =IF(G8="","",IF(ISNUMBER(G8),DATE(YEAR(Settings!$C$11),MONTH(Settings!$C$11)+G8,1),G8)) | I8: =IF(OR(B8="",N(C8)<=0,NOT(ISNUMBER(D8))),"",1+COUNTIFS($B$8:$B$17,"<>",$C$8:$C$17,">0",$D$8:$D$17,">=0",$D$8:$D$17,">"&D8)+COUNTIFS($B$8:$B$17,"<>",$C$8:$C$17,">0",$D$8:$D$17,">=0",$D$8:$D$17,D8,$C$8:$C$17,"<"&C8)+COUNTIFS($B$7:B7,"<>",$C$7:C7,C8,$D$7:D7,D8)) | J8: =IF(OR(B8="",N(C8)<=0,NOT(ISNUMBER(D8))),"",1+COUNTIFS($B$8:$B$17,"<>",$C$8:$C$17,">0",$D$8:$D$17,">=0",$C$8:$C$17,"<"&C8)+COUNTIFS($B$8:$B$17,"<>",$C$8:$C$17,">0",$D$8:$D$17,">=0",$C$8:$C$17,C8,$D$8:$D$17,">"&D8)+COUNTIFS($B$7:B7,"<>",$C$7:C7,C8,$D$7:D7,D8)) | K8: =IF(M8="","",IF(ISNUMBER(M8),DATE(YEAR(Settings!$C$11),MONTH(Settings!$C$11)+M8,1),M8)) | L8: =IF(B8="",IF(OR(C8<>"",D8<>"",E8<>""),"Enter a name",""),IF(N(C8)<=0,"Enter the balance",IF(NOT(ISNUMBER(D8)),"Enter the APR (0% if none)",IF(N(E8)<=0,"Enter the minimum payment",IF(E8<=C8*D8/12,"Minimum does not cover interest",""))))) | M8: =IF(OR(I8="",J8=""),"",IF($C$4="Snowball",INDEX('Debt Schedule'!$Z$8:$AI$8,1,J8),INDEX('Debt Schedule'!$AY$8:$BH$8,1,I8)))
B9: Medical bill | C9: 480 | D9: 0 | E9: 40 | F9: =IF(OR(B9="",N(C9)<=0,NOT(ISNUMBER(D9))),"",C9*D9/12) | G9: =IF(I9="","",'Debt Schedule'!D$8) | H9: =IF(G9="","",IF(ISNUMBER(G9),DATE(YEAR(Settings!$C$11),MONTH(Settings!$C$11)+G9,1),G9)) | I9: =IF(OR(B9="",N(C9)<=0,NOT(ISNUMBER(D9))),"",1+COUNTIFS($B$8:$B$17,"<>",$C$8:$C$17,">0",$D$8:$D$17,">=0",$D$8:$D$17,">"&D9)+COUNTIFS($B$8:$B$17,"<>",$C$8:$C$17,">0",$D$8:$D$17,">=0",$D$8:$D$17,D9,$C$8:$C$17,"<"&C9)+COUNTIFS($B$7:B8,"<>",$C$7:C8,C9,$D$7:D8,D9)) | J9: =IF(OR(B9="",N(C9)<=0,NOT(ISNUMBER(D9))),"",1+COUNTIFS($B$8:$B$17,"<>",$C$8:$C$17,">0",$D$8:$D$17,">=0",$C$8:$C$17,"<"&C9)+COUNTIFS($B$8:$B$17,"<>",$C$8:$C$17,">0",$D$8:$D$17,">=0",$C$8:$C$17,C9,$D$8:$D$17,">"&D9)+COUNTIFS($B$7:B8,"<>",$C$7:C8,C9,$D$7:D8,D9)) | K9: =IF(M9="","",IF(ISNUMBER(M9),DATE(YEAR(Settings!$C$11),MONTH(Settings!$C$11)+M9,1),M9)) | L9: =IF(B9="",IF(OR(C9<>"",D9<>"",E9<>""),"Enter a name",""),IF(N(C9)<=0,"Enter the balance",IF(NOT(ISNUMBER(D9)),"Enter the APR (0% if none)",IF(N(E9)<=0,"Enter the minimum payment",IF(E9<=C9*D9/12,"Minimum does not cover interest",""))))) | M9: =IF(OR(I9="",J9=""),"",IF($C$4="Snowball",INDEX('Debt Schedule'!$Z$8:$AI$8,1,J9),INDEX('Debt Schedule'!$AY$8:$BH$8,1,I9)))
B10: Personal loan | C10: 6200 | D10: 0.119 | E10: 210 | F10: =IF(OR(B10="",N(C10)<=0,NOT(ISNUMBER(D10))),"",C10*D10/12) | G10: =IF(I10="","",'Debt Schedule'!E$8) | H10: =IF(G10="","",IF(ISNUMBER(G10),DATE(YEAR(Settings!$C$11),MONTH(Settings!$C$11)+G10,1),G10)) | I10: =IF(OR(B10="",N(C10)<=0,NOT(ISNUMBER(D10))),"",1+COUNTIFS($B$8:$B$17,"<>",$C$8:$C$17,">0",$D$8:$D$17,">=0",$D$8:$D$17,">"&D10)+COUNTIFS($B$8:$B$17,"<>",$C$8:$C$17,">0",$D$8:$D$17,">=0",$D$8:$D$17,D10,$C$8:$C$17,"<"&C10)+COUNTIFS($B$7:B9,"<>",$C$7:C9,C10,$D$7:D9,D10)) | J10: =IF(OR(B10="",N(C10)<=0,NOT(ISNUMBER(D10))),"",1+COUNTIFS($B$8:$B$17,"<>",$C$8:$C$17,">0",$D$8:$D$17,">=0",$C$8:$C$17,"<"&C10)+COUNTIFS($B$8:$B$17,"<>",$C$8:$C$17,">0",$D$8:$D$17,">=0",$C$8:$C$17,C10,$D$8:$D$17,">"&D10)+COUNTIFS($B$7:B9,"<>",$C$7:C9,C10,$D$7:D9,D10)) | K10: =IF(M10="","",IF(ISNUMBER(M10),DATE(YEAR(Settings!$C$11),MONTH(Settings!$C$11)+M10,1),M10)) | L10: =IF(B10="",IF(OR(C10<>"",D10<>"",E10<>""),"Enter a name",""),IF(N(C10)<=0,"Enter the balance",IF(NOT(ISNUMBER(D10)),"Enter the APR (0% if none)",IF(N(E10)<=0,"Enter the minimum payment",IF(E10<=C10*D10/12,"Minimum does not cover interest",""))))) | M10: =IF(OR(I10="",J10=""),"",IF($C$4="Snowball",INDEX('Debt Schedule'!$Z$8:$AI$8,1,J10),INDEX('Debt Schedule'!$AY$8:$BH$8,1,I10)))
B11: Student loan | C11: 14500 | D11: 0.055 | E11: 165 | F11: =IF(OR(B11="",N(C11)<=0,NOT(ISNUMBER(D11))),"",C11*D11/12) | G11: =IF(I11="","",'Debt Schedule'!F$8) | H11: =IF(G11="","",IF(ISNUMBER(G11),DATE(YEAR(Settings!$C$11),MONTH(Settings!$C$11)+G11,1),G11)) | I11: =IF(OR(B11="",N(C11)<=0,NOT(ISNUMBER(D11))),"",1+COUNTIFS($B$8:$B$17,"<>",$C$8:$C$17,">0",$D$8:$D$17,">=0",$D$8:$D$17,">"&D11)+COUNTIFS($B$8:$B$17,"<>",$C$8:$C$17,">0",$D$8:$D$17,">=0",$D$8:$D$17,D11,$C$8:$C$17,"<"&C11)+COUNTIFS($B$7:B10,"<>",$C$7:C10,C11,$D$7:D10,D11)) | J11: =IF(OR(B11="",N(C11)<=0,NOT(ISNUMBER(D11))),"",1+COUNTIFS($B$8:$B$17,"<>",$C$8:$C$17,">0",$D$8:$D$17,">=0",$C$8:$C$17,"<"&C11)+COUNTIFS($B$8:$B$17,"<>",$C$8:$C$17,">0",$D$8:$D$17,">=0",$C$8:$C$17,C11,$D$8:$D$17,">"&D11)+COUNTIFS($B$7:B10,"<>",$C$7:C10,C11,$D$7:D10,D11)) | K11: =IF(M11="","",IF(ISNUMBER(M11),DATE(YEAR(Settings!$C$11),MONTH(Settings!$C$11)+M11,1),M11)) | L11: =IF(B11="",IF(OR(C11<>"",D11<>"",E11<>""),"Enter a name",""),IF(N(C11)<=0,"Enter the balance",IF(NOT(ISNUMBER(D11)),"Enter the APR (0% if none)",IF(N(E11)<=0,"Enter the minimum payment",IF(E11<=C11*D11/12,"Minimum does not cover interest",""))))) | M11: =IF(OR(I11="",J11=""),"",IF($C$4="Snowball",INDEX('Debt Schedule'!$Z$8:$AI$8,1,J11),INDEX('Debt Schedule'!$AY$8:$BH$8,1,I11)))
B12: Car loan | C12: 11800 | D12: 0.069 | E12: 389 | F12: =IF(OR(B12="",N(C12)<=0,NOT(ISNUMBER(D12))),"",C12*D12/12) | G12: =IF(I12="","",'Debt Schedule'!G$8) | H12: =IF(G12="","",IF(ISNUMBER(G12),DATE(YEAR(Settings!$C$11),MONTH(Settings!$C$11)+G12,1),G12)) | I12: =IF(OR(B12="",N(C12)<=0,NOT(ISNUMBER(D12))),"",1+COUNTIFS($B$8:$B$17,"<>",$C$8:$C$17,">0",$D$8:$D$17,">=0",$D$8:$D$17,">"&D12)+COUNTIFS($B$8:$B$17,"<>",$C$8:$C$17,">0",$D$8:$D$17,">=0",$D$8:$D$17,D12,$C$8:$C$17,"<"&C12)+COUNTIFS($B$7:B11,"<>",$C$7:C11,C12,$D$7:D11,D12)) | J12: =IF(OR(B12="",N(C12)<=0,NOT(ISNUMBER(D12))),"",1+COUNTIFS($B$8:$B$17,"<>",$C$8:$C$17,">0",$D$8:$D$17,">=0",$C$8:$C$17,"<"&C12)+COUNTIFS($B$8:$B$17,"<>",$C$8:$C$17,">0",$D$8:$D$17,">=0",$C$8:$C$17,C12,$D$8:$D$17,">"&D12)+COUNTIFS($B$7:B11,"<>",$C$7:C11,C12,$D$7:D11,D12)) | K12: =IF(M12="","",IF(ISNUMBER(M12),DATE(YEAR(Settings!$C$11),MONTH(Settings!$C$11)+M12,1),M12)) | L12: =IF(B12="",IF(OR(C12<>"",D12<>"",E12<>""),"Enter a name",""),IF(N(C12)<=0,"Enter the balance",IF(NOT(ISNUMBER(D12)),"Enter the APR (0% if none)",IF(N(E12)<=0,"Enter the minimum payment",IF(E12<=C12*D12/12,"Minimum does not cover interest",""))))) | M12: =IF(OR(I12="",J12=""),"",IF($C$4="Snowball",INDEX('Debt Schedule'!$Z$8:$AI$8,1,J12),INDEX('Debt Schedule'!$AY$8:$BH$8,1,I12)))
F13: =IF(OR(B13="",N(C13)<=0,NOT(ISNUMBER(D13))),"",C13*D13/12) | G13: =IF(I13="","",'Debt Schedule'!H$8) | H13: =IF(G13="","",IF(ISNUMBER(G13),DATE(YEAR(Settings!$C$11),MONTH(Settings!$C$11)+G13,1),G13)) | I13: =IF(OR(B13="",N(C13)<=0,NOT(ISNUMBER(D13))),"",1+COUNTIFS($B$8:$B$17,"<>",$C$8:$C$17,">0",$D$8:$D$17,">=0",$D$8:$D$17,">"&D13)+COUNTIFS($B$8:$B$17,"<>",$C$8:$C$17,">0",$D$8:$D$17,">=0",$D$8:$D$17,D13,$C$8:$C$17,"<"&C13)+COUNTIFS($B$7:B12,"<>",$C$7:C12,C13,$D$7:D12,D13)) | J13: =IF(OR(B13="",N(C13)<=0,NOT(ISNUMBER(D13))),"",1+COUNTIFS($B$8:$B$17,"<>",$C$8:$C$17,">0",$D$8:$D$17,">=0",$C$8:$C$17,"<"&C13)+COUNTIFS($B$8:$B$17,"<>",$C$8:$C$17,">0",$D$8:$D$17,">=0",$C$8:$C$17,C13,$D$8:$D$17,">"&D13)+COUNTIFS($B$7:B12,"<>",$C$7:C12,C13,$D$7:D12,D13)) | K13: =IF(M13="","",IF(ISNUMBER(M13),DATE(YEAR(Settings!$C$11),MONTH(Settings!$C$11)+M13,1),M13)) | L13: =IF(B13="",IF(OR(C13<>"",D13<>"",E13<>""),"Enter a name",""),IF(N(C13)<=0,"Enter the balance",IF(NOT(ISNUMBER(D13)),"Enter the APR (0% if none)",IF(N(E13)<=0,"Enter the minimum payment",IF(E13<=C13*D13/12,"Minimum does not cover interest",""))))) | M13: =IF(OR(I13="",J13=""),"",IF($C$4="Snowball",INDEX('Debt Schedule'!$Z$8:$AI$8,1,J13),INDEX('Debt Schedule'!$AY$8:$BH$8,1,I13)))
F14: =IF(OR(B14="",N(C14)<=0,NOT(ISNUMBER(D14))),"",C14*D14/12) | G14: =IF(I14="","",'Debt Schedule'!I$8) | H14: =IF(G14="","",IF(ISNUMBER(G14),DATE(YEAR(Settings!$C$11),MONTH(Settings!$C$11)+G14,1),G14)) | I14: =IF(OR(B14="",N(C14)<=0,NOT(ISNUMBER(D14))),"",1+COUNTIFS($B$8:$B$17,"<>",$C$8:$C$17,">0",$D$8:$D$17,">=0",$D$8:$D$17,">"&D14)+COUNTIFS($B$8:$B$17,"<>",$C$8:$C$17,">0",$D$8:$D$17,">=0",$D$8:$D$17,D14,$C$8:$C$17,"<"&C14)+COUNTIFS($B$7:B13,"<>",$C$7:C13,C14,$D$7:D13,D14)) | J14: =IF(OR(B14="",N(C14)<=0,NOT(ISNUMBER(D14))),"",1+COUNTIFS($B$8:$B$17,"<>",$C$8:$C$17,">0",$D$8:$D$17,">=0",$C$8:$C$17,"<"&C14)+COUNTIFS($B$8:$B$17,"<>",$C$8:$C$17,">0",$D$8:$D$17,">=0",$C$8:$C$17,C14,$D$8:$D$17,">"&D14)+COUNTIFS($B$7:B13,"<>",$C$7:C13,C14,$D$7:D13,D14)) | K14: =IF(M14="","",IF(ISNUMBER(M14),DATE(YEAR(Settings!$C$11),MONTH(Settings!$C$11)+M14,1),M14)) | L14: =IF(B14="",IF(OR(C14<>"",D14<>"",E14<>""),"Enter a name",""),IF(N(C14)<=0,"Enter the balance",IF(NOT(ISNUMBER(D14)),"Enter the APR (0% if none)",IF(N(E14)<=0,"Enter the minimum payment",IF(E14<=C14*D14/12,"Minimum does not cover interest",""))))) | M14: =IF(OR(I14="",J14=""),"",IF($C$4="Snowball",INDEX('Debt Schedule'!$Z$8:$AI$8,1,J14),INDEX('Debt Schedule'!$AY$8:$BH$8,1,I14)))
F15: =IF(OR(B15="",N(C15)<=0,NOT(ISNUMBER(D15))),"",C15*D15/12) | G15: =IF(I15="","",'Debt Schedule'!J$8) | H15: =IF(G15="","",IF(ISNUMBER(G15),DATE(YEAR(Settings!$C$11),MONTH(Settings!$C$11)+G15,1),G15)) | I15: =IF(OR(B15="",N(C15)<=0,NOT(ISNUMBER(D15))),"",1+COUNTIFS($B$8:$B$17,"<>",$C$8:$C$17,">0",$D$8:$D$17,">=0",$D$8:$D$17,">"&D15)+COUNTIFS($B$8:$B$17,"<>",$C$8:$C$17,">0",$D$8:$D$17,">=0",$D$8:$D$17,D15,$C$8:$C$17,"<"&C15)+COUNTIFS($B$7:B14,"<>",$C$7:C14,C15,$D$7:D14,D15)) | J15: =IF(OR(B15="",N(C15)<=0,NOT(ISNUMBER(D15))),"",1+COUNTIFS($B$8:$B$17,"<>",$C$8:$C$17,">0",$D$8:$D$17,">=0",$C$8:$C$17,"<"&C15)+COUNTIFS($B$8:$B$17,"<>",$C$8:$C$17,">0",$D$8:$D$17,">=0",$C$8:$C$17,C15,$D$8:$D$17,">"&D15)+COUNTIFS($B$7:B14,"<>",$C$7:C14,C15,$D$7:D14,D15)) | K15: =IF(M15="","",IF(ISNUMBER(M15),DATE(YEAR(Settings!$C$11),MONTH(Settings!$C$11)+M15,1),M15)) | L15: =IF(B15="",IF(OR(C15<>"",D15<>"",E15<>""),"Enter a name",""),IF(N(C15)<=0,"Enter the balance",IF(NOT(ISNUMBER(D15)),"Enter the APR (0% if none)",IF(N(E15)<=0,"Enter the minimum payment",IF(E15<=C15*D15/12,"Minimum does not cover interest",""))))) | M15: =IF(OR(I15="",J15=""),"",IF($C$4="Snowball",INDEX('Debt Schedule'!$Z$8:$AI$8,1,J15),INDEX('Debt Schedule'!$AY$8:$BH$8,1,I15)))
F16: =IF(OR(B16="",N(C16)<=0,NOT(ISNUMBER(D16))),"",C16*D16/12) | G16: =IF(I16="","",'Debt Schedule'!K$8) | H16: =IF(G16="","",IF(ISNUMBER(G16),DATE(YEAR(Settings!$C$11),MONTH(Settings!$C$11)+G16,1),G16)) | I16: =IF(OR(B16="",N(C16)<=0,NOT(ISNUMBER(D16))),"",1+COUNTIFS($B$8:$B$17,"<>",$C$8:$C$17,">0",$D$8:$D$17,">=0",$D$8:$D$17,">"&D16)+COUNTIFS($B$8:$B$17,"<>",$C$8:$C$17,">0",$D$8:$D$17,">=0",$D$8:$D$17,D16,$C$8:$C$17,"<"&C16)+COUNTIFS($B$7:B15,"<>",$C$7:C15,C16,$D$7:D15,D16)) | J16: =IF(OR(B16="",N(C16)<=0,NOT(ISNUMBER(D16))),"",1+COUNTIFS($B$8:$B$17,"<>",$C$8:$C$17,">0",$D$8:$D$17,">=0",$C$8:$C$17,"<"&C16)+COUNTIFS($B$8:$B$17,"<>",$C$8:$C$17,">0",$D$8:$D$17,">=0",$C$8:$C$17,C16,$D$8:$D$17,">"&D16)+COUNTIFS($B$7:B15,"<>",$C$7:C15,C16,$D$7:D15,D16)) | K16: =IF(M16="","",IF(ISNUMBER(M16),DATE(YEAR(Settings!$C$11),MONTH(Settings!$C$11)+M16,1),M16)) | L16: =IF(B16="",IF(OR(C16<>"",D16<>"",E16<>""),"Enter a name",""),IF(N(C16)<=0,"Enter the balance",IF(NOT(ISNUMBER(D16)),"Enter the APR (0% if none)",IF(N(E16)<=0,"Enter the minimum payment",IF(E16<=C16*D16/12,"Minimum does not cover interest",""))))) | M16: =IF(OR(I16="",J16=""),"",IF($C$4="Snowball",INDEX('Debt Schedule'!$Z$8:$AI$8,1,J16),INDEX('Debt Schedule'!$AY$8:$BH$8,1,I16)))
F17: =IF(OR(B17="",N(C17)<=0,NOT(ISNUMBER(D17))),"",C17*D17/12) | G17: =IF(I17="","",'Debt Schedule'!L$8) | H17: =IF(G17="","",IF(ISNUMBER(G17),DATE(YEAR(Settings!$C$11),MONTH(Settings!$C$11)+G17,1),G17)) | I17: =IF(OR(B17="",N(C17)<=0,NOT(ISNUMBER(D17))),"",1+COUNTIFS($B$8:$B$17,"<>",$C$8:$C$17,">0",$D$8:$D$17,">=0",$D$8:$D$17,">"&D17)+COUNTIFS($B$8:$B$17,"<>",$C$8:$C$17,">0",$D$8:$D$17,">=0",$D$8:$D$17,D17,$C$8:$C$17,"<"&C17)+COUNTIFS($B$7:B16,"<>",$C$7:C16,C17,$D$7:D16,D17)) | J17: =IF(OR(B17="",N(C17)<=0,NOT(ISNUMBER(D17))),"",1+COUNTIFS($B$8:$B$17,"<>",$C$8:$C$17,">0",$D$8:$D$17,">=0",$C$8:$C$17,"<"&C17)+COUNTIFS($B$8:$B$17,"<>",$C$8:$C$17,">0",$D$8:$D$17,">=0",$C$8:$C$17,C17,$D$8:$D$17,">"&D17)+COUNTIFS($B$7:B16,"<>",$C$7:C16,C17,$D$7:D16,D17)) | K17: =IF(M17="","",IF(ISNUMBER(M17),DATE(YEAR(Settings!$C$11),MONTH(Settings!$C$11)+M17,1),M17)) | L17: =IF(B17="",IF(OR(C17<>"",D17<>"",E17<>""),"Enter a name",""),IF(N(C17)<=0,"Enter the balance",IF(NOT(ISNUMBER(D17)),"Enter the APR (0% if none)",IF(N(E17)<=0,"Enter the minimum payment",IF(E17<=C17*D17/12,"Minimum does not cover interest",""))))) | M17: =IF(OR(I17="",J17=""),"",IF($C$4="Snowball",INDEX('Debt Schedule'!$Z$8:$AI$8,1,J17),INDEX('Debt Schedule'!$AY$8:$BH$8,1,I17)))
B18: Total | C18: =SUM(C8:C17) | D18: =IF(C18=0,"",SUMPRODUCT(C8:C17,D8:D17)/C18) | E18: =SUM(E8:E17) | F18: =SUM(F8:F17) | G18: =IF(C18=0,"",C24) | H18: =IF(C18=0,"",C25) | K18: =IF(C18=0,"",IF($C$4="Snowball",D25,E25))
B19: APR = the yearly interest rate on your statement (type 0% for an interest-free loan). The APR in the total row is the average weighted by balance.
B21: Compare the methods
C22: Minimums only | D22: Snowball | E22: Avalanche
B23: ="Paid each month"&Settings!$C$14 | C23: =$E$18 | D23: ='Debt Schedule'!$AK$7 | E23: ='Debt Schedule'!$BJ$7
B24: Months until debt-free | C24: ='Debt Schedule'!N$8 | D24: ='Debt Schedule'!AM$8 | E24: ='Debt Schedule'!BL$8
B25: Debt-free date | C25: =IF($C$18=0,"–",IF(ISNUMBER(C24),DATE(YEAR(Settings!$C$11),MONTH(Settings!$C$11)+C24,1),C24)) | D25: =IF($C$18=0,"–",IF(ISNUMBER(D24),DATE(YEAR(Settings!$C$11),MONTH(Settings!$C$11)+D24,1),D24)) | E25: =IF($C$18=0,"–",IF(ISNUMBER(E24),DATE(YEAR(Settings!$C$11),MONTH(Settings!$C$11)+E24,1),E24))
B26: ="Total interest"&Settings!$C$14 | C26: =IF(ISNUMBER(C24),'Debt Schedule'!M$8,"–") | D26: =IF(ISNUMBER(D24),'Debt Schedule'!AL$8,"–") | E26: =IF(ISNUMBER(E24),'Debt Schedule'!BK$8,"–")
B27: ="Interest saved vs minimums"&Settings!$C$14 | C27: ="–" | D27: =IF(AND(ISNUMBER($C$26),ISNUMBER(D26)),$C$26-D26,"–") | E27: =IF(AND(ISNUMBER($C$26),ISNUMBER(E26)),$C$26-E26,"–")
B28: =IF($C$18=0,"Your plan: enter your debts above.","Your plan: "&$C$4&IF(ISNUMBER(M28),", saving "&FIXED(M28,2)&" in interest compared with minimums only.","")) | M28: =IF($C$4="Snowball",D27,E27)
B29: If the minimum payments do not cover the interest, a debt is never paid off with minimums only ("Over 30 years").
B31: Avalanche order: highest APR first
B32: Debt | C32: ="Balance"&Settings!$C$14 | D32: APR | E32: ="Minimum"&Settings!$C$14 | F32: Paid off
A33: 1 | B33: =IFERROR(INDEX($B$8:$B$17,MATCH(1,$I$8:$I$17,0)),"") | C33: =IFERROR(INDEX($C$8:$C$17,MATCH(1,$I$8:$I$17,0)),"") | D33: =IFERROR(INDEX($D$8:$D$17,MATCH(1,$I$8:$I$17,0)),"") | E33: =IFERROR(INDEX($E$8:$E$17,MATCH(1,$I$8:$I$17,0)),"") | F33: =IF(B33="","",IF(ISNUMBER(INDEX('Debt Schedule'!$AY$8:$BH$8,1,1)),DATE(YEAR(Settings!$C$11),MONTH(Settings!$C$11)+INDEX('Debt Schedule'!$AY$8:$BH$8,1,1),1),INDEX('Debt Schedule'!$AY$8:$BH$8,1,1)))
